Workbook
Name Annee_Bench: Output!$N$435:INDEX(Output!$N:$N,434+COUNT(Output!$M$435:$M$10000))
Name Annee_Bottom: Output!$Q$435:INDEX(Output!$Q:$Q,434+COUNT(Output!$M$435:$M$10000))
Name Annee_Date: Output!$M$435:INDEX(Output!$M:$M,434+COUNT(Output!$M$435:$M$10000))
Name Annee_Ptf: Output!$O$435:INDEX(Output!$O:$O,434+COUNT(Output!$M$435:$M$10000))
Name Annee_Top: Output!$P$435:INDEX(Output!$P:$P,434+COUNT(Output!$M$435:$M$10000))
Name Courbe_Bench: Output!$E$435:INDEX(Output!$E:$E,434+COUNT(Output!$D$435:$D$10000))
Name Courbe_Bottom: Output!$H$435:INDEX(Output!$H:$H,434+COUNT(Output!$D$435:$D$10000))
Name Courbe_Date: Output!$D$435:INDEX(Output!$D:$D,434+COUNT(Output!$D$435:$D$10000))
Name Courbe_LS: Output!$I$435:INDEX(Output!$I:$I,434+COUNT(Output!$D$435:$D$10000))
Name Courbe_Ptf: Output!$F$435:INDEX(Output!$F:$F,434+COUNT(Output!$D$435:$D$10000))
Name Courbe_Top: Output!$G$435:INDEX(Output!$G:$G,434+COUNT(Output!$D$435:$D$10000))
Name DateExport: Config!$C$37
Name delta_Wi: Config!$C$33
Name ExportFile: Config!$C$39
Name ImportFile: Config!$C$38
Name IND_Auto: Config!$B$20
Name IND_Bench: Config!$B$7
Name IND_ConsGd: Config!$B$9
Name IND_Fin: Config!$B$11
Name IND_Health: Config!$B$12
Name IND_Indus: Config!$B$13
Name IND_Mat: Config!$B$8
Name Ind_Media: Config!$B$19
Name IND_Oil: Config!$B$14
Name IND_PersGoods: Config!$B$10
Name Ind_Retail: Config!$B$10
Name IND_Tech: Config!$B$15
Name IND_Telco: Config!$B$16
Name Ind_Travel: Config!$B$18
Name IND_Utili: Config!$B$17
Name nb_Bottom: Config!$C$28
Name nb_Long: Config!$C$30
Name nb_Short: Config!$C$31
Name nb_Top: Config!$C$27
Name RFolder: Config!$C$40
Name RFunction: Config!$C$41

Sheet Dashboard
I4: SCORECARD | BN4: Date: | BO4: =Output!B2 -> 46295 | BP4: =Output!B9 -> 46296 | BQ4: =Output!B10 -> 46266
I5: EU SECTORS
CC6: Last Month Allocation Performance
BP7: =Output!B11 -> Sectors Ranking Oct-2026 | BV7: =Output!B12 -> Sectors Ranking Sept-2026
I8: Low leverage rank | J8: Net debt to EBITDA | M8: FCF to Total Debt | P8: Total Debt to Equity | S8: Margin rank | T8: Operating margin | W8: Net margin | Z8: EBITDA margin | AC8: Valuation rank | AD8: PFCF | AG8: EV / EBITDA | AJ8: Price to sales | AM8: Momentum rank | AN8: Perf 6M-1M | AP8: Perf 12M-1M | AR8: Earnings revision ratio | AU8: Growth rank | AV8: EPS 12M growth forecast | AY8: Sales 12M growth forecast | BB8: EBITDA 12M growth forecast | BE8: Low volatility rank | BF8: Vol 6M | BH8: Vol downside 18M | BJ8: =Output!B13 -> Macro rank - Currently in Expansion | BK8: Rate signal - Bonus Leverage & Value | CD8: Last Month EQ Performance
J9: vs. moy secteurs perc. 5y | K9: vs. moy secteurs histo 5y | L9: metric | M9: vs. moy secteurs perc. 5y | N9: vs. moy secteurs histo 5y | O9: metric | P9: vs. moy secteurs perc. 5y | Q9: vs. moy secteurs histo 5y | R9: metric | T9: vs. moy secteurs perc. 5y | U9: vs. moy secteurs histo 5y | V9: metric | W9: vs. moy secteurs perc. 5y | X9: vs. moy secteurs histo 5y | Y9: metric | Z9: vs. moy secteurs perc. 5y | AA9: vs. moy secteurs histo 5y | AB9: metric | AD9: vs. moy secteurs perc. 5y | AE9: vs. moy secteurs histo 5y | AF9: metric | AG9: vs. moy secteurs perc. 5y | AH9: vs. moy secteurs histo 5y | AI9: metric | AJ9: vs. moy secteurs perc. 5y | AK9: vs. moy secteurs histo 5y | AL9: metric | AN9: Score (rank) | AO9: Perf | AP9: Score (rank) | AQ9: Perf | AR9: Score (rank) | AS9: Ratio histo 5y | AT9: Ratio | AV9: vs. moy secteurs perc. 5y | AW9: vs. moy secteurs histo 5y | AX9: metric | AY9: vs. moy secteurs perc. 5y | AZ9: vs. moy secteurs histo 5y | BA9: metric | BB9: vs. moy secteurs perc. 5y | BC9: vs. moy secteurs histo 5y | BD9: metric | BF9: Score (rank) | BG9: Vol | BH9: Score (rank) | BI9: Vol | BN9: Nb Top 3 pillars | BO9: Nb Worst 3 pillars | BP9: Global - Weighted Score | BQ9: Reco | BR9: Δ Reco | BU9: Previous nb piliers Top 3 | BV9: Previous nb piliers Worst 3 | BW9: Previous global - Weighted Score | BX9: Previous Reco | BY9: =Output!BU1 -> Sept-2026 EQ Performance | BZ9: =Output!BV1 -> Sept-2026 XSRet vs FTSE World Europe | CC9: Long Portfolio | CD9: =Output!B15 -> 0.014712331
H10: Materials | I10: =Output!E2 -> 12 | J10: =Output!F2 -> 3.9344262 | L10: =Output!H2 -> 1.5176704 | M10: =Output!I2 -> 0.6557377 | O10: =Output!K2 -> 10.980834 | P10: =Output!L2 -> 0.6557377 | R10: =Output!N2 -> 57.789196 | S10: =Output!O2 -> 10 | T10: =Output!P2 -> 3.3102144 | V10: =Output!R2 -> 8.6551612 | W10: =Output!S2 -> 3.8020177 | Y10: =Output!U2 -> 6.0453761 | Z10: =Output!V2 -> 2.9003783 | AB10: =Output!X2 -> 13.757778 | AC10: =Output!Y2 -> 11 | AD10: =Output!Z2 -> 0.32786885 | AF10: =Output!AB2 -> 8.9422186 | AG10: =Output!AC2 -> 0.49180328 | AI10: =Output!AE2 -> 7.7631122 | AJ10: =Output!AF2 -> 1.8032787 | AL10: =Output!AH2 -> 1.0583207 | AM10: =Output!AI2 -> 4 | AN10: =Output!AJ2 -> 6.1538462 | AO10: =Output!AK2 -> 0.13038207 | AP10: =Output!AL2 -> 9.2307692 | AQ10: =Output!AM2 -> 0.33963863 | AR10: =Output!AN2 -> 6.1538462 | AT10: =Output!AP2 -> 0.057142857 | AU10: =Output!AQ2 -> 4 | AV10: =Output!AR2 -> 5.7377049 | AX10: =Output!AT2 -> 18.168167 | AY10: =Output!AU2 -> 8.5245902 | BA10: =Output!AW2 -> 3.7950325 | BB10: =Output!AX2 -> 6.7213115 | BD10: =Output!AZ2 -> 10.282517 | BE10: =Output!BA2 -> 2 | BF10: =Output!BB2 -> 7.3770492 | BG10: =Output!BC2 -> 0.18247089 | BH10: =Output!BD2 -> 9.3442623 | BI10: =Output!BE2 -> 0.062962012 | BJ10: =Output!BF2 -> 8 | BK10: =Output!B6 -> On | BM10: Materials | BN10: =Output!BJ2 -> 1 | BO10: =Output!BK2 -> 4 | BP10: =Output!BL2 -> 6.7142857 | BQ10: =Output!BM2 -> Neutral | BR10: =Output!BN2 -> 0 | BU10: =Output!BQ2 -> 2 | BV10: =Output!BR2 -> 3 | BW10: =Output!BS2 -> 6.7142857 | BX10: =Output!BT2 -> Neutral | BY10: =Output!BU2 -> -0.043807237 | BZ10: =Output!BV2 -> -0.018626796 | CC10: Short Portfolio | CD10: =Output!B16 -> 0.067264722
H11: Consumer Staples | I11: =Output!E3 -> 10 | J11: =Output!F3 -> 4.2622951 | L11: =Output!H3 -> 2.57611 | M11: =Output!I3 -> 7.3770492 | O11: =Output!K3 -> 17.981573 | P11: =Output!L3 -> 0.32786885 | R11: =Output!N3 -> 115.95281 | S11: =Output!O3 -> 12 | T11: =Output!P3 -> 2.9886507 | V11: =Output!R3 -> 11.498439 | W11: =Output!S3 -> 3.3165195 | Y11: =Output!U3 -> 7.318707 | Z11: =Output!V3 -> 3.3417402 | AB11: =Output!X3 -> 15.836251 | AC11: =Output!Y3 -> 6 | AD11: =Output!Z3 -> 6.7213115 | AF11: =Output!AB3 -> 10.04444 | AG11: =Output!AC3 -> 7.3770492 | AI11: =Output!AE3 -> 9.7333979 | AJ11: =Output!AF3 -> 9.1803279 | AL11: =Output!AH3 -> 1.1770891 | AM11: =Output!AI3 -> 9 | AN11: =Output!AJ3 -> 4.6153846 | AO11: =Output!AK3 -> 0.02999415 | AP11: =Output!AL3 -> 3.8461538 | AQ11: =Output!AM3 -> 0.042321296 | AR11: =Output!AN3 -> 3.8461538 | AT11: =Output!AP3 -> -0.11363636 | AU11: =Output!AQ3 -> 11 | AV11: =Output!AR3 -> 3.9344262 | AX11: =Output!AT3 -> 6.9131176 | AY11: =Output!AU3 -> 2.9508197 | BA11: =Output!AW3 -> 3.6888091 | BB11: =Output!AX3 -> 3.442623 | BD11: =Output!AZ3 -> 4.8960757 | BE11: =Output!BA3 -> 12 | BF11: =Output!BB3 -> 3.2786885 | BG11: =Output!BC3 -> 0.18050462 | BH11: =Output!BD3 -> 1.147541 | BI11: =Output!BE3 -> 0.11597345 | BJ11: =Output!BF3 -> 12 | BK11: - A sector that is at least 3 times in worst 3 sectors (resp. top 3) of different pillars can not have a positive recommendation (resp. negative). - If two sectors are as many times in the top or worst 3, we differentiate them by their mean score. - Macro pillar counts twice. - If rate signal is on, value and leverage pillars count twice. | BM11: Consumer Staples | BN11: =Output!BJ3 -> 0 | BO11: =Output!BK3 -> 5 | BP11: =Output!BL3 -> 3.7142857 | BQ11: =Output!BM3 -> Negative | BR11: =Output!BN3 -> 0 | BU11: =Output!BQ3 -> 0 | BV11: =Output!BR3 -> 3 | BW11: =Output!BS3 -> 4.1428571 | BX11: =Output!BT3 -> Negative | BY11: =Output!BU3 -> -0.032147216 | BZ11: =Output!BV3 -> -0.0069667762 | CC11: L/S Portfolio | CD11: =Output!B17 -> 0.081977053
H12: Personal Goods | I12: =Output!E4 -> 4 | J12: =Output!F4 -> 4.9180328 | L12: =Output!H4 -> 0.73907005 | M12: =Output!I4 -> 7.2131148 | O12: =Output!K4 -> 33.20084 | P12: =Output!L4 -> 3.6065574 | R12: =Output!N4 -> 58.519142 | S12: =Output!O4 -> 8 | T12: =Output!P4 -> 4.4766709 | V12: =Output!R4 -> 18.044296 | W12: =Output!S4 -> 4.9117276 | Y12: =Output!U4 -> 11.481202 | Z12: =Output!V4 -> 4.8549811 | AB12: =Output!X4 -> 25.277612 | AC12: =Output!Y4 -> 2 | AD12: =Output!Z4 -> 10 | AF12: =Output!AB4 -> 14.473667 | AG12: =Output!AC4 -> 10 | AI12: =Output!AE4 -> 11.329662 | AJ12: =Output!AF4 -> 10 | AL12: =Output!AH4 -> 2.7591781 | AM12: =Output!AI4 -> 12 | AN12: =Output!AJ4 -> 5.3846154 | AO12: =Output!AK4 -> 0.09934833 | AP12: =Output!AL4 -> 2.3076923 | AQ12: =Output!AM4 -> -0.026194227 | AR12: =Output!AN4 -> 2.3076923 | AT12: =Output!AP4 -> -0.38461538 | AU12: =Output!AQ4 -> 12 | AV12: =Output!AR4 -> 3.7704918 | AX12: =Output!AT4 -> 13.004314 | AY12: =Output!AU4 -> 2.1311475 | BA12: =Output!AW4 -> 6.0954359 | BB12: =Output!AX4 -> 2.6229508 | BD12: =Output!AZ4 -> 7.7301313 | BE12: =Output!BA4 -> 7 | BF12: =Output!BB4 -> 5.4098361 | BG12: =Output!BC4 -> 0.25442201 | BH12: =Output!BD4 -> 2.1311475 | BI12: =Output!BE4 -> 0.18750445 | BJ12: =Output!BF4 -> 9 | BM12: Personal Goods | BN12: =Output!BJ4 -> 2 | BO12: =Output!BK4 -> 2 | BP12: =Output!BL4 -> 6.2857143 | BQ12: =Output!BM4 -> Neutral | BR12: =Output!BN4 -> 1 | BU12: =Output!BQ4 -> 1 | BV12: =Output!BR4 -> 4 | BW12: =Output!BS4 -> 6.2857143 | BX12: =Output!BT4 -> Negative | BY12: =Output!BU4 -> -0.079729636 | BZ12: =Output!BV4 -> -0.054549195 | CC12: Ptf dev secto | CD12: =Output!B18 -> -0.015123767
H13: Financials | I13: =Output!E5 -> 2 | J13: =Output!F5 -> 7.0491803 | L13: =Output!H5 -> 10.11696 | M13: =Output!I5 -> 3.1147541 | O13: =Output!K5 -> 2.8015014 | P13: =Output!L5 -> 8.6885246 | R13: =Output!N5 -> 417.95205 | S13: =Output!O5 -> 3 | T13: =Output!P5 -> 7.7805801 | V13: =Output!R5 -> 17.486197 | W13: =Output!S5 -> 8.6569987 | Y13: =Output!U5 -> 12.648923 | Z13: =Output!V5 -> 7.0491803 | AB13: =Output!X5 -> 51.665548 | AC13: =Output!Y5 -> n.a. | AD13: =Output!Z5 -> n.a. | AF13: =Output!AB5 -> n.a. | AG13: =Output!AC5 -> n.a. | AI13: =Output!AE5 -> n.a. | AJ13: =Output!AF5 -> 0.32786885 | AL13: =Output!AH5 -> 2.1662574 | AM13: =Output!AI5 -> 1 | AN13: =Output!AJ5 -> 9.2307692 | AO13: =Output!AK5 -> 0.23881973 | AP13: =Output!AL5 -> 8.4615385 | AQ13: =Output!AM5 -> 0.2750319 | AR13: =Output!AN5 -> 6.9230769 | AT13: =Output!AP5 -> 0.17094017 | AU13: =Output!AQ5 -> 9 | AV13: =Output!AR5 -> 4.0983607 | AX13: =Output!AT5 -> 10.637174 | AY13: =Output!AU5 -> 5.5737705 | BA13: =Output!AW5 -> 5.0359127 | BB13: =Output!AX5 -> n.a. | BD13: =Output!AZ5 -> n.a. | BE13: =Output!BA5 -> 8 | BF13: =Output!BB5 -> 2.7868852 | BG13: =Output!BC5 -> 0.20099649 | BH13: =Output!BD5 -> 3.442623 | BI13: =Output!BE5 -> 0.12262943 | BJ13: =Output!BF5 -> n.a. | BM13: Financials | BN13: =Output!BJ5 -> 4 | BO13: =Output!BK5 -> 0 | BP13: =Output!BL5 -> n.a. | BQ13: =Output!BM5 -> Positive | BR13: =Output!BN5 -> 0 | BU13: =Output!BQ5 -> 3 | BV13: =Output!BR5 -> 0 | BW13: =Output!BS5 -> n.a. | BX13: =Output!BT5 -> Positive | BY13: =Output!BU5 -> -0.029492517 | BZ13: =Output!BV5 -> -0.0043120766 | CC13: FTSE Europe | CD13: =Output!B19 -> -0.02518044
H14: HealthCare | I14: =Output!E6 -> 5 | J14: =Output!F6 -> 5.0819672 | L14: =Output!H6 -> 1.5089102 | M14: =Output!I6 -> 7.8688525 | O14: =Output!K6 -> 28.807423 | P14: =Output!L6 -> 1.9672131 | R14: =Output!N6 -> 66.839496 | S14: =Output!O6 -> 1 | T14: =Output!P6 -> 9.4262295 | V14: =Output!R6 -> 23.281359 | W14: =Output!S6 -> 7.8940731 | Y14: =Output!U6 -> 16.548002 | Z14: =Output!V6 -> 9.2307692 | AB14: =Output!X6 -> 31.620939 | AC14: =Output!Y6 -> 3 | AD14: =Output!Z6 -> 8.3606557 | AF14: =Output!AB6 -> 12.337819 | AG14: =Output!AC6 -> 8.852459 | AI14: =Output!AE6 -> 10.802642 | AJ14: =Output!AF6 -> 9.5081967 | AL14: =Output!AH6 -> 2.9853111 | AM14: =Output!AI6 -> 7 | AN14: =Output!AJ6 -> 3.8461538 | AO14: =Output!AK6 -> 0.024259956 | AP14: =Output!AL6 -> 4.6153846 | AQ14: =Output!AM6 -> 0.1062622 | AR14: =Output!AN6 -> 8.4615385 | AT14: =Output!AP6 -> 0.35555556 | AU14: =Output!AQ6 -> 10 | AV14: =Output!AR6 -> 3.9344262 | AX14: =Output!AT6 -> 8.06437 | AY14: =Output!AU6 -> 3.7704918 | BA14: =Output!AW6 -> 5.4978133 | BB14: =Output!AX6 -> 3.6065574 | BD14: =Output!AZ6 -> 7.6618302 | BE14: =Output!BA6 -> 3 | BF14: =Output!BB6 -> 8.0327869 | BG14: =Output!BC6 -> 0.12836426 | BH14: =Output!BD6 -> 7.3770492 | BI14: =Output!BE6 -> 0.085948425 | BJ14: =Output!BF6 -> 3 | BM14: HealthCare | BN14: =Output!BJ6 -> 6 | BO14: =Output!BK6 -> 0 | BP14: =Output!BL6 -> 9.4285714 | BQ14: =Output!BM6 -> Positive | BR14: =Output!BN6 -> 1 | BU14: =Output!BQ6 -> 2 | BV14: =Output!BR6 -> 0 | BW14: =Output!BS6 -> 8.5714286 | BX14: =Output!BT6 -> Neutral | BY14: =Output!BU6 -> -0.030060214 | BZ14: =Output!BV6 -> -0.0048797734
H15: Industrials | I15: =Output!E7 -> 3 | J15: =Output!F7 -> 4.2622951 | L15: =Output!H7 -> 1.6366061 | M15: =Output!I7 -> 10 | O15: =Output!K7 -> 22.892464 | P15: =Output!L7 -> 2.295082 | R15: =Output!N7 -> 85.294826 | S15: =Output!O7 -> 7 | T15: =Output!P7 -> 4.4892812 | V15: =Output!R7 -> 11.077253 | W15: =Output!S7 -> 5.3152585 | Y15: =Output!U7 -> 7.5557529 | Z15: =Output!V7 -> 5.2017654 | AB15: =Output!X7 -> 15.843936 | AC15: =Output!Y7 -> 10 | AD15: =Output!Z7 -> 1.3114754 | AF15: =Output!AB7 -> 13.814605 | AG15: =Output!AC7 -> 1.4754098 | AI15: =Output!AE7 -> 11.854577 | AJ15: =Output!AF7 -> 1.3114754 | AL15: =Output!AH7 -> 1.7658251 | AM15: =Output!AI7 -> 5 | AN15: =Output!AJ7 -> 6.9230769 | AO15: =Output!AK7 -> 0.13319026 | AP15: =Output!AL7 -> 5.3846154 | AQ15: =Output!AM7 -> 0.10708826 | AR15: =Output!AN7 -> 7.6923077 | AT15: =Output!AP7 -> 0.23478261 | AU15: =Output!AQ7 -> 2 | AV15: =Output!AR7 -> 6.7213115 | AX15: =Output!AT7 -> 16.132483 | AY15: =Output!AU7 -> 10 | BA15: =Output!AW7 -> 7.5180213 | BB15: =Output!AX7 -> 7.5409836 | BD15: =Output!AZ7 -> 10.381888 | BE15: =Output!BA7 -> 12 | BF15: =Output!BB7 -> 3.6065574 | BG15: =Output!BC7 -> 0.21927049 | BH15: =Output!BD7 -> 0.81967213 | BI15: =Output!BE7 -> 0.14291346 | BJ15: =Output!BF7 -> 6 | BM15: Industrials | BN15: =Output!BJ7 -> 3 | BO15: =Output!BK7 -> 1 | BP15: =Output!BL7 -> 7.5714286 | BQ15: =Output!BM7 -> Neutral | BR15: =Output!BN7 -> 0 | BU15: =Output!BQ7 -> 2 | BV15: =Output!BR7 -> 2 | BW15: =Output!BS7 -> 7.4285714 | BX15: =Output!BT7 -> Neutral | BY15: =Output!BU7 -> -0.037750141 | BZ15: =Output!BV7 -> -0.012569701
H16: Energy | I16: =Output!E8 -> 9 | J16: =Output!F8 -> 5.2459016 | L16: =Output!H8 -> 0.75166269 | M16: =Output!I8 -> 5.2459016 | O16: =Output!K8 -> 26.597811 | P16: =Output!L8 -> 1.9672131 | R16: =Output!N8 -> 62.418637 | S16: =Output!O8 -> 6 | T16: =Output!P8 -> 5.258512 | V16: =Output!R8 -> 12.707879 | W16: =Output!S8 -> 6.7339218 | Y16: =Output!U8 -> 7.516947 | Z16: =Output!V8 -> 5.4224464 | AB16: =Output!X8 -> 19.852902 | AC16: =Output!Y8 -> 13 | AD16: =Output!Z8 -> 0.32786885 | AF16: =Output!AB8 -> 5.34985 | AG16: =Output!AC8 -> 0.81967213 | AI16: =Output!AE8 -> 4.7964169 | AJ16: =Output!AF8 -> 0.6557377 | AL16: =Output!AH8 -> 0.87351089 | AM16: =Output!AI8 -> 4 | AN16: =Output!AJ8 -> 1.5384615 | AO16: =Output!AK8 -> -0.030101683 | AP16: =Output!AL8 -> 10 | AQ16: =Output!AM8 -> 0.41327662 | AR16: =Output!AN8 -> 10 | AT16: =Output!AP8 -> 0.77272727 | AU16: =Output!AQ8 -> 7 | AV16: =Output!AR8 -> 7.5409836 | AX16: =Output!AT8 -> 13.270838 | AY16: =Output!AU8 -> 1.8032787 | BA16: =Output!AW8 -> -0.3291555 | BB16: =Output!AX8 -> 7.0491803 | BD16: =Output!AZ8 -> 1.6743774 | BE16: =Output!BA8 -> 13 | BF16: =Output!BB8 -> 0.49180328 | BG16: =Output!BC8 -> 0.27017194 | BH16: =Output!BD8 -> 1.8032787 | BI16: =Output!BE8 -> 0.16184847 | BJ16: =Output!BF8 -> 11 | BM16: Energy | BN16: =Output!BJ8 -> 0 | BO16: =Output!BK8 -> 5 | BP16: =Output!BL8 -> 5 | BQ16: =Output!BM8 -> Negative | BR16: =Output!BN8 -> -2 | BU16: =Output!BQ8 -> 3 | BV16: =Output!BR8 -> 1 | BW16: =Output!BS8 -> 7.5714286 | BX16: =Output!BT8 -> Positive | BY16: =Output!BU8 -> 0.03336263 | BZ16: =Output!BV8 -> 0.05854307
H17: Tech | I17: =Output!E9 -> 8 | J17: =Output!F9 -> 5.0819672 | L17: =Output!H9 -> 0.43980775 | M17: =Output!I9 -> 7.3770492 | O17: =Output!K9 -> 51.01086 | P17: =Output!L9 -> 0.49180328 | R17: =Output!N9 -> 42.505912 | S17: =Output!O9 -> 2 | T17: =Output!P9 -> 8.8776797 | V17: =Output!R9 -> 23.063598 | W17: =Output!S9 -> 8.6065574 | Y17: =Output!U9 -> 21.193798 | Z17: =Output!V9 -> 8.3543506 | AB17: =Output!X9 -> 29.081963 | AC17: =Output!Y9 -> 5 | AD17: =Output!Z9 -> 8.1081081 | AF17: =Output!AB9 -> 21.186471 | AG17: =Output!AC9 -> 7.5675676 | AI17: =Output!AE9 -> 18.199697 | AJ17: =Output!AF9 -> 0.6557377 | AL17: =Output!AH9 -> 6.0528066 | AM17: =Output!AI9 -> 2 | AN17: =Output!AJ9 -> 10 | AO17: =Output!AK9 -> 0.32019032 | AP17: =Output!AL9 -> 7.6923077 | AQ17: =Output!AM9 -> 0.26770248 | AR17: =Output!AN9 -> 5.3846154 | AT17: =Output!AP9 -> -0.045454545 | AU17: =Output!AQ9 -> 1 | AV17: =Output!AR9 -> 8.1967213 | AX17: =Output!AT9 -> 27.448513 | AY17: =Output!AU9 -> 10 | BA17: =Output!AW9 -> 15.915395 | BB17: =Output!AX9 -> 9.6721311 | BD17: =Output!AZ9 -> 24.497585 | BE17: =Output!BA9 -> 10 | BF17: =Output!BB9 -> 0.81967213 | BG17: =Output!BC9 -> 0.32402071 | BH17: =Output!BD9 -> 4.4262295 | BI17: =Output!BE9 -> 0.12996419 | BJ17: =Output!BF9 -> 2 | BM17: Tech | BN17: =Output!BJ9 -> 5 | BO17: =Output!BK9 -> 0 | BP17: =Output!BL9 -> 9.7142857 | BQ17: =Output!BM9 -> Positive | BR17: =Output!BN9 -> 0 | BU17: =Output!BQ9 -> 6 | BV17: =Output!BR9 -> 0 | BW17: =Output!BS9 -> 9.8571429 | BX17: =Output!BT9 -> Positive | BY17: =Output!BU9 -> 0.04026688 | BZ17: =Output!BV9 -> 0.06544732
H18: Teleco | I18: =Output!E10 -> 7 | J18: =Output!F10 -> 6.2295082 | L18: =Output!H10 -> 2.6984758 | M18: =Output!I10 -> 6.2295082 | O18: =Output!K10 -> 14.772993 | P18: =Output!L10 -> 0.98360656 | R18: =Output!N10 -> 168.09143 | S18: =Output!O10 -> 4 | T18: =Output!P10 -> 6.8221942 | V18: =Output!R10 -> 15.845054 | W18: =Output!S10 -> 4.6532156 | Y18: =Output!U10 -> 6.9782061 | Z18: =Output!V10 -> 8.7137453 | AB18: =Output!X10 -> 36.809322 | AC18: =Output!Y10 -> 9 | AD18: =Output!Z10 -> 1.9672131 | AF18: =Output!AB10 -> 4.3402105 | AG18: =Output!AC10 -> 4.5901639 | AI18: =Output!AE10 -> 6.1657458 | AJ18: =Output!AF10 -> 3.2786885 | AL18: =Output!AH10 -> 1.1898465 | AM18: =Output!AI10 -> 10 | AN18: =Output!AJ10 -> 0.76923077 | AO18: =Output!AK10 -> -0.037905638 | AP18: =Output!AL10 -> 6.1538462 | AQ18: =Output!AM10 -> 0.1327567 | AR18: =Output!AN10 -> 4.6153846 | AT18: =Output!AP10 -> -0.090909091 | AU18: =Output!AQ10 -> 7 | AV18: =Output!AR10 -> 2.7868852 | AX18: =Output!AT10 -> 11.467269 | AY18: =Output!AU10 -> 8.0327869 | BA18: =Output!AW10 -> 4.1123275 | BB18: =Output!AX10 -> 5.5737705 | BD18: =Output!AZ10 -> 7.9311492 | BE18: =Output!BA10 -> 6 | BF18: =Output!BB10 -> 4.4262295 | BG18: =Output!BC10 -> 0.17849265 | BH18: =Output!BD10 -> 5.5737705 | BI18: =Output!BE10 -> 0.093612562 | BJ18: =Output!BF10 -> 8 | BM18: Teleco | BN18: =Output!BJ10 -> 0 | BO18: =Output!BK10 -> 0 | BP18: =Output!BL10 -> 6.7142857 | BQ18: =Output!BM10 -> Neutral | BR18: =Output!BN10 -> 0 | BU18: =Output!BQ10 -> 0 | BV18: =Output!BR10 -> 1 | BW18: =Output!BS10 -> 5.7142857 | BX18: =Output!BT10 -> Neutral | BY18: =Output!BU10 -> -0.050840092 | BZ18: =Output!BV10 -> -0.025659652
H19: Utilities | I19: =Output!E11 -> 11 | J19: =Output!F11 -> 2.7868852 | L19: =Output!H11 -> 3.8202383 | M19: =Output!I11 -> 2.4590164 | O19: =Output!K11 -> -0.77896414 | P19: =Output!L11 -> 3.6065574 | R19: =Output!N11 -> 161.16847 | S19: =Output!O11 -> 5 | T19: =Output!P11 -> 6.2736444 | V19: =Output!R11 -> 15.274553 | W19: =Output!S11 -> 6.519546 | Y19: =Output!U11 -> 9.3596083 | Z19: =Output!V11 -> 7.3392182 | AB19: =Output!X11 -> 24.749056 | AC19: =Output!Y11 -> 12 | AD19: =Output!Z11 -> 0.6557377 | AF19: =Output!AB11 -> 7.0686782 | AG19: =Output!AC11 -> 0.6557377 | AI19: =Output!AE11 -> 9.2075184 | AJ19: =Output!AF11 -> 0.6557377 | AL19: =Output!AH11 -> 1.3786408 | AM19: =Output!AI11 -> 6 | AN19: =Output!AJ11 -> 2.3076923 | AO19: =Output!AK11 -> -0.008192229 | AP19: =Output!AL11 -> 6.9230769 | AQ19: =Output!AM11 -> 0.22574507 | AR19: =Output!AN11 -> 9.2307692 | AT19: =Output!AP11 -> 0.4 | AU19: =Output!AQ11 -> 3 | AV19: =Output!AR11 -> 6.7213115 | AX19: =Output!AT11 -> 8.8611013 | AY19: =Output!AU11 -> 8.3606557 | BA19: =Output!AW11 -> 3.7008948 | BB19: =Output!AX11 -> 8.852459 | BD19: =Output!AZ11 -> 7.5169853 | BE19: =Output!BA11 -> 1 | BF19: =Output!BB11 -> 9.8360656 | BG19: =Output!BC11 -> 0.1232486 | BH19: =Output!BD11 -> 9.8360656 | BI19: =Output!BE11 -> 0.045158298 | BJ19: =Output!BF11 -> 4 | BM19: Utilities | BN19: =Output!BJ11 -> 2 | BO19: =Output!BK11 -> 4 | BP19: =Output!BL11 -> 8 | BQ19: =Output!BM11 -> Neutral | BR19: =Output!BN11 -> 0 | BU19: =Output!BQ11 -> 1 | BV19: =Output!BR11 -> 2 | BW19: =Output!BS11 -> 8.1428571 | BX19: =Output!BT11 -> Neutral | BY19: =Output!BU11 -> -0.01670002 | BZ19: =Output!BV11 -> 0.0084804198
H20: Travel & leisure | I20: =Output!E12 -> 6 | J20: =Output!F12 -> 7.5409836 | L20: =Output!H12 -> 2.270226 | M20: =Output!I12 -> 2.1311475 | O20: =Output!K12 -> 12.530214 | P20: =Output!L12 -> 4.5901639 | R20: =Output!N12 -> 140.78828 | S20: =Output!O12 -> 11 | T20: =Output!P12 -> 3.4489281 | V20: =Output!R12 -> 8.6825696 | W20: =Output!S12 -> 3.6948298 | Y20: =Output!U12 -> 6.9651861 | Z20: =Output!V12 -> 2.7931904 | AB20: =Output!X12 -> 15.6113 | AC20: =Output!Y12 -> 7 | AD20: =Output!Z12 -> 7.0491803 | AF20: =Output!AB12 -> 6.4467161 | AG20: =Output!AC12 -> 7.0491803 | AI20: =Output!AE12 -> 6.9236286 | AJ20: =Output!AF12 -> 8.5245902 | AL20: =Output!AH12 -> 0.86422859 | AM20: =Output!AI12 -> 8 | AN20: =Output!AJ12 -> 7.6923077 | AO20: =Output!AK12 -> 0.153393 | AP20: =Output!AL12 -> 3.0769231 | AQ20: =Output!AM12 -> 0.01906116 | AR20: =Output!AN12 -> 3.0769231 | AT20: =Output!AP12 -> -0.15384615 | AU20: =Output!AQ12 -> 13 | AV20: =Output!AR12 -> 2.295082 | AX20: =Output!AT12 -> 11.405847 | AY20: =Output!AU12 -> 0.49180328 | BA20: =Output!AW12 -> 5.2466352 | BB20: =Output!AX12 -> 1.6393443 | BD20: =Output!AZ12 -> 8.7677295 | BE20: =Output!BA12 -> 4 | BF20: =Output!BB12 -> 5.5737705 | BG20: =Output!BC12 -> 0.23539098 | BH20: =Output!BD12 -> 6.3934426 | BI20: =Output!BE12 -> 0.16722511 | BJ20: =Output!BF12 -> 10 | BM20: Travel & leisure | BN20: =Output!BJ12 -> 0 | BO20: =Output!BK12 -> 0 | BP20: =Output!BL12 -> 5.5714286 | BQ20: =Output!BM12 -> Neutral | BR20: =Output!BN12 -> 0 | BU20: =Output!BQ12 -> 0 | BV20: =Output!BR12 -> 0 | BW20: =Output!BS12 -> 4.4285714 | BX20: =Output!BT12 -> Neutral | BY20: =Output!BU12 -> -0.019294953 | BZ20: =Output!BV12 -> 0.0058854876
H21: Media | I21: =Output!E13 -> 1 | J21: =Output!F13 -> 5.7377049 | L21: =Output!H13 -> 1.3799431 | M21: =Output!I13 -> 9.0163934 | O21: =Output!K13 -> 36.153504 | P21: =Output!L13 -> 8.852459 | R21: =Output!N13 -> 52.438497 | S21: =Output!O13 -> 9 | T21: =Output!P13 -> 4.0037831 | V21: =Output!R13 -> 14.746342 | W21: =Output!S13 -> 5.3467844 | Y21: =Output!U13 -> 10.100818 | Z21: =Output!V13 -> 4.0037831 | AB21: =Output!X13 -> 21.01695 | AC21: =Output!Y13 -> 4 | AD21: =Output!Z13 -> 9.1803279 | AF21: =Output!AB13 -> 10.431807 | AG21: =Output!AC13 -> 8.5245902 | AI21: =Output!AE13 -> 9.1977671 | AJ21: =Output!AF13 -> 9.0163934 | AL21: =Output!AH13 -> 1.7470843 | AM21: =Output!AI13 -> 11 | AN21: =Output!AJ13 -> 8.4615385 | AO21: =Output!AK13 -> 0.17405353 | AP21: =Output!AL13 -> 1.5384615 | AQ21: =Output!AM13 -> -0.077522896 | AR21: =Output!AN13 -> 0.76923077 | AT21: =Output!AP13 -> -0.57142857 | AU21: =Output!AQ13 -> 8 | AV21: =Output!AR13 -> 3.9344262 | AX21: =Output!AT13 -> 9.433947 | AY21: =Output!AU13 -> 7.0491803 | BA21: =Output!AW13 -> 6.5215206 | BB21: =Output!AX13 -> 4.4262295 | BD21: =Output!AZ13 -> 8.0313612 | BE21: =Output!BA13 -> 6 | BF21: =Output!BB13 -> 1.6393443 | BG21: =Output!BC13 -> 0.21917602 | BH21: =Output!BD13 -> 8.3606557 | BI21: =Output!BE13 -> 0.085880967 | BJ21: =Output!BF13 -> 6 | BM21: Media | BN21: =Output!BJ13 -> 2 | BO21: =Output!BK13 -> 1 | BP21: =Output!BL13 -> 7.5714286 | BQ21: =Output!BM13 -> Neutral | BR21: =Output!BN13 -> 0 | BU21: =Output!BQ13 -> 1 | BV21: =Output!BR13 -> 1 | BW21: =Output!BS13 -> 7.1428571 | BX21: =Output!BT13 -> Neutral | BY21: =Output!BU13 -> -0.044827494 | BZ21: =Output!BV13 -> -0.019647054
H22: Automobile | I22: =Output!E14 -> 13 | J22: =Output!F14 -> 0.32786885 | L22: =Output!H14 -> 5.6573717 | M22: =Output!I14 -> 0.49180328 | O22: =Output!K14 -> 0.019678022 | P22: =Output!L14 -> 0.6557377 | R22: =Output!N14 -> 135.79482 | S22: =Output!O14 -> 13 | T22: =Output!P14 -> 0.54854981 | V22: =Output!R14 -> 2.5611904 | W22: =Output!S14 -> 1.0403531 | Y22: =Output!U14 -> 1.0105513 | Z22: =Output!V14 -> 0.95838588 | AB22: =Output!X14 -> 9.9166825 | AC22: =Output!Y14 -> 8 | AD22: =Output!Z14 -> 4.5901639 | AF22: =Output!AB14 -> 3.199751 | AG22: =Output!AC14 -> 0.16393443 | AI22: =Output!AE14 -> 7.3237932 | AJ22: =Output!AF14 -> 9.1803279 | AL22: =Output!AH14 -> 0.30671046 | AM22: =Output!AI14 -> 13 | AN22: =Output!AJ14 -> 3.0769231 | AO22: =Output!AK14 -> 0.0015710487 | AP22: =Output!AL14 -> 0.76923077 | AQ22: =Output!AM14 -> -0.12051359 | AR22: =Output!AN14 -> 1.5384615 | AT22: =Output!AP14 -> -0.46666667 | AU22: =Output!AQ14 -> 5 | AV22: =Output!AR14 -> 8.0327869 | AX22: =Output!AT14 -> 64.431376 | AY22: =Output!AU14 -> 1.4754098 | BA22: =Output!AW14 -> 1.9925869 | BB22: =Output!AX14 -> 7.8688525 | BD22: =Output!AZ14 -> 12.445815 | BE22: =Output!BA14 -> 9 | BF22: =Output!BB14 -> 3.6065574 | BG22: =Output!BC14 -> 0.25969496 | BH22: =Output!BD14 -> 2.295082 | BI22: =Output!BE14 -> 0.14671131 | BJ22: =Output!BF14 -> 13 | BM22: Automobile | BN22: =Output!BJ14 -> 0 | BO22: =Output!BK14 -> 6 | BP22: =Output!BL14 -> 3.4285714 | BQ22: =Output!BM14 -> Negative | BR22: =Output!BN14 -> 0 | BU22: =Output!BQ14 -> 0 | BV22: =Output!BR14 -> 5 | BW22: =Output!BS14 -> 3.7142857 | BX22: =Output!BT14 -> Negative | BY22: =Output!BU14 -> -0.089917315 | BZ22: =Output!BV14 -> -0.064736875
H26: =TEXT(Output!B2,"[$-040C]mmm-yyyy")&" Commentaire : " -> sept.-2026 Commentaire :

Sheet Output
A1: Marché | B1: EU | D1: Secteur | E1: Leverage | F1: Score net debt ebitda | H1: net debt ebitda | I1: Score fcf total debt | K1: fcf total debt | L1: Score debt equity | N1: debt equity | O1: Margin | P1: Score operating margin | R1: operating margin | S1: Score net margin | U1: net margin | V1: Score ebitda margin | X1: ebitda margin | Y1: Value | Z1: Score price fcf | AB1: price fcf | AC1: Score ev ebitda | AE1: ev ebitda | AF1: Score price sales | AH1: price sales | AI1: Momentum | AJ1: Score momentum 6m 1m | AK1: momentum 6m 1m | AL1: Score momentum 12m 1m | AM1: momentum 12m 1m | AN1: Score earnings revision ratio | AP1: earnings revision ratio | AQ1: Growth | AR1: Score eps growth | AT1: eps growth | AU1: Score sales growth | AW1: sales growth | AX1: Score ebitda growth | AZ1: ebitda growth | BA1: Volatility | BB1: Score volatility 6m | BC1: volatility 6m | BD1: Score downside volatility 18m | BE1: downside volatility 18m | BF1: Macro | BI1: Secteur | BJ1: Votes Top | BK1: Votes Worst | BL1: Score global | BM1: Reco | BN1: Variation reco | BQ1: Votes Top précédents | BR1: Votes Worst précédents | BS1: Score précédent | BT1: Reco précédente | BU1: Sept-2026 EQ Performance | BV1: Sept-2026 XSRet vs FTSE World Europe
A2: Date modèle | B2: 46295 | D2: Materials | E2: 12 | F2: 3.9344262 | H2: 1.5176704 | I2: 0.6557377 | K2: 10.980834 | L2: 0.6557377 | N2: 57.789196 | O2: 10 | P2: 3.3102144 | R2: 8.6551612 | S2: 3.8020177 | U2: 6.0453761 | V2: 2.9003783 | X2: 13.757778 | Y2: 11 | Z2: 0.32786885 | AB2: 8.9422186 | AC2: 0.49180328 | AE2: 7.7631122 | AF2: 1.8032787 | AH2: 1.0583207 | AI2: 4 | AJ2: 6.1538462 | AK2: 0.13038207 | AL2: 9.2307692 | AM2: 0.33963863 | AN2: 6.1538462 | AP2: 0.057142857 | AQ2: 4 | AR2: 5.7377049 | AT2: 18.168167 | AU2: 8.5245902 | AW2: 3.7950325 | AX2: 6.7213115 | AZ2: 10.282517 | BA2: 2 | BB2: 7.3770492 | BC2: 0.18247089 | BD2: 9.3442623 | BE2: 0.062962012 | BF2: 8 | BI2: Materials | BJ2: 1 | BK2: 4 | BL2: 6.7142857 | BM2: Neutral | BN2: 0 | BQ2: 2 | BR2: 3 | BS2: 6.7142857 | BT2: Neutral | BU2: -0.043807237 | BV2: -0.018626796
A3: Derniers piliers | B3: 46295 | D3: ConsStaples | E3: 10 | F3: 4.2622951 | H3: 2.57611 | I3: 7.3770492 | K3: 17.981573 | L3: 0.32786885 | N3: 115.95281 | O3: 12 | P3: 2.9886507 | R3: 11.498439 | S3: 3.3165195 | U3: 7.318707 | V3: 3.3417402 | X3: 15.836251 | Y3: 6 | Z3: 6.7213115 | AB3: 10.04444 | AC3: 7.3770492 | AE3: 9.7333979 | AF3: 9.1803279 | AH3: 1.1770891 | AI3: 9 | AJ3: 4.6153846 | AK3: 0.02999415 | AL3: 3.8461538 | AM3: 0.042321296 | AN3: 3.8461538 | AP3: -0.11363636 | AQ3: 11 | AR3: 3.9344262 | AT3: 6.9131176 | AU3: 2.9508197 | AW3: 3.6888091 | AX3: 3.442623 | AZ3: 4.8960757 | BA3: 12 | BB3: 3.2786885 | BC3: 0.18050462 | BD3: 1.147541 | BE3: 0.11597345 | BF3: 12 | BI3: ConsStaples | BJ3: 0 | BK3: 5 | BL3: 3.7142857 | BM3: Negative | BN3: 0 | BQ3: 0 | BR3: 3 | BS3: 4.1428571 | BT3: Negative | BU3: -0.032147216 | BV3: -0.0069667762
A4: Allocation | B4: 46296 | D4: Pers. Goods | E4: 4 | F4: 4.9180328 | H4: 0.73907005 | I4: 7.2131148 | K4: 33.20084 | L4: 3.6065574 | N4: 58.519142 | O4: 8 | P4: 4.4766709 | R4: 18.044296 | S4: 4.9117276 | U4: 11.481202 | V4: 4.8549811 | X4: 25.277612 | Y4: 2 | Z4: 10 | AB4: 14.473667 | AC4: 10 | AE4: 11.329662 | AF4: 10 | AH4: 2.7591781 | AI4: 12 | AJ4: 5.3846154 | AK4: 0.09934833 | AL4: 2.3076923 | AM4: -0.026194227 | AN4: 2.3076923 | AP4: -0.38461538 | AQ4: 12 | AR4: 3.7704918 | AT4: 13.004314 | AU4: 2.1311475 | AW4: 6.0954359 | AX4: 2.6229508 | AZ4: 7.7301313 | BA4: 7 | BB4: 5.4098361 | BC4: 0.25442201 | BD4: 2.1311475 | BE4: 0.18750445 | BF4: 9 | BI4: Pers. Goods | BJ4: 2 | BK4: 2 | BL4: 6.2857143 | BM4: Neutral | BN4: 1 | BQ4: 1 | BR4: 4 | BS4: 6.2857143 | BT4: Negative | BU4: -0.079729636 | BV4: -0.054549195
A5: Cycle | B5: E | D5: Fin | E5: 2 | F5: 7.0491803 | H5: 10.11696 | I5: 3.1147541 | K5: 2.8015014 | L5: 8.6885246 | N5: 417.95205 | O5: 3 | P5: 7.7805801 | R5: 17.486197 | S5: 8.6569987 | U5: 12.648923 | V5: 7.0491803 | X5: 51.665548 | Y5: n.a. | Z5: n.a. | AB5: n.a. | AC5: n.a. | AE5: n.a. | AF5: 0.32786885 | AH5: 2.1662574 | AI5: 1 | AJ5: 9.2307692 | AK5: 0.23881973 | AL5: 8.4615385 | AM5: 0.2750319 | AN5: 6.9230769 | AP5: 0.17094017 | AQ5: 9 | AR5: 4.0983607 | AT5: 10.637174 | AU5: 5.5737705 | AW5: 5.0359127 | AX5: n.a. | AZ5: n.a. | BA5: 8 | BB5: 2.7868852 | BC5: 0.20099649 | BD5: 3.442623 | BE5: 0.12262943 | BF5: n.a. | BI5: Fin | BJ5: 4 | BK5: 0 | BL5: n.a. | BM5: Positive | BN5: 0 | BQ5: 3 | BR5: 0 | BS5: n.a. | BT5: Positive | BU5: -0.029492517 | BV5: -0.0043120766
A6: Signal taux | B6: On | D6: HealthCare | E6: 5 | F6: 5.0819672 | H6: 1.5089102 | I6: 7.8688525 | K6: 28.807423 | L6: 1.9672131 | N6: 66.839496 | O6: 1 | P6: 9.4262295 | R6: 23.281359 | S6: 7.8940731 | U6: 16.548002 | V6: 9.2307692 | X6: 31.620939 | Y6: 3 | Z6: 8.3606557 | AB6: 12.337819 | AC6: 8.852459 | AE6: 10.802642 | AF6: 9.5081967 | AH6: 2.9853111 | AI6: 7 | AJ6: 3.8461538 | AK6: 0.024259956 | AL6: 4.6153846 | AM6: 0.1062622 | AN6: 8.4615385 | AP6: 0.35555556 | AQ6: 10 | AR6: 3.9344262 | AT6: 8.06437 | AU6: 3.7704918 | AW6: 5.4978133 | AX6: 3.6065574 | AZ6: 7.6618302 | BA6: 3 | BB6: 8.0327869 | BC6: 0.12836426 | BD6: 7.3770492 | BE6: 0.085948425 | BF6: 3 | BI6: HealthCare | BJ6: 6 | BK6: 0 | BL6: 9.4285714 | BM6: Positive | BN6: 1 | BQ6: 2 | BR6: 0 | BS6: 8.5714286 | BT6: Neutral | BU6: -0.030060214 | BV6: -0.0048797734
A7: Derniers poids benchmark | B7: 46326 | D7: Indus | E7: 3 | F7: 4.2622951 | H7: 1.6366061 | I7: 10 | K7: 22.892464 | L7: 2.295082 | N7: 85.294826 | O7: 7 | P7: 4.4892812 | R7: 11.077253 | S7: 5.3152585 | U7: 7.5557529 | V7: 5.2017654 | X7: 15.843936 | Y7: 10 | Z7: 1.3114754 | AB7: 13.814605 | AC7: 1.4754098 | AE7: 11.854577 | AF7: 1.3114754 | AH7: 1.7658251 | AI7: 5 | AJ7: 6.9230769 | AK7: 0.13319026 | AL7: 5.3846154 | AM7: 0.10708826 | AN7: 7.6923077 | AP7: 0.23478261 | AQ7: 2 | AR7: 6.7213115 | AT7: 16.132483 | AU7: 10 | AW7: 7.5180213 | AX7: 7.5409836 | AZ7: 10.381888 | BA7: 12 | BB7: 3.6065574 | BC7: 0.21927049 | BD7: 0.81967213 | BE7: 0.14291346 | BF7: 6 | BI7: Indus | BJ7: 3 | BK7: 1 | BL7: 7.5714286 | BM7: Neutral | BN7: 0 | BQ7: 2 | BR7: 2 | BS7: 7.4285714 | BT7: Neutral | BU7: -0.037750141 | BV7: -0.012569701
A8: Derniers rendements | B8: 46295 | D8: Oil | E8: 9 | F8: 5.2459016 | H8: 0.75166269 | I8: 5.2459016 | K8: 26.597811 | L8: 1.9672131 | N8: 62.418637 | O8: 6 | P8: 5.258512 | R8: 12.707879 | S8: 6.7339218 | U8: 7.516947 | V8: 5.4224464 | X8: 19.852902 | Y8: 13 | Z8: 0.32786885 | AB8: 5.34985 | AC8: 0.81967213 | AE8: 4.7964169 | AF8: 0.6557377 | AH8: 0.87351089 | AI8: 4 | AJ8: 1.5384615 | AK8: -0.030101683 | AL8: 10 | AM8: 0.41327662 | AN8: 10 | AP8: 0.77272727 | AQ8: 7 | AR8: 7.5409836 | AT8: 13.270838 | AU8: 1.8032787 | AW8: -0.3291555 | AX8: 7.0491803 | AZ8: 1.6743774 | BA8: 13 | BB8: 0.49180328 | BC8: 0.27017194 | BD8: 1.8032787 | BE8: 0.16184847 | BF8: 11 | BI8: Oil | BJ8: 0 | BK8: 5 | BL8: 5 | BM8: Negative | BN8: -2 | BQ8: 3 | BR8: 1 | BS8: 7.5714286 | BT8: Positive | BU8: 0.03336263 | BV8: 0.05854307
A9: Mois allocation | B9: 46296 | D9: Tech | E9: 8 | F9: 5.0819672 | H9: 0.43980775 | I9: 7.3770492 | K9: 51.01086 | L9: 0.49180328 | N9: 42.505912 | O9: 2 | P9: 8.8776797 | R9: 23.063598 | S9: 8.6065574 | U9: 21.193798 | V9: 8.3543506 | X9: 29.081963 | Y9: 5 | Z9: 8.1081081 | AB9: 21.186471 | AC9: 7.5675676 | AE9: 18.199697 | AF9: 0.6557377 | AH9: 6.0528066 | AI9: 2 | AJ9: 10 | AK9: 0.32019032 | AL9: 7.6923077 | AM9: 0.26770248 | AN9: 5.3846154 | AP9: -0.045454545 | AQ9: 1 | AR9: 8.1967213 | AT9: 27.448513 | AU9: 10 | AW9: 15.915395 | AX9: 9.6721311 | AZ9: 24.497585 | BA9: 10 | BB9: 0.81967213 | BC9: 0.32402071 | BD9: 4.4262295 | BE9: 0.12996419 | BF9: 2 | BI9: Tech | BJ9: 5 | BK9: 0 | BL9: 9.7142857 | BM9: Positive | BN9: 0 | BQ9: 6 | BR9: 0 | BS9: 9.8571429 | BT9: Positive | BU9: 0.04026688 | BV9: 0.06544732
A10: Mois signal | B10: 46266 | D10: Telco | E10: 7 | F10: 6.2295082 | H10: 2.6984758 | I10: 6.2295082 | K10: 14.772993 | L10: 0.98360656 | N10: 168.09143 | O10: 4 | P10: 6.8221942 | R10: 15.845054 | S10: 4.6532156 | U10: 6.9782061 | V10: 8.7137453 | X10: 36.809322 | Y10: 9 | Z10: 1.9672131 | AB10: 4.3402105 | AC10: 4.5901639 | AE10: 6.1657458 | AF10: 3.2786885 | AH10: 1.1898465 | AI10: 10 | AJ10: 0.76923077 | AK10: -0.037905638 | AL10: 6.1538462 | AM10: 0.1327567 | AN10: 4.6153846 | AP10: -0.090909091 | AQ10: 7 | AR10: 2.7868852 | AT10: 11.467269 | AU10: 8.0327869 | AW10: 4.1123275 | AX10: 5.5737705 | AZ10: 7.9311492 | BA10: 6 | BB10: 4.4262295 | BC10: 0.17849265 | BD10: 5.5737705 | BE10: 0.093612562 | BF10: 8 | BI10: Telco | BJ10: 0 | BK10: 0 | BL10: 6.7142857 | BM10: Neutral | BN10: 0 | BQ10: 0 | BR10: 1 | BS10: 5.7142857 | BT10: Neutral | BU10: -0.050840092 | BV10: -0.025659652
A11: Classement courant | B11: Sectors Ranking Oct-2026 | D11: Utili | E11: 11 | F11: 2.7868852 | H11: 3.8202383 | I11: 2.4590164 | K11: -0.77896414 | L11: 3.6065574 | N11: 161.16847 | O11: 5 | P11: 6.2736444 | R11: 15.274553 | S11: 6.519546 | U11: 9.3596083 | V11: 7.3392182 | X11: 24.749056 | Y11: 12 | Z11: 0.6557377 | AB11: 7.0686782 | AC11: 0.6557377 | AE11: 9.2075184 | AF11: 0.6557377 | AH11: 1.3786408 | AI11: 6 | AJ11: 2.3076923 | AK11: -0.008192229 | AL11: 6.9230769 | AM11: 0.22574507 | AN11: 9.2307692 | AP11: 0.4 | AQ11: 3 | AR11: 6.7213115 | AT11: 8.8611013 | AU11: 8.3606557 | AW11: 3.7008948 | AX11: 8.852459 | AZ11: 7.5169853 | BA11: 1 | BB11: 9.8360656 | BC11: 0.1232486 | BD11: 9.8360656 | BE11: 0.045158298 | BF11: 4 | BI11: Utili | BJ11: 2 | BK11: 4 | BL11: 8 | BM11: Neutral | BN11: 0 | BQ11: 1 | BR11: 2 | BS11: 8.1428571 | BT11: Neutral | BU11: -0.01670002 | BV11: 0.0084804198
A12: Classement précédent | B12: Sectors Ranking Sept-2026 | D12: Travel & leisure | E12: 6 | F12: 7.5409836 | H12: 2.270226 | I12: 2.1311475 | K12: 12.530214 | L12: 4.5901639 | N12: 140.78828 | O12: 11 | P12: 3.4489281 | R12: 8.6825696 | S12: 3.6948298 | U12: 6.9651861 | V12: 2.7931904 | X12: 15.6113 | Y12: 7 | Z12: 7.0491803 | AB12: 6.4467161 | AC12: 7.0491803 | AE12: 6.9236286 | AF12: 8.5245902 | AH12: 0.86422859 | AI12: 8 | AJ12: 7.6923077 | AK12: 0.153393 | AL12: 3.0769231 | AM12: 0.01906116 | AN12: 3.0769231 | AP12: -0.15384615 | AQ12: 13 | AR12: 2.295082 | AT12: 11.405847 | AU12: 0.49180328 | AW12: 5.2466352 | AX12: 1.6393443 | AZ12: 8.7677295 | BA12: 4 | BB12: 5.5737705 | BC12: 0.23539098 | BD12: 6.3934426 | BE12: 0.16722511 | BF12: 10 | BI12: Travel & leisure | BJ12: 0 | BK12: 0 | BL12: 5.5714286 | BM12: Neutral | BN12: 0 | BQ12: 0 | BR12: 0 | BS12: 4.4285714 | BT12: Neutral | BU12: -0.019294953 | BV12: 0.0058854876
A13: Classement macro | B13: Macro rank - Currently in Expansion | D13: Media | E13: 1 | F13: 5.7377049 | H13: 1.3799431 | I13: 9.0163934 | K13: 36.153504 | L13: 8.852459 | N13: 52.438497 | O13: 9 | P13: 4.0037831 | R13: 14.746342 | S13: 5.3467844 | U13: 10.100818 | V13: 4.0037831 | X13: 21.01695 | Y13: 4 | Z13: 9.1803279 | AB13: 10.431807 | AC13: 8.5245902 | AE13: 9.1977671 | AF13: 9.0163934 | AH13: 1.7470843 | AI13: 11 | AJ13: 8.4615385 | AK13: 0.17405353 | AL13: 1.5384615 | AM13: -0.077522896 | AN13: 0.76923077 | AP13: -0.57142857 | AQ13: 8 | AR13: 3.9344262 | AT13: 9.433947 | AU13: 7.0491803 | AW13: 6.5215206 | AX13: 4.4262295 | AZ13: 8.0313612 | BA13: 6 | BB13: 1.6393443 | BC13: 0.21917602 | BD13: 8.3606557 | BE13: 0.085880967 | BF13: 6 | BI13: Media | BJ13: 2 | BK13: 1 | BL13: 7.5714286 | BM13: Neutral | BN13: 0 | BQ13: 1 | BR13: 1 | BS13: 7.1428571 | BT13: Neutral | BU13: -0.044827494 | BV13: -0.019647054
A14: Référence | B14: Bench | D14: Auto | E14: 13 | F14: 0.32786885 | H14: 5.6573717 | I14: 0.49180328 | K14: 0.019678022 | L14: 0.6557377 | N14: 135.79482 | O14: 13 | P14: 0.54854981 | R14: 2.5611904 | S14: 1.0403531 | U14: 1.0105513 | V14: 0.95838588 | X14: 9.9166825 | Y14: 8 | Z14: 4.5901639 | AB14: 3.199751 | AC14: 0.16393443 | AE14: 7.3237932 | AF14: 9.1803279 | AH14: 0.30671046 | AI14: 13 | AJ14: 3.0769231 | AK14: 0.0015710487 | AL14: 0.76923077 | AM14: -0.12051359 | AN14: 1.5384615 | AP14: -0.46666667 | AQ14: 5 | AR14: 8.0327869 | AT14: 64.431376 | AU14: 1.4754098 | AW14: 1.9925869 | AX14: 7.8688525 | AZ14: 12.445815 | BA14: 9 | BB14: 3.6065574 | BC14: 0.25969496 | BD14: 2.295082 | BE14: 0.14671131 | BF14: 13 | BI14: Auto | BJ14: 0 | BK14: 6 | BL14: 3.4285714 | BM14: Negative | BN14: 0 | BQ14: 0 | BR14: 5 | BS14: 3.7142857 | BT14: Negative | BU14: -0.089917315 | BV14: -0.064736875
A15: Top | B15: 0.014712331
A16: Short | B16: 0.067264722
A17: Long / Short | B17: 0.081977053
A18: Portefeuille | B18: -0.015123767
A19: Benchmark | B19: -0.02518044
D22: EU Reco | E22: 45870 | F22: 45901 | G22: 45931 | H22: 45962 | I22: 45992 | J22: 46023 | K22: 46054 | L22: 46082 | M22: 46113 | N22: 46143 | O22: 46174 | P22: 46204 | Q22: 46235 | R22: 46266 | S22: 46296 | W22: Europe equity sectors Performance
D23: Materials | E23: 0 | F23: -1 | G23: -1 | H23: -1 | I23: -1 | J23: 0 | K23: 0 | L23: 0 | M23: 0 | N23: 1 | O23: 0 | P23: 1 | Q23: -1 | R23: 0 | S23: 0 | W23: Materials | X23: ConsStaples | Y23: Pers. Goods | Z23: Fin | AA23: HealthCare | AB23: Indus | AC23: Oil | AD23: Tech | AE23: Telco | AF23: Utili | AG23: Travel & leisure | AH23: Media | AI23: Auto
D24: ConsStaples | E24: 0 | F24: -1 | G24: -1 | H24: -1 | I24: -1 | J24: -1 | K24: -1 | L24: -1 | M24: -1 | N24: -1 | O24: -1 | P24: -1 | Q24: -1 | R24: -1 | S24: -1 | V24: 1M | W24: -0.043807237 | X24: -0.032147216 | Y24: -0.079729636 | Z24: -0.029492517 | AA24: -0.030060214 | AB24: -0.037750141 | AC24: 0.03336263 | AD24: 0.04026688 | AE24: -0.050840092 | AF24: -0.01670002 | AG24: -0.019294953 | AH24: -0.044827494 | AI24: -0.089917315
D25: Pers. Goods | E25: -1 | F25: 0 | G25: -1 | H25: 0 | I25: 0 | J25: -1 | K25: -1 | L25: -1 | M25: -1 | N25: -1 | O25: -1 | P25: -1 | Q25: 0 | R25: -1 | S25: 0 | V25: 3M | W25: 0.0427452 | X25: -0.048685946 | Y25: -0.09940537 | Z25: 0.036457237 | AA25: -0.051903929 | AB25: -0.028227302 | AC25: 0.13910881 | AD25: -0.026489059 | AE25: -0.048274053 | AF25: -0.045405094 | AG25: -0.063303054 | AH25: -0.026007204 | AI25: -0.026321971
D26: Fin | E26: 1 | F26: 1 | G26: 1 | H26: 1 | I26: 1 | J26: 1 | K26: 1 | L26: 1 | M26: 0 | N26: 0 | O26: 0 | P26: 0 | Q26: 0 | R26: 1 | S26: 1 | V26: YTD | W26: 0.22073486 | X26: -0.0001503357 | Y26: -0.17485053 | Z26: 0.16749572 | AA26: -0.010645471 | AB26: 0.070164104 | AC26: 0.39359227 | AD26: 0.28613537 | AE26: 0.087179055 | AF26: 0.12140323 | AG26: 0.018879819 | AH26: -0.072138314 | AI26: -0.17995834
D27: HealthCare | E27: 0 | F27: 0 | G27: 0 | H27: 0 | I27: 0 | J27: 0 | K27: 1 | L27: 0 | M27: 0 | N27: 0 | O27: 0 | P27: 0 | Q27: 0 | R27: 0 | S27: 1 | V27: 1Y | W27: 0.31520465 | X27: 0.046128609 | Y27: -0.089127272 | Z27: 0.29042655 | AA27: 0.099695101 | AB27: 0.085445802 | AC27: 0.51707098 | AD27: 0.28048153 | AE27: 0.11406794 | AF27: 0.24203082 | AG27: 0.024036422 | AH27: -0.0908249 | AI27: -0.16439077
D28: Indus | E28: 0 | F28: 0 | G28: 0 | H28: 0 | I28: 0 | J28: 0 | K28: 0 | L28: 0 | M28: -1 | N28: -1 | O28: 0 | P28: 0 | Q28: 0 | R28: 0 | S28: 0 | V28: 3Y | W28: 0.36726095 | X28: 0.063035257 | Y28: -0.11975984 | Z28: 1.3891311 | AA28: 0.12144016 | AB28: 0.70067364 | AC28: 0.66171784 | AD28: 0.84747424 | AE28: 0.57951211 | AF28: 0.70034887 | AG28: 0.26833428 | AH28: 0.10217513 | AI28: -0.17698084
D29: Oil | E29: -1 | F29: 0 | G29: 0 | H29: -1 | I29: 0 | J29: -1 | K29: -1 | L29: -1 | M29: 0 | N29: 0 | O29: 1 | P29: 0 | Q29: 0 | R29: 1 | S29: -1 | V29: 5Y | W29: 0.40166616 | X29: 0.059002477 | Y29: -0.042604777 | Z29: 1.8750191 | AA29: 0.25863487 | AB29: 0.69887572 | AC29: 1.4414555 | AD29: 0.66434199 | AE29: 0.44506623 | AF29: 0.87762153 | AG29: 0.18631449 | AH29: 0.30160625 | AI29: -0.099462702
D30: Tech | E30: 0 | F30: 1 | G30: 1 | H30: 1 | I30: 1 | J30: 1 | K30: 1 | L30: 1 | M30: 1 | N30: 1 | O30: 1 | P30: 1 | Q30: 1 | R30: 1 | S30: 1
D31: Telco | E31: 1 | F31: 0 | G31: 1 | H31: 1 | I31: 0 | J31: 0 | K31: 0 | L31: 1 | M31: 0 | N31: 0 | O31: 0 | P31: 0 | Q31: 0 | R31: 0 | S31: 0
D32: Utili | E32: 1 | F32: 1 | G32: 0 | H32: 0 | I32: 1 | J32: 1 | K32: 0 | L32: 0 | M32: 1 | N32: 1 | O32: 1 | P32: 1 | Q32: 1 | R32: 0 | S32: 0
D33: Travel & leisure | E33: 0 | F33: 0 | G33: 0 | H33: 0 | I33: 0 | J33: 0 | K33: 0 | L33: 0 | M33: 0 | N33: 0 | O33: 0 | P33: 0 | Q33: 0 | R33: 0 | S33: 0
D34: Media | E34: 0 | F34: 0 | G34: 0 | H34: 0 | I34: -1 | J34: 0 | K34: 0 | L34: 0 | M34: 1 | N34: 0 | O34: 0 | P34: 0 | Q34: 1 | R34: 0 | S34: 0
D35: Auto | E35: -1 | F35: -1 | G35: 0 | H35: 0 | I35: 0 | J35: 0 | K35: 0 | L35: 0 | M35: 0 | N35: 0 | O35: -1 | P35: -1 | Q35: -1 | R35: -1 | S35: -1
D38: Variable | E38: Secteur | F38: 46295 | G38: 46265 | H38: 46234 | I38: 46203 | J38: 46173 | K38: 46142 | L38: 46112 | M38: 46081 | N38: 46053 | O38: 46022 | P38: 45991 | Q38: 45961 | R38: 45930 | S38: 45900 | T38: 45869 | U38: 45838 | V38: 45808 | W38: 45777 | X38: 45747 | Y38: 45716 | Z38: 45688 | AA38: 45657 | AB38: 45626 | AC38: 45596 | AD38: 45565 | AE38: 45535 | AF38: 45504 | AG38: 45473 | AH38: 45443 | AI38: 45412 | AJ38: 45382 | AK38: 45351 | AL38: 45322 | AM38: 45291 | AN38: 45260 | AO38: 45230 | AP38: 45199 | AQ38: 45169 | AR38: 45138 | AS38: 45107 | AT38: 45077 | AU38: 45046 | AV38: 45016 | AW38: 44985 | AX38: 44957 | AY38: 44926 | AZ38: 44895 | BA38: 44865 | BB38: 44834 | BC38: 44804 | BD38: 44773 | BE38: 44742 | BF38: 44712 | BG38: 44681 | BH38: 44651 | BI38: 44620 | BJ38: 44592 | BK38: 44561 | BL38: 44530 | BM38: 44500
D39: net_debt_ebitda | E39: Materials | F39: -1.1833336 | G39: -1.1089537 | H39: -1.3648645 | I39: -1.3669497 | J39: -1.316195 | K39: -0.89222034 | L39: -0.89743153 | M39: -0.89387337 | N39: -1.2197486 | O39: -1.2234747 | P39: -1.2397965 | Q39: -0.85701623 | R39: -0.83641595 | S39: -0.82547232 | T39: -1.2197704 | U39: -1.2293163 | V39: -1.1731623 | W39: -0.69356232 | X39: -0.69397548 | Y39: -0.69959511 | Z39: -0.76612943 | AA39: -0.76997227 | AB39: -0.77010926 | AC39: -0.85303497 | AD39: -0.85059628 | AE39: -0.84238892 | AF39: -0.9077245 | AG39: -0.90142122 | AH39: -0.90198046 | AI39: -0.9748874 | AJ39: -0.96390473 | AK39: -0.97229296 | AL39: -1.6414242 | AM39: -1.6244064 | AN39: -1.6335519 | AO39: -1.2039697 | AP39: -1.2020554 | AQ39: -1.1991678 | AR39: -1.8687748 | AS39: -1.9183149 | AT39: -1.9362559 | AU39: -1.5320233 | AV39: -1.5568659 | AW39: -1.5110515 | AX39: -1.9779994 | AY39: -1.8806666 | AZ39: -1.8466724 | BA39: -1.8271768 | BB39: -1.8867189 | BC39: -1.8532664 | BD39: -2.3065876 | BE39: -2.2302514 | BF39: -2.3128409 | BG39: -2.2010161 | BH39: -2.2727873 | BI39: -2.3163657 | BJ39: -2.6460549 | BK39: -2.8651562 | BL39: -2.8283226 | BM39: -3.5696113
D40: net_debt_ebitda | E40: ConsStaples | F40: -0.12489404 | G40: -0.060838076 | H40: -0.54054818 | I40: -0.5403058 | J40: -0.5594406 | K40: -0.15315852 | L40: -0.14690004 | M40: -0.17514738 | N40: -0.20470101 | O40: -0.22367374 | P40: -0.21691049 | Q40: 0.11611023 | R40: 0.12201772 | S40: 0.10229786 | T40: -0.27094963 | U40: -0.27244637 | V40: -0.24745042 | W40: 0.12271103 | X40: 0.10929875 | Y40: 0.098832522 | Z40: 0.14555369 | AA40: 0.13643835 | AB40: 0.15328883 | AC40: 0.11151459 | AD40: 0.11208674 | AE40: 0.12023993 | AF40: 0.047467194 | AG40: 0.041979773 | AH40: 0.062732492 | AI40: -0.007735934 | AJ40: 0.0049033798 | AK40: -0.0019103086 | AL40: -0.31925737 | AM40: -0.33473832 | AN40: -0.33182771 | AO40: 0.15568788 | AP40: 0.16796374 | AQ40: 0.15946946 | AR40: -0.44880501 | AS40: -0.46715923 | AT40: -0.47985286 | AU40: -0.12199598 | AV40: -0.10436356 | AW40: -0.11785936 | AX40: -0.29832498 | AY40: -0.20786126 | AZ40: -0.21188648 | BA40: -0.17213898 | BB40: -0.17485124 | BC40: -0.18008225 | BD40: -0.76051896 | BE40: -0.75602723 | BF40: -0.77492241 | BG40: -0.7242952 | BH40: -0.79678657 | BI40: -0.80923509 | BJ40: -1.0803497 | BK40: -1.065819 | BL40: -1.0713966 | BM40: -1.7827848
D41: net_debt_ebitda | E41: Pers. Goods | F41: -1.961934 | G41: -1.8741242 | H41: -2.2661089 | I41: -2.2804201 | J41: -2.2448421 | K41: -1.8508127 | L41: -1.8804456 | M41: -1.8967963 | N41: -2.0133267 | O41: -2.0035086 | P41: -2.0293782 | Q41: -1.7533558 | R41: -1.7130936 | S41: -1.7475286 | T41: -1.9859109 | U41: -2.0033002 | V41: -1.9305588 | W41: -1.5692666 | X41: -1.5711057 | Y41: -1.5644353 | Z41: -1.4191301 | AA41: -1.4170273 | AB41: -1.4395392 | AC41: -1.6048561 | AD41: -1.5882143 | AE41: -1.5731301 | AF41: -1.5909249 | AG41: -1.579986 | AH41: -1.5539598 | AI41: -1.6756413 | AJ41: -1.6721401 | AK41: -1.6948991 | AL41: -2.1849494 | AM41: -2.1564806 | AN41: -2.1345775 | AO41: -1.7222003 | AP41: -1.7200456 | AQ41: -1.7351729 | AR41: -2.2046983 | AS41: -2.2595602 | AT41: -2.2580552 | AU41: -1.8189468 | AV41: -1.845697 | AW41: -1.8227348 | AX41: -2.2534794 | AY41: -2.1564583 | AZ41: -2.1150048 | BA41: -2.1424059 | BB41: -2.216454 | BC41: -2.1806656 | BD41: -2.6701702 | BE41: -2.5792806 | BF41: -2.6507404 | BG41: -2.5177027 | BH41: -2.5860364 | BI41: -2.6553016 | BJ41: -2.9802671 | BK41: -2.992544 | BL41: -2.978761 | BM41: -3.7058429
D42: net_debt_ebitda | E42: Fin | F42: 7.4159561 | G42: 6.4794726 | H42: 11.805699 | I42: 11.863528 | J42: 11.79832 | K42: 8.0511556 | L42: 8.1833137 | M42: 7.9847409 | N42: 11.284631 | O42: 11.350897 | P42: 11.448198 | Q42: 7.2677131 | R42: 7.0746248 | S42: 7.3436517 | T42: 11.843701 | U42: 11.945076 | V42: 11.302872 | W42: 7.0340717 | X42: 7.0798236 | Y42: 6.9820333 | Z42: 5.9388225 | AA42: 5.9682129 | AB42: 5.9718288 | AC42: 6.9622761 | AD42: 6.9002668 | AE42: 6.8908117 | AF42: 7.1768962 | AG42: 7.1166561 | AH42: 7.1064971 | AI42: 8.8512626 | AJ42: 8.8006103 | AK42: 8.9445341 | AL42: 13.821553 | AM42: 13.706896 | AN42: 13.574999 | AO42: 7.8499878 | AP42: 7.8900645 | AQ42: 7.9386427 | AR42: 13.758532 | AS42: 14.147798 | AT42: 14.307221 | AU42: 8.6584375 | AV42: 8.841965 | AW42: 8.4403859 | AX42: 11.162758 | AY42: 10.03157 | AZ42: 9.834278 | BA42: 8.8335447 | BB42: 8.9062247 | BC42: 8.8176936 | BD42: 12.343276 | BE42: 11.840635 | BF42: 12.258457 | BG42: 8.5208549 | BH42: 8.4301251 | BI42: 8.5687217 | BJ42: 9.9907089 | BK42: 10.132468 | BL42: 10.015146 | BM42: 5.4661317
D43: net_debt_ebitda | E43: HealthCare | F43: -1.1920938 | G43: -1.1139941 | H43: -1.457199 | I43: -1.4658077 | J43: -1.4605678 | K43: -1.2331533 | L43: -1.2477767 | M43: -1.256427 | N43: -1.5047175 | O43: -1.5019102 | P43: -1.5195568 | Q43: -1.1455167 | R43: -1.1195116 | S43: -1.1894332 | T43: -1.3011006 | U43: -1.3122482 | V43: -1.2666432 | W43: -0.95337886 | X43: -0.95449562 | Y43: -0.94136116 | Z43: -0.78484282 | AA43: -0.79074661 | AB43: -0.79735044 | AC43: -0.81269464 | AD43: -0.80722024 | AE43: -0.7988802 | AF43: -0.76757705 | AG43: -0.7665156 | AH43: -0.74552725 | AI43: -0.98245314 | AJ43: -0.9725472 | AK43: -0.98157515 | AL43: -1.3519547 | AM43: -1.3435758 | AN43: -1.3236664 | AO43: -0.77379804 | AP43: -0.74614033 | AQ43: -0.75490724 | AR43: -1.2379518 | AS43: -1.2694126 | AT43: -1.2853123 | AU43: -0.99064831 | AV43: -1.0038667 | AW43: -0.96776732 | AX43: -1.2576655 | AY43: -1.166796 | AZ43: -1.1471933 | BA43: -1.088085 | BB43: -1.128136 | BC43: -1.0393622 | BD43: -1.491177 | BE43: -1.4355412 | BF43: -1.4800695 | BG43: -1.4389928 | BH43: -1.513319 | BI43: -1.5912606 | BJ43: -1.9709991 | BK43: -1.9648794 | BL43: -1.9438682 | BM43: -2.6023326
D44: net_debt_ebitda | E44: Indus | F44: -1.0643979 | G44: -0.96381168 | H44: -1.3472502 | I44: -1.3592243 | J44: -1.3625301 | K44: -1.0405681 | L44: -1.0513062 | M44: -1.06652 | N44: -1.1451506 | O44: -1.1359613 | P44: -1.1569549 | Q44: -0.79070373 | R44: -0.77986496 | S44: -0.79476101 | T44: -1.1902913 | U44: -1.200215 | V44: -1.1764526 | W44: -0.85276129 | X44: -0.85463008 | Y44: -0.85370507 | Z44: -0.48847026 | AA44: -0.49236828 | AB44: -0.49041129 | AC44: -0.6281815 | AD44: -0.62686175 | AE44: -0.65096992 | AF44: -0.75271756 | AG44: -0.75222005 | AH44: -0.73362258 | AI44: -0.94529404 | AJ44: -0.93980185 | AK44: -0.95650561 | AL44: -1.2510981 | AM44: -1.2432124 | AN44: -1.1947266 | AO44: -0.77308201 | AP44: -0.76516862 | AQ44: -0.78272829 | AR44: -1.4139133 | AS44: -1.4475174 | AT44: -1.4531938 | AU44: -1.0593523 | AV44: -1.078016 | AW44: -1.0690384 | AX44: -1.3564038 | AY44: -1.2642554 | AZ44: -1.2391787 | BA44: -1.0772179 | BB44: -1.1238061 | BC44: -1.1392352 | BD44: -1.5685125 | BE44: -1.5216369 | BF44: -1.5713194 | BG44: -1.4890144 | BH44: -1.5620161 | BI44: -1.6038058 | BJ44: -1.8570448 | BK44: -1.8719268 | BL44: -1.8635956 | BM44: -2.5483514
D45: net_debt_ebitda | E45: Oil | F45: -1.9493413 | G45: -1.8481819 | H45: -1.9871046 | I45: -1.9934221 | J45: -1.9767965 | K45: -1.5530685 | L45: -1.5728286 | M45: -1.5709413 | N45: -1.9264124 | O45: -1.9224628 | P45: -1.939464 | Q45: -1.5944434 | R45: -1.5552874 | S45: -1.6348855 | T45: -1.8913929 | U45: -1.9028908 | V45: -1.8566489 | W45: -1.4966762 | X45: -1.4992795 | Y45: -1.4626641 | Z45: -1.4941027 | AA45: -1.49822 | AB45: -1.5068639 | AC45: -1.6472385 | AD45: -1.6392003 | AE45: -1.6309786 | AF45: -1.529974 | AG45: -1.5139511 | AH45: -1.4960747 | AI45: -1.7037726 | AJ45: -1.6934475 | AK45: -1.7197877 | AL45: -2.2073113 | AM45: -2.1838841 | AN45: -2.166674 | AO45: -1.7667446 | AP45: -1.7670962 | AQ45: -1.7862588 | AR45: -2.2782358 | AS45: -2.3379256 | AT45: -2.3607123 | AU45: -1.9523941 | AV45: -1.9860897 | AW45: -1.9652255 | AX45: -2.3406447 | AY45: -2.2399118 | AZ45: -2.195637 | BA45: -2.0705868 | BB45: -2.1351687 | BC45: -2.116344 | BD45: -2.3212469 | BE45: -2.246818 | BF45: -2.3281149 | BG45: -1.9847846 | BH45: -2.0540634 | BI45: -2.0856591 | BJ45: -2.1646073 | BK45: -2.1603749 | BL45: -2.1316433 | BM45: -2.6107183
D46: net_debt_ebitda | E46: Tech | F46: -2.2611963 | G46: -2.1975701 | H46: -2.569271 | I46: -2.5876807 | J46: -2.5712512 | K46: -2.3040066 | L46: -2.3379096 | M46: -2.3463546 | N46: -2.4595827 | O46: -2.4460694 | P46: -2.4765415 | Q46: -2.2031389 | R46: -2.1497646 | S46: -2.2358537 | T46: -2.595955 | U46: -2.6217663 | V46: -2.5503883 | W46: -2.1802532 | X46: -2.1893932 | Y46: -2.3453499 | Z46: -2.044943 | AA46: -2.0458228 | AB46: -2.0681217 | AC46: -2.2451345 | AD46: -2.2282295 | AE46: -2.2182032 | AF46: -2.2099587 | AG46: -2.1951999 | AH46: -2.1685571 | AI46: -2.2220124 | AJ46: -2.2108297 | AK46: -2.2369557 | AL46: -2.6159169 | AM46: -2.5849306 | AN46: -2.5536701 | AO46: -2.2146744 | AP46: -2.2126292 | AQ46: -2.1804682 | AR46: -2.4686343 | AS46: -2.5285337 | AT46: -2.5550534 | AU46: -2.0570741 | AV46: -2.0904844 | AW46: -2.0565472 | AX46: -2.1799916 | AY46: -2.0756824 | AZ46: -2.0332747 | BA46: -1.9991153 | BB46: -2.0689862 | BC46: -1.946286 | BD46: -2.384379 | BE46: -2.3028459 | BF46: -2.3803251 | BG46: -2.4526937 | BH46: -2.522994 | BI46: -2.5496493 | BJ46: -2.8550104 | BK46: -2.8660177 | BL46: -2.8126271 | BM46: -3.4133286
D47: net_debt_ebitda | E47: Telco | F47: -0.0025281656 | G47: 0.048123042 | H47: -0.41561791 | I47: -0.41803593 | J47: -0.41325812 | K47: 0.10574231 | L47: 0.11437803 | M47: 0.076260479 | N47: -0.24704787 | O47: -0.26173279 | P47: -0.27211516 | Q47: 0.060259013 | R47: 0.054151362 | S47: 0.046588339 | T47: -0.23499613 | U47: -0.23601417 | V47: -0.21952808 | W47: 0.38170667 | X47: 0.39110644 | Y47: 0.38869887 | Z47: 0.35961903 | AA47: 0.35894106 | AB47: 0.3658053 | AC47: 0.37684261 | AD47: 0.36656624 | AE47: 0.39412233 | AF47: 0.52909412 | AG47: 0.52269752 | AH47: 0.53658957 | AI47: 0.54336444 | AJ47: 0.54324038 | AK47: 0.54982288 | AL47: 0.014667103 | AM47: 0.0049247002 | AN47: 0.0081381281 | AO47: 0.57292987 | AP47: 0.57968689 | AQ47: 0.56428344 | AR47: -0.025823458 | AS47: -0.02771697 | AT47: -0.052662104 | AU47: 0.59930977 | AV47: 0.60694085 | AW47: 0.62133527 | AX47: 0.26309192 | AY47: 0.35229728 | AZ47: 0.3490212 | BA47: 0.21082501 | BB47: 0.1812924 | BC47: 0.17076206 | BD47: -0.55980951 | BE47: -0.55517036 | BF47: -0.56653771 | BG47: -0.18329782 | BH47: -0.26240051 | BI47: -0.26054063 | BJ47: -1.1876001 | BK47: -1.1755318 | BL47: -1.1718504 | BM47: -1.9205278
D48: net_debt_ebitda | E48: Utili | F48: 1.1192343 | G48: 1.1550168 | H48: 0.6553367 | I48: 0.66234373 | J48: 0.66080128 | K48: 1.0081808 | L48: 1.032707 | M48: 0.99684167 | N48: 0.61604194 | O48: 0.58941664 | P48: 0.59385377 | Q48: 0.90520202 | R48: 0.88155213 | S48: 0.89859925 | T48: 0.45043334 | U48: 0.45650369 | V48: 0.46358758 | W48: 0.78837047 | X48: 0.7976865 | Y48: 0.81013071 | Z48: 0.77801607 | AA48: 0.78276989 | AB48: 0.79685014 | AC48: 0.68407121 | AD48: 0.67529748 | AE48: 0.66933629 | AF48: 0.64025543 | AG48: 0.64637213 | AH48: 0.60742663 | AI48: 0.44611621 | AJ48: 0.44906625 | AK48: 0.44817558 | AL48: 0.078468472 | AM48: 0.081125226 | AN48: 0.071852766 | AO48: 0.61662397 | AP48: 0.63041783 | AQ48: 0.62124288 | AR48: 0.47687558 | AS48: 0.48914169 | AT48: 0.48099871 | AU48: 1.583573 | AV48: 1.6086894 | AW48: 1.6430473 | AX48: 1.7670316 | AY48: 1.8544995 | AZ48: 1.8491802 | BA48: 1.5312344 | BB48: 1.520026 | BC48: 1.4341354 | BD48: 1.2700437 | BE48: 1.3062577 | BF48: 1.3579554 | BG48: 2.0958373 | BH48: 2.0174554 | BI48: 2.0433962 | BJ48: 0.78701808 | BK48: 0.81052745 | BL48: 0.78088471 | BM48: -0.41192773
D49: net_debt_ebitda | E49: Travel & leisure | F49: -0.43077798 | G49: -0.28758038 | H49: -0.77394335 | I49: -0.774293 | J49: -0.78127626 | K49: -0.48562808 | L49: -0.55377806 | M49: -0.50839074 | N49: -0.76781146 | O49: -0.78027937 | P49: -0.7450707 | Q49: -0.4264415 | R49: -0.38165753 | S49: -0.39257049 | T49: -0.55865084 | U49: -0.56415323 | V49: -0.55778028 | W49: -0.28374084 | X49: -0.32519475 | Y49: -0.40255125 | Z49: -0.19440083 | AA49: -0.20428548 | AB49: -0.19950414 | AC49: -0.30942676 | AD49: -0.26870346 | AE49: -0.2732582 | AF49: -0.11870515 | AG49: -0.11504124 | AH49: -0.067232367 | AI49: -0.29436666 | AJ49: -0.3204349 | AK49: -0.3273825 | AL49: -0.62741638 | AM49: -0.62888043 | AN49: -0.61516681 | AO49: 0.040373912 | AP49: -0.077618926 | AQ49: -0.1114648 | AR49: -0.31811883 | AS49: -0.34405615 | AT49: -0.32048636 | AU49: 0.016177916 | AV49: -0.026464636 | AW49: 0.092165094 | AX49: -0.081031277 | AY49: 0.015809315 | AZ49: -0.0032369438 | BA49: 0.79597752 | BB49: 1.2102504 | BC49: 1.1478882 | BD49: 2.4943815 | BE49: 2.4695611 | BF49: 2.4759385 | BG49: 4.1466995 | BH49: 5.0410789 | BI49: 5.1890375 | BJ49: 8.0353927 | BK49: 8.0753575 | BL49: 8.0448482 | BM49: 20.516201
... D119: price_fcf | E119: Pers. Goods | F119: 4.6706472 | G119: 5.6434023 | H119: 5.9497936 | I119: 6.1033257 | J119: 5.8066092 | K119: 5.0349991 | L119: 4.9691051 | M119: 6.5463926 | N119: 6.4289714 | O119: 7.6267896 | P119: 7.614168 | Q119: 7.3562984 | R119: 6.382475 | S119: 6.238189 | T119: 6.0227765 | U119: 5.7549921 | V119: 6.1140507 | W119: 6.2071091 | X119: 6.338734 | Y119: 7.9322898 | Z119: 8.0858933 | AA119: 7.0202946 | AB119: 5.6988483 | AC119: 5.9891619 | AD119: 6.4104167 | AE119: 5.8448868 | AF119: 5.7599339 | AG119: 6.189353 | AH119: 6.6934293 | AI119: 6.9180038 | AJ119: 7.4651204 | AK119: 7.6892541 | AL119: 6.583298 | AM119: 6.436351 | AN119: 6.1388331 | AO119: 5.7705309 | AP119: 6.0288533 | AQ119: 6.7805208 | AR119: 7.7240911 | AS119: 8.101314 | AT119: 7.2803483 | AU119: 8.2589338 | AV119: 8.2063897 | AW119: 7.2401311 | AX119: 7.4041798 | AY119: 6.0257049 | AZ119: 6.8429841 | BA119: 5.2818925 | BB119: 5.6501543 | BC119: 6.0544989 | BD119: 6.394434 | BE119: 5.3193206 | BF119: 5.0149664 | BG119: 5.6414672 | BH119: 6.3703171 | BI119: 6.926911 | BJ119: 8.2288526 | BK119: 9.1946131 | BL119: 9.9341586 | BM119: 8.911444
D120: price_fcf | E120: Fin
D121: price_fcf | E121: HealthCare | F121: 2.5347994 | G121: 2.7933741 | H121: 2.9477915 | I121: 2.5929951 | J121: 2.3554202 | K121: 2.7370055 | L121: 3.2237917 | M121: 3.3453131 | N121: 3.1899613 | O121: 2.942496 | P121: 2.7735405 | Q121: 1.978338 | R121: 1.8214073 | S121: 2.3400839 | T121: 1.880605 | U121: 1.9312695 | V121: 1.9589565 | W121: 2.381546 | X121: 2.7012407 | Y121: 2.7404058 | Z121: 2.646725 | AA121: 2.5156317 | AB121: 3.1333464 | AC121: 3.5496927 | AD121: 3.8536022 | AE121: 4.7937206 | AF121: 4.5012119 | AG121: 4.2538294 | AH121: 3.937875 | AI121: 3.6197079 | AJ121: 3.3417743 | AK121: 2.9896008 | AL121: 3.0765768 | AM121: 3.0939101 | AN121: 3.1599284 | AO121: 3.4198297 | AP121: 3.8703033 | AQ121: 4.0090577 | AR121: 3.6120154 | AS121: 3.2460364 | AT121: 3.7181887 | AU121: 3.8155259 | AV121: 3.4013702 | AW121: 3.182415 | AX121: 3.2453445 | AY121: 3.787687 | AZ121: 3.5538896 | BA121: 3.8227704 | BB121: 3.4877329 | BC121: 3.6184086 | BD121: 4.0039084 | BE121: 4.3800136 | BF121: 4.1656108 | BG121: 4.3479286 | BH121: 4.1546585 | BI121: 3.4153221 | BJ121: 3.0773143 | BK121: 3.451553 | BL121: 2.9694041 | BM121: 3.076411
D122: price_fcf | E122: Indus | F122: 4.0115856 | G122: 4.169092 | H122: 4.1807182 | I122: 4.0760718 | J122: 4.3405897 | K122: 4.2510641 | L122: 3.8253942 | M122: 4.6782798 | N122: 4.4228419 | O122: 3.7320043 | P122: 3.4815584 | Q122: 3.7548907 | R122: 3.9917337 | S122: 3.5897443 | T122: 3.8830315 | U122: 3.5745342 | V122: 3.0517103 | W122: 2.6086982 | X122: 2.6575405 | Y122: 2.0813324 | Z122: 1.7532029 | AA122: 1.568798 | AB122: 1.7946204 | AC122: 1.6635503 | AD122: 1.5320899 | AE122: 1.3340626 | AF122: 1.444974 | AG122: 1.0928642 | AH122: 1.4827189 | AI122: 1.29637 | AJ122: 1.4944118 | AK122: 1.1553611 | AL122: 0.74892121 | AM122: 1.3371683 | AN122: 0.97414113 | AO122: 0.47526618 | AP122: 0.78951698 | AQ122: 0.75185814 | AR122: 0.91506849 | AS122: 0.89136597 | AT122: 0.83319332 | AU122: 0.64856658 | AV122: 0.84716042 | AW122: 1.0468032 | AX122: 0.75732498 | AY122: 0.63097094 | AZ122: 0.55951041 | BA122: 0.71818092 | BB122: 0.17441755 | BC122: 0.11045633 | BD122: 0.37816307 | BE122: -0.011969498 | BF122: 0.1888738 | BG122: 0.21588457 | BH122: 0.29996402 | BI122: -0.066640602 | BJ122: 0.10819137 | BK122: 0.50982691 | BL122: 0.11811229 | BM122: -0.13047848
D123: price_fcf | E123: Oil | F123: -4.4531695 | G123: -4.905976 | H123: -4.9064276 | I123: -5.7788951 | J123: -5.2483886 | K123: -4.5326555 | L123: -3.4668241 | M123: -4.7813816 | N123: -4.9042162 | O123: -5.2866932 | P123: -5.4414518 | Q123: -5.5281734 | R123: -5.4099483 | S123: -5.1335388 | T123: -5.1776507 | U123: -5.3859163 | V123: -5.9562387 | W123: -5.8643778 | X123: -5.595143 | Y123: -6.8021508 | Z123: -6.734972 | AA123: -6.3905939 | AB123: -6.3799772 | AC123: -6.2564246 | AD123: -6.6465774 | AE123: -6.476281 | AF123: -6.3641991 | AG123: -6.6813731 | AH123: -6.6590909 | AI123: -6.4308162 | AJ123: -6.8833376 | AK123: -7.0365243 | AL123: -6.6905789 | AM123: -6.2294189 | AN123: -5.8750425 | AO123: -5.3207816 | AP123: -5.3225289 | AQ123: -5.8206021 | AR123: -6.2372572 | AS123: -6.4984996 | AT123: -6.4100828 | AU123: -6.3835707 | AV123: -6.593947 | AW123: -6.2810632 | AX123: -6.3030749 | AY123: -5.7688374 | AZ123: -6.130508 | BA123: -5.7503973 | BB123: -5.5923948 | BC123: -5.9796824 | BD123: -6.6299618 | BE123: -5.8258346 | BF123: -6.0740752 | BG123: -6.6219438 | BH123: -6.7436143 | BI123: -6.3994493 | BJ123: -6.7183188 | BK123: -7.7480922 | BL123: -7.6507494 | BM123: -7.8723576
D124: price_fcf | E124: Tech | F124: 11.383451 | G124: 10.69549 | H124: 10.214888 | I124: 13.978532 | J124: 12.786373 | K124: 11.208279 | L124: 9.9029474 | M124: 11.736248 | N124: 12.558713 | O124: 11.869804 | P124: 12.154272 | Q124: 13.632625 | R124: 13.203915 | S124: 11.420971 | T124: 12.299575 | U124: 13.095773 | V124: 13.092296 | W124: 11.957441 | X124: 11.807909 | Y124: 12.698217 | Z124: 13.031962 | AA124: 12.200601 | AB124: 12.089597 | AC124: 11.320698 | AD124: 12.076726 | AE124: 12.887284 | AF124: 13.485609 | AG124: 15.592053 | AH124: 14.34582 | AI124: 14.016742 | AJ124: 15.260445 | AK124: 15.973182 | AL124: 14.89264 | AM124: 11.786543 | AN124: 11.565816 | AO124: 9.4344853 | AP124: 8.9962354 | AQ124: 9.9707555 | AR124: 10.846395 | AS124: 11.054503 | AT124: 11.459853 | AU124: 9.9055542 | AV124: 10.617478 | AW124: 10.110831 | AX124: 10.718921 | AY124: 8.7829282 | AZ124: 10.117984 | BA124: 8.6129948 | BB124: 8.0544565 | BC124: 8.7605741 | BD124: 10.088127 | BE124: 8.3725477 | BF124: 9.625232 | BG124: 9.7830077 | BH124: 11.274476 | BI124: 11.570604 | BJ124: 12.878112 | BK124: 15.662911 | BL124: 15.53552 | BM124: 16.106046
D125: price_fcf | E125: Telco | F125: -5.462809 | G125: -5.6291758 | H125: -5.4729692 | I125: -5.7206893 | J125: -5.0182817 | K125: -4.9049724 | L125: -4.7208277 | M125: -5.4673149 | N125: -5.753515 | O125: -5.8196411 | P125: -5.8554731 | Q125: -5.842907 | R125: -5.5891212 | S125: -5.3044933 | T125: -5.3138834 | U125: -5.3890968 | V125: -5.5724152 | W125: -5.4620249 | X125: -5.3779522 | Y125: -6.2525687 | Z125: -6.5603778 | AA125: -6.1439387 | AB125: -6.0492336 | AC125: -6.1775993 | AD125: -6.5133674 | AE125: -6.7791813 | AF125: -6.8843966 | AG125: -7.1950367 | AH125: -7.2101178 | AI125: -7.2859727 | AJ125: -7.5223991 | AK125: -7.4794095 | AL125: -7.1057858 | AM125: -6.7295579 | AN125: -6.2703143 | AO125: -5.8908521 | AP125: -6.0310955 | AQ125: -6.3951368 | AR125: -6.7189881 | AS125: -6.6500293 | AT125: -6.3409722 | AU125: -6.5551916 | AV125: -6.5067044 | AW125: -6.3330691 | AX125: -6.4894568 | AY125: -6.0042102 | AZ125: -6.2498479 | BA125: -5.5948922 | BB125: -5.2177457 | BC125: -5.3613282 | BD125: -5.891844 | BE125: -5.0887708 | BF125: -5.6932907 | BG125: -6.1248136 | BH125: -6.5932618 | BI125: -7.5342799 | BJ125: -7.8274118 | BK125: -8.6625236 | BL125: -8.5595805 | BM125: -9.2619251
D126: price_fcf | E126: Utili | F126: -2.7343412 | G126: -3.0017365 | H126: -2.6956157 | I126: -2.8802337 | J126: -3.2409152 | K126: -2.5194476 | L126: -2.3925416 | M126: -3.0937839 | N126: -3.2125377 | O126: -3.5531028 | P126: -3.503368 | Q126: -3.6726009 | R126: -3.8758495 | S126: -3.8088075 | T126: -3.7474011 | U126: -3.7123876 | V126: -4.0419273 | W126: -3.7824927 | X126: -3.9283521 | Y126: -5.0612364 | Z126: -5.1815761 | AA126: -4.56851 | AB126: -4.5356037 | AC126: -4.5270678 | AD126: -4.613183 | AE126: -4.6740796 | AF126: -4.5872072 | AG126: -5.1538245 | AH126: -5.0479154 | AI126: -5.1143844 | AJ126: -5.6125238 | AK126: -5.6181268 | AL126: -5.0413439 | AM126: -4.4158042 | AN126: -4.0530336 | AO126: -3.9853099 | AP126: -4.2986826 | AQ126: -4.3309043 | AR126: -4.5063251 | AS126: -4.2426872 | AT126: -3.8960516 | AU126: -4.076 | AV126: -4.160961 | AW126: -4.1012688 | AX126: -4.2624422 | AY126: -3.4426501 | AZ126: -3.6565036 | BA126: -3.3009012 | BB126: -3.1367546 | BC126: -3.2726479 | BD126: -3.6205457 | BE126: -3.2258838 | BF126: -3.4446926 | BG126: -3.7189264 | BH126: -4.3007854 | BI126: -3.94639 | BJ126: -4.3771103 | BK126: -4.8862663 | BL126: -5.0847194 | BM126: -5.8045088
D127: price_fcf | E127: Travel & leisure | F127: -3.3563033 | G127: -3.5403498 | H127: -3.616001 | I127: -3.4826176 | J127: -3.9508796 | K127: -3.9022792 | L127: -4.3880935 | M127: -4.8365771 | N127: -4.3992871 | O127: -4.0103696 | P127: -3.6659092 | Q127: -4.0505873 | R127: -3.5570059 | S127: -3.4784336 | T127: -3.5454511 | U127: -3.9102115 | V127: -4.1337466 | W127: -4.0058414 | X127: -3.5452069 | Y127: -1.881035 | Z127: -1.7385193 | AA127: -1.4454636 | AB127: -1.2002831 | AC127: -1.4089741 | AD127: -1.6773001 | AE127: -1.9515439 | AF127: -2.7811481 | AG127: -2.8409819 | AH127: -2.4470964 | AI127: -1.7239526 | AJ127: -1.8938606 | AK127: -1.4935955 | AL127: -1.0117853 | AM127: -1.1518737 | AN127: -1.7419539 | AO127: -1.1938869 | AP127: -1.0254661 | AQ127: -0.71921266 | AR127: -0.47109229 | AS127: -0.2552142 | AT127: -0.56431618 | AU127: -0.54378664 | AV127: -0.75477455 | AW127: -0.75504076 | AX127: -0.59225223 | AY127: -0.71803454 | AZ127: -0.89057473 | BA127: -0.6255049 | BB127: -0.91315267 | BC127: -0.74299802 | BD127: -1.1677407 | BE127: -0.99681529 | BF127: -0.3204245 | BG127: -0.087966797 | BH127: -0.037260076 | BI127: 0.73361996 | BJ127: 0.60355577 | BK127: -0.029312162 | BL127: 0.99668258 | BM127: 5.2014294
D128: price_fcf | E128: Media | F128: 0.62878793 | G128: 0.90373743 | H128: 0.77283131 | I128: 0.3448838 | J128: 0.63528093 | K128: 0.38566287 | L128: 0.26974917 | M128: -0.57776594 | N128: 0.11369066 | O128: 0.86488328 | P128: 0.84079792 | Q128: 1.1208672 | R128: 1.0631531 | S128: 1.1510223 | T128: 1.4373567 | U128: 1.8554077 | V128: 3.3683697 | W128: 3.432644 | X128: 2.9504967 | Y128: 4.9611687 | Z128: 5.863948 | AA128: 5.3590909 | AB128: 5.4590095 | AC128: 5.1427313 | AD128: 4.8191512 | AE128: 4.8506485 | AF128: 5.1157343 | AG128: 5.278662 | AH128: 5.0655733 | AI128: 4.6836205 | AJ128: 4.9847738 | AK128: 4.7540056 | AL128: 4.4010454 | AM128: 4.2942462 | AN128: 4.1786529 | AO128: 4.257314 | AP128: 4.0564333 | AQ128: 3.1582369 | AR128: 3.1274873 | AS128: 3.0758432 | AT128: 2.8199113 | AU128: 3.4676198 | AV128: 3.5285934 | AW128: 3.854602 | AX128: 3.2682275 | AY128: 3.089921 | AZ128: 3.0543482 | BA128: 3.3578234 | BB128: 3.4144213 | BC128: 3.1803968 | BD128: 3.6633122 | BE128: 3.3670877 | BF128: 3.2247749 | BG128: 3.8876711 | BH128: 3.8725283 | BI128: 2.6958198 | BJ128: 2.3004067 | BK128: 2.2473842 | BL128: 2.1478978 | BM128: 1.4839778
D129: price_fcf | E129: Auto | F129: -6.6032684 | G129: -6.7693906 | H129: -6.8488058 | I129: -7.4952924 | J129: -7.082649 | K129: -6.9110262 | L129: -6.5896534 | M129: -7.0225549 | N129: -6.8946484 | O129: -6.6541311 | P129: -6.5939625 | Q129: -6.7493118 | R129: -6.4593925 | S129: -6.141473 | T129: -6.2735286 | U129: -6.3501251 | V129: -6.5081152 | W129: -6.3118866 | X129: -6.2859412 | Y129: -6.866019 | Z129: -7.0287614 | AA129: -6.5937934 | AB129: -6.9282864 | AC129: -6.6988786 | AD129: -7.0033982 | AE129: -7.08441 | AF129: -7.0512206 | AG129: -7.2758476 | AH129: -7.3458069 | AI129: -7.1642075 | AJ129: -7.0988633 | AK129: -7.0306283 | AL129: -7.0957186 | AM129: -6.7214611 | AN129: -6.4479311 | AO129: -6.1411106 | AP129: -6.2043597 | AQ129: -6.5467563 | AR129: -6.6581443 | AS129: -6.5072755 | AT129: -6.5387122 | AU129: -6.8779784 | AV129: -6.6773501 | AW129: -6.3955114 | AX129: -6.4756096 | AY129: -5.9575292 | AZ129: -6.1638922 | BA129: -5.8344655 | BB129: -5.5963171 | BC129: -5.8526302 | BD129: -6.303389 | BE129: -5.8523016 | BF129: -6.1893229 | BG129: -6.6362035 | BH129: -6.9148321 | BI129: -6.5274828 | BJ129: -6.6844065 | BK129: -7.4019957 | BL129: -7.2309861 | BM129: -7.6436171
D130: ev_ebitda | E130: Materials | F130: -1.6783843 | G130: -1.4890187 | H130: -1.8576235 | I130: -2.4105435 | J130: -1.79904 | K130: -1.6920919 | L130: -1.658532 | M130: -1.8695225 | N130: -1.9938769 | O130: -2.2369814 | P130: -2.3676822 | Q130: -2.2935163 | R130: -1.9929561 | S130: -1.9570957 | T130: -2.18642 | U130: -2.163615 | V130: -2.4220834 | W130: -2.2657887 | X130: -2.3457332 | Y130: -3.0713142 | Z130: -3.3891901 | AA130: -3.1835068 | AB130: -3.0981805 | AC130: -2.8174987 | AD130: -2.5021651 | AE130: -2.9885615 | AF130: -2.9699038 | AG130: -3.0043505 | AH130: -2.6613815 | AI130: -2.6066932 | AJ130: -2.8845559 | AK130: -3.0960774 | AL130: -2.8744326 | AM130: -2.1846816 | AN130: -2.3680845 | AO130: -2.3036065 | AP130: -2.374564 | AQ130: -2.504015 | AR130: -2.6014219 | AS130: -3.0598879 | AT130: -3.3419168 | AU130: -3.2936431 | AV130: -3.2866608 | AW130: -3.0634592 | AX130: -2.7972721 | AY130: -2.63235 | AZ130: -3.0002138 | BA130: -3.1692475 | BB130: -3.2783795 | BC130: -3.569481 | BD130: -3.9562947 | BE130: -3.8686225 | BF130: -3.7831926 | BG130: -4.1395224 | BH130: -4.1165802 | BI130: -3.7816123 | BJ130: -4.1908512 | BK130: -5.4874498 | BL130: -5.6882677 | BM130: -6.0640496
D131: ev_ebitda | E131: ConsStaples | F131: 0.29190145 | G131: 0.30493145 | H131: 0.62861372 | I131: 0.19341339 | J131: 0.04526025 | K131: 0.40340653 | L131: 0.60381312 | M131: 0.78744269 | N131: 0.2602428 | O131: 0.26539568 | P131: 0.41641166 | Q131: 0.25325585 | R131: 0.25693588 | S131: 0.74152067 | T131: 0.47578507 | U131: 0.61382114 | V131: 0.80852287 | W131: 0.98846417 | X131: 0.78759933 | Y131: -0.02042479 | Z131: -0.23665967 | AA131: 0.12596655 | AB131: 0.15647816 | AC131: 0.38387722 | AD131: 0.37204971 | AE131: 0.43109232 | AF131: 0.2279846 | AG131: -0.11547918 | AH131: 0.076081889 | AI131: 0.11026929 | AJ131: 0.018045134 | AK131: 0.018268785 | AL131: 0.49678121 | AM131: 0.64443806 | AN131: 0.91325305 | AO131: 1.4140991 | AP131: 1.4509931 | AQ131: 1.4730948 | AR131: 1.2600414 | AS131: 1.2297271 | AT131: 1.3327561 | AU131: 1.5268542 | AV131: 1.4187677 | AW131: 1.4059199 | AX131: 1.5314845 | AY131: 1.9779229 | AZ131: 1.9152246 | BA131: 2.2984961 | BB131: 2.6651503 | BC131: 2.8197877 | BD131: 2.5089645 | BE131: 2.7200437 | BF131: 2.5492702 | BG131: 2.7713157 | BH131: 2.1567603 | BI131: 2.2072298 | BJ131: 1.8847693 | BK131: 1.7831554 | BL131: 1.4543016 | BM131: 1.2171813
D132: ev_ebitda | E132: Pers. Goods | F132: 1.8881656 | G132: 2.6065275 | H132: 2.9717666 | I132: 2.8953092 | J132: 2.8876121 | K132: 2.4226831 | L132: 2.4458106 | M132: 3.4855766 | N132: 3.4677442 | O132: 4.8387427 | P132: 4.7945247 | Q132: 4.4694326 | R132: 3.9061869 | S132: 3.789468 | T132: 3.6834596 | U132: 3.4480633 | V132: 3.8182868 | W132: 3.9320786 | X132: 3.875706 | Y132: 5.0583152 | Z132: 5.2235306 | AA132: 4.3039512 | AB132: 3.3311951 | AC132: 3.5392975 | AD132: 4.273246 | AE132: 3.7457667 | AF132: 3.5952567 | AG132: 3.9841531 | AH132: 4.4187879 | AI132: 4.5757148 | AJ132: 4.9707359 | AK132: 5.2189912 | AL132: 4.3268953 | AM132: 4.2685988 | AN132: 3.9361043 | AO132: 3.5291981 | AP132: 3.5671554 | AQ132: 4.3480042 | AR132: 5.1876312 | AS132: 5.4244497 | AT132: 4.9344924 | AU132: 5.9250706 | AV132: 5.985898 | AW132: 5.3459878 | AX132: 4.9951656 | AY132: 3.7253519 | AZ132: 4.2120146 | BA132: 2.8798174 | BB132: 3.0281767 | BC132: 3.4676927 | BD132: 3.7600297 | BE132: 2.8934889 | BF132: 2.6480412 | BG132: 2.9763312 | BH132: 3.6956436 | BI132: 3.9252588 | BJ132: 4.8772858 | BK132: 5.8001562 | BL132: 6.4538839 | BM132: 5.7183898
D133: ev_ebitda | E133: Fin | S133: 5.0369013 | T133: 9.3205831 | U133: 10.388298 | V133: 9.8221736 | W133: 5.7531268 | X133: 6.0476002 | Y133: 5.5424354 | Z133: 2.9329269 | AA133: 3.4681571 | AB133: 3.386263 | AC133: 4.0569675 | AD133: 3.5184205 | AE133: 3.4358869 | AF133: 3.6806811 | AG133: 3.4838133 | AH133: 3.7545312 | AI133: 6.6495625 | AJ133: 6.2383047 | AK133: 6.5965798 | AL133: 9.6870945 | AM133: 9.2738561 | AN133: 9.6790756 | AO133: 5.6910781 | AP133: 5.7634092 | AQ133: 5.3878015 | AR133: 10.434736 | AS133: 11.211014 | AT133: 11.622295 | AU133: 5.1196169 | AV133: 5.2510811 | AW133: 57.846211 | AX133: 74.111454 | AY133: 46.359298 | AZ133: 45.630792 | BA133: 72.273838 | BB133: 50.554137 | BC133: 48.113794 | BD133: 58.86541 | BE133: 11.82476 | BF133: 11.613466 | BG133: 8.258158 | BH133: 7.9400847 | BI133: 7.5677179 | BJ133: 10.129222 | BK133: 12.234657 | BL133: 12.486658 | BM133: 8.3376207
D134: ev_ebitda | E134: HealthCare | F134: 1.3611452 | G134: 1.5434157 | H134: 1.7859867 | I134: 1.6558122 | J134: 1.452049 | K134: 1.5695242 | L134: 1.9345547 | M134: 2.1449439 | N134: 2.0743598 | O134: 1.7190245 | P134: 1.6162094 | Q134: 0.97512999 | R134: 0.86275156 | S134: 1.1577577 | T134: 0.91799407 | U134: 1.0307361 | V134: 1.0732492 | W134: 1.3538596 | X134: 1.6060567 | Y134: 1.6295284 | Z134: 1.4933656 | AA134: 1.4669047 | AB134: 1.9158721 | AC134: 2.2230772 | AD134: 2.5800759 | AE134: 3.3555727 | AF134: 3.0486717 | AG134: 2.8160194 | AH134: 2.6441708 | AI134: 2.4060875 | AJ134: 2.2798001 | AK134: 2.1345858 | AL134: 2.3667652 | AM134: 2.4124512 | AN134: 2.4067432 | AO134: 2.4860638 | AP134: 2.9890271 | AQ134: 2.9496317 | AR134: 2.6919137 | AS134: 2.5809109 | AT134: 2.8336557 | AU134: 2.8038805 | AV134: 2.4235653 | AW134: 2.3480842 | AX134: 2.4509012 | AY134: 2.915366 | AZ134: 2.6782109 | BA134: 2.8887564 | BB134: 2.683037 | BC134: 2.7909368 | BD134: 3.190592 | BE134: 3.4255634 | BF134: 3.224007 | BG134: 3.370868 | BH134: 3.1728262 | BI134: 2.5816731 | BJ134: 2.3515058 | BK134: 2.5792792 | BL134: 2.1067235 | BM134: 2.0864039
D135: ev_ebitda | E135: Indus | F135: 2.4130804 | G135: 2.6172044 | H135: 2.7702224 | I135: 2.5755238 | J135: 2.70585 | K135: 2.7159963 | L135: 2.3121128 | M135: 2.9408956 | N135: 2.7951974 | O135: 2.2293319 | P135: 2.0508019 | Q135: 2.3763181 | R135: 2.4404891 | S135: 2.1488051 | T135: 2.2457142 | U135: 1.9322444 | V135: 1.5890308 | W135: 1.2237588 | X135: 1.2596682 | Y135: 0.72097982 | Z135: 0.6894624 | AA135: 0.74993135 | AB135: 0.86868033 | AC135: 0.7218802 | AD135: 0.62870856 | AE135: 0.45286126 | AF135: 0.43649281 | AG135: 0.1980848 | AH135: 0.65458538 | AI135: 0.37197039 | AJ135: 0.43496157 | AK135: 0.2555146 | AL135: 0.15319269 | AM135: 0.50322086 | AN135: 0.25738366 | AO135: 0.01608358 | AP135: 0.26494784 | AQ135: 0.29692988 | AR135: 0.17664402 | AS135: 0.17689797 | AT135: 0.1986408 | AU135: 0.042677259 | AV135: 0.1296958 | AW135: 0.30895713 | AX135: 0.27141264 | AY135: 0.1990286 | AZ135: 0.042628382 | BA135: 0.16758819 | BB135: -0.18338329 | BC135: -0.30012469 | BD135: -0.20437208 | BE135: -0.51264163 | BF135: -0.32845224 | BG135: -0.3235226 | BH135: -0.30145266 | BI135: -0.4016712 | BJ135: -0.21999705 | BK135: 0.08445229 | BL135: -0.23431282 | BM135: -0.5001309
D136: ev_ebitda | E136: Oil | F136: -4.6450795 | G136: -4.8016296 | H136: -4.6501127 | I136: -5.4270255 | J136: -5.0882291 | K136: -4.5485696 | L136: -3.6775533 | M136: -4.4073962 | N136: -4.5219083 | O136: -4.9070889 | P136: -5.00724 | Q136: -5.1182865 | R136: -5.0575074 | S136: -4.8853067 | T136: -4.9128976 | U136: -4.9354218 | V136: -5.3679415 | W136: -5.3269912 | X136: -5.1649445 | Y136: -6.2276427 | Z136: -6.3838749 | AA136: -6.0155703 | AB136: -6.0509032 | AC136: -5.9368424 | AD136: -6.1555192 | AE136: -6.0911283 | AF136: -5.9664042 | AG136: -6.1253069 | AH136: -6.036793 | AI136: -5.9552353 | AJ136: -6.3001578 | AK136: -6.431545 | AL136: -6.1604677 | AM136: -5.8052639 | AN136: -5.5900714 | AO136: -5.2614782 | AP136: -5.3026876 | AQ136: -5.5772887 | AR136: -5.8363148 | AS136: -6.1047895 | AT136: -6.0817827 | AU136: -6.0479672 | AV136: -6.3393923 | AW136: -6.1087374 | AX136: -6.1239865 | AY136: -5.7658139 | AZ136: -6.0104792 | BA136: -5.7522893 | BB136: -5.6913713 | BC136: -5.9036169 | BD136: -6.2075416 | BE136: -5.6069829 | BF136: -5.8518327 | BG136: -6.2089517 | BH136: -6.2232699 | BI136: -5.9731412 | BJ136: -6.1908899 | BK136: -6.9249816 | BL136: -6.8032676 | BM136: -6.7999402
D137: ev_ebitda | E137: Tech | F137: 8.7582003 | G137: 8.187715 | H137: 7.9389397 | I137: 11.195385 | J137: 10.082094 | K137: 8.6319793 | L137: 7.4645545 | M137: 9.0274745 | N137: 9.7181629 | O137: 9.2574147 | P137: 9.3121389 | Q137: 10.248368 | R137: 10.256576 | S137: 8.767228 | T137: 9.3019242 | U137: 10.029347 | V137: 9.9187848 | W137: 8.9736662 | X137: 8.8399744 | Y137: 9.7792496 | Z137: 10.478612 | AA137: 9.8178943 | AB137: 9.3104351 | AC137: 8.5047497 | AD137: 8.8429601 | AE137: 9.539391 | AF137: 10.124834 | AG137: 11.499289 | AH137: 10.319915 | AI137: 10.03334 | AJ137: 11.036906 | AK137: 11.102432 | AL137: 10.415402 | AM137: 8.1945623 | AN137: 7.9986893 | AO137: 6.0889016 | AP137: 5.8032276 | AQ137: 6.4308048 | AR137: 7.3301798 | AS137: 7.3142024 | AT137: 7.4552741 | AU137: 6.3819644 | AV137: 7.1676673 | AW137: 6.6776277 | AX137: 7.2805049 | AY137: 6.0592036 | AZ137: 7.0162741 | BA137: 5.7383593 | BB137: 5.3163353 | BC137: 5.7867169 | BD137: 6.7836318 | BE137: 5.3591065 | BF137: 6.3702447 | BG137: 6.5672106 | BH137: 7.8448408 | BI137: 7.8205287 | BJ137: 8.7578103 | BK137: 11.20856 | BL137: 10.995178 | BM137: 11.683281
D138: ev_ebitda | E138: Telco | F138: -3.2757506 | G138: -3.3900209 | H138: -3.378852 | I138: -3.628387 | J138: -3.2074109 | K138: -2.7961536 | L138: -2.6209028 | M138: -3.2222186 | N138: -3.4726256 | O138: -3.4990084 | P138: -3.4639421 | Q138: -3.4895043 | R138: -3.5265688 | S138: -3.1236252 | T138: -3.1048087 | U138: -3.2438233 | V138: -3.3028354 | W138: -2.9066367 | X138: -2.7308078 | Y138: -3.4999644 | Z138: -3.8228587 | AA138: -3.3654338 | AB138: -3.3233472 | AC138: -3.1486486 | AD138: -3.4621668 | AE138: -3.6189181 | AF138: -3.5087448 | AG138: -3.7845847 | AH138: -3.8406178 | AI138: -3.7537418 | AJ138: -4.0107307 | AK138: -3.9961612 | AL138: -3.7365549 | AM138: -3.5703043 | AN138: -3.2268659 | AO138: -2.7401871 | AP138: -2.8158653 | AQ138: -3.1420105 | AR138: -3.5401666 | AS138: -3.4167288 | AT138: -3.1372529 | AU138: -3.2162714 | AV138: -3.2105232 | AW138: -3.025932 | AX138: -3.3087782 | AY138: -3.0285201 | AZ138: -3.1848579 | BA138: -2.595749 | BB138: -2.4040948 | BC138: -2.5360806 | BD138: -2.8590179 | BE138: -2.2633014 | BF138: -2.7960401 | BG138: -2.893827 | BH138: -3.3471553 | BI138: -3.540259 | BJ138: -3.9533369 | BK138: -4.6180888 | BL138: -4.4908341 | BM138: -5.1952554
D139: ev_ebitda | E139: Utili | F139: -0.23397806 | G139: -0.3746392 | H139: -0.2254996 | I139: -0.36184137 | J139: -0.57069491 | K139: -0.084938808 | L139: 0.057078421 | M139: -0.44633157 | N139: -0.69616243 | O139: -0.9655765 | P139: -0.84231337 | Q139: -1.045423 | R139: -1.2973206 | S139: -1.2523675 | T139: -1.1462 | U139: -1.1178141 | V139: -1.4438756 | W139: -1.4295966 | X139: -1.4101212 | Y139: -2.3556015 | Z139: -2.4014851 | AA139: -1.8367978 | AB139: -1.7422283 | AC139: -1.8218754 | AD139: -1.9538473 | AE139: -2.0550549 | AF139: -1.9986708 | AG139: -2.3064687 | AH139: -2.2675147 | AI139: -2.2792625 | AJ139: -2.5612516 | AK139: -2.589939 | AL139: -2.2568315 | AM139: -1.8664421 | AN139: -1.5810843 | AO139: -1.2708688 | AP139: -1.4287212 | AQ139: -1.6084492 | AR139: -1.840821 | AS139: -1.5483094 | AT139: -1.342375 | AU139: -1.5405991 | AV139: -1.5749733 | AW139: -1.4701709 | AX139: -1.4146063 | AY139: -0.94279647 | AZ139: -1.0025336 | BA139: -0.71799967 | BB139: -0.33288149 | BC139: -0.53260094 | BD139: -0.87319917 | BE139: -0.31170389 | BF139: -0.2959554 | BG139: -0.7060661 | BH139: -1.1556951 | BI139: -0.97643399 | BJ139: -1.4123889 | BK139: -1.908487 | BL139: -1.904721 | BM139: -2.564144
D140: ev_ebitda | E140: Travel & leisure | F140: -2.5178678 | G140: -2.6153874 | H140: -2.6304312 | I140: -2.6581606 | J140: -2.9163539 | K140: -3.1428674 | L140: -3.2971236 | M140: -3.6324943 | N140: -3.5930868 | O140: -3.3015653 | P140: -3.3499002 | Q140: -3.4503055 | R140: -3.177046 | S140: -2.8982555 | T140: -2.6892228 | U140: -2.898938 | V140: -3.0871579 | W140: -3.0620249 | X140: -2.9522311 | Y140: -1.5999396 | Z140: -1.6918762 | AA140: -1.4120928 | AB140: -1.2197914 | AC140: -1.6003832 | AD140: -1.7680865 | AE140: -1.9051834 | AF140: -1.878073 | AG140: -2.0168062 | AH140: -1.6947021 | AI140: -1.3277721 | AJ140: -1.4070474 | AK140: -0.91027886 | AL140: -0.89419103 | AM140: -0.94460037 | AN140: -1.2155284 | AO140: -0.83340312 | AP140: -0.84718815 | AQ140: -0.62169621 | AR140: -0.19318982 | AS140: 0.04398933 | AT140: -0.073409149 | AU140: -0.085451092 | AV140: -0.31866738 | AW140: -0.50191044 | AX140: -0.7688671 | AY140: -0.74553703 | AZ140: -0.70071912 | BA140: -0.34295965 | BB140: -0.53323472 | BC140: -0.28262409 | BD140: -0.40356828 | BE140: -0.14319389 | BF140: 0.33537963 | BG140: 0.42660696 | BH140: 0.40739755 | BI140: 0.7847301 | BJ140: 0.51142801 | BK140: 0.46883568 | BL140: 1.0385515 | BM140: 4.0329073
D141: ev_ebitda | E141: Media | F141: -0.24372932 | G141: -0.086279635 | H141: -0.73194034 | I141: -0.85530312 | J141: -0.61005563 | K141: -0.71877435 | L141: -1.0472088 | M141: -1.827347 | N141: -0.83880277 | O141: -0.38217846 | P141: -0.34464814 | Q141: -0.21127404 | R141: -0.060056014 | S141: -0.10545946 | T141: -0.054960261 | U141: 0.41674692 | V141: 1.570413 | W141: 1.5157368 | X141: 1.2102575 | Y141: 2.987183 | Z141: 4.0601769 | AA141: 2.9873387 | AB141: 3.6704327 | AC141: 3.4304272 | AD141: 3.0986007 | AE141: 3.2549348 | AF141: 3.197405 | AG141: 3.2397462 | AH141: 3.143272 | AI141: 3.0303506 | AJ141: 3.1099715 | AK141: 2.8739266 | AL141: 2.8200887 | AM141: 2.7936785 | AN141: 2.7107417 | AO141: 2.8488719 | AP141: 2.7005816 | AQ141: 2.1821198 | AR141: 1.8549838 | AS141: 1.6728555 | AT141: 1.5789679 | AU141: 2.1217017 | AV141: 2.044245 | AW141: 2.2155516 | AX141: 2.028621 | AY141: 2.0184039 | AZ141: 1.9502494 | BA141: 2.1402572 | BB141: 2.0916372 | BC141: 1.9375742 | BD141: 2.2031419 | BE141: 2.0498541 | BF141: 1.9178028 | BG141: 2.3728869 | BH141: 2.3370254 | BI141: 1.7338217 | BJ141: 1.8877001 | BK141: 1.857005 | BL141: 1.8129669 | BM141: 1.325908
D142: ev_ebitda | E142: Auto | F142: -2.1177032 | G142: -2.5028187 | H142: -2.62107 | I142: -3.1741826 | J142: -2.9810812 | K142: -2.7601939 | L142: -2.5166037 | M142: -2.981023 | N142: -3.1992443 | O142: -3.0175106 | P142: -2.8143606 | Q142: -2.7141949 | R142: -2.611485 | S142: -2.3826694 | T142: -2.5303679 | U142: -3.1113466 | V142: -3.1543937 | W142: -2.9965262 | X142: -2.9754244 | Y142: -3.4003687 | Z142: -4.0192033 | AA142: -3.6385852 | AB142: -3.8186429 | AC142: -3.4780606 | AD142: -3.953856 | AE142: -4.1207726 | AF142: -4.3088479 | AG142: -4.3842961 | AH142: -4.7558042 | AI142: -4.6050279 | AJ142: -4.686677 | AK142: -4.5797172 | AL142: -4.6566477 | AM142: -4.4456574 | AN142: -4.2412806 | AO142: -3.9736745 | AP142: -4.0069065 | AQ142: -4.2271258 | AR142: -4.4894799 | AS142: -4.3133171 | AT142: -4.3570504 | AU142: -4.6182168 | AV142: -4.439622 | AW142: -4.1319184 | AX142: -4.1445796 | AY142: -3.7802593 | AZ142: -3.9157985 | BA142: -3.5350295 | BB142: -3.3609913 | BC142: -3.6781802 | BD142: -3.9423661 | BE142: -3.7416103 | BF142: -3.9892727 | BG142: -4.2133295 | BH142: -4.4703407 | BI142: -4.3801245 | BJ142: -4.3030354 | BK142: -4.8424364 | BL142: -4.7402024 | BM142: -4.9405515
D143: price_sales | E143: Materials | F143: -0.81281848 | G143: -0.78466211 | H143: -0.82761492 | I143: -0.93626984 | J143: -0.83417404 | K143: -0.79008393 | L143: -0.74217533 | M143: -0.8262925 | N143: -0.83307472 | O143: -0.89209074 | P143: -0.91447382 | Q143: -0.9304746 | R143: -0.88661832 | S143: -0.87810356 | T143: -0.90469891 | U143: -0.91211273 | V143: -0.95983851 | W143: -0.91795648 | X143: -0.92766268 | Y143: -1.1019845 | Z143: -1.1232398 | AA143: -1.0073505 | AB143: -0.99815041 | AC143: -0.94184672 | AD143: -0.93650835 | AE143: -1.0135487 | AF143: -0.99269697 | AG143: -1.0123981 | AH143: -0.96059875 | AI143: -0.94501895 | AJ143: -1.0282421 | AK143: -1.0459279 | AL143: -0.97775864 | AM143: -0.87686467 | AN143: -0.87349135 | AO143: -0.81767273 | AP143: -0.83293491 | AQ143: -0.88227907 | AR143: -0.91342841 | AS143: -0.95722365 | AT143: -0.95592032 | AU143: -0.95270338 | AV143: -0.94163411 | AW143: -0.88269508 | AX143: -0.83670196 | AY143: -0.75763463 | AZ143: -0.79595423 | BA143: -0.77705982 | BB143: -0.76154399 | BC143: -0.7987153 | BD143: -0.87597365 | BE143: -0.80242609 | BF143: -0.78205091 | BG143: -0.83570273 | BH143: -0.8509935 | BI143: -0.85497034 | BJ143: -0.94078235 | BK143: -1.0283985 | BL143: -1.0248421 | BM143: -1.0621978
D144: price_sales | E144: ConsStaples | F144: -0.69405015 | G144: -0.69428292 | H144: -0.64187479 | I144: -0.73575562 | J144: -0.725175 | K144: -0.65267396 | L144: -0.58497282 | M144: -0.59277564 | N144: -0.66973815 | O144: -0.64566862 | P144: -0.61985732 | Q144: -0.64782886 | R144: -0.63776278 | S144: -0.52812147 | T144: -0.56152922 | U144: -0.56240691 | V144: -0.52213259 | W144: -0.4728233 | X144: -0.50247096 | Y144: -0.70869311 | Z144: -0.74809798 | AA144: -0.62720093 | AB144: -0.61308367 | AC144: -0.57528181 | AD144: -0.59137075 | AE144: -0.59684572 | AF144: -0.61654389 | AG144: -0.67554347 | AH144: -0.63424749 | AI144: -0.61751608 | AJ144: -0.64644005 | AK144: -0.6211739 | AL144: -0.53631288 | AM144: -0.49826831 | AN144: -0.44141859 | AO144: -0.33456904 | AP144: -0.34701187 | AQ144: -0.35615931 | AR144: -0.3892855 | AS144: -0.38754281 | AT144: -0.35068044 | AU144: -0.31248197 | AV144: -0.32802232 | AW144: -0.31493146 | AX144: -0.30465916 | AY144: -0.17172375 | AZ144: -0.18853347 | BA144: -0.08968231 | BB144: -0.018800658 | BC144: 0.011649111 | BD144: -0.044053912 | BE144: 0.002677772 | BF144: -0.054210791 | BG144: -0.026160899 | BH144: -0.1327215 | BI144: -0.10948022 | BJ144: -0.17278814 | BK144: -0.22054892 | BL144: -0.24676644 | BM144: -0.29041553
D145: price_sales | E145: Pers. Goods | F145: 0.88803889 | G145: 1.1134325 | H145: 1.1926167 | I145: 1.1730026 | J145: 1.1598879 | K145: 1.0316258 | L145: 1.0541793 | M145: 1.3698187 | N145: 1.3304849 | O145: 1.6789383 | P145: 1.677689 | Q145: 1.6128111 | R145: 1.4539825 | S145: 1.342707 | T145: 1.2779213 | U145: 1.2232311 | V145: 1.3055423 | W145: 1.3194264 | X145: 1.3885778 | Y145: 1.7087431 | Z145: 1.7295479 | AA145: 1.5288265 | AB145: 1.2966116 | AC145: 1.385529 | AD145: 1.6056395 | AE145: 1.5011992 | AF145: 1.469616 | AG145: 1.6102368 | AH145: 1.7543333 | AI145: 1.8088159 | AJ145: 1.9527995 | AK145: 2.0317556 | AL145: 1.7986505 | AM145: 1.7320783 | AN145: 1.667614 | AO145: 1.6024633 | AP145: 1.6597424 | AQ145: 1.9065737 | AR145: 2.1009477 | AS145: 2.1621701 | AT145: 1.9915778 | AU145: 2.2488483 | AV145: 2.2266916 | AW145: 2.0416281 | AX145: 2.0259545 | AY145: 1.6391239 | AZ145: 1.7797436 | BA145: 1.4467418 | BB145: 1.4942271 | BC145: 1.630016 | BD145: 1.7579257 | BE145: 1.4943218 | BF145: 1.4919219 | BG145: 1.6240878 | BH145: 1.817535 | BI145: 1.8985942 | BJ145: 2.1678217 | BK145: 2.4058119 | BL145: 2.4321876 | BM145: 2.2593463
... D197: ebitda_growth | E197: Pers. Goods | F197: -1.5879891 | G197: -1.0535695 | H197: -1.4638678 | I197: -2.3703506 | J197: -3.0337963 | K197: -3.3128554 | L197: -2.6981975 | M197: -2.0805039 | N197: -1.8992445 | O197: -0.8879498 | P197: -1.0480148 | Q197: -0.71835446 | R197: -0.42228064 | S197: -0.34544411 | T197: -0.52991083 | U197: -0.038134474 | V197: 0.47336218 | W197: 0.29940179 | X197: 2.9529914 | Y197: 3.716625 | Z197: 3.1856129 | AA197: 2.1658495 | AB197: 0.86028517 | AC197: -0.34677623 | AD197: -0.35260821 | AE197: 0.7854506 | AF197: 0.37210451 | AG197: 0.78271704 | AH197: 1.2172345 | AI197: 1.3715512 | AJ197: 1.8669575 | AK197: 2.183554 | AL197: 2.6451815 | AM197: 3.4685449 | AN197: 3.921611 | AO197: 4.3637602 | AP197: 5.0929993 | AQ197: 5.7861281 | AR197: 5.3826674 | AS197: 5.1916525 | AT197: 4.8908247 | AU197: 4.6634364 | AV197: 3.4069891 | AW197: 2.2659635 | AX197: 5.0787285 | AY197: 3.8268523 | AZ197: 2.9776475 | BA197: 1.6988925 | BB197: 0.76040692 | BC197: 0.067723603 | BD197: -0.30504213 | BE197: -1.6322345 | BF197: -1.9967033 | BG197: -2.1851369 | BH197: -3.2436482 | BI197: -1.5181334 | BJ197: -3.4289126 | BK197: -2.9416408 | BL197: -6.2406131 | BM197: -7.3824132
D198: ebitda_growth | E198: Fin
D199: ebitda_growth | E199: HealthCare | F199: -1.6562902 | G199: -2.024866 | H199: -2.5177615 | I199: -2.9756181 | J199: -3.4307049 | K199: -3.9322049 | L199: -3.7235128 | M199: -3.578953 | N199: -2.7998069 | O199: -2.2302694 | P199: -1.3924204 | Q199: 0.54987839 | R199: 0.72571491 | S199: 1.5019906 | T199: 2.386449 | U199: 3.4419238 | V199: 3.6291944 | W199: 4.1389264 | X199: 3.5566404 | Y199: 3.4108228 | Z199: 4.0435776 | AA199: 3.1749371 | AB199: 3.5574684 | AC199: 4.7629465 | AD199: 3.9127913 | AE199: 3.7695976 | AF199: 3.6248533 | AG199: 3.4064098 | AH199: 3.5063299 | AI199: 3.549417 | AJ199: 2.8194394 | AK199: 3.2732773 | AL199: 3.7090031 | AM199: 2.9702346 | AN199: 2.6181638 | AO199: 3.1103258 | AP199: 3.0575759 | AQ199: 2.3743081 | AR199: 2.1452339 | AS199: 1.7447756 | AT199: 1.4183365 | AU199: 1.2949233 | AV199: 0.93289707 | AW199: 0.81067877 | AX199: 2.2490767 | AY199: 3.2297438 | AZ199: 1.5566205 | BA199: 0.046350169 | BB199: -1.6043031 | BC199: -3.1384766 | BD199: -4.009314 | BE199: -4.001068 | BF199: -4.9213595 | BG199: -5.6841409 | BH199: -6.4742904 | BI199: -3.8119383 | BJ199: -6.9420302 | BK199: -7.5217933 | BL199: -13.295669 | BM199: -17.580809
D200: ebitda_growth | E200: Indus | F200: 1.0637677 | G200: 0.98032506 | H200: 0.49098917 | I200: -0.23572596 | J200: -0.81423882 | K200: -1.1496659 | L200: -0.67868015 | M200: -0.74802544 | N200: 0.13840767 | O200: 0.14378936 | P200: 0.45039345 | Q200: 0.73224179 | R200: 0.97289607 | S200: 1.4223558 | T200: 1.5122739 | U200: 2.0952628 | V200: 1.969417 | W200: 2.0747863 | X200: 1.8189256 | Y200: 2.1199053 | Z200: 2.4672194 | AA200: 2.0430588 | AB200: 2.4973146 | AC200: 2.2644721 | AD200: 2.0428788 | AE200: 1.6252353 | AF200: 1.915837 | AG200: 0.99862859 | AH200: 0.99377767 | AI200: 1.1129911 | AJ200: 0.92838508 | AK200: 0.90250376 | AL200: 0.38491631 | AM200: 0.015953335 | AN200: -0.25870966 | AO200: -0.84242007 | AP200: -0.68708162 | AQ200: -0.73657887 | AR200: -0.80601047 | AS200: -1.1297596 | AT200: -1.7172545 | AU200: -1.753778 | AV200: -2.5463877 | AW200: -3.3409688 | AX200: -4.0633138 | AY200: -4.7213959 | AZ200: -5.1722808 | BA200: -5.6124703 | BB200: -5.8795957 | BC200: -5.5760475 | BD200: -5.4421187 | BE200: -5.1011253 | BF200: -5.2529697 | BG200: -5.8467162 | BH200: -6.1753716 | BI200: -3.5131987 | BJ200: -5.6142909 | BK200: -6.4995845 | BL200: -10.842536 | BM200: -14.041499
D201: ebitda_growth | E201: Oil | F201: -7.643743 | G201: -6.0889092 | H201: -2.9156306 | I201: 0.365911 | J201: 4.0794346 | K201: 6.2325719 | L201: -3.1562862 | M201: -9.7386132 | N201: -10.50126 | O201: -11.158546 | P201: -9.9730467 | Q201: -9.672405 | R201: -9.1397926 | S201: -8.7826446 | T201: -8.6645839 | U201: -9.7700574 | V201: -10.34828 | W201: -8.8931201 | X201: -8.0346427 | Y201: -8.0540923 | Z201: -7.9404794 | AA201: -10.041602 | AB201: -9.3928039 | AC201: -9.4757044 | AD201: -9.0282115 | AE201: -8.5189473 | AF201: -8.3708132 | AG201: -8.3196217 | AH201: -8.435307 | AI201: -8.8344785 | AJ201: -10.075578 | AK201: -9.3847159 | AL201: -9.0554161 | AM201: -7.3573632 | AN201: -8.729487 | AO201: -10.108626 | AP201: -13.621108 | AQ201: -15.111292 | AR201: -16.454836 | AS201: -16.783421 | AT201: -17.282048 | AU201: -18.711532 | AV201: -17.864501 | AW201: -16.43012 | AX201: -16.671616 | AY201: -13.650118 | AZ201: -10.665493 | BA201: -6.1065331 | BB201: -2.5043906 | BC201: 0.92027827 | BD201: 4.9239493 | BE201: 4.4168806 | BF201: 6.7412007 | BG201: 5.6601798 | BH201: 3.1058109 | BI201: -4.2070059 | BJ201: -6.0595882 | BK201: -8.1461177 | BL201: -8.6534479 | BM201: -7.0693964
D202: ebitda_growth | E202: Tech | F202: 15.179464 | G202: 14.645658 | H202: 14.251018 | I202: 9.985969 | J202: 8.1580716 | K202: 7.7951873 | L202: 6.9457032 | M202: 6.6586677 | N202: 6.0480636 | O202: 2.5524825 | P202: 3.0323967 | Q202: 3.8083589 | R202: 3.8609809 | S202: 4.6380799 | T202: 5.2595773 | U202: 7.0650909 | V202: 6.7912049 | W202: 7.2723687 | X202: 7.089756 | Y202: 7.2751903 | Z202: 7.4966612 | AA202: 7.6681107 | AB202: 6.3214152 | AC202: 7.4568414 | AD202: 13.151305 | AE202: 11.48847 | AF202: 9.7200531 | AG202: 8.0219661 | AH202: 6.3997193 | AI202: 4.7658283 | AJ202: 3.330805 | AK202: 1.8155765 | AL202: 1.005709 | AM202: 3.0474925 | AN202: 4.2305832 | AO202: 5.6114711 | AP202: 8.6251648 | AQ202: 10.220081 | AR202: 11.005809 | AS202: 12.994534 | AT202: 13.79399 | AU202: 14.869096 | AV202: 16.386005 | AW202: 17.248496 | AX202: 15.095022 | AY202: 10.382927 | AZ202: 8.2830965 | BA202: 6.1226661 | BB202: 6.2857745 | BC202: 3.7318024 | BD202: 2.2580699 | BE202: 1.4744644 | BF202: 0.48189497 | BG202: 0.092091243 | BH202: -0.9199987 | BI202: 1.1902651 | BJ202: -0.2323431 | BK202: -1.682369 | BL202: -7.3705153 | BM202: -12.212876
D203: ebitda_growth | E203: Telco | F203: -1.3869712 | G203: -1.1313333 | H203: -1.686841 | I203: -1.418507 | J203: -0.74513245 | K203: -1.9596388 | L203: -0.45535871 | M203: -0.19765458 | N203: -3.5500675 | O203: -3.5602825 | P203: -2.6609412 | Q203: -2.2928786 | R203: 0.63689325 | S203: -0.19620825 | T203: 0.68555293 | U203: 1.5687834 | V203: 1.7869559 | W203: 0.66542972 | X203: 0.073381895 | Y203: 0.28018657 | Z203: -1.6904584 | AA203: -2.6076403 | AB203: -2.2910536 | AC203: -2.9141415 | AD203: -3.0754018 | AE203: -2.4738823 | AF203: -1.9516561 | AG203: -1.2643228 | AH203: -0.88552261 | AI203: -0.40608116 | AJ203: 0.88411584 | AK203: 2.0933317 | AL203: 0.13108383 | AM203: -0.43655026 | AN203: -0.39730973 | AO203: -0.81916529 | AP203: -1.3885653 | AQ203: -2.0226578 | AR203: -2.2571214 | AS203: -2.1715707 | AT203: -2.2376747 | AU203: -1.0399282 | AV203: 0.036284627 | AW203: 0.30905885 | AX203: 0.36573534 | AY203: 1.6529801 | AZ203: -1.3354689 | BA203: -3.7885871 | BB203: -6.9751986 | BC203: -8.9270742 | BD203: -11.049515 | BE203: -13.906743 | BF203: -14.92257 | BG203: -16.784801 | BH203: -17.848596 | BI203: -16.209323 | BJ203: -22.785045 | BK203: -23.183764 | BL203: -27.610295 | BM203: -29.559748
D204: ebitda_growth | E204: Utili | F204: -1.8011351 | G204: -2.2418636 | H204: -2.8338645 | I204: -3.2638803 | J204: -3.6166161 | K204: -3.879881 | L204: -3.4231247 | M204: -3.8694509 | N204: -3.5660811 | O204: -3.3428436 | P204: -3.1976702 | Q204: -2.8871144 | R204: -2.9576565 | S204: -2.3144724 | T204: -1.9135936 | U204: -2.3973617 | V204: -2.5734175 | W204: -2.9599049 | X204: -4.8831765 | Y204: -5.1023422 | Z204: -4.2822922 | AA204: -5.3630051 | AB204: -4.9491433 | AC204: -4.5457113 | AD204: -5.3191172 | AE204: -5.5925364 | AF204: -5.5221925 | AG204: -5.6642015 | AH204: -5.7813864 | AI204: -5.7913868 | AJ204: -5.607399 | AK204: -5.3224807 | AL204: -4.7160667 | AM204: -4.7687924 | AN204: -4.2393885 | AO204: -3.8458136 | AP204: -3.4394731 | AQ204: -2.8916709 | AR204: -2.0812218 | AS204: -1.8712893 | AT204: -1.9188956 | AU204: -2.065434 | AV204: -1.8814043 | AW204: -1.049642 | AX204: 0.76255969 | AY204: 5.2052031 | AZ204: 3.1994043 | BA204: 2.4006934 | BB204: -0.38936843 | BC204: -0.64258844 | BD204: -4.3411237 | BE204: -6.6040611 | BF204: -8.1552744 | BG204: -8.2859268 | BH204: -8.9661284 | BI204: -9.4662579 | BJ204: -10.78435 | BK204: -9.9001349 | BL204: -15.526936 | BM204: -20.776386
D205: ebitda_growth | E205: Travel & leisure | F205: -0.55039086 | G205: -1.9821456 | H205: -2.8360764 | I205: -3.6570902 | J205: -4.9815116 | K205: -4.807257 | L205: -1.269336 | M205: -2.164175 | N205: -1.4906322 | O205: -1.2119175 | P205: -0.17468923 | Q205: 0.90055793 | R205: 3.1026158 | S205: 3.5725902 | T205: 3.7352052 | U205: 3.3356785 | V205: 3.8315053 | W205: 3.5977575 | X205: 3.1164729 | Y205: 8.3468562 | Z205: 6.4272926 | AA205: 5.2798029 | AB205: 6.2025921 | AC205: 5.5441663 | AD205: 4.1843595 | AE205: 4.1556996 | AF205: 4.405987 | AG205: 6.5186019 | AH205: 6.4732949 | AI205: 7.1170693 | AJ205: 8.5703266 | AK205: 8.2924934 | AL205: 8.19107 | AM205: 8.7896146 | AN205: 9.0998799 | AO205: 10.659152 | AP205: 12.332904 | AQ205: 14.213727 | AR205: 15.371153 | AS205: 15.470283 | AT205: 16.227773 | AU205: 16.397964 | AV205: 16.612789 | AW205: 16.031831 | AX205: 15.566568 | AY205: 14.667873 | AZ205: 24.889707 | BA205: 33.849462 | BB205: 43.082375 | BC205: 50.34838 | BD205: 57.389369 | BE205: 65.571578 | BF205: 71.705945 | BG205: 79.079495 | BH205: 90.766573 | BI205: 91.227565 | BJ205: 108.14197 | BK205: 117.80096 | BL205: 159.87969 | BM205: 188.18192
D206: ebitda_growth | E206: Media | F206: -1.2867592 | G206: -1.8171672 | H206: -2.3919287 | I206: -2.402608 | J206: -3.2461678 | K206: -3.7842954 | L206: -2.8445725 | M206: -3.0734936 | N206: -3.0854392 | O206: -2.5778763 | P206: -2.78862 | Q206: -2.3249708 | R206: -1.7772543 | S206: -0.58193731 | T206: -0.49941847 | U206: 0.50096939 | V206: 1.6002609 | W206: 1.9200302 | X206: 2.0085063 | Y206: -4.9273194 | Z206: -5.0627604 | AA206: 0.5339707 | AB206: 0.73588764 | AC206: 0.98576069 | AD206: 0.54755433 | AE206: 0.80987793 | AF206: 1.6983018 | AG206: 2.5423351 | AH206: 2.8642717 | AI206: 3.3740733 | AJ206: 3.9028914 | AK206: 4.0272179 | AL206: 3.4995995 | AM206: 2.549286 | AN206: 2.6152306 | AO206: 2.1400978 | AP206: 1.7362933 | AQ206: 1.6285308 | AR206: 2.2346202 | AS206: 2.7171693 | AT206: 2.8278531 | AU206: 3.0363325 | AV206: 4.2774025 | AW206: 4.0434562 | AX206: 3.1785111 | AY206: 3.2294817 | AZ206: 2.0885013 | BA206: 1.9163961 | BB206: -0.43729752 | BC206: -1.807979 | BD206: -2.8271187 | BE206: -4.2475167 | BF206: -5.1291311 | BG206: -5.3669189 | BH206: -5.9959973 | BI206: -2.9141534 | BJ206: -5.8180987 | BK206: -5.8407905 | BL206: -12.746635 | BM206: -16.733475
D207: ebitda_growth | E207: Auto | F207: 3.1276943 | G207: 3.1492218 | H207: 3.9312603 | I207: 6.1146035 | J207: 7.9623608 | K207: 8.847653 | L207: 10.23339 | M207: 16.437019 | N207: 17.842679 | O207: 19.258249 | P207: 15.475694 | Q207: 11.073028 | R207: 6.8988266 | S207: 3.2940663 | T207: 0.016627094 | U207: -3.06242 | V207: -4.4824578 | W207: -5.6553454 | X207: -4.7283099 | Y207: -4.9725449 | Z207: -4.4595194 | AA207: -3.4113277 | AB207: -4.2257382 | AC207: -4.8054398 | AD207: -5.9019667 | AE207: -5.7791697 | AF207: -5.7778942 | AG207: -6.8910667 | AH207: -5.6596571 | AI207: -5.483689 | AJ207: -5.5201016 | AK207: -6.4286549 | AL207: -7.469863 | AM207: -8.6039222 | AN207: -7.6671931 | AO207: -6.5245168 | AP207: -4.3884129 | AQ207: -3.8670681 | AR207: -2.191177 | AS207: -2.4442716 | AT207: -2.2895017 | AU207: -3.0152069 | AV207: -5.2244663 | AW207: -5.5447024 | AX207: -6.765247 | AY207: -7.885566 | AZ207: -8.2879559 | BA207: -9.161133 | BB207: -9.0661588 | BC207: -10.369038 | BD207: -11.312773 | BE207: -11.911502 | BF207: -13.635522 | BG207: -15.704475 | BH207: -17.593569 | BI207: -19.517949 | BJ207: -10.299492 | BK207: -13.339009 | BL207: -12.483265 | BM207: -14.198736
D210: Date | E210: Secteur | F210: Pilier | G210: Variable | H210: Mesure | I210: Score
D211: 46295 | E211: Materials | F211: Leverage | G211: net_debt_ebitda | H211: 1.5176704 | I211: 3.9344262
D212: 46295 | E212: ConsStaples | F212: Leverage | G212: net_debt_ebitda | H212: 2.57611 | I212: 4.2622951
D213: 46295 | E213: Pers. Goods | F213: Leverage | G213: net_debt_ebitda | H213: 0.73907005 | I213: 4.9180328
D214: 46295 | E214: Fin | F214: Leverage | G214: net_debt_ebitda | H214: 10.11696 | I214: 7.0491803
D215: 46295 | E215: HealthCare | F215: Leverage | G215: net_debt_ebitda | H215: 1.5089102 | I215: 5.0819672
D216: 46295 | E216: Indus | F216: Leverage | G216: net_debt_ebitda | H216: 1.6366061 | I216: 4.2622951
D217: 46295 | E217: Oil | F217: Leverage | G217: net_debt_ebitda | H217: 0.75166269 | I217: 5.2459016
D218: 46295 | E218: Tech | F218: Leverage | G218: net_debt_ebitda | H218: 0.43980775 | I218: 5.0819672
D219: 46295 | E219: Telco | F219: Leverage | G219: net_debt_ebitda | H219: 2.6984758 | I219: 6.2295082
D220: 46295 | E220: Utili | F220: Leverage | G220: net_debt_ebitda | H220: 3.8202383 | I220: 2.7868852
D221: 46295 | E221: Travel & leisure | F221: Leverage | G221: net_debt_ebitda | H221: 2.270226 | I221: 7.5409836
D222: 46295 | E222: Media | F222: Leverage | G222: net_debt_ebitda | H222: 1.3799431 | I222: 5.7377049
... D291: 46295 | E291: Pers. Goods | F291: Value | G291: price_fcf | H291: 14.473667 | I291: 10
D292: 46295 | E292: Fin | F292: Value | G292: price_fcf
D293: 46295 | E293: HealthCare | F293: Value | G293: price_fcf | H293: 12.337819 | I293: 8.3606557
D294: 46295 | E294: Indus | F294: Value | G294: price_fcf | H294: 13.814605 | I294: 1.3114754
...

Sheet Reco_histo
B1: Top | O1: Worst
B2: Materials | C2: ConsStaples | D2: Pers. Goods | E2: Fin | F2: HealthCare | G2: Indus | H2: Oil | I2: Tech | J2: Telco | K2: Utili | L2: Travel & leisure | M2: Media | N2: Auto | O2: Materials | P2: ConsStaples | Q2: Pers. Goods | R2: Fin | S2: HealthCare | T2: Indus | U2: Oil | V2: Tech | W2: Telco | X2: Utili | Y2: Travel & leisure | Z2: Media | AA2: Auto
A3: 40235 | B3: 1 | C3: 0 | D3: 0 | E3: 0 | F3: 0 | G3: 1 | H3: 0 | I3: 1 | J3: 0 | K3: 0 | L3: 0 | M3: 0 | N3: 0 | O3: 0 | P3: 0 | Q3: 0 | R3: 0 | S3: 0 | T3: 0 | U3: 0 | V3: 0 | W3: 1 | X3: 1 | Y3: 0 | Z3: 0 | AA3: 1
A4: 40268 | B4: 0 | C4: 1 | D4: 1 | E4: 0 | F4: 1 | G4: 0 | H4: 0 | I4: 0 | J4: 0 | K4: 0 | L4: 0 | M4: 0 | N4: 0 | O4: 0 | P4: 0 | Q4: 0 | R4: 0 | S4: 0 | T4: 0 | U4: 0 | V4: 0 | W4: 0 | X4: 1 | Y4: 0 | Z4: 0 | AA4: 1
A5: 40298 | B5: 0 | C5: 0 | D5: 1 | E5: 0 | F5: 1 | G5: 0 | H5: 0 | I5: 0 | J5: 0 | K5: 0 | L5: 0 | M5: 1 | N5: 0 | O5: 0 | P5: 0 | Q5: 0 | R5: 1 | S5: 0 | T5: 0 | U5: 0 | V5: 0 | W5: 0 | X5: 0 | Y5: 0 | Z5: 0 | AA5: 1
A6: 40326 | B6: 0 | C6: 1 | D6: 1 | E6: 0 | F6: 0 | G6: 0 | H6: 0 | I6: 0 | J6: 0 | K6: 0 | L6: 0 | M6: 1 | N6: 0 | O6: 0 | P6: 0 | Q6: 0 | R6: 0 | S6: 0 | T6: 0 | U6: 1 | V6: 0 | W6: 0 | X6: 0 | Y6: 0 | Z6: 0 | AA6: 1
A7: 40359 | B7: 1 | C7: 1 | D7: 0 | E7: 0 | F7: 0 | G7: 0 | H7: 0 | I7: 0 | J7: 0 | K7: 0 | L7: 0 | M7: 1 | N7: 0 | O7: 0 | P7: 0 | Q7: 0 | R7: 0 | S7: 0 | T7: 0 | U7: 1 | V7: 0 | W7: 0 | X7: 1 | Y7: 0 | Z7: 0 | AA7: 1
A8: 40389 | B8: 0 | C8: 1 | D8: 0 | E8: 0 | F8: 0 | G8: 0 | H8: 0 | I8: 0 | J8: 0 | K8: 0 | L8: 0 | M8: 1 | N8: 0 | O8: 0 | P8: 0 | Q8: 0 | R8: 1 | S8: 0 | T8: 1 | U8: 0 | V8: 0 | W8: 1 | X8: 0 | Y8: 0 | Z8: 0 | AA8: 0
A9: 40421 | B9: 1 | C9: 1 | D9: 1 | E9: 0 | F9: 0 | G9: 0 | H9: 0 | I9: 0 | J9: 0 | K9: 0 | L9: 0 | M9: 0 | N9: 0 | O9: 0 | P9: 0 | Q9: 0 | R9: 1 | S9: 0 | T9: 0 | U9: 0 | V9: 0 | W9: 1 | X9: 1 | Y9: 0 | Z9: 0 | AA9: 0
A10: 40451 | B10: 0 | C10: 1 | D10: 1 | E10: 0 | F10: 1 | G10: 0 | H10: 0 | I10: 0 | J10: 0 | K10: 0 | L10: 0 | M10: 0 | N10: 0 | O10: 0 | P10: 0 | Q10: 0 | R10: 0 | S10: 0 | T10: 0 | U10: 1 | V10: 1 | W10: 1 | X10: 0 | Y10: 0 | Z10: 0 | AA10: 0
A11: 40480 | B11: 1 | C11: 1 | D11: 0 | E11: 0 | F11: 0 | G11: 0 | H11: 0 | I11: 0 | J11: 0 | K11: 0 | L11: 0 | M11: 0 | N11: 0 | O11: 0 | P11: 0 | Q11: 0 | R11: 0 | S11: 0 | T11: 0 | U11: 1 | V11: 0 | W11: 1 | X11: 1 | Y11: 0 | Z11: 0 | AA11: 0
A12: 40512 | B12: 0 | C12: 1 | D12: 0 | E12: 0 | F12: 0 | G12: 0 | H12: 0 | I12: 0 | J12: 0 | K12: 0 | L12: 0 | M12: 1 | N12: 1 | O12: 0 | P12: 0 | Q12: 0 | R12: 1 | S12: 0 | T12: 0 | U12: 1 | V12: 0 | W12: 1 | X12: 0 | Y12: 0 | Z12: 0 | AA12: 0
A13: 40543 | B13: 0 | C13: 1 | D13: 0 | E13: 0 | F13: 0 | G13: 0 | H13: 0 | I13: 0 | J13: 0 | K13: 0 | L13: 0 | M13: 0 | N13: 1 | O13: 0 | P13: 0 | Q13: 0 | R13: 0 | S13: 0 | T13: 0 | U13: 1 | V13: 1 | W13: 0 | X13: 1 | Y13: 0 | Z13: 0 | AA13: 0
A14: 40574 | B14: 0 | C14: 1 | D14: 1 | E14: 0 | F14: 0 | G14: 0 | H14: 0 | I14: 0 | J14: 0 | K14: 0 | L14: 0 | M14: 0 | N14: 1 | O14: 0 | P14: 0 | Q14: 0 | R14: 1 | S14: 0 | T14: 0 | U14: 1 | V14: 0 | W14: 1 | X14: 0 | Y14: 0 | Z14: 0 | AA14: 0
... A202: 46295 | B202: 0 | C202: 0 | D202: 0 | E202: 1 | F202: 1 | G202: 0 | H202: 0 | I202: 1 | J202: 0 | K202: 0 | L202: 0 | M202: 0 | N202: 0 | O202: 0 | P202: 1 | Q202: 0 | R202: 0 | S202: 0 | T202: 0 | U202: 1 | V202: 0 | W202: 0 | X202: 0 | Y202: 0 | Z202: 0 | AA202: 1

Sheet Config
B4: FACTSET Ids | C4: INDEX NAME | D4: Named Range | E4: Secto Name
B7: 181085 | C7: {=_xll.FDS(B7,"FG_COMPANY_NAME")} -> FTSE World Europe | D7: IND_Bench | F7: Nb of Const
B8: I00037 | C8: {=_xll.FDS(B8,"FG_COMPANY_NAME")} -> FTSE World Europe / Basic Materials - IND | D8: IND_Mat | E8: Materials | F8: {=_xll.FDS(B8,"FTAW_NUMBER_IDX(0,0,D,""CLOSE"")")} -> 49
B9: I00109 | C9: {=_xll.FDS(B9,"FG_COMPANY_NAME")} -> FTSE World Europe / Consumer Staples - IND | D9: IND_ConsGd | E9: ConsStaples | F9: {=_xll.FDS(B9,"FTAW_NUMBER_IDX(0,0,D,""CLOSE"")")} -> 47
B10: I20438 | C10: {=_xll.FDS(B10,"FG_COMPANY_NAME")} -> FTSE World Europe / Personal Goods - SEC | D10: IND_PersGoods | E10: Pers. Goods | F10: {=_xll.FDS(B10,"FTAW_NUMBER_IDX(0,0,D,""CLOSE"")")} -> 14
B11: I00253 | C11: {=_xll.FDS(B11,"FG_COMPANY_NAME")} -> FTSE World Europe / Financials - IND | D11: IND_Fin | E11: Fin | F11: {=_xll.FDS(B11,"FTAW_NUMBER_IDX(0,0,D,""CLOSE"")")} -> 128
B12: I20436 | C12: {=_xll.FDS(B12,"FG_COMPANY_NAME")} -> FTSE World Europe / Health Care - IND | D12: IND_Health | E12: HealthCare | F12: {=_xll.FDS(B12,"FTAW_NUMBER_IDX(0,0,D,""CLOSE"")")} -> 49
B13: I00073 | C13: {=_xll.FDS(B13,"FG_COMPANY_NAME")} -> FTSE World Europe / Industrials - IND | D13: IND_Indus | E13: Indus | F13: {=_xll.FDS(B13,"FTAW_NUMBER_IDX(0,0,D,""CLOSE"")")} -> 132
B14: I20433 | C14: {=_xll.FDS(B14,"FG_COMPANY_NAME")} -> FTSE World Europe / Energy - IND | D14: IND_Oil | E14: Oil | F14: {=_xll.FDS(B14,"FTAW_NUMBER_IDX(0,0,D,""CLOSE"")")} -> 23
B15: I20448 | C15: {=_xll.FDS(B15,"FG_COMPANY_NAME")} -> FTSE World Europe / Technology - IND | D15: IND_Tech | E15: Tech | F15: {=_xll.FDS(B15,"FTAW_NUMBER_IDX(0,0,D,""CLOSE"")")} -> 24
B16: I20443 | C16: {=_xll.FDS(B16,"FG_COMPANY_NAME")} -> FTSE World Europe / Telecommunications - IND | D16: IND_Telco | E16: Telco | F16: {=_xll.FDS(B16,"FTAW_NUMBER_IDX(0,0,D,""CLOSE"")")} -> 23
B17: I00577 | C17: {=_xll.FDS(B17,"FG_COMPANY_NAME")} -> FTSE World Europe / Utilities - IND | D17: IND_Utili | E17: Utili | F17: {=_xll.FDS(B17,"FTAW_NUMBER_IDX(0,0,D,""CLOSE"")")} -> 39
B18: I00901 | C18: {=_xll.FDS(B18,"FG_COMPANY_NAME")} -> FTSE World Europe / Travel and Leisure - SEC | D18: IND_Travel | E18: Travel & leisure | F18: {=_xll.FDS(B18,"FTAW_NUMBER_IDX(0,0,D,""CLOSE"")")} -> 14
B19: I00937 | C19: {=_xll.FDS(B19,"FG_COMPANY_NAME")} -> FTSE World Europe / Media - SEC | D19: IND_Media | E19: Media | F19: {=_xll.FDS(B19,"FTAW_NUMBER_IDX(0,0,D,""CLOSE"")")} -> 7
B20: I00649 | C20: {=_xll.FDS(B20,"FG_COMPANY_NAME")} -> FTSE World Europe / Automobiles and Parts - SEC | D20: IND_Auto | E20: Auto | F20: {=_xll.FDS(B20,"FTAW_NUMBER_IDX(0,0,D,""CLOSE"")")} -> 17

Sheet Returns_EQ
A1: StartDate: | B1: 36494 | D1: CUMRET TIME SERIES
A2: EndDate: | B2: =TODAY() -> 46321 | D2: EQUITY
B4: =IND_Bench -> 181085 | C4: =IND_Mat -> I00037 | D4: =IND_ConsGd -> I00109 | E4: =IND_PersGoods -> I20438 | F4: =IND_Fin -> I00253 | G4: =IND_Health -> I20436 | H4: =IND_Indus -> I00073 | I4: =IND_Oil -> I20433 | J4: =IND_Tech -> I20448 | K4: =IND_Telco -> I20443 | L4: =IND_Utili -> I00577 | M4: =Ind_Travel -> I00901 | N4: =Ind_Media -> I00937 | O4: {=IND_Auto} -> I00649
B5: {=_xll.FDS(B4,"FG_COMPANY_NAME")} -> FTSE World Europe | C5: {=_xll.FDS(C4,"FG_COMPANY_NAME")} -> FTSE World Europe / Basic Materials - IND | D5: {=_xll.FDS(D4,"FG_COMPANY_NAME")} -> FTSE World Europe / Consumer Staples - IND | E5: {=_xll.FDS(E4,"FG_COMPANY_NAME")} -> FTSE World Europe / Personal Goods - SEC | F5: {=_xll.FDS(F4,"FG_COMPANY_NAME")} -> FTSE World Europe / Financials - IND | G5: {=_xll.FDS(G4,"FG_COMPANY_NAME")} -> FTSE World Europe / Health Care - IND | H5: {=_xll.FDS(H4,"FG_COMPANY_NAME")} -> FTSE World Europe / Industrials - IND | I5: {=_xll.FDS(I4,"FG_COMPANY_NAME")} -> FTSE World Europe / Energy - IND | ... O5: {=_xll.FDS(O4,"FG_COMPANY_NAME")} -> FTSE World Europe / Automobiles and Parts - SEC
B6: PX_LAST
A7: {=_xll.FDS(B4,"JULIAN(FG_TOTAL_RET_IDX(0,-20AY,M,EUR).dates)")} -> 46295 | B7: {=_xll.FDS(B4,"FG_TOTAL_RET_IDX(0,-20AY,M,EUR)")} -> 2754.36 | C7: {=_xll.FDS(C4,"FG_TOTAL_RET_IDX(0,-20AY,M,EUR)")} -> 2997.4655 | D7: {=_xll.FDS(D4,"FG_TOTAL_RET_IDX(0,-20AY,M,EUR)")} -> 3696.854 | E7: {=_xll.FDS(E4,"FG_TOTAL_RET_IDX(0,-20AY,M,EUR)")} -> 12469.292 | F7: {=_xll.FDS(F4,"FG_TOTAL_RET_IDX(0,-20AY,M,EUR)")} -> 2026.0789 | G7: {=_xll.FDS(G4,"FG_TOTAL_RET_IDX(0,-20AY,M,EUR)")} -> 3580.0213 | H7: {=_xll.FDS(H4,"FG_TOTAL_RET_IDX(0,-20AY,M,EUR)")} -> 3693.7532 | I7: {=_xll.FDS(I4,"FG_TOTAL_RET_IDX(0,-20AY,M,EUR)")} -> 5489.6236 | ... O7: {=_xll.FDS(O4,"FG_TOTAL_RET_IDX(0,-20AY,M,EUR)")} -> 820.67868
A8: 46265 | B8: 2825.5075 | C8: 3134.7921 | D8: 3819.6449 | E8: 13549.596 | F8: 2087.6489 | G8: 3690.9727 | H8: 3838.6633 | I8: 5312.3883 | J8: 749.10393 | K8: 1136.2984 | L8: 6704.2006 | M8: 1665.4474 | N8: 1668.2993 | O8: 901.76276
A9: 46234 | B9: 2811.2472 | C9: 2938.2818 | D9: 3966.6345 | E9: 13796.799 | F9: 2064.8267 | G9: 3723.0895 | H9: 3825.5512 | I9: 5312.5759 | J9: 722.41908 | K9: 1108.5592 | L9: 6825.4911 | M9: 1659.1791 | N9: 1611.4803 | O9: 878.49601
A10: 46203 | B10: 2777.6709 | C10: 2874.5906 | D10: 3886.05 | E10: 13845.621 | F10: 1954.8118 | G10: 3776.0111 | H10: 3801.0465 | I10: 4819.2266 | J10: 800.47175 | K10: 1133.2348 | L10: 6905.7988 | M10: 1743.6938 | N10: 1636.0631 | O10: 842.86453
A11: 46171 | B11: 2699.1581 | C11: 3007.2845 | D11: 3716.9173 | E11: 13509.827 | F11: 1848.4868 | G11: 3611.9132 | H11: 3753.9118 | I11: 5076.3325 | J11: 732.13979 | K11: 1250.494 | L11: 6589.8374 | M11: 1605.9745 | N11: 1610.5157 | O11: 927.44539
A12: 46142 | B12: 2616.4729 | C12: 2857.9808 | D12: 3695.0246 | E12: 12566.467 | F12: 1782.6055 | G12: 3538.4825 | H12: 3627.4718 | I12: 5421.3365 | J12: 653.00474 | K12: 1196.7438 | L12: 6889.2027 | M12: 1473.7685 | N12: 1515.3035 | O12: 883.28693
A13: 46112 | B13: 2479.4879 | C13: 2720.7588 | D13: 3617.8885 | E13: 12174.593 | F13: 1638.5043 | G13: 3570.5142 | H13: 3342.5583 | I13: 5389.3602 | J13: 585.69694 | K13: 1153.5791 | L13: 6606.4901 | M13: 1419.8813 | N13: 1385.6613 | O13: 863.28072
A14: 46080 | B14: 2685.0594 | C14: 2875.6489 | D14: 4061.3825 | E14: 14188.436 | F14: 1781.3889 | G14: 3846.0602 | H14: 3790.1968 | I14: 4682.3906 | J14: 649.78545 | K14: 1197.4447 | L14: 6819.5161 | M14: 1564.8988 | N14: 1522.3848 | O14: 986.71612
A15: 46052 | B15: 2584.1688 | C15: 2640.3121 | D15: 3689.9997 | E15: 13773.655 | F15: 1779.1268 | G15: 3746.2787 | H15: 3633.3426 | I15: 4302.0106 | J15: 649.74156 | K15: 1033.5828 | L15: 6323.054 | M15: 1554.3512 | N15: 1630.3609 | O15: 959.55821
A16: 46022 | B16: 2498.9399 | C16: 2455.4599 | D16: 3697.4098 | E16: 15111.555 | F16: 1735.4058 | G16: 3618.5424 | H16: 3451.5764 | I16: 3939.1891 | J16: 605.8989 | K16: 992.04351 | L16: 5878.5637 | M16: 1603.0474 | N16: 1717.4043 | O16: 1000.7768
A17: 45989 | B17: 2430.5728 | C17: 2348.1531 | D17: 3722.4936 | E17: 14918.508 | F17: 1631.1488 | G17: 3573.0809 | H17: 3352.1935 | I17: 3944.7269 | J17: 599.5407 | K17: 973.27795 | L17: 5823.9755 | M17: 1565.2582 | N17: 1702.9141 | O17: 980.90986
A18: 45961 | B18: 2407.4275 | C18: 2331.7815 | D18: 3640.0502 | E18: 14581.111 | F18: 1580.4578 | G18: 3393.7039 | H18: 3459.1932 | I18: 3850.9219 | J18: 629.68588 | K18: 988.79679 | L18: 5694.026 | M18: 1551.4829 | N18: 1741.4983 | O18: 953.93706
A19: 45930 | B19: 2346.388 | C19: 2279.0868 | D19: 3533.8427 | E19: 13689.39 | F19: 1570.0846 | G19: 3255.4672 | H19: 3402.9826 | I19: 3618.5674 | J19: 608.57419 | K19: 968.09978 | L19: 5307.6302 | M19: 1594.9751 | N19: 1752.7027 | O19: 982.13214
... A246: 39021 | B246: 808.84 | C246: 801.06 | D246: 808.2 | E246: 2127.2 | F246: 828.37 | G246: 822.28 | H246: 696.83 | I246: 1616.32 | J246: 143.82 | K246: 502.09 | L246: 2110.88 | M246: 702.34 | N246: 546.26 | O246: 272.04

Sheet Leverage_FMA
A1: Time frame | AF1: Net Debt to EBITDA
A2: 60 | AF2: FMA_NDEBT_EBITDA
AF3: Historical Ratio
B6: Materials | C6: ConsStaples | D6: Pers. Goods | E6: Fin | F6: HealthCare | G6: Indus | H6: Oil | I6: Tech | J6: Telco | K6: Utili | L6: Travel & leisure | M6: Media | N6: Auto | Q6: Materials | R6: ConsStaples | S6: Pers. Goods | T6: Fin | U6: HealthCare | V6: Indus | W6: Oil | X6: Tech | Y6: Telco | Z6: Utili | AA6: Travel & leisure | AB6: Media | AC6: Auto | AF6: Materials | AG6: ConsStaples | AH6: Pers. Goods | AI6: Fin | AJ6: HealthCare | AK6: Indus | AL6: Oil | AM6: Tech | AN6: Telco | AO6: Utili | AP6: Travel & leisure | AQ6: Media | AR6: Auto | AS6: Materials | AT6: ConsStaples | AU6: Pers. Goods | AV6: Fin | AW6: HealthCare | AX6: Indus | AY6: Oil | AZ6: Tech | BA6: Telco | BB6: Utili | BC6: Travel & leisure | BD6: Media | BE6: Auto | BV6: Materials | BW6: ConsStaples | BX6: Pers. Goods | BY6: Fin | BZ6: HealthCare | CA6: Indus | CB6: Oil | CC6: Tech | CD6: Telco | CE6: Utili | CF6: Travel & leisure | CG6: Media | CH6: Auto | CI6: Materials | CJ6: ConsStaples | CK6: Pers. Goods | CL6: Fin | CM6: HealthCare | CN6: Indus | CO6: Oil | CP6: Tech | CQ6: Telco | CR6: Utili | CS6: Travel & leisure | CT6: Media | CU6: Auto | DL6: Materials | DM6: ConsStaples | DN6: Pers. Goods | DO6: Fin | DP6: HealthCare | DQ6: Indus | DR6: Oil | DS6: Tech | DT6: Telco | DU6: Utili | DV6: Travel & leisure | DW6: Media | DX6: Auto | DY6: Materials | DZ6: ConsStaples | EA6: Pers. Goods | EB6: Fin | EC6: HealthCare | ED6: Indus | EE6: Oil | EF6: Tech | EG6: Telco | EH6: Utili | EI6: Travel & leisure | EJ6: Media | EK6: Auto | FB6: Materials | FC6: ConsStaples | FD6: Pers. Goods | FE6: Fin | FF6: HealthCare | FG6: Indus | FH6: Oil | FI6: Tech | FJ6: Telco | FK6: Utili | FL6: Travel & leisure | FM6: Media | FN6: Auto | FO6: Materials | FP6: ConsStaples | FQ6: Pers. Goods | FR6: Fin | FS6: HealthCare | FT6: Indus | FU6: Oil | FV6: Tech | FW6: Telco | FX6: Utili | FY6: Travel & leisure | FZ6: Media | GA6: Auto | GR6: Materials | GS6: ConsStaples | GT6: Pers. Goods | GU6: Fin | GV6: HealthCare | GW6: Indus | GX6: Oil | GY6: Tech | GZ6: Telco | HA6: Utili | HB6: Travel & leisure | HC6: Media | HD6: Auto | HE6: Materials | HF6: ConsStaples | HG6: Pers. Goods | HH6: Fin | HI6: HealthCare | HJ6: Indus | HK6: Oil | HL6: Tech | HM6: Telco | HN6: Utili | HO6: Travel & leisure | HP6: Media | HQ6: Auto
AF7: I00037 | AG7: I00109 | AH7: I20438 | AI7: I00253 | AJ7: I20436 | AK7: I00073 | AL7: I20433 | AM7: I20448 | AN7: I20443 | AO7: I00577 | AP7: I00901 | AQ7: I00937 | AR7: I00649 | AS7: diff vs. moy | AT7: diff vs. moy | AU7: diff vs. moy | AV7: diff vs. moy | AW7: diff vs. moy | AX7: diff vs. moy | AY7: diff vs. moy | AZ7: diff vs. moy | BA7: diff vs. moy | BB7: diff vs. moy | BC7: diff vs. moy | BD7: diff vs. moy | BE7: diff vs. moy | BV7: I00037 | BW7: I00109 | BX7: I20438 | BY7: I00253 | BZ7: I20436 | CA7: I00073 | CB7: I20433 | CC7: I20448 | CD7: I20443 | CE7: I00577 | CF7: I00901 | CG7: I00937 | CH7: I00649 | CI7: diff vs. moy | CJ7: diff vs. moy | CK7: diff vs. moy | CL7: diff vs. moy | CM7: diff vs. moy | CN7: diff vs. moy | CO7: diff vs. moy | CP7: diff vs. moy | CQ7: diff vs. moy | CR7: diff vs. moy | CS7: diff vs. moy | CT7: diff vs. moy | CU7: diff vs. moy | DL7: I00037 | DM7: I00109 | DN7: I20438 | DO7: I00253 | DP7: I20436 | DQ7: I00073 | DR7: I20433 | DS7: I20448 | DT7: I20443 | DU7: I00577 | DV7: I00901 | DW7: I00937 | DX7: I00649 | DY7: diff vs. moy | DZ7: diff vs. moy | EA7: diff vs. moy | EB7: diff vs. moy | EC7: diff vs. moy | ED7: diff vs. moy | EE7: diff vs. moy | EF7: diff vs. moy | EG7: diff vs. moy | EH7: diff vs. moy | EI7: diff vs. moy | EJ7: diff vs. moy | EK7: diff vs. moy | FB7: I00037 | FC7: I00109 | FD7: I20438 | FE7: I00253 | FF7: I20436 | FG7: I00073 | FH7: I20433 | FI7: I20448 | FJ7: I20443 | FK7: I00577 | FL7: I00901 | FM7: I00937 | FN7: I00649 | FO7: diff vs. moy | FP7: diff vs. moy | FQ7: diff vs. moy | FR7: diff vs. moy | FS7: diff vs. moy | FT7: diff vs. moy | FU7: diff vs. moy | FV7: diff vs. moy | FW7: diff vs. moy | FX7: diff vs. moy | FY7: diff vs. moy | FZ7: diff vs. moy | GA7: diff vs. moy | GR7: I00037 | GS7: I00109 | GT7: I20438 | GU7: I00253 | GV7: I20436 | GW7: I00073 | GX7: I20433 | GY7: I20448 | GZ7: I20443 | HA7: I00577 | HB7: I00901 | HC7: I00937 | HD7: I00649 | HE7: diff vs. moy | HF7: diff vs. moy | HG7: diff vs. moy | HH7: diff vs. moy | HI7: diff vs. moy | HJ7: diff vs. moy | HK7: diff vs. moy | HL7: diff vs. moy | HM7: diff vs. moy | HN7: diff vs. moy | HO7: diff vs. moy | HP7: diff vs. moy | HQ7: diff vs. moy
A8: =AE8 -> 46295 | AE8: {=_xll.FDS(AF7,"JULIAN(FMA_NDEBT_EBITDA(LTM,0,-20AY,M,EUR,""PORTAGG"",""MEANR"").dates)")} -> 46295 | AF8: {=_xll.FDS(AF7,"FMA_NDEBT_EBITDA(LTM,0,-20AY,M,EUR,""PORTAGG"",""MEANR"")")} -> 1.5176704 | AG8: {=_xll.FDS(AG7,"FMA_NDEBT_EBITDA(LTM,0,-20AY,M,EUR,""PORTAGG"",""MEANR"")")} -> 2.57611 | AH8: {=_xll.FDS(AH7,"FMA_NDEBT_EBITDA(LTM,0,-20AY,M,EUR,""PORTAGG"",""MEANR"")")} -> 0.73907005 | AI8: {=_xll.FDS(AI7,"FMA_NDEBT_EBITDA(LTM,0,-20AY,M,EUR,""PORTAGG"",""MEANR"")")} -> 10.11696 | AJ8: {=_xll.FDS(AJ7,"FMA_NDEBT_EBITDA(LTM,0,-20AY,M,EUR,""PORTAGG"",""MEANR"")")} -> 1.5089102 | AK8: {=_xll.FDS(AK7,"FMA_NDEBT_EBITDA(LTM,0,-20AY,M,EUR,""PORTAGG"",""MEANR"")")} -> 1.6366061 | AL8: {=_xll.FDS(AL7,"FMA_NDEBT_EBITDA(LTM,0,-20AY,M,EUR,""PORTAGG"",""MEANR"")")} -> 0.75166269 | AM8: {=_xll.FDS(AM7,"FMA_NDEBT_EBITDA(LTM,0,-20AY,M,EUR,""PORTAGG"",""MEANR"")")} -> 0.43980775 | ... AR8: {=_xll.FDS(AR7,"FMA_NDEBT_EBITDA(LTM,0,-20AY,M,EUR,""PORTAGG"",""MEANR"")")} -> 5.6573717 | FB8: {=_xll.FDS(FB7,"FMA_FCF_DEBT(LTM,0,-20AY,M,""PORTAGG"")")} -> 10.980834 | FC8: {=_xll.FDS(FC7,"FMA_FCF_DEBT(LTM,0,-20AY,M,""PORTAGG"")")} -> 17.981573 | FD8: {=_xll.FDS(FD7,"FMA_FCF_DEBT(LTM,0,-20AY,M,""PORTAGG"")")} -> 33.20084 | FE8: {=_xll.FDS(FE7,"FMA_FCF_DEBT(LTM,0,-20AY,M,""PORTAGG"")")} -> 2.8015014 | FF8: {=_xll.FDS(FF7,"FMA_FCF_DEBT(LTM,0,-20AY,M,""PORTAGG"")")} -> 28.807423 | FG8: {=_xll.FDS(FG7,"FMA_FCF_DEBT(LTM,0,-20AY,M,""PORTAGG"")")} -> 22.892464 | FH8: {=_xll.FDS(FH7,"FMA_FCF_DEBT(LTM,0,-20AY,M,""PORTAGG"")")} -> 26.597811 | FI8: {=_xll.FDS(FI7,"FMA_FCF_DEBT(LTM,0,-20AY,M,""PORTAGG"")")} -> 51.01086 | ... FN8: {=_xll.FDS(FN7,"FMA_FCF_DEBT(LTM,0,-20AY,M,""PORTAGG"")")} -> 0.019678022 | GR8: {=_xll.FDS(FB7,"FMA_DEBT_EQ(LTM,0,-20AY,M,""PORTAGG"")")} -> 57.789196 | GS8: {=_xll.FDS(FC7,"FMA_DEBT_EQ(LTM,0,-20AY,M,""PORTAGG"")")} -> 115.95281 | GT8: {=_xll.FDS(FD7,"FMA_DEBT_EQ(LTM,0,-20AY,M,""PORTAGG"")")} -> 58.519142 | GU8: {=_xll.FDS(FE7,"FMA_DEBT_EQ(LTM,0,-20AY,M,""PORTAGG"")")} -> 417.95205 | GV8: {=_xll.FDS(FF7,"FMA_DEBT_EQ(LTM,0,-20AY,M,""PORTAGG"")")} -> 66.839496 | GW8: {=_xll.FDS(FG7,"FMA_DEBT_EQ(LTM,0,-20AY,M,""PORTAGG"")")} -> 85.294826 | GX8: {=_xll.FDS(FH7,"FMA_DEBT_EQ(LTM,0,-20AY,M,""PORTAGG"")")} -> 62.418637 | GY8: {=_xll.FDS(FI7,"FMA_DEBT_EQ(LTM,0,-20AY,M,""PORTAGG"")")} -> 42.505912 | ... HD8: {=_xll.FDS(FN7,"FMA_DEBT_EQ(LTM,0,-20AY,M,""PORTAGG"")")} -> 135.79482
A9: =AE9 -> 46265 | AE9: 46265 | AF9: 1.4958886 | AG9: 2.5440042 | AH9: 0.7307181 | AI9: 9.0843149 | AJ9: 1.4908482 | AK9: 1.6410306 | AL9: 0.75666043 | AM9: 0.40727223 | AN9: 2.6529653 | AO9: 3.7598591 | AP9: 2.3172619 | AQ9: 1.3609239 | AR9: 5.6212024 | FB9: 11.201093 | FC9: 18.214802 | FD9: 33.345147 | FE9: 3.0450564 | FF9: 29.163509 | FG9: 23.038333 | FH9: 25.723958 | FI9: 52.970629 | FJ9: 15.331863 | FK9: -0.76047409 | FL9: 12.818879 | FM9: 36.783964 | FN9: -0.13866191 | GR9: 57.436565 | GS9: 116.04617 | GT9: 58.440357 | GU9: 379.55648 | GV9: 66.892741 | GW9: 85.425095 | GX9: 63.651527 | GY9: 41.161624 | GZ9: 169.13376 | HA9: 160.57267 | HB9: 152.51244 | HC9: 52.496003 | HD9: 133.42291
A10: =AE10 -> 46234 | AE10: 46234 | AF10: 1.549661 | AG10: 2.3739773 | AH10: 0.64841657 | AI10: 14.720224 | AJ10: 1.4573265 | AK10: 1.5672753 | AL10: 0.92742092 | AM10: 0.34525446 | AN10: 2.4989076 | AO10: 3.5698622 | AP10: 2.1405821 | AQ10: 0.81608864 | AR10: 5.2738347 | FB10: 13.11978 | FC10: 17.19837 | FD10: 32.42722 | FE10: 3.0630081 | FF10: 27.236136 | FG10: 21.34751 | FH10: 16.740986 | FI10: 52.925017 | FJ10: 15.489838 | FK10: -2.5823743 | FL10: 13.622638 | FM10: 43.098772 | FN10: -0.12250748 | GR10: 54.087347 | GS10: 109.81559 | GT10: 56.160841 | GU10: 429.2043 | GV10: 68.154333 | GW10: 84.921897 | GX10: 65.526108 | GY10: 36.871491 | GZ10: 156.03813 | HA10: 158.24827 | HB10: 145.07135 | HC10: 43.755562 | HD10: 125.41786
A11: =AE11 -> 46203 | AE11: 46203 | AF11: 1.5663558 | AG11: 2.3929997 | AH11: 0.65288539 | AI11: 14.796834 | AJ11: 1.4674978 | AK11: 1.5740812 | AL11: 0.93988341 | AM11: 0.34562477 | AN11: 2.5152696 | AO11: 3.5956492 | AP11: 2.1590125 | AQ11: 0.82235371 | AR11: 5.3045246 | FB11: 12.987411 | FC11: 17.061587 | FD11: 32.260868 | FE11: 3.0461691 | FF11: 27.030592 | FG11: 21.270114 | FH11: 16.614474 | FI11: 52.599707 | FJ11: 15.391272 | FK11: -2.5709933 | FL11: 13.541755 | FM11: 42.77877 | FN11: -0.066935884 | GR11: 54.160592 | GS11: 109.79701 | GT11: 56.189226 | GU11: 429.7837 | GV11: 68.133603 | GW11: 84.918594 | GX11: 65.558614 | GY11: 36.835389 | GZ11: 156.02917 | HA11: 158.20322 | HB11: 144.8677 | HC11: 43.752856 | HD11: 125.50958
A12: =AE12 -> 46171 | AE12: 46171 | AF12: 1.5910127 | AG12: 2.3477671 | AH12: 0.66236562 | AI12: 14.705528 | AJ12: 1.4466399 | AK12: 1.5446776 | AL12: 0.93041117 | AM12: 0.33595651 | AN12: 2.4939496 | AO12: 3.568009 | AP12: 2.1259314 | AQ12: 0.80657927 | AR12: 5.234872 | FB12: 12.715537 | FC12: 17.444294 | FD12: 32.350159 | FE12: 3.0655825 | FF12: 27.531504 | FG12: 21.699828 | FH12: 16.848306 | FI12: 53.736396 | FJ12: 15.520187 | FK12: -2.6211649 | FL12: 13.819198 | FM12: 43.296613 | FN12: -0.076269272 | GR12: 53.967092 | GS12: 109.91087 | GT12: 56.571692 | GU12: 430.49076 | GV12: 68.271698 | GW12: 85.781216 | GX12: 65.684083 | GY12: 35.697571 | GZ12: 156.27713 | HA12: 158.36555 | HB12: 144.19261 | HC12: 43.235061 | HD12: 125.5062
A13: =AE13 -> 46142 | AE13: 46142 | AF13: 1.6373341 | AG13: 2.376396 | AH13: 0.67874176 | AI13: 10.58071 | AJ13: 1.2964012 | AK13: 1.4889863 | AL13: 0.97648599 | AM13: 0.22554793 | AN13: 2.6352968 | AO13: 3.5377353 | AP13: 2.0439264 | AQ13: 0.78729105 | AR13: 4.6193553 | FB13: 12.164846 | FC13: 17.287173 | FD13: 32.006495 | FE13: 3.0086454 | FF13: 30.448076 | FG13: 22.205138 | FH13: 19.062256 | FI13: 57.92396 | FJ13: 15.175507 | FK13: -2.8833321 | FL13: 14.180433 | FM13: 43.390682 | FN13: 0.31850236 | GR13: 54.063533 | GS13: 110.02454 | GT13: 58.065247 | GU13: 403.25133 | GV13: 63.785937 | GW13: 85.805929 | GX13: 67.178753 | GY13: 37.523612 | GZ13: 160.30064 | HA13: 157.80769 | HB13: 150.50227 | HC13: 43.223984 | HD13: 125.16498
A14: =AE14 -> 46112 | AE14: 46112 | AF14: 1.6741689 | AG14: 2.4247004 | AH14: 0.69115486 | AI14: 10.754914 | AJ14: 1.3238237 | AK14: 1.5202942 | AL14: 0.99877185 | AM14: 0.23369083 | AN14: 2.6859784 | AO14: 3.6043075 | AP14: 2.0178224 | AQ14: 0.80630539 | AR14: 4.6948729 | FB14: 11.876507 | FC14: 16.098032 | FD14: 31.435862 | FE14: 2.958035 | FF14: 29.807883 | FG14: 21.733452 | FH14: 18.633791 | FI14: 57.132192 | FJ14: 14.864234 | FK14: -2.8315055 | FL14: 13.949691 | FM14: 42.453715 | FN14: 0.31680308 | GR14: 54.0968 | GS14: 109.66565 | GT14: 58.040888 | GU14: 403.93375 | GV14: 63.769462 | GW14: 85.840126 | GX14: 67.092584 | GY14: 37.600899 | GZ14: 159.96726 | HA14: 157.8132 | HB14: 150.78356 | HC14: 43.27168 | HD14: 125.1354
A15: =AE15 -> 46080 | AE15: 46080 | AF15: 1.673474 | AG15: 2.3922 | AH15: 0.67055099 | AI15: 10.552088 | AJ15: 1.3109204 | AK15: 1.5008273 | AL15: 0.99640604 | AM15: 0.22099272 | AN15: 2.6436078 | AO15: 3.564189 | AP15: 2.0589566 | AQ15: 1.1333483 | AR15: 4.6579541 | FB15: 11.834921 | FC15: 16.280642 | FD15: 32.045455 | FE15: 4.0105855 | FF15: 30.112366 | FG15: 22.074523 | FH15: 18.775747 | FI15: 58.458365 | FJ15: 14.981165 | FK15: -2.9370427 | FL15: 13.896843 | FM15: 30.279627 | FN15: 0.26653502 | GR15: 54.605772 | GS15: 109.509 | GT15: 57.522001 | GU15: 493.48064 | GV15: 63.794275 | GW15: 85.640363 | GX15: 67.03353 | GY15: 37.28215 | GZ15: 159.23186 | HA15: 157.1533 | HB15: 154.89217 | HC15: 63.095349 | HD15: 124.61008
A16: =AE16 -> 46052 | AE16: 46052 | AF16: 1.6167843 | AG16: 2.6318319 | AH16: 0.82320616 | AI16: 14.121164 | AJ16: 1.3318153 | AK16: 1.6913823 | AL16: 0.91012051 | AM16: 0.37695022 | AN16: 2.589485 | AO16: 3.4525748 | AP16: 2.0687214 | AQ16: 1.4254467 | AR16: 3.8354445 | FB16: 11.245123 | FC16: 16.511523 | FD16: 30.933835 | FE16: 4.7788173 | FF16: 31.830898 | FG16: 20.936575 | FH16: 20.187461 | FI16: 54.56312 | FJ16: 15.151632 | FK16: -2.4851532 | FL16: 14.132932 | FM16: 28.573345 | FN16: 1.9451461 | GR16: 56.508639 | GS16: 115.68277 | GT16: 61.020291 | GU16: 542.61695 | GV16: 65.506409 | GW16: 90.093551 | GX16: 65.284653 | GY16: 36.124964 | GZ16: 151.32551 | HA16: 160.57588 | HB16: 156.34183 | HC16: 64.128432 | HD16: 121.54154
A17: =AE17 -> 46022 | AE17: 46022 | AF17: 1.5932829 | AG17: 2.5930839 | AH17: 0.813249 | AI17: 14.167655 | AJ17: 1.3148474 | AK17: 1.6807964 | AL17: 0.89429478 | AM17: 0.3706882 | AN17: 2.5550248 | AO17: 3.4061743 | AP17: 2.0364782 | AQ17: 1.3993883 | AR17: 3.7928863 | FB17: 11.406431 | FC17: 16.76267 | FD17: 31.263228 | FE17: 4.776616 | FF17: 32.235547 | FG17: 21.232996 | FH17: 20.522331 | FI17: 55.309936 | FJ17: 15.353131 | FK17: -2.538148 | FL17: 14.329417 | FM17: 29.077863 | FN17: 1.9806256 | GR17: 56.508973 | GS17: 115.74633 | GT17: 61.011759 | GU17: 545.31483 | GV17: 65.508325 | GW17: 90.728785 | GX17: 65.409696 | GY17: 36.075755 | GZ17: 151.38482 | HA17: 160.66396 | HB17: 156.12854 | HC17: 64.093625 | HD17: 121.47965
A18: =AE18 -> 45989 | AE18: 45989 | AF18: 1.6109957 | AG18: 2.6338817 | AH18: 0.82141389 | AI18: 14.29899 | AJ18: 1.3312354 | AK18: 1.6938373 | AL18: 0.91132813 | AM18: 0.37425064 | AN18: 2.578677 | AO18: 3.4446459 | AP18: 2.1057214 | AQ18: 1.4195325 | AR18: 3.8357879 | FB18: 11.291091 | FC18: 16.399033 | FD18: 30.803595 | FE18: 4.7325176 | FF18: 31.795946 | FG18: 21.00221 | FH18: 20.185592 | FI18: 54.483307 | FJ18: 15.102679 | FK18: -2.6003262 | FL18: 13.94935 | FM18: 28.754278 | FN18: 1.9643037 | GR18: 56.592085 | GS18: 117.19568 | GT18: 60.931107 | GU18: 545.59764 | GV18: 65.540468 | GW18: 90.622317 | GX18: 65.479745 | GY18: 36.138157 | GZ18: 150.44385 | HA18: 160.46846 | HB18: 159.2359 | HC18: 64.151346 | HD18: 121.84757
A19: =AE19 -> 45961 | AE19: 45961 | AF19: 1.6806374 | AG19: 2.6537639 | AH19: 0.78429788 | AI19: 9.8053668 | AJ19: 1.3921369 | AK19: 1.7469499 | AL19: 0.94321026 | AM19: 0.33451472 | AN19: 2.5979127 | AO19: 3.4428557 | AP19: 2.1112122 | AQ19: 1.4266518 | AR19: 4.0699874 | FB19: 10.267257 | FC19: 16.651101 | FD19: 30.637695 | FE19: 6.0577832 | FF19: 31.7052 | FG19: 20.449825 | FH19: 19.756891 | FI19: 54.032405 | FJ19: 15.543785 | FK19: -2.9691976 | FL19: 14.300481 | FM19: 28.507135 | FN19: 1.5508851 | GR19: 58.268056 | GS19: 117.63561 | GT19: 59.945017 | GU19: 481.30878 | GV19: 65.588931 | GW19: 92.445263 | GX19: 64.292823 | GY19: 36.473072 | GZ19: 161.42642 | HA19: 161.72925 | HB19: 163.2513 | HC19: 64.299009 | HD19: 123.78958
A20: =AE20 -> 45930 | AE20: 45930 | AF20: 1.6386287 | AG20: 2.5970624 | AH20: 0.76195112 | AI20: 9.5496695 | AJ20: 1.355533 | AK20: 1.6951797 | AL20: 0.91975725 | AM20: 0.32528008 | AN20: 2.529196 | AO20: 3.3565968 | AP20: 2.0933871 | AQ20: 1.3907866 | AR20: 3.9625524 | FB20: 10.530657 | FC20: 16.425691 | FD20: 31.430351 | FE20: 6.2201092 | FF20: 32.555351 | FG20: 21.052198 | FH20: 20.232605 | FI20: 55.490256 | FJ20: 15.958235 | FK20: -3.0492769 | FL20: 15.166612 | FM20: 29.231238 | FN20: 1.6061992 | GR20: 58.282521 | GS20: 117.52067 | GT20: 59.919202 | GU20: 481.41879 | GV20: 65.636585 | GW20: 92.335498 | GX20: 64.352698 | GY20: 36.48018 | GZ20: 161.13204 | HA20: 161.68363 | HB20: 161.76862 | HC20: 64.335449 | HD20: 123.74321
... A247: =AE247 -> 39021 | AE247: 39021 | AF247: 1.1834915 | AG247: 2.4344864 | AH247: 1.0128347 | AI247: 4.6213042 | AJ247: 0.1107719 | AK247: 2.0122777 | AL247: 0.2617597 | AM247: -0.7024698 | AN247: 1.6576704 | AO247: 2.3943958 | AP247: 2.2136142 | AQ247: 1.7040297 | AR247: 3.6222093 | FB247: 19.12641 | FC247: 4.2088596 | FD247: 27.266957 | FE247: -10.598142 | FF247: 70.05021 | FG247: 11.28295 | FH247: 53.163243 | FI247: 53.267447 | FJ247: 18.861388 | FK247: 4.243608 | FL247: 11.363589 | FM247: 21.68801 | FN247: -6.0317867 | GR247: 60.293761 | GS247: 123.35185 | GT247: 47.782471 | GU247: 71.301041 | GV247: 32.872663 | GW247: 103.51742 | GX247: 31.557861 | GY247: 29.444467 | GZ247: 102.27206 | HA247: 123.75651 | HB247: 124.53711 | HC247: 92.592353 | HD247: 197.50671

Sheet Margin_FMA
A1: Time frame | BV1: Operating Margin | DL1: Net Margin | GR1: EBITDA Margin
A2: 60 | BV2: FMA_OPER_INC_SALES | DL2: FMA_NET_MGN | GR2: FMA_EBITDA_MARGIN
BV3: Historical Ratio | DL3: Historical Ratio | GR3: Historical Ratio
B6: Materials | C6: ConsStaples | D6: Pers. Goods | E6: Fin | F6: HealthCare | G6: Indus | H6: Oil | I6: Tech | J6: Telco | K6: Utili | L6: Travel & leisure | M6: Media | N6: Auto | Q6: Materials | R6: ConsStaples | S6: Pers. Goods | T6: Fin | U6: HealthCare | V6: Indus | W6: Oil | X6: Tech | Y6: Telco | Z6: Utili | AA6: Travel & leisure | AB6: Media | AC6: Auto | AF6: Materials | AG6: ConsStaples | AH6: Pers. Goods | AI6: Fin | AJ6: HealthCare | AK6: Indus | AL6: Oil | AM6: Tech | AN6: Telco | AO6: Utili | AP6: Travel & leisure | AQ6: Media | AR6: Auto | AS6: Materials | AT6: ConsStaples | AU6: Pers. Goods | AV6: Fin | AW6: HealthCare | AX6: Indus | AY6: Oil | AZ6: Tech | BA6: Telco | BB6: Utili | BC6: Travel & leisure | BD6: Media | BE6: Auto | BV6: Materials | BW6: ConsStaples | BX6: Pers. Goods | BY6: Fin | BZ6: HealthCare | CA6: Indus | CB6: Oil | CC6: Tech | CD6: Telco | CE6: Utili | CF6: Travel & leisure | CG6: Media | CH6: Auto | CI6: Materials | CJ6: ConsStaples | CK6: Pers. Goods | CL6: Fin | CM6: HealthCare | CN6: Indus | CO6: Oil | CP6: Tech | CQ6: Telco | CR6: Utili | CS6: Travel & leisure | CT6: Media | CU6: Auto | DL6: Materials | DM6: ConsStaples | DN6: Pers. Goods | DO6: Fin | DP6: HealthCare | DQ6: Indus | DR6: Oil | DS6: Tech | DT6: Telco | DU6: Utili | DV6: Travel & leisure | DW6: Media | DX6: Auto | DY6: Materials | DZ6: ConsStaples | EA6: Pers. Goods | EB6: Fin | EC6: HealthCare | ED6: Indus | EE6: Oil | EF6: Tech | EG6: Telco | EH6: Utili | EI6: Travel & leisure | EJ6: Media | EK6: Auto | FB6: Materials | FC6: ConsStaples | FD6: Pers. Goods | FE6: Fin | FF6: HealthCare | FG6: Indus | FH6: Oil | FI6: Tech | FJ6: Telco | FK6: Utili | FL6: Travel & leisure | FM6: Media | FN6: Auto | FO6: Materials | FP6: ConsStaples | FQ6: Pers. Goods | FR6: Fin | FS6: HealthCare | FT6: Indus | FU6: Oil | FV6: Tech | FW6: Telco | FX6: Utili | FY6: Travel & leisure | FZ6: Media | GA6: Auto | GR6: Materials | GS6: ConsStaples | GT6: Pers. Goods | GU6: Fin | GV6: HealthCare | GW6: Indus | GX6: Oil | GY6: Tech | GZ6: Telco | HA6: Utili | HB6: Travel & leisure | HC6: Media | HD6: Auto | HE6: Materials | HF6: ConsStaples | HG6: Pers. Goods | HH6: Fin | HI6: HealthCare | HJ6: Indus | HK6: Oil | HL6: Tech | HM6: Telco | HN6: Utili | HO6: Travel & leisure | HP6: Media | HQ6: Auto
AF7: I00037 | AG7: I00109 | AH7: I20438 | AI7: I00253 | AJ7: I20436 | AK7: I00073 | AL7: I20433 | AM7: I20448 | AN7: I20443 | AO7: I00577 | AP7: I00901 | AQ7: I00937 | AR7: I00649 | AS7: diff vs. moy | AT7: diff vs. moy | AU7: diff vs. moy | AV7: diff vs. moy | AW7: diff vs. moy | AX7: diff vs. moy | AY7: diff vs. moy | AZ7: diff vs. moy | BA7: diff vs. moy | BB7: diff vs. moy | BC7: diff vs. moy | BD7: diff vs. moy | BE7: diff vs. moy | BV7: I00037 | BW7: I00109 | BX7: I20438 | BY7: I00253 | BZ7: I20436 | CA7: I00073 | CB7: I20433 | CC7: I20448 | CD7: I20443 | CE7: I00577 | CF7: I00901 | CG7: I00937 | CH7: I00649 | CI7: diff vs. moy | CJ7: diff vs. moy | CK7: diff vs. moy | CL7: diff vs. moy | CM7: diff vs. moy | CN7: diff vs. moy | CO7: diff vs. moy | CP7: diff vs. moy | CQ7: diff vs. moy | CR7: diff vs. moy | CS7: diff vs. moy | CT7: diff vs. moy | CU7: diff vs. moy | DL7: I00037 | DM7: I00109 | DN7: I20438 | DO7: I00253 | DP7: I20436 | DQ7: I00073 | DR7: I20433 | DS7: I20448 | DT7: I20443 | DU7: I00577 | DV7: I00901 | DW7: I00937 | DX7: I00649 | DY7: diff vs. moy | DZ7: diff vs. moy | EA7: diff vs. moy | EB7: diff vs. moy | EC7: diff vs. moy | ED7: diff vs. moy | EE7: diff vs. moy | EF7: diff vs. moy | EG7: diff vs. moy | EH7: diff vs. moy | EI7: diff vs. moy | EJ7: diff vs. moy | EK7: diff vs. moy | FB7: I00037 | FC7: I00109 | FD7: I20438 | FE7: I00253 | FF7: I20436 | FG7: I00073 | FH7: I20433 | FI7: I20448 | FJ7: I20443 | FK7: I00577 | FL7: I00901 | FM7: I00937 | FN7: I00649 | FO7: diff vs. moy | FP7: diff vs. moy | FQ7: diff vs. moy | FR7: diff vs. moy | FS7: diff vs. moy | FT7: diff vs. moy | FU7: diff vs. moy | FV7: diff vs. moy | FW7: diff vs. moy | FX7: diff vs. moy | FY7: diff vs. moy | FZ7: diff vs. moy | GA7: diff vs. moy | GR7: I00037 | GS7: I00109 | GT7: I20438 | GU7: I00253 | GV7: I20436 | GW7: I00073 | GX7: I20433 | GY7: I20448 | GZ7: I20443 | HA7: I00577 | HB7: I00901 | HC7: I00937 | HD7: I00649 | HE7: diff vs. moy | HF7: diff vs. moy | HG7: diff vs. moy | HH7: diff vs. moy | HI7: diff vs. moy | HJ7: diff vs. moy | HK7: diff vs. moy | HL7: diff vs. moy | HM7: diff vs. moy | HN7: diff vs. moy | HO7: diff vs. moy | HP7: diff vs. moy | HQ7: diff vs. moy
A8: =AE8 -> 46295 | AE8: {=_xll.FDS(AF7,"JULIAN(FMA_GROSS_MARGIN(LTM,0,-20AY,M,EUR,""PORTAGG"",""MEANR"").dates)")} -> 46295 | BV8: {=_xll.FDS(BV7,"FMA_OPER_INC_SALES(LTM,0,-20AY,M,""PORTAGG"")")} -> 8.6551612 | BW8: {=_xll.FDS(BW7,"FMA_OPER_INC_SALES(LTM,0,-20AY,M,""PORTAGG"")")} -> 11.498439 | BX8: {=_xll.FDS(BX7,"FMA_OPER_INC_SALES(LTM,0,-20AY,M,""PORTAGG"")")} -> 18.044296 | BY8: {=_xll.FDS(BY7,"FMA_OPER_INC_SALES(LTM,0,-20AY,M,""PORTAGG"")")} -> 17.486197 | BZ8: {=_xll.FDS(BZ7,"FMA_OPER_INC_SALES(LTM,0,-20AY,M,""PORTAGG"")")} -> 23.281359 | CA8: {=_xll.FDS(CA7,"FMA_OPER_INC_SALES(LTM,0,-20AY,M,""PORTAGG"")")} -> 11.077253 | CB8: {=_xll.FDS(CB7,"FMA_OPER_INC_SALES(LTM,0,-20AY,M,""PORTAGG"")")} -> 12.707879 | CC8: {=_xll.FDS(CC7,"FMA_OPER_INC_SALES(LTM,0,-20AY,M,""PORTAGG"")")} -> 23.063598 | ... CH8: {=_xll.FDS(CH7,"FMA_OPER_INC_SALES(LTM,0,-20AY,M,""PORTAGG"")")} -> 2.5611904 | DL8: {=_xll.FDS(DL7,"FMA_NET_MGN(LTM,0,-20AY,M,""PORTAGG"")")} -> 6.0453761 | DM8: {=_xll.FDS(DM7,"FMA_NET_MGN(LTM,0,-20AY,M,""PORTAGG"")")} -> 7.318707 | DN8: {=_xll.FDS(DN7,"FMA_NET_MGN(LTM,0,-20AY,M,""PORTAGG"")")} -> 11.481202 | DO8: {=_xll.FDS(DO7,"FMA_NET_MGN(LTM,0,-20AY,M,""PORTAGG"")")} -> 12.648923 | DP8: {=_xll.FDS(DP7,"FMA_NET_MGN(LTM,0,-20AY,M,""PORTAGG"")")} -> 16.548002 | DQ8: {=_xll.FDS(DQ7,"FMA_NET_MGN(LTM,0,-20AY,M,""PORTAGG"")")} -> 7.5557529 | DR8: {=_xll.FDS(DR7,"FMA_NET_MGN(LTM,0,-20AY,M,""PORTAGG"")")} -> 7.516947 | DS8: {=_xll.FDS(DS7,"FMA_NET_MGN(LTM,0,-20AY,M,""PORTAGG"")")} -> 21.193798 | ... DX8: {=_xll.FDS(DX7,"FMA_NET_MGN(LTM,0,-20AY,M,""PORTAGG"")")} -> 1.0105513 | GR8: {=_xll.FDS(FB7,"FMA_EBITDA_MARGIN(LTM,0,-20AY,M,""PORTAGG"")")} -> 13.757778 | GS8: {=_xll.FDS(FC7,"FMA_EBITDA_MARGIN(LTM,0,-20AY,M,""PORTAGG"")")} -> 15.836251 | GT8: {=_xll.FDS(FD7,"FMA_EBITDA_MARGIN(LTM,0,-20AY,M,""PORTAGG"")")} -> 25.277612 | GU8: {=_xll.FDS(FE7,"FMA_EBITDA_MARGIN(LTM,0,-20AY,M,""PORTAGG"")")} -> 51.665548 | GV8: {=_xll.FDS(FF7,"FMA_EBITDA_MARGIN(LTM,0,-20AY,M,""PORTAGG"")")} -> 31.620939 | GW8: {=_xll.FDS(FG7,"FMA_EBITDA_MARGIN(LTM,0,-20AY,M,""PORTAGG"")")} -> 15.843936 | GX8: {=_xll.FDS(FH7,"FMA_EBITDA_MARGIN(LTM,0,-20AY,M,""PORTAGG"")")} -> 19.852902 | GY8: {=_xll.FDS(FI7,"FMA_EBITDA_MARGIN(LTM,0,-20AY,M,""PORTAGG"")")} -> 29.081963 | ... HD8: {=_xll.FDS(FN7,"FMA_EBITDA_MARGIN(LTM,0,-20AY,M,""PORTAGG"")")} -> 9.9166825
A9: =AE9 -> 46265 | AE9: 46265 | BV9: 8.6713933 | BW9: 11.472703 | BX9: 18.006086 | BY9: 17.548251 | BZ9: 23.274637 | CA9: 11.090578 | CB9: 12.78119 | CC9: 22.605026 | CD9: 15.668198 | CE9: 15.292488 | CF9: 9.0098789 | CG9: 14.74251 | CH9: 2.1648613 | DL9: 6.0711932 | DM9: 7.3030761 | DN9: 11.480401 | DO9: 12.700157 | DP9: 16.537956 | DQ9: 7.4728444 | DR9: 7.5153315 | DS9: 20.759675 | DT9: 6.780211 | DU9: 9.3711922 | DV9: 6.2264916 | DW9: 10.097643 | DX9: 0.67433289 | GR9: 13.782107 | GS9: 15.806148 | GT9: 25.240312 | GU9: 52.631187 | GV9: 31.613802 | GW9: 16.029981 | GX9: 19.843572 | GY9: 28.37418 | GZ9: 36.811565 | HA9: 24.788555 | HB9: 16.354607 | HC9: 21.045347 | HD9: 9.5380001
A10: =AE10 -> 46234 | AE10: 46234 | BV10: 7.7508786 | BW10: 11.476783 | BX10: 18.017435 | BY10: 17.824026 | BZ10: 23.175442 | CA10: 10.865633 | CB10: 11.430768 | CC10: 22.265401 | CD10: 14.92448 | CE10: 15.038105 | CF10: 9.8808563 | CG10: 15.49159 | CH10: 2.479897 | DL10: 4.3229631 | DM10: 7.6713225 | DN10: 11.63467 | DO10: 13.001812 | DP10: 16.847369 | DQ10: 7.5744117 | DR10: 6.3410656 | DS10: 21.190836 | DT10: 5.5572316 | DU10: 8.7102937 | DV10: 8.0957062 | DW10: 11.502727 | DX10: -0.58831401 | GR10: 13.365026 | GS10: 15.671254 | GT10: 25.238328 | GU10: 51.723434 | GV10: 31.330104 | GW10: 15.843865 | GX10: 19.163973 | GY10: 28.158379 | GZ10: 36.00746 | HA10: 24.748569 | HB10: 17.104832 | HC10: 21.441514 | HD10: 9.5001751
A11: =AE11 -> 46203 | AE11: 46203 | BV11: 7.740818 | BW11: 11.469503 | BX11: 18.014489 | BY11: 17.811919 | BZ11: 23.165795 | CA11: 10.858938 | CB11: 11.376662 | CC11: 22.250598 | CD11: 14.920304 | CE11: 15.032489 | CF11: 9.8622263 | CG11: 15.486139 | CH11: 2.4244418 | DL11: 4.3145338 | DM11: 7.6627565 | DN11: 11.632103 | DO11: 12.996996 | DP11: 16.837368 | DQ11: 7.5676595 | DR11: 6.3391072 | DS11: 21.194604 | DT11: 5.5513224 | DU11: 8.7059017 | DV11: 8.0958492 | DW11: 11.500895 | DX11: -0.65707815 | GR11: 13.352248 | GS11: 15.664639 | GT11: 25.235135 | GU11: 51.541973 | GV11: 31.321516 | GW11: 15.833572 | GX11: 19.093529 | GY11: 28.133078 | GZ11: 35.998577 | HA11: 24.742325 | HB11: 17.087802 | HC11: 21.426764 | HD11: 9.4411782
A12: =AE12 -> 46171 | AE12: 46171 | BV12: 7.4941556 | BW12: 11.536797 | BX12: 18.075903 | BY12: 17.789133 | BZ12: 23.189129 | CA12: 10.972375 | CB12: 11.323435 | CC12: 22.28185 | CD12: 14.789637 | CE12: 15.012918 | CF12: 9.924253 | CG12: 15.485024 | CH12: 2.5690365 | DL12: 4.2719891 | DM12: 7.7085536 | DN12: 11.642673 | DO12: 12.969844 | DP12: 16.873795 | DQ12: 7.6144122 | DR12: 6.3278409 | DS12: 21.182388 | DT12: 5.3869045 | DU12: 8.6703188 | DV12: 8.1507311 | DW12: 11.5088 | DX12: -0.51366417 | GR12: 13.062965 | GS12: 15.742242 | GT12: 25.29565 | GU12: 51.389394 | GV12: 31.344987 | GW12: 15.948266 | GX12: 19.043404 | GY12: 28.190737 | GZ12: 35.846733 | HA12: 24.718725 | HB12: 17.14707 | HC12: 21.526865 | HD12: 9.5962305
A13: =AE13 -> 46142 | AE13: 46142 | BV13: 7.1519707 | BW13: 11.583908 | BX13: 18.096486 | BY13: 16.30335 | BZ13: 23.236133 | CA13: 10.773941 | CB13: 8.772078 | CC13: 22.83782 | CD13: 14.673068 | CE13: 14.94653 | CF13: 10.598859 | CG13: 15.471047 | CH13: 2.5692145 | DL13: 4.325931 | DM13: 7.7131255 | DN13: 12.035235 | DO13: 11.878645 | DP13: 16.750343 | DQ13: 7.6632968 | DR13: 5.4114057 | DS13: 21.618996 | DT13: 4.8750586 | DU13: 9.0951316 | DV13: 8.0743084 | DW13: 11.536146 | DX13: -0.2163103 | GR13: 12.710268 | GS13: 15.792375 | GT13: 25.348595 | GU13: 69.312933 | GV13: 31.191758 | GW13: 15.699737 | GX13: 16.878538 | GY13: 28.568802 | GZ13: 35.413921 | HA13: 23.531534 | HB13: 17.77512 | HC13: 21.511758 | HD13: 10.626621
A14: =AE14 -> 46112 | AE14: 46112 | BV14: 7.1425825 | BW14: 11.609397 | BX14: 18.082649 | BY14: 16.295073 | BZ14: 23.214929 | CA14: 10.760036 | CB14: 8.7624442 | CC14: 22.854121 | CD14: 14.64055 | CE14: 14.951957 | CF14: 10.665536 | CG14: 15.466643 | CH14: 2.5680467 | DL14: 4.3151283 | DM14: 7.7308714 | DN14: 12.020995 | DO14: 11.876436 | DP14: 16.728974 | DQ14: 7.6501742 | DR14: 5.4163984 | DS14: 21.45238 | DT14: 4.8462553 | DU14: 9.0973006 | DV14: 8.1756684 | DW14: 11.533734 | DX14: -0.21760521 | GR14: 12.698778 | GS14: 15.816296 | GT14: 25.333388 | GU14: 69.278683 | GV14: 31.174244 | GW14: 15.686448 | GX14: 16.853947 | GY14: 28.588203 | GZ14: 35.387837 | HA14: 23.536732 | HB14: 17.79259 | HC14: 21.488584 | HD14: 10.623861
A15: =AE15 -> 46080 | AE15: 46080 | BV15: 7.0916785 | BW15: 11.581565 | BX15: 18.007155 | BY15: 16.226953 | BZ15: 23.175032 | CA15: 10.464758 | CB15: 8.7587405 | CC15: 23.129693 | CD15: 14.757985 | CE15: 14.962568 | CF15: 10.643847 | CG15: 13.558498 | CH15: 2.5874163 | DL15: 4.2733377 | DM15: 7.706614 | DN15: 11.992553 | DO15: 11.8082 | DP15: 16.676745 | DQ15: 7.4198792 | DR15: 5.4494916 | DS15: 21.759932 | DT15: 4.9414488 | DU15: 9.118483 | DV15: 8.1572533 | DW15: 8.9008958 | DX15: -0.1926013 | GR15: 12.687833 | GS15: 15.786331 | GT15: 25.252804 | GU15: 65.908025 | GV15: 31.139878 | GW15: 15.213857 | GX15: 16.839683 | GY15: 28.916579 | GZ15: 35.461385 | HA15: 23.555267 | HB15: 17.759281 | HC15: 18.724545 | HD15: 10.645986
A16: =AE16 -> 46052 | AE16: 46052 | BV16: 7.8928151 | BW16: 10.61867 | BX16: 17.896624 | BY16: 17.272612 | BZ16: 22.292957 | CA16: 10.610785 | CB16: 10.494449 | CC16: 23.120652 | CD16: 15.806292 | CE16: 14.800191 | CF16: 9.6511218 | CG16: 14.315794 | CH16: 5.5446643 | DL16: 3.4009717 | DM16: 6.9490375 | DN16: 12.164024 | DO16: 11.937503 | DP16: 16.289878 | DQ16: 7.8834391 | DR16: 5.6097543 | DS16: 22.036377 | DT16: 5.6456077 | DU16: 8.3610835 | DV16: 8.6147038 | DW16: 10.532672 | DX16: 2.0344171 | GR16: 13.862877 | GS16: 14.809398 | GT16: 25.134427 | GU16: 54.059882 | GV16: 30.629132 | GW16: 15.395432 | GX16: 18.026718 | GY16: 29.024913 | GZ16: 36.216233 | HA16: 24.183448 | HB16: 16.648172 | HC16: 19.554318 | HD16: 12.667779
A17: =AE17 -> 46022 | AE17: 46022 | BV17: 7.8722815 | BW17: 10.623531 | BX17: 17.896852 | BY17: 17.266409 | BZ17: 22.292119 | CA17: 10.705361 | CB17: 10.505766 | CC17: 23.125304 | CD17: 15.803657 | CE17: 14.809037 | CF17: 9.6441162 | CG17: 14.314584 | CH17: 5.5410755 | DL17: 3.3827862 | DM17: 6.9525645 | DN17: 12.164074 | DO17: 11.938481 | DP17: 16.2918 | DQ17: 7.9288744 | DR17: 5.6099909 | DS17: 22.037405 | DT17: 5.6420487 | DU17: 8.3654247 | DV17: 8.6113527 | DW17: 10.524252 | DX17: 2.0317021 | GR17: 13.836997 | GS17: 14.813065 | GT17: 25.136358 | GU17: 54.384865 | GV17: 30.632035 | GW17: 15.634939 | GX17: 18.048127 | GY17: 29.029356 | GZ17: 36.220185 | HA17: 24.181915 | HB17: 16.652799 | HC17: 19.556065 | HD17: 12.657959
A18: =AE18 -> 45989 | AE18: 45989 | BV18: 7.831831 | BW18: 10.507851 | BX18: 17.952445 | BY18: 17.234082 | BZ18: 22.247372 | CA18: 10.718055 | CB18: 10.522054 | CC18: 23.130977 | CD18: 15.694116 | CE18: 14.797957 | CF18: 9.6213176 | CG18: 14.32417 | CH18: 5.5330791 | DL18: 3.3657363 | DM18: 6.8464509 | DN18: 12.236537 | DO18: 11.914488 | DP18: 16.244517 | DQ18: 7.9443936 | DR18: 5.612973 | DS18: 22.213241 | DT18: 5.5667903 | DU18: 8.3664066 | DV18: 8.5606688 | DW18: 10.530663 | DX18: 1.9878874 | GR18: 13.78015 | GS18: 14.670563 | GT18: 25.187751 | GU18: 55.053916 | GV18: 30.585028 | GW18: 15.64864 | GX18: 18.080685 | GY18: 29.036333 | GZ18: 36.123547 | HA18: 24.177453 | HB18: 16.596386 | HC18: 19.586177 | HD18: 12.650435
A19: =AE19 -> 45961 | AE19: 45961 | BV19: 7.6499945 | BW19: 10.631586 | BX19: 17.848386 | BY19: 16.847259 | BZ19: 21.772122 | CA19: 10.748652 | CB19: 10.029077 | CC19: 23.066518 | CD19: 15.508201 | CE19: 14.70241 | CF19: 9.7031891 | CG19: 14.31578 | CH19: 5.4064314 | DL19: 3.2671281 | DM19: 7.0191318 | DN19: 11.47517 | DO19: 11.604595 | DP19: 15.643769 | DQ19: 7.997743 | DR19: 5.1427805 | DS19: 21.189694 | DT19: 5.4566701 | DU19: 8.3759246 | DV19: 8.7990616 | DW19: 10.524822 | DX19: 1.8018913 | GR19: 13.566267 | GS19: 14.780325 | GT19: 25.122024 | GU19: 59.142114 | GV19: 30.216602 | GW19: 15.645742 | GX19: 17.502075 | GY19: 28.843472 | GZ19: 35.645443 | HA19: 23.976798 | HB19: 16.672472 | HC19: 19.577436 | HD19: 12.119795
A20: =AE20 -> 45930 | AE20: 45930 | BV20: 7.6524262 | BW20: 10.669081 | BX20: 17.840871 | BY20: 16.840847 | BZ20: 21.786132 | CA20: 10.748903 | CB20: 10.026538 | CC20: 23.065686 | CD20: 15.500351 | CE20: 14.696945 | CF20: 9.6995691 | CG20: 14.313791 | CH20: 5.4048043 | DL20: 3.2659998 | DM20: 7.0515206 | DN20: 11.469298 | DO20: 11.599934 | DP20: 15.658997 | DQ20: 8.0048803 | DR20: 5.1411398 | DS20: 21.188612 | DT20: 5.4632389 | DU20: 8.3713944 | DV20: 8.795318 | DW20: 10.522469 | DX20: 1.8002215 | GR20: 13.569177 | GS20: 14.825266 | GT20: 25.113873 | GU20: 59.053159 | GV20: 30.230698 | GW20: 15.628242 | GX20: 17.495777 | GY20: 28.841788 | GZ20: 35.617856 | HA20: 23.973923 | HB20: 16.652684 | HC20: 19.570843 | HD20: 12.115922
... A247: =AE247 -> 39021 | AE247: 39021 | BV247: 13.639438 | BW247: 8.4590111 | BX247: 16.489805 | BY247: 14.188479 | BZ247: 23.298795 | CA247: 7.880677 | CB247: 14.35938 | CC247: 11.714899 | CD247: 18.430521 | CE247: 12.51536 | CF247: 6.2414431 | CG247: 14.712353 | CH247: 3.835393 | DL247: 10.174257 | DM247: 6.5131186 | DN247: 11.292209 | DO247: 9.5496237 | DP247: 17.411275 | DQ247: 5.1492749 | DR247: 8.5353796 | DS247: 8.6662608 | DT247: 5.9890803 | DU247: 7.8970827 | DV247: 4.8512514 | DW247: 9.3414842 | DX247: 3.1839893 | GR247: 19.348518 | GS247: 14.047183 | GT247: 19.659914 | GU247: 52.525465 | GV247: 29.467702 | GW247: 11.252233 | GX247: 18.366824 | GY247: 16.347225 | GZ247: 34.733964 | HA247: 18.747083 | HB247: 10.274136 | HC247: 21.025061 | HD247: 11.223937

Sheet Valuation_FMA_hist
A1: Time frame | DL1: Price to Free Cash Flow | FB1: EV to EBITDA | GR1: Price to Sales
A2: 60 | DL2: FMA_PFCF | FB2: FMA_EVAL_EBITDA | GR2: FMA_PSALES
DL3: 12M Forecast Ratio | FB3: 12M Forecast Ratio | GR3: 12M Forecast Ratio
B6: Materials | C6: ConsStaples | D6: Pers. Goods | E6: Fin | F6: HealthCare | G6: Indus | H6: Oil | I6: Tech | J6: Telco | K6: Utili | L6: Travel & leisure | M6: Media | N6: Auto | Q6: Materials | R6: ConsStaples | S6: Pers. Goods | T6: Fin | U6: HealthCare | V6: Indus | W6: Oil | X6: Tech | Y6: Telco | Z6: Utili | AA6: Travel & leisure | AB6: Media | AC6: Auto | AF6: Materials | AG6: ConsStaples | AH6: Pers. Goods | AI6: Fin | AJ6: HealthCare | AK6: Indus | AL6: Oil | AM6: Tech | AN6: Telco | AO6: Utili | AP6: Travel & leisure | AQ6: Media | AR6: Auto | AS6: Materials | AT6: ConsStaples | AU6: Pers. Goods | AV6: Fin | AW6: HealthCare | AX6: Indus | AY6: Oil | AZ6: Tech | BA6: Telco | BB6: Utili | BC6: Travel & leisure | BD6: Media | BE6: Auto | BV6: Materials | BW6: ConsStaples | BX6: Pers. Goods | BY6: Fin | BZ6: HealthCare | CA6: Indus | CB6: Oil | CC6: Tech | CD6: Telco | CE6: Utili | CF6: Travel & leisure | CG6: Media | CH6: Auto | CI6: Materials | CJ6: ConsStaples | CK6: Pers. Goods | CL6: Fin | CM6: HealthCare | CN6: Indus | CO6: Oil | CP6: Tech | CQ6: Telco | CR6: Utili | CS6: Travel & leisure | CT6: Media | CU6: Auto | DL6: Materials | DM6: ConsStaples | DN6: Pers. Goods | DO6: Fin | DP6: HealthCare | DQ6: Indus | DR6: Oil | DS6: Tech | DT6: Telco | DU6: Utili | DV6: Travel & leisure | DW6: Media | DX6: Auto | DY6: Materials | DZ6: ConsStaples | EA6: Pers. Goods | EB6: Fin | EC6: HealthCare | ED6: Indus | EE6: Oil | EF6: Tech | EG6: Telco | EH6: Utili | EI6: Travel & leisure | EJ6: Media | EK6: Auto | FB6: Materials | FC6: ConsStaples | FD6: Pers. Goods | FE6: Fin | FF6: HealthCare | FG6: Indus | FH6: Oil | FI6: Tech | FJ6: Telco | FK6: Utili | FL6: Travel & leisure | FM6: Media | FN6: Auto | FO6: Materials | FP6: ConsStaples | FQ6: Pers. Goods | FR6: Fin | FS6: HealthCare | FT6: Indus | FU6: Oil | FV6: Tech | FW6: Telco | FX6: Utili | FY6: Travel & leisure | FZ6: Media | GA6: Auto | GR6: Materials | GS6: ConsStaples | GT6: Pers. Goods | GU6: Fin | GV6: HealthCare | GW6: Indus | GX6: Oil | GY6: Tech | GZ6: Telco | HA6: Utili | HB6: Travel & leisure | HC6: Media | HD6: Auto | HE6: Materials | HF6: ConsStaples | HG6: Pers. Goods | HH6: Fin | HI6: HealthCare | HJ6: Indus | HK6: Oil | HL6: Tech | HM6: Telco | HN6: Utili | HO6: Travel & leisure | HP6: Media | HQ6: Auto | IH6: Materials | II6: ConsStaples | IJ6: Pers. Goods | IK6: Fin | IL6: HealthCare | IM6: Indus | IN6: Oil | IO6: Tech | IP6: Telco | IQ6: Utili | IR6: Travel & leisure | IS6: Media | IT6: Auto | IU6: Materials | IV6: ConsStaples | IW6: Pers. Goods | IX6: Fin | IY6: HealthCare | IZ6: Indus | JA6: Oil | JB6: Tech | JC6: Telco | JD6: Utili | JE6: Travel & leisure | JF6: Media | JG6: Auto
AF7: I00037 | AG7: I00109 | AH7: I20438 | AI7: I00253 | AJ7: I20436 | AK7: I00073 | AL7: I20433 | AM7: I20448 | AN7: I20443 | AO7: I00577 | AP7: I00901 | AQ7: I00937 | AR7: I00649 | AS7: diff vs. moy | AT7: diff vs. moy | AU7: diff vs. moy | AV7: diff vs. moy | AW7: diff vs. moy | AX7: diff vs. moy | AY7: diff vs. moy | AZ7: diff vs. moy | BA7: diff vs. moy | BB7: diff vs. moy | BC7: diff vs. moy | BD7: diff vs. moy | BE7: diff vs. moy | BV7: I00037 | BW7: I00109 | BX7: I20438 | BY7: I00253 | BZ7: I20436 | CA7: I00073 | CB7: I20433 | CC7: I20448 | CD7: I20443 | CE7: I00577 | CF7: I00901 | CG7: I00937 | CH7: I00649 | CI7: diff vs. moy | CJ7: diff vs. moy | CK7: diff vs. moy | CL7: diff vs. moy | CM7: diff vs. moy | CN7: diff vs. moy | CO7: diff vs. moy | CP7: diff vs. moy | CQ7: diff vs. moy | CR7: diff vs. moy | CS7: diff vs. moy | CT7: diff vs. moy | CU7: diff vs. moy | DL7: I00037 | DM7: I00109 | DN7: I20438 | DO7: I00253 | DP7: I20436 | DQ7: I00073 | DR7: I20433 | DS7: I20448 | DT7: I20443 | DU7: I00577 | DV7: I00901 | DW7: I00937 | DX7: I00649 | DY7: diff vs. moy | DZ7: diff vs. moy | EA7: diff vs. moy | EB7: diff vs. moy | EC7: diff vs. moy | ED7: diff vs. moy | EE7: diff vs. moy | EF7: diff vs. moy | EG7: diff vs. moy | EH7: diff vs. moy | EI7: diff vs. moy | EJ7: diff vs. moy | EK7: diff vs. moy | FB7: I00037 | FC7: I00109 | FD7: I20438 | FE7: I00253 | FF7: I20436 | FG7: I00073 | FH7: I20433 | FI7: I20448 | FJ7: I20443 | FK7: I00577 | FL7: I00901 | FM7: I00937 | FN7: I00649 | FO7: diff vs. moy | FP7: diff vs. moy | FQ7: diff vs. moy | FR7: diff vs. moy | FS7: diff vs. moy | FT7: diff vs. moy | FU7: diff vs. moy | FV7: diff vs. moy | FW7: diff vs. moy | FX7: diff vs. moy | FY7: diff vs. moy | FZ7: diff vs. moy | GA7: diff vs. moy | GR7: I00037 | GS7: I00109 | GT7: I20438 | GU7: I00253 | GV7: I20436 | GW7: I00073 | GX7: I20433 | GY7: I20448 | GZ7: I20443 | HA7: I00577 | HB7: I00901 | HC7: I00937 | HD7: I00649 | HE7: diff vs. moy | HF7: diff vs. moy | HG7: diff vs. moy | HH7: diff vs. moy | HI7: diff vs. moy | HJ7: diff vs. moy | HK7: diff vs. moy | HL7: diff vs. moy | HM7: diff vs. moy | HN7: diff vs. moy | HO7: diff vs. moy | HP7: diff vs. moy | HQ7: diff vs. moy | IH7: I00037 | II7: I00109 | IJ7: I20438 | IK7: I00253 | IL7: I20436 | IM7: I00073 | IN7: I20433 | IO7: I20448 | IP7: I20443 | IQ7: I00577 | IR7: I00901 | IS7: I00937 | IT7: I00649 | IU7: diff vs. moy | IV7: diff vs. moy | IW7: diff vs. moy | IX7: diff vs. moy | IY7: diff vs. moy | IZ7: diff vs. moy | JA7: diff vs. moy | JB7: diff vs. moy | JC7: diff vs. moy | JD7: diff vs. moy | JE7: diff vs. moy | JF7: diff vs. moy | JG7: diff vs. moy
A8: =AE8 -> 46295 | AE8: {=_xll.FDS(AF7,"JULIAN(FMA_PE(NTMA,0,-20AY,M,""PORTAGG"",""MEANR"").dates)")} -> 46295 | DL8: {=_xll.FDS(DL7,"FMA_PCF(NTMA,0,-20AY,M,""PORTAGG"",""MEANR"")")} -> 8.9422186 | DM8: {=_xll.FDS(DM7,"FMA_PCF(NTMA,0,-20AY,M,""PORTAGG"",""MEANR"")")} -> 10.04444 | DN8: {=_xll.FDS(DN7,"FMA_PCF(NTMA,0,-20AY,M,""PORTAGG"",""MEANR"")")} -> 14.473667 | DO8: {=_xll.FDS(DO7,"FMA_PCF(NTMA,0,-20AY,M,""PORTAGG"",""MEANR"")")} -> #N/A | DP8: {=_xll.FDS(DP7,"FMA_PCF(NTMA,0,-20AY,M,""PORTAGG"",""MEANR"")")} -> 12.337819 | DQ8: {=_xll.FDS(DQ7,"FMA_PCF(NTMA,0,-20AY,M,""PORTAGG"",""MEANR"")")} -> 13.814605 | DR8: {=_xll.FDS(DR7,"FMA_PCF(NTMA,0,-20AY,M,""PORTAGG"",""MEANR"")")} -> 5.34985 | DS8: {=_xll.FDS(DS7,"FMA_PCF(NTMA,0,-20AY,M,""PORTAGG"",""MEANR"")")} -> 21.186471 | ... DX8: {=_xll.FDS(DX7,"FMA_PCF(NTMA,0,-20AY,M,""PORTAGG"",""MEANR"")")} -> 3.199751 | FB8: {=_xll.FDS(FB7,"FMA_EVAL_EBITDA(NTMA,0,-20AY,M,""PORTAGG"",""MEANR"")")} -> 7.7631122 | FC8: {=_xll.FDS(FC7,"FMA_EVAL_EBITDA(NTMA,0,-20AY,M,""PORTAGG"",""MEANR"")")} -> 9.7333979 | FD8: {=_xll.FDS(FD7,"FMA_EVAL_EBITDA(NTMA,0,-20AY,M,""PORTAGG"",""MEANR"")")} -> 11.329662 | FE8: {=_xll.FDS(FE7,"FMA_EVAL_EBITDA(NTMA,0,-20AY,M,""PORTAGG"",""MEANR"")")} -> #N/A | FF8: {=_xll.FDS(FF7,"FMA_EVAL_EBITDA(NTMA,0,-20AY,M,""PORTAGG"",""MEANR"")")} -> 10.802642 | FG8: {=_xll.FDS(FG7,"FMA_EVAL_EBITDA(NTMA,0,-20AY,M,""PORTAGG"",""MEANR"")")} -> 11.854577 | FH8: {=_xll.FDS(FH7,"FMA_EVAL_EBITDA(NTMA,0,-20AY,M,""PORTAGG"",""MEANR"")")} -> 4.7964169 | FI8: {=_xll.FDS(FI7,"FMA_EVAL_EBITDA(NTMA,0,-20AY,M,""PORTAGG"",""MEANR"")")} -> 18.199697 | ... FN8: {=_xll.FDS(FN7,"FMA_EVAL_EBITDA(NTMA,0,-20AY,M,""PORTAGG"",""MEANR"")")} -> 7.3237932 | GR8: {=_xll.FDS(GR7,"FMA_PSALES(NTMA,0,-20AY,M,""PORTAGG"",""MEANR"")")} -> 1.0583207 | GS8: {=_xll.FDS(GS7,"FMA_PSALES(NTMA,0,-20AY,M,""PORTAGG"",""MEANR"")")} -> 1.1770891 | GT8: {=_xll.FDS(GT7,"FMA_PSALES(NTMA,0,-20AY,M,""PORTAGG"",""MEANR"")")} -> 2.7591781 | GU8: {=_xll.FDS(GU7,"FMA_PSALES(NTMA,0,-20AY,M,""PORTAGG"",""MEANR"")")} -> 2.1662574 | GV8: {=_xll.FDS(GV7,"FMA_PSALES(NTMA,0,-20AY,M,""PORTAGG"",""MEANR"")")} -> 2.9853111 | GW8: {=_xll.FDS(GW7,"FMA_PSALES(NTMA,0,-20AY,M,""PORTAGG"",""MEANR"")")} -> 1.7658251 | GX8: {=_xll.FDS(GX7,"FMA_PSALES(NTMA,0,-20AY,M,""PORTAGG"",""MEANR"")")} -> 0.87351089 | GY8: {=_xll.FDS(GY7,"FMA_PSALES(NTMA,0,-20AY,M,""PORTAGG"",""MEANR"")")} -> 6.0528066 | ... HD8: {=_xll.FDS(HD7,"FMA_PSALES(NTMA,0,-20AY,M,""PORTAGG"",""MEANR"")")} -> 0.30671046
A9: =AE9 -> 46265 | AE9: 46265 | DL9: 9.591915 | DM9: 10.413244 | DN9: 15.825215 | DO9: #N/A | DP9: 12.975187 | DQ9: 14.350905 | DR9: 5.275837 | DS9: 20.877303 | DT9: 4.5526372 | DU9: 7.1800764 | DV9: 6.6414632 | DW9: 11.08555 | DX9: 3.4124224 | FB9: 8.1555471 | FC9: 9.9494973 | FD9: 12.251093 | FE9: #N/A | FF9: 11.187982 | FG9: 12.26177 | FH9: 4.8429362 | FI9: 17.832281 | FJ9: 6.2545449 | FK9: 9.2699266 | FL9: 7.0291785 | FM9: 9.5582862 | FN9: 7.1417471 | GR9: 1.1276573 | GS9: 1.2180365 | GT9: 3.0257519 | GU9: 2.2066656 | GV9: 3.1016627 | GW9: 1.8382048 | GX9: 0.84710621 | GY9: 5.7572097 | GZ9: 1.2521251 | HA9: 1.4168572 | HB9: 0.89241164 | HC9: 1.8461446 | HD9: 0.33031872
A10: =AE10 -> 46234 | AE10: 46234 | DL10: 9.0329927 | DM10: 10.814235 | DN10: 16.136509 | DO10: #N/A | DP10: 13.134507 | DQ10: 14.367434 | DR10: 5.2802877 | DS10: 20.401603 | DT10: 4.7137462 | DU10: 7.4910996 | DV10: 6.5707144 | DW10: 10.959547 | DX10: 3.3379096 | FB10: 7.7051822 | FC10: 10.191419 | FD10: 12.534572 | FE10: #N/A | FF10: 11.348792 | FG10: 12.333028 | FH10: 4.912693 | FI10: 17.501745 | FJ10: 6.1839537 | FK10: 9.3373061 | FL10: 6.9323745 | FM10: 8.8308653 | FN10: 6.9417357 | GR10: 1.0825157 | GS10: 1.2682559 | GT10: 3.1027474 | GU10: 2.2096603 | GV10: 3.1483333 | GW10: 1.8373134 | GX10: 0.84888234 | GY10: 5.639021 | GZ10: 1.225388 | HA10: 1.4499302 | HB10: 0.8915673 | HC10: 1.8070652 | HD10: 0.32101843
A11: =AE11 -> 46203 | AE11: 46203 | DL11: 8.8983573 | DM11: 10.641566 | DN11: 16.742328 | DO11: #N/A | DP11: 13.231997 | DQ11: 14.715074 | DR11: 4.860107 | DS11: 24.617534 | DT11: 4.9183129 | DU11: 7.7587685 | DV11: 7.1563846 | DW11: 10.983886 | DX11: 3.1437098 | FB11: 7.5526634 | FC11: 10.15662 | FD11: 12.858516 | FE11: #N/A | FF11: 11.619019 | FG11: 12.538731 | FH11: 4.5361815 | FI11: 21.158592 | FJ11: 6.3348199 | FK11: 9.6013656 | FL11: 7.3050463 | FM11: 9.1079038 | FN11: 6.7890243 | GR11: 1.0523819 | GS11: 1.2528961 | GT11: 3.1616544 | GU11: 2.1134174 | GV11: 3.2133171 | GW11: 1.8537423 | GX11: 0.75928659 | GY11: 6.5784429 | GZ11: 1.2663883 | HA11: 1.4806241 | HB11: 0.93649128 | HC11: 1.8726349 | HD11: 0.31119509
A12: =AE12 -> 46171 | AE12: 46171 | DL12: 9.3707061 | DM12: 10.289188 | DN12: 16.328136 | DO12: #N/A | DP12: 12.876947 | DQ12: 14.862116 | DR12: 5.2731379 | DS12: 23.307899 | DT12: 5.5032448 | DU12: 7.2806114 | DV12: 6.5706469 | DW12: 11.156807 | DX12: 3.4388776 | FB12: 7.997482 | FC12: 9.8417822 | FD12: 12.684134 | FE12: #N/A | FF12: 11.248571 | FG12: 12.502372 | FH12: 4.7082929 | FI12: 19.878616 | FJ12: 6.5891111 | FK12: 9.2258271 | FL12: 6.8801681 | FM12: 9.1864664 | FN12: 6.8154408 | GR12: 1.1122559 | GS12: 1.221255 | GT12: 3.1063179 | GU12: 2.0255855 | GV12: 3.1026674 | GW12: 1.854618 | GX12: 0.82898861 | GY12: 6.1309796 | GZ12: 1.405723 | HA12: 1.4092003 | HB12: 0.87334169 | HC12: 1.890261 | HD12: 0.34239542
A13: =AE13 -> 46142 | AE13: 46142 | DL13: 9.2323355 | DM13: 10.380129 | DN13: 15.264546 | DO13: #N/A | DP13: 12.966553 | DQ13: 14.480611 | DR13: 5.6968916 | DS13: 21.437826 | DT13: 5.3245747 | DU13: 7.7100996 | DV13: 6.3272679 | DW13: 10.61521 | DX13: 3.3185209 | FB13: 7.8461918 | FC13: 9.9416903 | FD13: 11.960967 | FE13: #N/A | FF13: 11.107808 | FG13: 12.25428 | FH13: 4.9897142 | FI13: 18.170263 | FJ13: 6.7421302 | FK13: 9.4533449 | FL13: 6.3954164 | FM13: 8.8195094 | FN13: 6.7780899 | GR13: 1.0899051 | GS13: 1.2273151 | GT13: 2.9116148 | GU13: 2.0199523 | GV13: 3.0863464 | GW13: 1.8139127 | GX13: 0.90872505 | GY13: 5.6045459 | GZ13: 1.3524706 | HA13: 1.4810167 | HB13: 0.80179993 | HC13: 1.8103482 | HD13: 0.33190448
A14: =AE14 -> 46112 | AE14: 46112 | DL14: 8.847536 | DM14: 10.332665 | DN14: 14.875729 | DO14: #N/A | DP14: 13.130416 | DQ14: 13.732018 | DR14: 6.4398001 | DS14: 19.809572 | DT14: 5.1857965 | DU14: 7.5140827 | DV14: 5.5185307 | DW14: 10.176373 | DX14: 3.3169708 | FB14: 7.7282377 | FC14: 9.9905828 | FD14: 11.83258 | FE14: #N/A | FF14: 11.321324 | FG14: 11.698882 | FH14: 5.7092164 | FI14: 16.851324 | FJ14: 6.7658669 | FK14: 9.4438481 | FL14: 6.0896461 | FM14: 8.3395608 | FN14: 6.870166 | GR14: 1.0710115 | GS14: 1.228214 | GT14: 2.8673661 | GU14: 1.9123864 | GV14: 3.1247927 | GW14: 1.7126875 | GX14: 0.94683721 | GY14: 5.1396297 | GZ14: 1.3388887 | HA14: 1.4353439 | HB14: 0.78845568 | HC14: 1.6763414 | HD14: 0.32947354
A15: =AE15 -> 46080 | AE15: 46080 | DL15: 9.5391048 | DM15: 11.620127 | DN15: 17.389436 | DO15: #N/A | DP15: 14.188357 | DQ15: 15.521323 | DR15: 6.0616621 | DS15: 22.579292 | DT15: 5.3757287 | DU15: 7.7492598 | DV15: 6.0064666 | DW15: 10.265278 | DX15: 3.8204887 | FB15: 8.1953138 | FC15: 10.852279 | FD15: 13.550413 | FE15: #N/A | FF15: 12.20978 | FG15: 13.005732 | FH15: 5.6574401 | FI15: 19.092311 | FJ15: 6.8426177 | FK15: 9.6185048 | FL15: 6.432342 | FM15: 8.2374893 | FN15: 7.0838133 | GR15: 1.1483568 | GS15: 1.3818737 | GT15: 3.3444681 | GU15: 2.1098713 | GV15: 3.4208855 | GW15: 1.892203 | GX15: 0.88033299 | GY15: 5.8772414 | GZ15: 1.4034149 | HA15: 1.4809763 | HB15: 0.87331587 | HC15: 1.4833114 | HD15: 0.3741898
A16: =AE16 -> 46052 | AE16: 46052 | DL16: 8.8613062 | DM16: 10.573381 | DN16: 16.921302 | DO16: #N/A | DP16: 13.682292 | DQ16: 14.915172 | DR16: 5.5881143 | DS16: 23.051043 | DT16: 4.7388154 | DU16: 7.2797927 | DV16: 6.0930433 | DW16: 10.606021 | DX16: 3.597682 | FB16: 7.852553 | FC16: 10.106673 | FD16: 13.314174 | FE16: #N/A | FF16: 11.92079 | FG16: 12.641627 | FH16: 5.3245216 | FI16: 19.564593 | FJ16: 6.3738042 | FK16: 9.1502675 | FL16: 6.2533431 | FM16: 9.0076271 | FN16: 6.6471855 | GR16: 1.0881662 | GS16: 1.2515028 | GT16: 3.2517258 | GU16: 2.070644 | GV16: 3.3462247 | GW16: 1.8060645 | GX16: 0.8305776 | GY16: 5.9531155 | GZ16: 1.210087 | HA16: 1.3579837 | HB16: 0.86677179 | HC16: 1.5804192 | HD16: 0.36284924
A17: =AE17 -> 46022 | AE17: 46022 | DL17: 8.292687 | DM17: 10.653636 | DN17: 17.955971 | DO17: #N/A | DP17: 13.271677 | DQ17: 14.061186 | DR17: 5.0424883 | DS17: 22.198986 | DT17: 4.5095404 | DU17: 6.7760787 | DV17: 6.3188119 | DW17: 11.194065 | DX17: 3.6750504 | FB17: 7.6071041 | FC17: 10.109481 | FD17: 14.682828 | FE17: #N/A | FF17: 11.56311 | FG17: 12.073417 | FH17: 4.9369967 | FI17: 19.1015 | FJ17: 6.3450772 | FK17: 8.8785091 | FL17: 6.5425202 | FM17: 9.4619071 | FN17: 6.826575 | GR17: 1.0076037 | GS17: 1.2540259 | GT17: 3.5786328 | GU17: 2.021169 | GV17: 3.2327151 | GW17: 1.7316707 | GX17: 0.76635214 | GY17: 5.6979485 | GZ17: 1.1670598 | HA17: 1.2777289 | HB17: 0.90203143 | HC17: 1.6807752 | HD17: 0.37831512
A18: =AE18 -> 45989 | AE18: 45989 | DL18: 8.1071282 | DM18: 10.727679 | DN18: 17.933658 | DO18: #N/A | DP18: 13.09303 | DQ18: 13.801048 | DR18: 4.8780382 | DS18: 22.473762 | DT18: 4.4640169 | DU18: 6.816122 | DV18: 6.6535807 | DW18: 11.160288 | DX18: 3.7255275 | FB18: 7.487428 | FC18: 10.271522 | FD18: 14.649635 | FE18: #N/A | FF18: 11.47132 | FG18: 11.905912 | FH18: 4.8478702 | FI18: 19.167249 | FJ18: 6.3911682 | FK18: 9.0127969 | FL18: 6.5052101 | FM18: 9.5104621 | FN18: 7.0407497 | GR18: 0.95554928 | GS18: 1.2501658 | GT18: 3.5477121 | GU18: 1.8871416 | GV18: 3.188888 | GW18: 1.6957752 | GX18: 0.73355791 | GY18: 5.7124998 | GZ18: 1.156705 | HA18: 1.2613738 | HB18: 0.87511716 | HC18: 1.6741701 | HD18: 0.37164454
A19: =AE19 -> 45961 | AE19: 45961 | DL19: 8.1995285 | DM19: 10.605482 | DN19: 17.758524 | DO19: #N/A | DP19: 12.380563 | DQ19: 14.157116 | DR19: 4.8740517 | DS19: 24.03485 | DT19: 4.5593181 | DU19: 6.7296242 | DV19: 6.3516378 | DW19: 11.523092 | DX19: 3.6529133 | FB19: 7.634756 | FC19: 10.181528 | FD19: 14.397705 | FE19: #N/A | FF19: 10.903402 | FG19: 12.30459 | FH19: 4.8099858 | FI19: 20.17664 | FJ19: 6.438768 | FK19: 8.8828493 | FL19: 6.4779668 | FM19: 9.7169983 | FN19: 7.2140774 | GR19: 0.95031245 | GS19: 1.2329582 | GT19: 3.4935981 | GU19: 1.8466991 | GV19: 3.0257377 | GW19: 1.7549491 | GX19: 0.72096142 | GY19: 6.061846 | GZ19: 1.1786352 | HA19: 1.2328312 | HB19: 0.87217245 | HC19: 1.7172551 | HD19: 0.36227551
A20: =AE20 -> 45930 | AE20: 45930 | DL20: 8.3724803 | DM20: 10.372636 | DN20: 16.540716 | DO20: #N/A | DP20: 11.979649 | DQ20: 14.149975 | DR20: 4.748293 | DS20: 23.362156 | DT20: 4.5691202 | DU20: 6.2823919 | DV20: 6.6012354 | DW20: 11.221394 | DX20: 3.6988488 | FB20: 7.7054613 | FC20: 9.9553533 | FD20: 13.604604 | FE20: #N/A | FF20: 10.561169 | FG20: 12.138906 | FH20: 4.64091 | FI20: 19.954994 | FJ20: 6.1718486 | FK20: 8.4010968 | FL20: 6.5213714 | FM20: 9.6383614 | FN20: 7.0869324 | GR20: 0.95364925 | GS20: 1.2025048 | GT20: 3.2942501 | GU20: 1.8971764 | GV20: 2.9247415 | GW20: 1.7338857 | GX20: 0.6790799 | GY20: 5.9294453 | GZ20: 1.1661875 | HA20: 1.1538925 | HB20: 0.89806741 | HC20: 1.7177667 | HD20: 0.37283137
A21: =AE21 -> 45898 | AE21: 45898 | DL21: 8.16956 | DM21: 10.913733 | DN21: 16.216468 | DO21: #N/A | DP21: 12.318362 | DQ21: 13.568023 | DR21: 4.8447397 | DS21: 21.39925 | DT21: 4.6737852 | DU21: 6.169471 | DV21: 6.4998449 | DW21: 11.129301 | DX21: 3.8368055 | FB21: 7.6474904 | FC21: 10.346107 | FD21: 13.394054 | FE21: 14.641487 | FF21: 10.762344 | FG21: 11.753391 | FH21: 4.7192794 | FI21: 18.371814 | FJ21: 6.4809608 | FK21: 8.3522185 | FL21: 6.7063305 | FM21: 9.4991266 | FN21: 7.2219166 | GR21: 0.91012114 | GS21: 1.2601032 | GT21: 3.1309317 | GU21: 1.8722166 | GV21: 2.9848781 | GW21: 1.6680218 | GX21: 0.69052221 | GY21: 5.434246 | GZ21: 1.1987259 | HA21: 1.1173263 | HB21: 0.90995762 | HC21: 1.6881241 | HD21: 0.3817463
A22: =AE22 -> 45869 | AE22: 45869 | DL22: 7.8476995 | DM22: 10.639626 | DN22: 15.999155 | DO22: #N/A | DP22: 11.856983 | DQ22: 13.85941 | DR22: 4.7987273 | DS22: 22.275953 | DT22: 4.6624947 | DU22: 6.228977 | DV22: 6.4309269 | DW22: 11.413735 | DX22: 3.7028494 | FB22: 7.3111515 | FC22: 9.9733565 | FD22: 13.181031 | FE22: 18.818155 | FF22: 10.415566 | FG22: 11.743286 | FH22: 4.5846739 | FI22: 18.799496 | FJ22: 6.3927628 | FK22: 8.3513715 | FL22: 6.8083487 | FM22: 9.4426112 | FN22: 6.9672036 | GR22: 0.88089729 | GS22: 1.224067 | GT22: 3.0635175 | GU22: 1.8603318 | GV22: 2.8655207 | GW22: 1.6861824 | GX22: 0.6905237 | GY22: 5.5881363 | GZ22: 1.18343 | HA22: 1.1308948 | HB22: 0.92100901 | HC22: 1.7559069 | HD22: 0.36233326
A23: =AE23 -> 45838 | AE23: 45838 | DL23: 7.8272784 | DM23: 10.778678 | DN23: 15.79009 | DO23: #N/A | DP23: 11.966367 | DQ23: 13.609632 | DR23: 4.6491815 | DS23: 23.130871 | DT23: 4.646001 | DU23: 6.3227102 | DV23: 6.1248864 | DW23: 11.890506 | DX23: 3.6849727 | FB23: 7.2918696 | FC23: 10.069306 | FD23: 12.903548 | FE23: 19.843783 | FF23: 10.486221 | FG23: 11.387729 | FH23: 4.5200627 | FI23: 19.484832 | FJ23: 6.2116613 | FK23: 8.3376704 | FL23: 6.5565466 | FM23: 9.8722315 | FN23: 6.344138 | GR23: 0.89202235 | GS23: 1.2417282 | GT23: 3.0273662 | GU23: 1.7964982 | GV23: 2.9071666 | GW23: 1.6596994 | GX23: 0.66876972 | GY23: 5.811439 | GZ23: 1.1931285 | HA23: 1.1360408 | HB23: 0.87624998 | HC23: 1.8777271 | HD23: 0.36592007
A24: =AE24 -> 45807 | AE24: 45807 | DL24: 7.9292655 | DM24: 11.364093 | DN24: 16.4472 | DO24: #N/A | DP24: 12.292106 | DQ24: 13.38486 | DR24: 4.3769105 | DS24: 23.425445 | DT24: 4.760734 | DU24: 6.2912219 | DV24: 6.1994026 | DW24: 13.701519 | DX24: 3.825034 | FB24: 7.2106031 | FC24: 10.441209 | FD24: 13.450973 | FE24: 19.45486 | FF24: 10.705936 | FG24: 11.221717 | FH24: 4.264745 | FI24: 19.551471 | FJ24: 6.3298511 | FK24: 8.1888109 | FL24: 6.5455286 | FM24: 11.203099 | FN24: 6.4782927 | GR24: 0.88117591 | GS24: 1.3188818 | GT24: 3.1465567 | GU24: 1.7690692 | GV24: 2.9753642 | GW24: 1.6124564 | GX24: 0.63700929 | GY24: 5.7859387 | GZ24: 1.232447 | HA24: 1.1098185 | HB24: 0.88872477 | HC24: 2.1818204 | HD24: 0.39392454
A25: =AE25 -> 45777 | AE25: 45777 | DL25: 7.650026 | DM25: 11.067861 | DN25: 16.14646 | DO25: #N/A | DP25: 12.320897 | DQ25: 12.548049 | DR25: 4.0749731 | DS25: 21.896792 | DT25: 4.477326 | DU25: 6.1568582 | DV25: 5.9335095 | DW25: 13.371995 | DX25: 3.6274643 | FB25: 7.0200772 | FC25: 10.27433 | FD25: 13.217945 | FE25: 15.038993 | FF25: 10.639726 | FG25: 10.509625 | FH25: 3.9588747 | FI25: 18.259532 | FJ25: 6.3792293 | FK25: 7.8562694 | FL25: 6.223841 | FM25: 10.801603 | FN25: 6.2893397 | GR25: 0.85448628 | GS25: 1.2996195 | GT25: 3.0918692 | GU25: 1.6975476 | GV25: 2.9801384 | GW25: 1.5066217 | GX25: 0.57928698 | GY25: 5.4298461 | GZ25: 1.1859137 | HA25: 1.0868918 | HB25: 0.85187519 | HC25: 2.0974591 | HD25: 0.38020047
A26: =AE26 -> 45747 | AE26: 45747 | DL26: 7.3539797 | DM26: 10.679441 | DN26: 16.217107 | DO26: #N/A | DP26: 12.579614 | DQ26: 12.535913 | DR26: 4.2832298 | DS26: 21.686281 | DT26: 4.5004206 | DU26: 5.9500207 | DV26: 6.3331659 | DW26: 12.828869 | DX26: 3.5924316 | FB26: 6.9075354 | FC26: 10.040868 | FD26: 13.128975 | FE26: 15.300869 | FF26: 10.859325 | FG26: 10.512937 | FH26: 4.0883241 | FI26: 18.093243 | FJ26: 6.5224608 | FK26: 7.8431474 | FL26: 6.3010375 | FM26: 10.463526 | FN26: 6.2778442 | GR26: 0.83654253 | GS26: 1.2617343 | GT26: 3.152783 | GU26: 1.6810052 | GV26: 3.0377588 | GW26: 1.5057622 | GX26: 0.63025345 | GY26: 5.3521377 | GZ26: 1.1820114 | HA26: 1.0321494 | HB26: 0.8678434 | HC26: 2.0136758 | HD26: 0.3810106
A27: =AE27 -> 45716 | AE27: 45716 | DL27: 7.6030179 | DM27: 10.473033 | DN27: 18.745517 | DO27: #N/A | DP27: 13.553633 | DQ27: 12.89456 | DR27: 4.0110764 | DS27: 23.511444 | DT27: 4.5606585 | DU27: 5.7519909 | DV27: 8.9321922 | DW27: 15.774396 | DX27: 3.9472082 | FB27: 7.0706073 | FC27: 10.121497 | FD27: 15.200237 | FE27: 15.684357 | FF27: 11.77145 | FG27: 10.862901 | FH27: 3.9142788 | FI27: 19.921171 | FJ27: 6.6419571 | FK27: 7.78632 | FL27: 8.5419819 | FM27: 13.129104 | FN27: 6.7415528 | GR27: 0.86157053 | GS27: 1.2548619 | GT27: 3.6722981 | GU27: 1.7232977 | GV27: 3.3142131 | GW27: 1.5733839 | GX27: 0.58816462 | GY27: 5.7538601 | GZ27: 1.1803432 | HA27: 0.94599807 | HB27: 1.3231335 | HC27: 2.9121073 | HD27: 0.42298335
A28: =AE28 -> 45688 | AE28: 45688 | DL28: 7.2758672 | DM28: 10.238189 | DN28: 18.911683 | DO28: #N/A | DP28: 13.472515 | DQ28: 12.578993 | DR28: 4.0908181 | DS28: 23.857752 | DT28: 4.2654123 | DU28: 5.644214 | DV28: 9.0872708 | DW28: 16.689738 | DX28: 3.7970287 | FB28: 6.864118 | FC28: 10.016648 | FD28: 15.476839 | FE28: 13.186235 | FF28: 11.746674 | FG28: 10.94277 | FH28: 3.8694332 | FI28: 20.73192 | FJ28: 6.4304493 | FK28: 7.851823 | FL28: 8.5614319 | FM28: 14.313485 | FN28: 6.2341048 | GR28: 0.84308573 | GS28: 1.2182276 | GT28: 3.6958735 | GU28: 1.6091068 | GV28: 3.2624683 | GW28: 1.535984 | GX28: 0.59230889 | GY28: 5.9329445 | GZ28: 1.1191167 | HA28: 0.91254983 | HB28: 1.3321026 | HC28: 3.0974922 | HD28: 0.41097151
A29: =AE29 -> 45657 | AE29: 45657 | DL29: 6.9233251 | DM29: 9.9639334 | DN29: 17.224982 | DO29: #N/A | DP29: 12.720319 | DQ29: 11.773486 | DR29: 3.8140938 | DS29: 22.405289 | DT29: 4.060749 | DU29: 5.6361777 | DV29: 8.7592241 | DW29: 15.563779 | DX29: 3.6108943 | FB29: 6.5787256 | FC29: 9.888199 | FD29: 14.066184 | FE29: 13.23039 | FF29: 11.229137 | FG29: 10.512164 | FH29: 3.7466622 | FI29: 19.580127 | FJ29: 6.3967987 | FK29: 7.9254347 | FL29: 8.3501397 | FM29: 12.749571 | FN29: 6.1236473 | GR29: 0.81194928 | GS29: 1.1920989 | GT29: 3.3481263 | GU29: 1.4657687 | GV29: 3.0723083 | GW29: 1.4540659 | GX29: 0.56924985 | GY29: 5.5580868 | GZ29: 1.0721025 | HA29: 0.90167896 | HB29: 1.3009738 | HC29: 2.5122622 | HD29: 0.39222625
A30: =AE30 -> 45625 | AE30: 45625 | DL30: 7.2252261 | DM30: 10.331697 | DN30: 16.018329 | DO30: #N/A | DP30: 13.452827 | DQ30: 12.114101 | DR30: 3.9395031 | DS30: 22.409078 | DT30: 4.2702467 | DU30: 5.7838766 | DV30: 9.1191972 | DW30: 15.77849 | DX30: 3.391194 | FB30: 6.7825181 | FC30: 10.037177 | FD30: 13.211894 | FE30: 13.266962 | FF30: 11.796571 | FG30: 10.749379 | FH30: 3.8297954 | FI30: 19.191134 | FJ30: 6.5573514 | FK30: 8.1384703 | FL30: 8.6609072 | FM30: 13.551131 | FN30: 6.0620558 | GR30: 0.84040521 | GS30: 1.225472 | GT30: 3.1351672 | GU30: 1.4517926 | GV30: 3.2328838 | GW30: 1.4854338 | GX30: 0.58532329 | GY30: 5.4233058 | GZ30: 1.1137406 | HA30: 0.93916204 | HB30: 1.3384986 | HC30: 2.7411787 | HD30: 0.38885961
A31: =AE31 -> 45596 | AE31: 45596 | DL31: 7.547976 | DM31: 10.379592 | DN31: 16.251391 | DO31: #N/A | DP31: 13.811922 | DQ31: 11.925779 | DR31: 4.0058042 | DS31: 21.582927 | DT31: 4.0846295 | DU31: 5.735161 | DV31: 8.8532547 | DW31: 15.40496 | DX31: 3.5633502 | FB31: 6.989301 | FC31: 10.190677 | FD31: 13.346097 | FE31: 13.863767 | FF31: 12.029877 | FG31: 10.52868 | FH31: 3.8699573 | FI31: 18.311549 | FJ31: 6.6581511 | FK31: 7.9849243 | FL31: 8.2064165 | FM31: 13.237227 | FN31: 6.3287392 | GR31: 0.87560445 | GS31: 1.2421694 | GT31: 3.2029802 | GU31: 1.4138362 | GV31: 3.3136742 | GW31: 1.4559548 | GX31: 0.58741651 | GY31: 5.2044741 | GZ31: 1.0864723 | HA31: 0.93093814 | HB31: 1.2333607 | HC31: 2.6766573 | HD31: 0.40332697
A32: =AE32 -> 45565 | AE32: 45565 | DL32: 8.1406118 | DM32: 10.82687 | DN32: 17.013237 | DO32: #N/A | DP32: 14.456423 | DQ32: 12.13491 | DR32: 3.956243 | DS32: 22.679546 | DT32: 4.0894529 | DU32: 5.9896374 | DV32: 8.9255203 | DW32: 15.421972 | DX32: 3.5994222 | FB32: 7.4432749 | FC32: 10.31749 | FD32: 14.218686 | FE32: 13.463861 | FF32: 12.525516 | FG32: 10.574149 | FH32: 3.7899208 | FI32: 18.7884 | FJ32: 6.4832732 | FK32: 7.9915927 | FL32: 8.1773535 | FM32: 13.044041 | FN32: 5.991584 | GR32: 0.95240611 | GS32: 1.2975437 | GT32: 3.494554 | GU32: 1.4470848 | GV32: 3.4691395 | GW32: 1.4732185 | GX32: 0.5885998 | GY32: 5.4980255 | GZ32: 1.0779376 | HA32: 0.98322454 | HB32: 1.2227584 | HC32: 2.6417966 | HD32: 0.40959896
... A75: =AE75 -> 44253 | AE75: 44253 | DL75: 8.4309537 | DM75: 10.939628 | DN75: 18.746978 | DO75: #N/A | DP75: 13.876875 | DQ75: 13.346472 | DR75: 4.9286662 | DS75: 24.009963 | DT75: 3.098871 | DU75: 6.3847196 | DV75: 15.303256 | DW75: 12.313545 | DX75: 4.4953393 | FB75: 6.4046689 | FC75: 10.660061 | FD75: 15.068969 | FE75: 26.80141 | FF75: 12.109427 | FG75: 11.20505 | FH75: 5.6080687 | FI75: 18.447406 | FJ75: 6.0862477 | FK75: 8.6623045 | FL75: 17.893453 | FM75: 11.64938 | FN75: 6.8138211 | GR75: 1.1695032 | GS75: 1.5357673 | GT75: 3.2008498 | GU75: 1.308713 | GV75: 3.1759166 | GW75: 1.4290594 | GX75: 0.64883051 | GY75: 4.0599017 | GZ75: 0.86836327 | HA75: 0.92933417 | HB75: 1.588663 | HC75: 2.1979246 | HD75: 0.46648571
A76: =AE76 -> 44225 | AE76: 44225 | DL76: 8.1221221 | DM76: 11.135493 | DN76: 18.726394 | DO76: 14.989632 | DP76: 14.193071 | DQ76: 12.844036 | DR76: 4.6879052 | DS76: 24.099759 | DT76: 3.1852571 | DU76: 6.7205428 | DV76: 11.954103 | DW76: 11.905525 | DX76: 4.3964967 | FB76: 6.3297117 | FC76: 11.016813 | FD76: 15.238459 | FE76: 26.894313 | FF76: 12.246522 | FG76: 11.180927 | FH76: 5.5310329 | FI76: 18.531263 | FJ76: 5.9236503 | FK76: 8.9730736 | FL76: 16.421152 | FM76: 11.895849 | FN76: 6.9807154 | GR76: 1.1082844 | GS76: 1.5463722 | GT76: 3.1732393 | GU76: 1.2055495 | GV76: 3.2454387 | GW76: 1.3862834 | GX76: 0.60150719 | GY76: 3.9954028 | GZ76: 0.87601992 | HA76: 0.99619799 | HB76: 1.3915503 | HC76: 2.1417808 | HD76: 0.4405884
A77: =AE77 -> 44196 | AE77: 44196 | DL77: 8.5499148 | DM77: 11.518472 | DN77: 19.954239 | DO77: 15.89004 | DP77: 14.0642 | DQ77: 13.016573 | DR77: 4.8215428 | DS77: 23.676369 | DT77: 3.1179021 | DU77: 6.8650451 | DV77: 15.030313 | DW77: 11.937111 | DX77: 4.4174406 | FB77: 6.9748173 | FC77: 11.4335 | FD77: 16.168957 | FE77: 26.786063 | FF77: 12.158915 | FG77: 11.249245 | FH77: 5.7156878 | FI77: 18.245058 | FJ77: 5.9063544 | FK77: 8.9210408 | FL77: 16.266954 | FM77: 11.7315 | FN77: 7.2275229 | GR77: 1.1434208 | GS77: 1.6095519 | GT77: 3.3250134 | GU77: 1.248186 | GV77: 3.2239235 | GW77: 1.4016394 | GX77: 0.61317229 | GY77: 3.9000707 | GZ77: 0.85249488 | HA77: 1.0078371 | HB77: 1.4259196 | HC77: 2.1487999 | HD77: 0.45343262
A78: =AE78 -> 44165 | AE78: 44165 | DL78: 8.4821493 | DM78: 11.430699 | DN78: 20.349631 | DO78: #N/A | DP78: 14.03549 | DQ78: 13.08883 | DR78: 4.6825241 | DS78: 22.632272 | DT78: 3.2071257 | DU78: 6.7334344 | DV78: 12.474953 | DW78: 12.87597 | DX78: 4.3534437 | FB78: 6.9838022 | FC78: 11.539157 | FD78: 15.998262 | FE78: 26.954857 | FF78: 12.24946 | FG78: 11.402269 | FH78: 5.663857 | FI78: 17.590025 | FJ78: 6.1193657 | FK78: 8.9706016 | FL78: 18.70386 | FM78: 12.121605 | FN78: 7.5894792 | GR78: 1.0901245 | GS78: 1.577964 | GT78: 3.2525556 | GU78: 1.2332056 | GV78: 3.2223685 | GW78: 1.3624307 | GX78: 0.57837714 | GY78: 3.7537181 | GZ78: 0.87848166 | HA78: 0.97611917 | HB78: 1.3178202 | HC78: 2.2231271 | HD78: 0.43802833
A79: =AE79 -> 44134 | AE79: 44134 | DL79: 7.5655153 | DM79: 10.624383 | DN79: 18.827704 | DO79: 13.041187 | DP79: 13.047865 | DQ79: 11.872145 | DR79: 3.6242425 | DS79: 19.792404 | DT79: 2.8301511 | DU79: 6.1949062 | DV79: 6.3120932 | DW79: 11.644399 | DX79: 3.7403015 | FB79: 6.5150404 | FC79: 11.22088 | FD79: 14.953026 | FE79: 24.686176 | FF79: 11.714934 | FG79: 10.773699 | FH79: 5.0512675 | FI79: 15.533867 | FJ79: 6.0681314 | FK79: 8.8065257 | FL79: 17.865468 | FM79: 11.481431 | FN79: 7.6867009 | GR79: 0.95002192 | GS79: 1.4431193 | GT79: 2.9457335 | GU79: 0.97182548 | GV79: 3.0200425 | GW79: 1.2023837 | GX79: 0.44032163 | GY79: 3.294364 | GZ79: 0.78057327 | HA79: 0.87381649 | HB79: 1.0644737 | HC79: 2.0062509 | HD79: 0.36292477
A80: =AE80 -> 44104 | AE80: 44104 | DL80: 8.2328625 | DM80: 11.663555 | DN80: 19.635092 | DO80: 14.704142 | DP80: 14.362219 | DQ80: 13.347434 | DR80: 3.8926269 | DS80: 21.927463 | DT80: 2.9297805 | DU80: 6.4975238 | DV80: -3.8526845 | DW80: 11.718211 | DX80: 4.3107045 | FB80: 6.9812841 | FC80: 12.081105 | FD80: 15.616981 | FE80: 24.984428 | FF80: 12.461861 | FG80: 11.33648 | FH80: 5.2287995 | FI80: 16.746741 | FJ80: 6.0707818 | FK80: 8.8704564 | FL80: 18.529673 | FM80: 11.745358 | FN80: 8.5846774 | GR80: 1.0208711 | GS80: 1.5396352 | GT80: 3.0681191 | GU80: 1.0153994 | GV80: 3.2589138 | GW80: 1.245191 | GX80: 0.4728785 | GY80: 3.5994219 | GZ80: 0.80072432 | HA80: 0.89248848 | HB80: 1.0759512 | HC80: 2.0592144 | HD80: 0.38534219
A81: =AE81 -> 44074 | AE81: 44074 | DL81: 8.6860063 | DM81: 11.653182 | DN81: 18.768204 | DO81: 15.730756 | DP81: 13.742704 | DQ81: 13.221965 | DR81: 4.500528 | DS81: 21.916835 | DT81: 3.0852986 | DU81: 6.5434905 | DV81: -20.266749 | DW81: 11.084521 | DX81: 4.3954006 | FB81: 7.2724272 | FC81: 11.950699 | FD81: 15.009146 | FE81: 24.0015 | FF81: 12.207334 | FG81: 11.283382 | FH81: 5.6193661 | FI81: 16.740481 | FJ81: 5.9423833 | FK81: 8.624602 | FL81: 22.407503 | FM81: 11.09003 | FN81: 8.5048897 | GR81: 1.0620438 | GS81: 1.5339636 | GT81: 2.9184873 | GU81: 1.0892755 | GV81: 3.2110566 | GW81: 1.2300382 | GX81: 0.53005379 | GY81: 3.638065 | GZ81: 0.83031372 | HA81: 0.89931509 | HB81: 0.95908929 | HC81: 2.0185726 | HD81: 0.38281834
A82: =AE82 -> 44043 | AE82: 44043 | DL82: 8.5368554 | DM82: 11.586159 | DN82: 18.654947 | DO82: 15.57247 | DP82: 13.610412 | DQ82: 12.644788 | DR82: 4.4389376 | DS82: 21.474731 | DT82: 3.1077047 | DU82: 6.6563045 | DV82: -34.972083 | DW82: 10.499387 | DX82: 4.1358839 | FB82: 7.1175601 | FC82: 11.882128 | FD82: 14.820139 | FE82: 24.617561 | FF82: 12.393098 | FG82: 10.893722 | FH82: 5.6225109 | FI82: 16.047092 | FJ82: 5.542394 | FK82: 8.6994858 | FL82: 19.161966 | FM82: 10.463425 | FN82: 8.4451071 | GR82: 1.0042253 | GS82: 1.51375 | GT82: 2.86606 | GU82: 1.0513605 | GV82: 3.2363595 | GW82: 1.1704425 | GX82: 0.51690104 | GY82: 3.5165361 | GZ82: 0.83109701 | HA82: 0.90815569 | HB82: 0.82494442 | HC82: 1.8831622 | HD82: 0.34966532
A83: =AE83 -> 44012 | AE83: 44012 | DL83: 8.1909485 | DM83: 11.864063 | DN83: 18.813416 | DO83: 15.78867 | DP83: 13.917248 | DQ83: 12.841506 | DR83: 4.6696592 | DS83: 22.088491 | DT83: 3.2755734 | DU83: 6.5481721 | DV83: -128.98501 | DW83: 11.37823 | DX83: 4.4436526 | FB83: 7.0153352 | FC83: 12.188131 | FD83: 14.887358 | FE83: 25.340995 | FF83: 12.678118 | FG83: 11.086951 | FH83: 5.9685432 | FI83: 16.387998 | FJ83: 5.8959256 | FK83: 8.7681496 | FL83: 20.228254 | FM83: 11.267763 | FN83: 9.0908287 | GR83: 0.97416915 | GS83: 1.5363677 | GT83: 2.8858233 | GU83: 1.080586 | GV83: 3.286153 | GW83: 1.1665921 | GX83: 0.55479606 | GY83: 3.5076435 | GZ83: 0.90935596 | HA83: 0.88021607 | HB83: 0.84072183 | HC83: 2.0299625 | HD83: 0.36430067
A84: =AE84 -> 43980 | AE84: 43980 | DL84: 7.8034808 | DM84: 11.723696 | DN84: 18.198593 | DO84: 15.16036 | DP84: 14.098103 | DQ84: 12.123922 | DR84: 4.6281733 | DS84: 20.808962 | DT84: 3.2499933 | DU84: 6.2429094 | DV84: 26.630353 | DW84: 10.939732 | DX84: 4.367324 | FB84: 6.8988205 | FC84: 12.105945 | FD84: 14.517679 | FE84: 25.511333 | FF84: 12.885114 | FG84: 10.749386 | FH84: 6.1141156 | FI84: 15.486819 | FJ84: 5.9412714 | FK84: 8.541522 | FL84: 16.907479 | FM84: 11.0923 | FN84: 9.1322331 | GR84: 0.9337307 | GS84: 1.5124313 | GT84: 2.8048503 | GU84: 1.0068521 | GV84: 3.3125626 | GW84: 1.1285109 | GX84: 0.56619351 | GY84: 3.2206593 | GZ84: 0.90524054 | HA84: 0.81465017 | HB84: 0.81766276 | HC84: 1.9879207 | HD84: 0.3517967
A85: =AE85 -> 43951 | AE85: 43951 | DL85: 7.2778916 | DM85: 11.168793 | DN85: 17.009218 | DO85: 14.018842 | DP85: 13.902801 | DQ85: 10.993748 | DR85: 4.6024645 | DS85: 19.37281 | DT85: 3.1070653 | DU85: 5.844968 | DV85: 11.777605 | DW85: 10.558371 | DX85: 4.0944643 | FB85: 6.5643498 | FC85: 11.719279 | FD85: 13.945554 | FE85: 24.084434 | FF85: 12.462834 | FG85: 9.7970421 | FH85: 5.8168142 | FI85: 14.555136 | FJ85: 6.0710686 | FK85: 8.2250095 | FL85: 11.050124 | FM85: 10.601999 | FN85: 8.8198158 | GR85: 0.87701184 | GS85: 1.4647624 | GT85: 2.6962424 | GU85: 1.0219493 | GV85: 3.2456353 | GW85: 1.007239 | GX85: 0.58305822 | GY85: 3.0186596 | GZ85: 0.86662555 | HA85: 0.76553716 | HB85: 0.71125841 | HC85: 1.882705 | HD85: 0.33494651
A86: =AE86 -> 43921 | AE86: 43921 | DL86: 6.3962049 | DM86: 9.4684352 | DN86: 15.097601 | DO86: 11.548033 | DP86: 12.866927 | DQ86: 8.9453264 | DR86: 4.0648824 | DS86: 16.609238 | DT86: 2.9832797 | DU86: 5.6281928 | DV86: 5.9106287 | DW86: 9.0495805 | DX86: 2.9203175 | FB86: 5.7743787 | FC86: 10.284481 | FD86: 12.265802 | FE86: 23.093752 | FF86: 11.548509 | FG86: 8.3604635 | FH86: 5.2306775 | FI86: 12.609459 | FJ86: 5.9525803 | FK86: 8.0265264 | FL86: 7.1135808 | FM86: 9.4503928 | FN86: 7.2127375 | GR86: 0.76464866 | GS86: 1.3088843 | GT86: 2.4452645 | GU86: 0.96260607 | GV86: 2.95736 | GW86: 0.88454951 | GX86: 0.54920512 | GY86: 2.680797 | GZ86: 0.83103529 | HA86: 0.73894853 | HB86: 0.57290651 | HC86: 1.7109065 | HD86: 0.27848247
A87: =AE87 -> 43889 | AE87: 43889 | DL87: 6.8859925 | DM87: 9.785815 | DN87: 15.677546 | DO87: #N/A | DP87: 13.442708 | DQ87: 10.166742 | DR87: 3.8916446 | DS87: 18.050004 | DT87: 3.4549224 | DU87: 6.6715362 | DV87: 6.1883736 | DW87: 9.6488524 | DX87: 3.4361045 | FB87: 6.0264969 | FC87: 10.370819 | FD87: 12.697171 | FE87: 23.077778 | FF87: 11.931112 | FG87: 9.1647229 | FH87: 4.2726658 | FI87: 13.642444 | FJ87: 6.3926311 | FK87: 8.7532842 | FL87: 7.1898111 | FM87: 10.151392 | FN87: 7.0436168 | GR87: 0.82359646 | GS87: 1.3803557 | GT87: 2.5476602 | GU87: 1.2363567 | GV87: 3.0733011 | GW87: 1.0658849 | GX87: 0.50169418 | GY87: 2.9713636 | GZ87: 0.96806937 | HA87: 0.86451025 | HB87: 0.72643493 | HC87: 1.8390013 | HD87: 0.34300585
A88: =AE88 -> 43861 | AE88: 43861 | DL88: 7.6846904 | DM88: 10.639226 | DN88: 16.956948 | DO88: #N/A | DP88: 14.22892 | DQ88: 11.03552 | DR88: 4.4938857 | DS88: 18.719966 | DT88: 3.7191523 | DU88: 6.8840415 | DV88: 6.9965545 | DW88: 10.654316 | DX88: 3.704231 | FB88: 6.5652204 | FC88: 11.067352 | FD88: 13.784856 | FE88: 24.025274 | FF88: 12.817129 | FG88: 10.118539 | FH88: 4.6603519 | FI88: 14.334937 | FJ88: 6.4199277 | FK88: 8.7760642 | FL88: 7.6443203 | FM88: 10.836222 | FN88: 7.1914941 | GR88: 0.93402049 | GS88: 1.509841 | GT88: 2.7724838 | GU88: 1.3772315 | GV88: 3.3083004 | GW88: 1.1703982 | GX88: 0.57570968 | GY88: 3.1292059 | GZ88: 1.0331755 | HA88: 0.87333324 | HB88: 0.82883576 | HC88: 2.0256478 | HD88: 0.37245866
A89: =AE89 -> 43830 | AE89: 43830 | DL89: 8.0870128 | DM89: 10.704755 | DN89: 17.364651 | DO89: #N/A | DP89: 14.287924 | DQ89: 11.164796 | DR89: 4.8228211 | DS89: 19.057862 | DT89: 3.7474143 | DU89: 6.4519188 | DV89: 7.5770727 | DW89: 10.629271 | DX89: 4.0409861 | FB89: 6.8565633 | FC89: 11.181486 | FD89: 14.245109 | FE89: 23.859615 | FF89: 12.668456 | FG89: 10.230338 | FH89: 4.9758084 | FI89: 14.454243 | FJ89: 6.4337868 | FK89: 8.4259386 | FL89: 8.0910816 | FM89: 10.830267 | FN89: 7.4874896 | GR89: 0.98609353 | GS89: 1.5248073 | GT89: 2.8220018 | GU89: 1.3835013 | GV89: 3.2543034 | GW89: 1.1810962 | GX89: 0.6284608 | GY89: 3.1818307 | GZ89: 1.0371245 | HA89: 0.88046431 | HB89: 0.89781792 | HC89: 2.0624907 | HD89: 0.41106272
A90: =AE90 -> 43798 | AE90: 43798 | DL90: 7.7445947 | DM90: 10.654507 | DN90: 17.626469 | DO90: #N/A | DP90: 14.080128 | DQ90: 10.957315 | DR90: 4.745422 | DS90: 22.795733 | DT90: 3.967864 | DU90: 6.2558779 | DV90: 7.3020063 | DW90: 10.376478 | DX90: 4.1600632 | FB90: 6.5554154 | FC90: 11.138008 | FD90: 14.388961 | FE90: 25.933886 | FF90: 12.50431 | FG90: 10.133754 | FH90: 4.8294627 | FI90: 14.213095 | FJ90: 6.5651168 | FK90: 8.2705861 | FL90: 7.7676343 | FM90: 10.629511 | FN90: 7.6067998 | GR90: 0.94178114 | GS90: 1.5112717 | GT90: 2.8597937 | GU90: 1.3579792 | GV90: 3.2056457 | GW90: 1.150066 | GX90: 0.61342916 | GY90: 3.1162691 | GZ90: 1.0906066 | HA90: 0.84858262 | HB90: 0.86310795 | HC90: 2.0036613 | HD90: 0.4189342
A91: =AE91 -> 43769 | AE91: 43769 | DL91: 7.5718946 | DM91: 10.463447 | DN91: 17.538018 | DO91: #N/A | DP91: 13.549986 | DQ91: 10.584722 | DR91: 4.7838112 | DS91: 18.029713 | DT91: 3.9868251 | DU91: 6.2540536 | DV91: 7.3331475 | DW91: 10.728497 | DX91: 4.0772819 | FB91: 6.4082907 | FC91: 10.928058 | FD91: 14.149086 | FE91: 25.133835 | FF91: 12.194093 | FG91: 9.8786152 | FH91: 4.8687982 | FI91: 13.570733 | FJ91: 6.0287965 | FK91: 8.1193125 | FL91: 7.8211753 | FM91: 10.717612 | FN91: 7.4270441 | GR91: 0.91468525 | GS91: 1.4861253 | GT91: 2.8185785 | GU91: 1.3508686 | GV91: 3.1302124 | GW91: 1.111416 | GX91: 0.63177202 | GY91: 2.9683311 | GZ91: 1.0946866 | HA91: 0.8618938 | HB91: 0.87630422 | HC91: 2.0271502 | HD91: 0.41535347
A92: =AE92 -> 43738 | AE92: 43738 | DL92: 7.2595399 | DM92: 10.604707 | DN92: 17.746179 | DO92: #N/A | DP92: 13.839417 | DQ92: 10.384625 | DR92: 4.8501004 | DS92: 17.742661 | DT92: 3.9866028 | DU92: 6.2798068 | DV92: 7.2511692 | DW92: 10.829556 | DX92: 3.817899 | FB92: 6.1984006 | FC92: 11.128673 | FD92: 14.309002 | FE92: 25.522835 | FF92: 12.153117 | FG92: 9.7406887 | FH92: 4.8445733 | FI92: 13.266031 | FJ92: 6.1699632 | FK92: 8.4041282 | FL92: 7.558506 | FM92: 11.001663 | FN92: 7.3458943 | GR92: 0.88125852 | GS92: 1.5084397 | GT92: 2.8363695 | GU92: 1.3630019 | GV92: 3.0890535 | GW92: 1.0768639 | GX92: 0.6357783 | GY92: 2.9148181 | GZ92: 1.0825373 | HA92: 0.8700383 | HB92: 0.85874327 | HC92: 2.0389621 | HD92: 0.38827542
A93: =AE93 -> 43707 | AE93: 43707 | DL93: 6.9712182 | DM93: 10.636159 | DN93: 17.850718 | DO93: #N/A | DP93: 13.83374 | DQ93: 10.135005 | DR93: 4.5876064 | DS93: 16.161451 | DT93: 3.7739122 | DU93: 6.1317017 | DV93: 7.0982133 | DW93: 10.949395 | DX93: 3.6308284 | FB93: 6.036536 | FC93: 11.242588 | FD93: 14.497711 | FE93: 25.062786 | FF93: 12.156375 | FG93: 9.6434242 | FH93: 4.6527402 | FI93: 12.234259 | FJ93: 6.0563017 | FK93: 8.3337052 | FL93: 7.3968575 | FM93: 11.10296 | FN93: 7.2590032 | GR93: 0.84105903 | GS93: 1.5143544 | GT93: 2.8619229 | GU93: 1.261993 | GV93: 3.0557516 | GW93: 1.039645 | GX93: 0.59900006 | GY93: 2.6725085 | GZ93: 1.0262465 | HA93: 0.82944572 | HB93: 0.82757643 | HC93: 2.0237209 | HD93: 0.3666972
A94: =AE94 -> 43677 | AE94: 43677 | DL94: 7.3070495 | DM94: 10.772887 | DN94: 17.995239 | DO94: #N/A | DP94: 13.680692 | DQ94: 10.458089 | DR94: 4.9390702 | DS94: 17.127994 | DT94: 3.8198686 | DU94: 5.9179556 | DV94: 7.3716839 | DW94: 11.058363 | DX94: 3.9323816 | FB94: 6.0079856 | FC94: 10.951598 | FD94: 14.120177 | FE94: 24.443256 | FF94: 11.976974 | FG94: 9.399176 | FH94: 4.9172132 | FI94: 12.795255 | FJ94: 5.8845847 | FK94: 7.9362487 | FL94: 7.2211307 | FM94: 10.375399 | FN94: 7.1334639 | GR94: 0.89180739 | GS94: 1.5143959 | GT94: 2.8782763 | GU94: 1.3185043 | GV94: 3.0057743 | GW94: 1.0574896 | GX94: 0.6605073 | GY94: 2.8030126 | GZ94: 1.0262135 | HA94: 0.80880412 | HB94: 0.84847983 | HC94: 2.0317624 | HD94: 0.39054946
A95: =AE95 -> 43644 | AE95: 43644 | DL95: 7.5455523 | DM95: 10.590794 | DN95: 17.908983 | DO95: #N/A | DP95: 13.656901 | DQ95: 10.49006 | DR95: 5.0459933 | DS95: 17.16703 | DT95: 3.781773 | DU95: 5.9351793 | DV95: 7.2617243 | DW95: 11.214541 | DX95: 3.9528084 | FB95: 6.1796021 | FC95: 10.7727 | FD95: 14.396859 | FE95: 24.341026 | FF95: 12.00179 | FG95: 9.509603 | FH95: 4.9911903 | FI95: 12.968382 | FJ95: 5.8660802 | FK95: 7.9211524 | FL95: 7.1717493 | FM95: 10.488298 | FN95: 7.0429187 | GR95: 0.92263856 | GS95: 1.4829696 | GT95: 2.9298559 | GU95: 1.3262264 | GV95: 2.9850665 | GW95: 1.0621066 | GX95: 0.67071464 | GY95: 2.8162534 | GZ95: 1.0182018 | HA95: 0.80783328 | HB95: 0.83916075 | HC95: 2.0492015 | HD95: 0.39597657
A96: =AE96 -> 43616 | AE96: 43616 | DL96: 6.819995 | DM96: 10.338651 | DN96: 17.121994 | DO96: #N/A | DP96: 12.979878 | DQ96: 9.8800841 | DR96: 4.8600074 | DS96: 16.447172 | DT96: 3.8514337 | DU96: 5.7712771 | DV96: 6.8944127 | DW96: 11.271648 | DX96: 3.7919143 | FB96: 5.7440497 | FC96: 10.600411 | FD96: 13.808023 | FE96: 25.147452 | FF96: 11.537242 | FG96: 9.0776242 | FH96: 4.824275 | FI96: 12.389433 | FJ96: 5.9273289 | FK96: 7.8692341 | FL96: 6.8726808 | FM96: 10.436788 | FN96: 6.9280552 | GR96: 0.83629799 | GS96: 1.4417149 | GT96: 2.796322 | GU96: 1.3054535 | GV96: 2.8300638 | GW96: 0.99661315 | GX96: 0.64660299 | GY96: 2.6624281 | GZ96: 1.007493 | HA96: 0.75213219 | HB96: 0.80781753 | HC96: 1.9459313 | HD96: 0.37721475
A97: =AE97 -> 43585 | AE97: 43585 | DL97: 7.6033985 | DM97: 10.624069 | DN97: 17.563471 | DO97: #N/A | DP97: 13.605023 | DQ97: 10.665915 | DR97: 5.3046756 | DS97: 17.638021 | DT97: 3.9997905 | DU97: 5.8573235 | DV97: 7.4927812 | DW97: 11.487411 | DX97: 4.316037 | FB97: 6.2332631 | FC97: 10.74254 | FD97: 14.063731 | FE97: 24.461027 | FF97: 11.516062 | FG97: 9.5922768 | FH97: 4.9392921 | FI97: 13.067624 | FJ97: 5.9799959 | FK97: 7.812836 | FL97: 7.2550577 | FM97: 10.603678 | FN97: 6.9884346 | GR97: 0.93841381 | GS97: 1.5022594 | GT97: 2.8487129 | GU97: 1.4404712 | GV97: 2.9163328 | GW97: 1.0780015 | GX97: 0.67555841 | GY97: 2.8305397 | GZ97: 1.0415701 | HA97: 0.75649119 | HB97: 0.85889452 | HC97: 1.9952936 | HD97: 0.44064962
A98: =AE98 -> 43553 | AE98: 43553 | DL98: 7.4925754 | DM98: 10.332168 | DN98: 17.157979 | DO98: #N/A | DP98: 13.797624 | DQ98: 10.031801 | DR98: 5.4135532 | DS98: 16.392577 | DT98: 4.0244246 | DU98: 5.9313565 | DV98: 7.3075087 | DW98: 10.631381 | DX98: 3.9063424 | FB98: 6.1760599 | FC98: 10.515244 | FD98: 13.694736 | FE98: 24.935445 | FF98: 11.879723 | FG98: 9.1798213 | FH98: 5.0819365 | FI98: 12.303025 | FJ98: 6.0090551 | FK98: 7.9438082 | FL98: 7.3347442 | FM98: 10.263987 | FN98: 6.6712515 | GR98: 0.92901473 | GS98: 1.4605537 | GT98: 2.7555754 | GU98: 1.367463 | GV98: 2.9889486 | GW98: 1.0079228 | GX98: 0.6829019 | GY98: 2.6388277 | GZ98: 1.0493151 | HA98: 0.75997006 | HB98: 0.84040715 | HC98: 1.9154726 | HD98: 0.40302234
... A220: =AE220 -> 39843 | AE220: 39843 | DL220: 4.2391951 | DM220: 6.9837678 | DN220: 7.5513185 | DO220: #N/A | DP220: 8.6231084 | DQ220: 4.9495411 | DR220: 4.3288102 | DS220: 9.6939895 | DT220: 3.8099964 | DU220: 4.9191224 | DV220: 5.1269471 | DW220: 5.5190478 | DX220: 2.9620314 | FB220: 4.4979122 | FC220: 8.3850622 | FD220: 7.0156047 | FE220: 14.422155 | FF220: 7.2772779 | FG220: 6.000129 | FH220: 3.7163206 | FI220: 7.1925286 | FJ220: 5.020114 | FK220: 5.9728104 | FL220: 5.5453652 | FM220: 5.4673204 | FN220: 8.8261189 | GR220: 0.6332372 | GS220: 0.8125188 | GT220: 1.1139477 | GU220: 0.65275991 | GV220: 2.2347428 | GW220: 0.45522285 | GX220: 0.56598869 | GY220: 0.88907044 | GZ220: 0.98504682 | HA220: 0.74831665 | HB220: 0.40958854 | HC220: 0.83216222 | HD220: 0.25856862
A221: =AE221 -> 39813 | AE221: 39813 | DL221: 4.1332479 | DM221: 7.0272623 | DN221: 8.2126354 | DO221: #N/A | DP221: 8.9805697 | DQ221: 5.2212814 | DR221: 4.2501196 | DS221: 8.5403679 | DT221: 4.0308275 | DU221: 5.3059542 | DV221: 5.3824105 | DW221: 5.7649623 | DX221: 3.3655088 | FB221: 4.2603208 | FC221: 8.2473772 | FD221: 7.3783825 | FE221: #N/A | FF221: 7.577351 | FG221: 5.9891072 | FH221: 3.5272948 | FI221: 6.4546215 | FJ221: 5.0469043 | FK221: 6.0839499 | FL221: 5.6343616 | FM221: 5.5676612 | FN221: 8.2490923 | GR221: 0.64367422 | GS221: 0.81041547 | GT221: 1.2453491 | GU221: 0.72722076 | GV221: 2.3206803 | GW221: 0.48784628 | GX221: 0.53171488 | GY221: 0.88294921 | GZ221: 1.0458043 | HA221: 0.81788986 | HB221: 0.43216634 | HC221: 0.8865288 | HD221: 0.30618339
A222: =AE222 -> 39780 | AE222: 39780 | DL222: 3.8800706 | DM222: 6.925889 | DN222: 8.0939328 | DO222: #N/A | DP222: 8.7571098 | DQ222: 4.7967286 | DR222: 4.2263075 | DS222: 7.4190581 | DT222: 4.0352874 | DU222: 5.1888791 | DV222: 4.9386695 | DW222: 5.5975294 | DX222: 3.2110335 | FB222: 3.9818129 | FC222: 8.495068 | FD222: 7.3439954 | FE222: #N/A | FF222: 7.4618253 | FG222: 6.0531521 | FH222: 3.4454421 | FI222: 5.7367543 | FJ222: 5.4324354 | FK222: 6.366352 | FL222: 5.5917047 | FM222: 5.851401 | FN222: 8.3707634 | GR222: 0.61877818 | GS222: 0.81215011 | GT222: 1.1912784 | GU222: 0.74827197 | GV222: 2.2576104 | GW222: 0.45968713 | GX222: 0.51448173 | GY222: 0.85666029 | GZ222: 1.0524716 | HA222: 0.79396996 | HB222: 0.41448312 | HC222: 0.86834706 | HD222: 0.30593763
A223: =AE223 -> 39752 | AE223: 39752 | DL223: 3.8386916 | DM223: 7.5416002 | DN223: 8.3987091 | DO223: #N/A | DP223: 9.5277767 | DQ223: 4.592966 | DR223: 4.1541963 | DS223: 7.437306 | DT223: 3.8040109 | DU223: 5.4415559 | DV223: 4.7949987 | DW223: 5.481221 | DX223: 4.4670295 | FB223: 3.6088967 | FC223: 8.8921693 | FD223: 7.5733857 | FE223: #N/A | FF223: 7.9187543 | FG223: 5.8989429 | FH223: 3.2759133 | FI223: 5.3918215 | FJ223: 5.3109027 | FK223: 6.5049398 | FL223: 5.1825105 | FM223: 5.8461072 | FN223: 8.9801894 | GR223: 0.637919 | GS223: 0.89587128 | GT223: 1.2621871 | GU223: 0.81315584 | GV223: 2.4564877 | GW223: 0.45458296 | GX223: 0.51151384 | GY223: 0.8713388 | GZ223: 0.99911649 | HA223: 0.83943676 | HB223: 0.40674548 | HC223: 0.85268434 | HD223: 0.43130642
A224: =AE224 -> 39721 | AE224: 39721 | DL224: 4.5115596 | DM224: 7.5019562 | DN224: 9.9632967 | DO224: #N/A | DP224: 9.766119 | DQ224: 5.5537946 | DR224: 4.0841699 | DS224: 8.2519854 | DT224: 4.1234673 | DU224: 6.1936416 | DV224: 5.7727574 | DW224: 5.9244889 | DX224: 3.5883407 | FB224: 3.9847948 | FC224: 8.6961061 | FD224: 8.7438608 | FE224: #N/A | FF224: 8.2181489 | FG224: 6.362067 | FH224: 3.0832669 | FI224: 5.993262 | FJ224: 5.4426548 | FK224: 6.9591192 | FL224: 5.7513801 | FM224: 6.0813398 | FN224: 7.1416473 | GR224: 0.79063355 | GS224: 0.92036911 | GT224: 1.6194004 | GU224: 1.0785513 | GV224: 2.5210073 | GW224: 0.5634334 | GX224: 0.49083421 | GY224: 1.0100563 | GZ224: 1.0861069 | HA224: 0.95913439 | HB224: 0.46766607 | HC224: 0.95160118 | HD224: 0.37898492
A225: =AE225 -> 39689 | AE225: 39689 | DL225: 6.2797356 | DM225: 7.6018927 | DN225: 11.112279 | DO225: #N/A | DP225: 10.586663 | DQ225: 6.61638 | DR225: 4.8873462 | DS225: 10.027334 | DT225: 4.4110989 | DU225: 6.9196548 | DV225: 5.607845 | DW225: 6.6639126 | DX225: 3.7162381 | FB225: 5.1545817 | FC225: 8.8041876 | FD225: 9.6298374 | FE225: #N/A | FF225: 8.8251288 | FG225: 7.0237326 | FH225: 3.5252695 | FI225: 7.2383475 | FJ225: 5.5966572 | FK225: 7.4149647 | FL225: 6.5571815 | FM225: 6.51292 | FN225: 6.9795263 | GR225: 1.0814441 | GS225: 0.92916391 | GT225: 1.8074258 | GU225: 1.1925402 | GV225: 2.7262444 | GW225: 0.66427571 | GX225: 0.60169634 | GY225: 1.2154792 | GZ225: 1.1635276 | HA225: 1.0541632 | HB225: 0.53754946 | HC225: 1.0184655 | HD225: 0.39807002
A226: =AE226 -> 39660 | AE226: 39660 | DL226: 6.7657609 | DM226: 7.3159914 | DN226: 10.874319 | DO226: #N/A | DP226: 10.59246 | DQ226: 6.4923768 | DR226: 5.0696665 | DS226: 9.915441 | DT226: 4.3443163 | DU226: 6.986281 | DV226: 5.4306671 | DW226: 6.3768577 | DX226: 3.6166089 | FB226: 5.4520421 | FC226: 8.0374323 | FD226: 9.1931528 | FE226: #N/A | FF226: 8.6908801 | FG226: 6.6230275 | FH226: 3.6296329 | FI226: 6.9342639 | FJ226: 5.3239469 | FK226: 7.148028 | FL226: 6.3427018 | FM226: 5.5027889 | FN226: 6.2715612 | GR226: 1.1544854 | GS226: 0.89063493 | GT226: 1.780773 | GU226: 1.1796393 | GV226: 2.71678 | GW226: 0.65765032 | GX226: 0.63901068 | GY226: 1.1859707 | GZ226: 1.150198 | HA226: 1.1010104 | HB226: 0.52790574 | HC226: 0.98509757 | HD226: 0.38656577
A227: =AE227 -> 39629 | AE227: 39629 | DL227: 7.9283709 | DM227: 7.1182109 | DN227: 10.544366 | DO227: #N/A | DP227: 10.314945 | DQ227: 6.5872964 | DR227: 5.9091109 | DS227: 9.2557231 | DT227: 4.4761937 | DU227: 7.2885448 | DV227: 5.261971 | DW227: 6.12789 | DX227: 3.3431453 | FB227: 6.107117 | FC227: 7.8778388 | FD227: 8.9937207 | FE227: #N/A | FF227: 8.4437806 | FG227: 6.6570003 | FH227: 4.1265421 | FI227: 6.4002983 | FJ227: 5.4169681 | FK227: 7.5132628 | FL227: 6.2372989 | FM227: 5.4036917 | FN227: 5.8823784 | GR227: 1.307088 | GS227: 0.88664898 | GT227: 1.7528363 | GU227: 1.1587392 | GV227: 2.6358184 | GW227: 0.67544969 | GX227: 0.75673335 | GY227: 1.0997696 | GZ227: 1.1877401 | HA227: 1.1227841 | HB227: 0.52828509 | HC227: 0.96899891 | HD227: 0.37550849
A228: =AE228 -> 39598 | AE228: 39598 | DL228: 8.4741253 | DM228: 8.0863335 | DN228: 11.917498 | DO228: #N/A | DP228: 10.365525 | DQ228: 7.6353209 | DR228: 6.4797532 | DS228: 11.091506 | DT228: 4.9224848 | DU228: 7.9405461 | DV228: 5.8930937 | DW228: 7.2268707 | DX228: 3.8922737 | FB228: 6.3514064 | FC228: 8.7546683 | FD228: 10.146113 | FE228: #N/A | FF228: 8.5283974 | FG228: 7.4914556 | FH228: 4.5794925 | FI228: 7.6751166 | FJ228: 5.792363 | FK228: 8.0881412 | FL228: 6.7160072 | FM228: 6.1628755 | FN228: 6.484155 | GR228: 1.3614696 | GS228: 1.0071461 | GT228: 1.9912798 | GU228: 1.3571334 | GV228: 2.6594938 | GW228: 0.78251637 | GX228: 0.81894373 | GY228: 1.3026936 | GZ228: 1.2993166 | HA228: 1.2423336 | HB228: 0.60576853 | HC228: 1.1407924 | HD228: 0.4386365
A229: =AE229 -> 39568 | AE229: 39568 | DL229: 8.1047869 | DM229: 8.1217566 | DN229: 11.757486 | DO229: #N/A | DP229: 10.401001 | DQ229: 7.3560659 | DR229: 6.4231463 | DS229: 10.918918 | DT229: 4.9553621 | DU229: 7.7402423 | DV229: 5.7698411 | DW229: 7.565122 | DX229: 3.9894917 | FB229: 6.1231743 | FC229: 8.453681 | FD229: 9.8511179 | FE229: #N/A | FF229: 8.5365525 | FG229: 7.5331966 | FH229: 4.6726814 | FI229: 7.5693377 | FJ229: 5.7007527 | FK229: 7.9902718 | FL229: 6.5666162 | FM229: 6.3424791 | FN229: 6.3992612 | GR229: 1.3340747 | GS229: 1.0096788 | GT229: 1.9239281 | GU229: 1.4129297 | GV229: 2.6772073 | GW229: 0.76054089 | GX229: 0.81609472 | GY229: 1.2644746 | GZ229: 1.3050712 | HA229: 1.206842 | HB229: 0.61171767 | HC229: 1.2016587 | HD229: 0.44960474
A230: =AE230 -> 39538 | AE230: 39538 | DL230: 7.7654276 | DM230: 8.1067705 | DN230: 11.569576 | DO230: #N/A | DP230: 10.373471 | DQ230: 7.1691806 | DR230: 5.8047854 | DS230: 10.027137 | DT230: 4.7261404 | DU230: 7.4307264 | DV230: 5.4886931 | DW230: 7.4902294 | DX230: 4.0284502 | FB230: 5.9266956 | FC230: 8.3299794 | FD230: 9.5945548 | FE230: #N/A | FF230: 8.4289059 | FG230: 7.3151291 | FH230: 4.2825157 | FI230: 7.002741 | FJ230: 5.45793 | FK230: 7.6791735 | FL230: 6.1808358 | FM230: 6.6012707 | FN230: 6.2452111 | GR230: 1.2289797 | GS230: 1.009643 | GT230: 1.8742652 | GU230: 1.3331498 | GV230: 2.6367205 | GW230: 0.73390147 | GX230: 0.73109018 | GY230: 1.1648082 | GZ230: 1.2444914 | HA230: 1.1520898 | HB230: 0.58030638 | HC230: 1.2386146 | HD230: 0.45781148
A231: =AE231 -> 39507 | AE231: 39507 | DL231: 8.2462177 | DM231: 8.2137822 | DN231: 11.95784 | DO231: #N/A | DP231: 10.711325 | DQ231: 7.4670107 | DR231: 6.1793349 | DS231: 10.557237 | DT231: 5.2715659 | DU231: 7.7665313 | DV231: 5.6920054 | DW231: 7.9941321 | DX231: 3.9513665 | FB231: 6.3012081 | FC231: 8.4359961 | FD231: 9.7320902 | FE231: #N/A | FF231: 8.7420026 | FG231: 7.5266187 | FH231: 4.6199545 | FI231: 7.9217887 | FJ231: 5.87061 | FK231: 7.9312427 | FL231: 6.3855508 | FM231: 6.9579574 | FN231: 6.2390603 | GR231: 1.3065247 | GS231: 1.0168603 | GT231: 1.9022381 | GU231: 1.3353744 | GV231: 2.7473756 | GW231: 0.76332654 | GX231: 0.78375611 | GY231: 1.3162742 | GZ231: 1.3725704 | HA231: 1.2169213 | HB231: 0.60907898 | HC231: 1.3192038 | HD231: 0.44225239
A232: =AE232 -> 39478 | AE232: 39478 | DL232: 7.6757631 | DM232: 8.2506533 | DN232: 11.983889 | DO232: #N/A | DP232: 10.82132 | DQ232: 7.3326319 | DR232: 5.9007237 | DS232: 10.664484 | DT232: 5.7467129 | DU232: 7.7985354 | DV232: 5.8409605 | DW232: 8.2150745 | DX232: 3.9791938 | FB232: 5.8875514 | FC232: 8.4670882 | FD232: 9.6931494 | FE232: #N/A | FF232: 8.7941648 | FG232: 7.2387551 | FH232: 4.3793037 | FI232: 8.0549446 | FJ232: 6.281105 | FK232: 7.6101001 | FL232: 6.6221397 | FM232: 7.5859802 | FN232: 6.2949871 | GR232: 1.2333772 | GS232: 1.0249306 | GT232: 1.9028582 | GU232: 1.3410094 | GV232: 2.8122806 | GW232: 0.75110708 | GX232: 0.7705568 | GY232: 1.355774 | GZ232: 1.4808818 | HA232: 1.2466601 | HB232: 0.64333528 | HC232: 1.360196 | HD232: 0.44523755
... A240: =AE240 -> 39233 | AE240: 39233 | DL240: 8.3081859 | DM240: 9.9598113 | DN240: 15.044084 | DO240: #N/A | DP240: 12.971509 | DQ240: 10.084809 | DR240: 6.8066213 | DS240: 12.754893 | DT240: 6.0320597 | DU240: 8.8680418 | DV240: 9.6514852 | DW240: 11.143409 | DX240: 5.1806787 | FB240: 6.585135 | FC240: 10.429348 | FD240: 12.336062 | FE240: #N/A | FF240: 10.291203 | FG240: 9.2220918 | FH240: 5.1306444 | FI240: 9.3209077 | FJ240: 6.4991568 | FK240: 8.2392459 | FL240: 8.924042 | FM240: 9.1246108 | FN240: 8.7160716 | GR240: 1.5004888 | GS240: 1.1938932 | GT240: 2.4272479 | GU240: 1.9698531 | GV240: 3.318548 | GW240: 1.004355 | GX240: 0.93044755 | GY240: 1.6333504 | GZ240: 1.5398182 | HA240: 1.4203201 | HB240: 0.97970968 | HC240: 1.746639 | HD240: 0.52207618
