Workbook
Name Annee_Bench: Output!$N$416:INDEX(Output!$N:$N,415+COUNT(Output!$M$416:$M$10000))
Name Annee_Bottom: Output!$Q$416:INDEX(Output!$Q:$Q,415+COUNT(Output!$M$416:$M$10000))
Name Annee_Date: Output!$M$416:INDEX(Output!$M:$M,415+COUNT(Output!$M$416:$M$10000))
Name Annee_Ptf: Output!$O$416:INDEX(Output!$O:$O,415+COUNT(Output!$M$416:$M$10000))
Name Annee_Top: Output!$P$416:INDEX(Output!$P:$P,415+COUNT(Output!$M$416:$M$10000))
Name Courbe_Bench: Output!$E$416:INDEX(Output!$E:$E,415+COUNT(Output!$D$416:$D$10000))
Name Courbe_Bottom: Output!$H$416:INDEX(Output!$H:$H,415+COUNT(Output!$D$416:$D$10000))
Name Courbe_Date: Output!$D$416:INDEX(Output!$D:$D,415+COUNT(Output!$D$416:$D$10000))
Name Courbe_LS: Output!$I$416:INDEX(Output!$I:$I,415+COUNT(Output!$D$416:$D$10000))
Name Courbe_Ptf: Output!$F$416:INDEX(Output!$F:$F,415+COUNT(Output!$D$416:$D$10000))
Name Courbe_Top: Output!$G$416:INDEX(Output!$G:$G,415+COUNT(Output!$D$416:$D$10000))
Name DateExport: Config!$C$34
Name delta_Wi: Config!$C$30
Name ExportFile: Config!$C$36
Name ImportFile: Config!$C$35
Name IND_Bench: Config!$B$7
Name IND_ConsGd: Config!$B$9
Name IND_Fin: Config!$B$11
Name IND_Health: Config!$B$12
Name IND_Indus: Config!$B$13
Name IND_Mat: Config!$B$8
Name Ind_Media: Config!$B$19
Name IND_Oil: Config!$B$14
Name Ind_Retail: Config!$B$10
Name IND_Tech: Config!$B$15
Name IND_Telco: Config!$B$16
Name Ind_Travel: Config!$B$18
Name IND_Utili: Config!$B$17
Name nb_Bottom: Config!$C$25
Name nb_Long: Config!$C$27
Name nb_Short: Config!$C$28
Name nb_Top: Config!$C$24
Name RFolder: Config!$C$37
Name RFunction: Config!$C$38

Sheet Dashboard
I4: SCORECARD | BN4: Date: | BO4: =Output!B2 -> 46295 | BP4: =Output!B9 -> Oct-2026 | BQ4: =Output!B10 -> Sept-2026
I5: US SECTORS
R6: S | BP6: =Output!B11 -> Sectors Ranking Oct-2026 | BV6: =Output!B12 -> Sectors Ranking Sept-2026
CC7: Last Month Allocation Performance
I8: Low leverage rank | J8: Net debt to EBITDA | M8: FCF to Total Debt | P8: Margin rank | Q8: Operating margin | T8: Net margin | W8: EBITDA margin | Z8: Valuation rank | AA8: PFCF | AD8: EV / EBITDA | AG8: Price to sales | AJ8: Momentum rank | AK8: Perf 6M-1M | AM8: Perf 12M-1M | AO8: Earnings revision ratio | AR8: Growth rank | AS8: EPS 12M growth forecast | AV8: Sales 12M growth forecast | AY8: EBITDA 12M growth forecast | BB8: Cash Flow 12M growth forecast | BE8: Low volatility rank | BF8: Vol 6M | BH8: Vol downside 18M | BJ8: =Output!B13 -> Macro rank - Currently in Expansion | BK8: Rate signal - Bonus Leverage & Value
J9: vs. moy secteurs perc. 5y | K9: vs. moy secteurs histo 5y | L9: metric | M9: vs. moy secteurs perc. 5y | N9: vs. moy secteurs histo 5y | O9: metric | Q9: vs. moy secteurs perc. 5y | R9: vs. moy secteurs histo 5y | S9: metric | T9: vs. moy secteurs perc. 5y | U9: vs. moy secteurs histo 5y | V9: metric | W9: vs. moy secteurs perc. 5y | X9: vs. moy secteurs histo 5y | Y9: metric | AA9: vs. moy secteurs perc. 5y | AB9: vs. moy secteurs histo 5y | AC9: metric | AD9: vs. moy secteurs perc. 5y | AE9: vs. moy secteurs histo 5y | AF9: metric | AG9: vs. moy secteurs perc. 5y | AH9: vs. moy secteurs histo 5y | AI9: metric | AK9: rank (rank) | AL9: Perf | AM9: rank (rank) | AN9: Perf | AO9: rank (rank) | AP9: Ratio histo 5y | AQ9: Ratio | AS9: vs. moy secteurs perc. 5y | AT9: vs. moy secteurs histo 5y | AU9: metric | AV9: vs. moy secteurs perc. 5y | AW9: vs. moy secteurs histo 5y | AX9: metric | AY9: vs. moy secteurs perc. 5y | AZ9: vs. moy secteurs histo 5y | BA9: metric | BB9: vs. moy secteurs perc. 5y | BC9: vs. moy secteurs histo 5y | BD9: metric | BF9: rank (rank) | BG9: Vol | BH9: rank (rank) | BI9: Vol | BN9: Nb Top 3 pillars | BO9: Nb Worst 3 pillars | BP9: Global - Weighted Score | BQ9: Reco | BR9: Δ Reco | BU9: Previous nb piliers Top 3 | BV9: Previous nb piliers Worst 3 | BW9: Previous global - Weighted Score | BX9: Previous Reco | BY9: =Output!BU1 -> Sept-2026 EQ Performance | BZ9: =Output!BV1 -> Sept-2026 XSRet vs WIUSAU Index | CD9: Last Month EQ Performance
H10: Materials | I10: =Output!E2 -> 7 | J10: =Output!F2 -> 4.8019126 | L10: =Output!H2 -> 1.22262 | M10: =Output!I2 -> 4.2076503 | O10: =Output!K2 -> 22.028238 | P10: =Output!L2 -> 5 | Q10: =Output!M2 -> 6.4480874 | S10: =Output!O2 -> 19.657374 | T10: =Output!P2 -> 4.4672131 | V10: =Output!R2 -> 12.336806 | W10: =Output!S2 -> 5.5327869 | Y10: =Output!U2 -> 27.295065 | Z10: =Output!V2 -> 11 | AA10: =Output!W2 -> 0.6557377 | AC10: =Output!Y2 -> 12.53727 | AD10: =Output!Z2 -> 0.32786885 | AF10: =Output!AB2 -> 10.69341 | AG10: =Output!AC2 -> 0.49180328 | AI10: =Output!AE2 -> 3.0101644 | AJ10: =Output!AF2 -> 3 | AK10: =Output!AG2 -> 8 | AL10: =Output!AH2 -> 0.099930284 | AM10: =Output!AI2 -> 10 | AN10: =Output!AJ2 -> 0.27859081 | AO10: =Output!AK2 -> 9 | AQ10: =Output!AM2 -> 0.30769231 | AR10: =Output!AN2 -> 2 | AS10: =Output!AO2 -> 8.1967213 | AU10: =Output!AQ2 -> 19.596372 | AV10: =Output!AR2 -> 8.6885246 | AX10: =Output!AT2 -> 6.8923117 | AY10: =Output!AU2 -> 8.0327869 | BA10: =Output!AW2 -> 14.662707 | BB10: =Output!AX2 -> 9.0163934 | BD10: =Output!AZ2 -> 22.047794 | BE10: =Output!BA2 -> 1 | BF10: =Output!BB2 -> 9.3442623 | BG10: =Output!BC2 -> 0.17282112 | BH10: =Output!BD2 -> 9.1803279 | BI10: =Output!BE2 -> 0.086038617 | BJ10: =Output!BF2 -> 3 | BK10: =Output!B6 -> On | BM10: Materials | BN10: =Output!BJ2 -> 4 | BO10: =Output!BK2 -> 2 | BP10: =Output!BL2 -> 8.5 | BQ10: =Output!BM2 -> Positive | BR10: =Output!BN2 -> 1 | BU10: =Output!BQ2 -> 2 | BV10: =Output!BR2 -> 1 | BW10: =Output!BS2 -> 6.5 | BX10: =Output!BT2 -> Neutral | BY10: =Output!BU2 -> -0.054387894 | BZ10: =Output!BV2 -> -0.049961435 | CC10: Long Portfolio | CD10: =Output!B15 -> -0.021838073
H11: Consumer Staples | I11: =Output!E3 -> 8 | J11: =Output!F3 -> 2.4795082 | L11: =Output!H3 -> 1.9202542 | M11: =Output!I3 -> 6.4412568 | O11: =Output!K3 -> 25.178694 | P11: =Output!L3 -> 12 | Q11: =Output!M3 -> 0.49863388 | S11: =Output!O3 -> 6.9512161 | T11: =Output!P3 -> 0.49863388 | V11: =Output!R3 -> 4.979818 | W11: =Output!S3 -> 0.49863388 | Y11: =Output!U3 -> 8.4210974 | Z11: =Output!V3 -> 6 | AA11: =Output!W3 -> 3.7704918 | AC11: =Output!Y3 -> 14.235069 | AD11: =Output!Z3 -> 3.2786885 | AF11: =Output!AB3 -> 12.611009 | AG11: =Output!AC3 -> 7.8688525 | AI11: =Output!AE3 -> 0.91152254 | AJ11: =Output!AF3 -> 10 | AK11: =Output!AG3 -> 5 | AL11: =Output!AH3 -> 0.057409307 | AM11: =Output!AI3 -> 6 | AN11: =Output!AJ3 -> 0.10520092 | AO11: =Output!AK3 -> 2 | AQ11: =Output!AM3 -> -0.038461538 | AR11: =Output!AN3 -> 8 | AS11: =Output!AO3 -> 7.8688525 | AU11: =Output!AQ3 -> 6.9321977 | AV11: =Output!AR3 -> 2.1311475 | AX11: =Output!AT3 -> 4.4229456 | AY11: =Output!AU3 -> 1.9672131 | BA11: =Output!AW3 -> 5.7536922 | BB11: =Output!AX3 -> 3.442623 | BD11: =Output!AZ3 -> 9.7312479 | BE11: =Output!BA3 -> 12 | BF11: =Output!BB3 -> 4.5901639 | BG11: =Output!BC3 -> 0.15794132 | BH11: =Output!BD3 -> 0.98360656 | BI11: =Output!BE3 -> 0.094598589 | BJ11: =Output!BF3 -> 12 | BK11: A sector that is at least 3 times in worst 3 sectors (resp. top 3) of different pillars can not have a positive recommendation (resp. negative). If two sectors are as many times in the top or worst 3, we differentiate them by their mean score. If rate signal is on, value and leverage pillars count twice. Negative recommendation doesn't include margin pillar. | BM11: Consumer Staples | BN11: =Output!BJ3 -> 0 | BO11: =Output!BK3 -> 3 | BP11: =Output!BL3 -> 3.6666667 | BQ11: =Output!BM3 -> Negative | BR11: =Output!BN3 -> 0 | BU11: =Output!BQ3 -> 0 | BV11: =Output!BR3 -> 2 | BW11: =Output!BS3 -> 4.1666667 | BX11: =Output!BT3 -> Negative | BY11: =Output!BU3 -> -0.036884392 | BZ11: =Output!BV3 -> -0.032457934 | CC11: Short Portfolio | CD11: =Output!B16 -> 0.046805463
H12: Retail | I12: =Output!E4 -> 10 | J12: =Output!F4 -> 4.3306011 | L12: =Output!H4 -> 0.49591342 | M12: =Output!I4 -> 2.397541 | O12: =Output!K4 -> 17.857379 | P12: =Output!L4 -> 11 | Q12: =Output!M4 -> 1.8989071 | S12: =Output!O4 -> 8.9815098 | T12: =Output!P4 -> 3.1284153 | V12: =Output!R4 -> 7.0708821 | W12: =Output!S4 -> 2.1448087 | Y12: =Output!U4 -> 13.587507 | Z12: =Output!V4 -> 2 | AA12: =Output!W4 -> 10 | AC12: =Output!Y4 -> 13.787961 | AD12: =Output!Z4 -> 10 | AF12: =Output!AB4 -> 11.773436 | AG12: =Output!AC4 -> 9.1803279 | AI12: =Output!AE4 -> 1.8559352 | AJ12: =Output!AF4 -> 8 | AK12: =Output!AG4 -> 6 | AL12: =Output!AH4 -> 0.079188564 | AM12: =Output!AI4 -> 4 | AN12: =Output!AJ4 -> 0.081707795 | AO12: =Output!AK4 -> 8 | AQ12: =Output!AM4 -> 0.2 | AR12: =Output!AN4 -> 3 | AS12: =Output!AO4 -> 2.4590164 | AU12: =Output!AQ4 -> 5.5615651 | AV12: =Output!AR4 -> 5.4098361 | AX12: =Output!AT4 -> 8.8864034 | AY12: =Output!AU4 -> 10 | BA12: =Output!AW4 -> 21.205741 | BB12: =Output!AX4 -> 3.6065574 | BD12: =Output!AZ4 -> 19.614034 | BE12: =Output!BA4 -> 8 | BF12: =Output!BB4 -> 0.6557377 | BG12: =Output!BC4 -> 0.26849553 | BH12: =Output!BD4 -> 7.3770492 | BI12: =Output!BE4 -> 0.084264252 | BJ12: =Output!BF4 -> 5 | BM12: Retail | BN12: =Output!BJ4 -> 3 | BO12: =Output!BK4 -> 2 | BP12: =Output!BL4 -> 7 | BQ12: =Output!BM4 -> Neutral | BR12: =Output!BN4 -> -1 | BU12: =Output!BQ4 -> 3 | BV12: =Output!BR4 -> 2 | BW12: =Output!BS4 -> 7.8333333 | BX12: =Output!BT4 -> Positive | BY12: =Output!BU4 -> -0.043559021 | BZ12: =Output!BV4 -> -0.039132563 | CC12: L/S Portfolio | CD12: =Output!B17 -> 0.02496739
H13: Financials | I13: =Output!E5 -> 1 | J13: =Output!F5 -> 9.0163934 | L13: =Output!H5 -> -2.0866902 | M13: =Output!I5 -> 6.6734973 | O13: =Output!K5 -> 22.209445 | P13: =Output!L5 -> 2 | Q13: =Output!M5 -> 7.9439891 | S13: =Output!O5 -> 21.658118 | T13: =Output!P5 -> 7.9439891 | V13: =Output!R5 -> 16.054846 | W13: =Output!S5 -> 5.1297814 | Y13: =Output!U5 -> 28.346714 | Z13: =Output!V5 -> 8 | AA13: =Output!W5 -> n.a. | AC13: =Output!Y5 -> n.a. | AD13: =Output!Z5 -> n.a. | AF13: =Output!AB5 -> n.a. | AG13: =Output!AC5 -> 5.7377049 | AI13: =Output!AE5 -> 2.8520047 | AJ13: =Output!AF5 -> 6 | AK13: =Output!AG5 -> 11 | AL13: =Output!AH5 -> 0.14490912 | AM13: =Output!AI5 -> 5 | AN13: =Output!AJ5 -> 0.089314593 | AO13: =Output!AK5 -> 5 | AQ13: =Output!AM5 -> 0.014925373 | AR13: =Output!AN5 -> 6 | AS13: =Output!AO5 -> 5.9016393 | AU13: =Output!AQ5 -> 9.7731301 | AV13: =Output!AR5 -> 2.4590164 | AX13: =Output!AT5 -> 6.0163324 | AY13: =Output!AU5 -> n.a. | BA13: =Output!AW5 -> n.a. | BB13: =Output!AX5 -> n.a. | BD13: =Output!AZ5 -> n.a. | BE13: =Output!BA5 -> 3 | BF13: =Output!BB5 -> 7.0491803 | BG13: =Output!BC5 -> 0.17070161 | BH13: =Output!BD5 -> 7.3770492 | BI13: =Output!BE5 -> 0.071893946 | BJ13: =Output!BF5 -> 3 | BM13: Financials | BN13: =Output!BJ5 -> 5 | BO13: =Output!BK5 -> 0 | BP13: =Output!BL5 -> 8.5 | BQ13: =Output!BM5 -> Positive | BR13: =Output!BN5 -> 0 | BU13: =Output!BQ5 -> 4 | BV13: =Output!BR5 -> 1 | BW13: =Output!BS5 -> 8.1666667 | BX13: =Output!BT5 -> Positive | BY13: =Output!BU5 -> -0.074213842 | BZ13: =Output!BV5 -> -0.069787384 | CC13: Ptf dev secto | CD13: =Output!B18 -> 0.00036872701
H14: HealthCare | I14: =Output!E6 -> 9 | J14: =Output!F6 -> 2.1653005 | L14: =Output!H6 -> 1.7058441 | M14: =Output!I6 -> 6.0519126 | O14: =Output!K6 -> 27.543317 | P14: =Output!L6 -> 8 | Q14: =Output!M6 -> 1.9057377 | S14: =Output!O6 -> 12.913112 | T14: =Output!P6 -> 1.7418033 | V14: =Output!R6 -> 9.2893927 | W14: =Output!S6 -> 8.5040984 | Y14: =Output!U6 -> 32.941353 | Z14: =Output!V6 -> 10 | AA14: =Output!W6 -> 0.16393443 | AC14: =Output!Y6 -> 16.987361 | AD14: =Output!Z6 -> 0.16393443 | AF14: =Output!AB6 -> 15.705992 | AG14: =Output!AC6 -> 6.0655738 | AI14: =Output!AE6 -> 2.4448214 | AJ14: =Output!AF6 -> 4 | AK14: =Output!AG6 -> 10 | AL14: =Output!AH6 -> 0.14390425 | AM14: =Output!AI6 -> 9 | AN14: =Output!AJ6 -> 0.22268254 | AO14: =Output!AK6 -> 3 | AQ14: =Output!AM6 -> 0 | AR14: =Output!AN6 -> 4 | AS14: =Output!AO6 -> 9.1803279 | AU14: =Output!AQ6 -> 17.856892 | AV14: =Output!AR6 -> 0.98360656 | AX14: =Output!AT6 -> 4.5266928 | AY14: =Output!AU6 -> 6.557377 | BA14: =Output!AW6 -> 14.497431 | BB14: =Output!AX6 -> 6.8852459 | BD14: =Output!AZ6 -> 15.896039 | BE14: =Output!BA6 -> 11 | BF14: =Output!BB6 -> 5.2459016 | BG14: =Output!BC6 -> 0.16169832 | BH14: =Output!BD6 -> 1.147541 | BI14: =Output!BE6 -> 0.086891746 | BJ14: =Output!BF6 -> 9 | BM14: HealthCare | BN14: =Output!BJ6 -> 0 | BO14: =Output!BK6 -> 3 | BP14: =Output!BL6 -> 5.1666667 | BQ14: =Output!BM6 -> Neutral | BR14: =Output!BN6 -> 0 | BU14: =Output!BQ6 -> 0 | BV14: =Output!BR6 -> 1 | BW14: =Output!BS6 -> 5 | BX14: =Output!BT6 -> Neutral | BY14: =Output!BU6 -> -0.0067022413 | BZ14: =Output!BV6 -> -0.0022757826 | CC14: S&P 500 | CD14: =Output!B19 -> -0.0044264587
H15: Industrials | I15: =Output!E7 -> 6 | J15: =Output!F7 -> 2.6502732 | L15: =Output!H7 -> 1.7344032 | M15: =Output!I7 -> 8.6680328 | O15: =Output!K7 -> 26.948095 | P15: =Output!L7 -> 10 | Q15: =Output!M7 -> 2.1653005 | S15: =Output!O7 -> 16.237674 | T15: =Output!P7 -> 4.3101093 | V15: =Output!R7 -> 12.887893 | W15: =Output!S7 -> 1.3319672 | Y15: =Output!U7 -> 21.062697 | Z15: =Output!V7 -> 7 | AA15: =Output!W7 -> 1.6393443 | AC15: =Output!Y7 -> 17.405303 | AD15: =Output!Z7 -> 1.3114754 | AF15: =Output!AB7 -> 15.327033 | AG15: =Output!AC7 -> 7.5409836 | AI15: =Output!AE7 -> 2.9930543 | AJ15: =Output!AF7 -> 6 | AK15: =Output!AG7 -> 7 | AL15: =Output!AH7 -> 0.093829499 | AM15: =Output!AI7 -> 7 | AN15: =Output!AJ7 -> 0.11693454 | AO15: =Output!AK7 -> 7 | AQ15: =Output!AM7 -> 0.096774194 | AR15: =Output!AN7 -> 9 | AS15: =Output!AO7 -> 8.1967213 | AU15: =Output!AQ7 -> 13.931877 | AV15: =Output!AR7 -> 5.4098361 | AX15: =Output!AT7 -> 7.9835015 | AY15: =Output!AU7 -> 2.4590164 | BA15: =Output!AW7 -> 11.738682 | BB15: =Output!AX7 -> 2.1311475 | BD15: =Output!AZ7 -> 14.563399 | BE15: =Output!BA7 -> 9 | BF15: =Output!BB7 -> 5.7377049 | BG15: =Output!BC7 -> 0.18457319 | BH15: =Output!BD7 -> 1.4754098 | BI15: =Output!BE7 -> 0.099040037 | BJ15: =Output!BF7 -> 8 | BM15: Industrials | BN15: =Output!BJ7 -> 0 | BO15: =Output!BK7 -> 0 | BP15: =Output!BL7 -> 5.5 | BQ15: =Output!BM7 -> Neutral | BR15: =Output!BN7 -> 0 | BU15: =Output!BQ7 -> 0 | BV15: =Output!BR7 -> 0 | BW15: =Output!BS7 -> 6 | BX15: =Output!BT7 -> Neutral | BY15: =Output!BU7 -> -0.048431204 | BZ15: =Output!BV7 -> -0.044004745
H16: Energy | I16: =Output!E8 -> 5 | J16: =Output!F8 -> 5.6352459 | L16: =Output!H8 -> 1.0167123 | M16: =Output!I8 -> 6.7964481 | O16: =Output!K8 -> 36.24289 | P16: =Output!L8 -> 9 | Q16: =Output!M8 -> 3.7978142 | S16: =Output!O8 -> 13.425094 | T16: =Output!P8 -> 3.6338798 | V16: =Output!R8 -> 9.7795478 | W16: =Output!S8 -> 3.6338798 | Y16: =Output!U8 -> 21.631408 | Z16: =Output!V8 -> 9 | AA16: =Output!W8 -> 1.4754098 | AC16: =Output!Y8 -> 7.3348122 | AD16: =Output!Z8 -> 0.98360656 | AF16: =Output!AB8 -> 6.8885213 | AG16: =Output!AC8 -> 4.4262295 | AI16: =Output!AE8 -> 1.5599016 | AJ16: =Output!AF8 -> 3 | AK16: =Output!AG8 -> 3 | AL16: =Output!AH8 -> 0.021864807 | AM16: =Output!AI8 -> 12 | AN16: =Output!AJ8 -> 0.42613895 | AO16: =Output!AK8 -> 12 | AQ16: =Output!AM8 -> 0.5 | AR16: =Output!AN8 -> 7 | AS16: =Output!AO8 -> 9.0163934 | AU16: =Output!AQ8 -> 14.60133 | AV16: =Output!AR8 -> 2.7868852 | AX16: =Output!AT8 -> 1.1215868 | AY16: =Output!AU8 -> 3.442623 | BA16: =Output!AW8 -> 8.1029064 | BB16: =Output!AX8 -> 4.9180328 | BD16: =Output!AZ8 -> 9.8949627 | BE16: =Output!BA8 -> 6 | BF16: =Output!BB8 -> 3.9344262 | BG16: =Output!BC8 -> 0.26727375 | BH16: =Output!BD8 -> 5.4098361 | BI16: =Output!BE8 -> 0.14596108 | BJ16: =Output!BF8 -> 4 | BM16: Energy | BN16: =Output!BJ8 -> 1 | BO16: =Output!BK8 -> 0 | BP16: =Output!BL8 -> 7.3333333 | BQ16: =Output!BM8 -> Neutral | BR16: =Output!BN8 -> 0 | BU16: =Output!BQ8 -> 2 | BV16: =Output!BR8 -> 0 | BW16: =Output!BS8 -> 8.5 | BX16: =Output!BT8 -> Neutral | BY16: =Output!BU8 -> -0.029401703 | BZ16: =Output!BV8 -> -0.024975244
H17: Tech | I17: =Output!E9 -> 4 | J17: =Output!F9 -> 5.6489071 | L17: =Output!H9 -> 0.10783016 | M17: =Output!I9 -> 6.8852459 | O17: =Output!K9 -> 64.397494 | P17: =Output!L9 -> 1 | Q17: =Output!M9 -> 10 | S17: =Output!O9 -> 34.782338 | T17: =Output!P9 -> 10 | V17: =Output!R9 -> 30.22492 | W17: =Output!S9 -> 10 | Y17: =Output!U9 -> 41.002375 | Z17: =Output!V9 -> 3 | AA17: =Output!W9 -> 8.3783784 | AC17: =Output!Y9 -> 18.31349 | AD17: =Output!Z9 -> 8.3783784 | AF17: =Output!AB9 -> 15.584779 | AG17: =Output!AC9 -> 3.6065574 | AI17: =Output!AE9 -> 7.5240099 | AJ17: =Output!AF9 -> 1 | AK17: =Output!AG9 -> 12 | AL17: =Output!AH9 -> 0.40754468 | AM17: =Output!AI9 -> 11 | AN17: =Output!AJ9 -> 0.33255594 | AO17: =Output!AK9 -> 11 | AQ17: =Output!AM9 -> 0.41558442 | AR17: =Output!AN9 -> 1 | AS17: =Output!AO9 -> 9.8360656 | AU17: =Output!AQ9 -> 36.001467 | AV17: =Output!AR9 -> 10 | AX17: =Output!AT9 -> 29.560464 | AY17: =Output!AU9 -> 10 | BA17: =Output!AW9 -> 38.714997 | BB17: =Output!AX9 -> 10 | BD17: =Output!AZ9 -> 40.42734 | BE17: =Output!BA9 -> 10 | BF17: =Output!BB9 -> 0.81967213 | BG17: =Output!BC9 -> 0.31534498 | BH17: =Output!BD9 -> 6.2295082 | BI17: =Output!BE9 -> 0.10283097 | BJ17: =Output!BF9 -> 1 | BM17: Tech | BN17: =Output!BJ9 -> 6 | BO17: =Output!BK9 -> 1 | BP17: =Output!BL9 -> 9.6666667 | BQ17: =Output!BM9 -> Positive | BR17: =Output!BN9 -> 0 | BU17: =Output!BQ9 -> 5 | BV17: =Output!BR9 -> 0 | BW17: =Output!BS9 -> 9.6666667 | BX17: =Output!BT9 -> Positive | BY17: =Output!BU9 -> 0.052258645 | BZ17: =Output!BV9 -> 0.056685103
H18: Teleco | I18: =Output!E10 -> 11 | J18: =Output!F10 -> 1.2431694 | L18: =Output!H10 -> 2.5053768 | M18: =Output!I10 -> 1.489071 | O18: =Output!K10 -> 16.521243 | P18: =Output!L10 -> 7 | Q18: =Output!M10 -> 4.3306011 | S18: =Output!O10 -> 21.28983 | T18: =Output!P10 -> 4.2486339 | V18: =Output!R10 -> 14.124129 | W18: =Output!S10 -> 4.2486339 | Y18: =Output!U10 -> 33.946443 | Z18: =Output!V10 -> 12 | AA18: =Output!W10 -> 0.16393443 | AC18: =Output!Y10 -> 8.3836912 | AD18: =Output!Z10 -> 0.16393443 | AF18: =Output!AB10 -> 9.0730263 | AG18: =Output!AC10 -> 0.16393443 | AI18: =Output!AE10 -> 2.4858615 | AJ18: =Output!AF10 -> 7 | AK18: =Output!AG10 -> 9 | AL18: =Output!AH10 -> 0.10659809 | AM18: =Output!AI10 -> 8 | AN18: =Output!AJ10 -> 0.14705402 | AO18: =Output!AK10 -> 3 | AQ18: =Output!AM10 -> 0 | AR18: =Output!AN10 -> 5 | AS18: =Output!AO10 -> 10 | AU18: =Output!AQ10 -> 11.360303 | AV18: =Output!AR10 -> 4.7540984 | AX18: =Output!AT10 -> 4.0875964 | AY18: =Output!AU10 -> 3.7704918 | BA18: =Output!AW10 -> 6.1977528 | BB18: =Output!AX10 -> 7.2131148 | BD18: =Output!AZ10 -> 9.3484409 | BE18: =Output!BA10 -> 5 | BF18: =Output!BB10 -> 3.1147541 | BG18: =Output!BC10 -> 0.1867086 | BH18: =Output!BD10 -> 6.8852459 | BI18: =Output!BE10 -> 0.062384629 | BJ18: =Output!BF10 -> 11 | BM18: Teleco | BN18: =Output!BJ10 -> 0 | BO18: =Output!BK10 -> 5 | BP18: =Output!BL10 -> 4.5 | BQ18: =Output!BM10 -> Negative | BR18: =Output!BN10 -> 0 | BU18: =Output!BQ10 -> 0 | BV18: =Output!BR10 -> 3 | BW18: =Output!BS10 -> 4.5 | BX18: =Output!BT10 -> Negative | BY18: =Output!BU10 -> -0.043942083 | BZ18: =Output!BV10 -> -0.039515624
H19: Utilities | I19: =Output!E11 -> 12 | J19: =Output!F11 -> 0.74453552 | L19: =Output!H11 -> 5.5479955 | M19: =Output!I11 -> 0.49863388 | O19: =Output!K11 -> -4.7788353 | P19: =Output!L11 -> 4 | Q19: =Output!M11 -> 6.1270492 | S19: =Output!O11 -> 21.232479 | T19: =Output!P11 -> 4.6448087 | V19: =Output!R11 -> 13.297373 | W19: =Output!S11 -> 6.7964481 | Y19: =Output!U11 -> 37.04345 | Z19: =Output!V11 -> 5 | AA19: =Output!W11 -> 6.557377 | AC19: =Output!Y11 -> 7.9412878 | AD19: =Output!Z11 -> 6.3934426 | AF19: =Output!AB11 -> 10.88924 | AG19: =Output!AC11 -> 10 | AI19: =Output!AE11 -> 2.4471488 | AJ19: =Output!AF11 -> 11 | AK19: =Output!AG11 -> 1 | AL19: =Output!AH11 -> -0.088632992 | AM19: =Output!AI11 -> 2 | AN19: =Output!AJ11 -> -0.0265588 | AO19: =Output!AK11 -> 6 | AQ19: =Output!AM11 -> 0.032258065 | AR19: =Output!AN11 -> 10 | AS19: =Output!AO11 -> 6.8852459 | AU19: =Output!AQ11 -> 9.49338 | AV19: =Output!AR11 -> 3.1147541 | AX19: =Output!AT11 -> 5.8426547 | AY19: =Output!AU11 -> 2.1311475 | BA19: =Output!AW11 -> 10.967616 | BB19: =Output!AX11 -> 1.6393443 | BD19: =Output!AZ11 -> 8.1241154 | BE19: =Output!BA11 -> 2 | BF19: =Output!BB11 -> 8.6885246 | BG19: =Output!BC11 -> 0.12102276 | BH19: =Output!BD11 -> 6.0655738 | BI19: =Output!BE11 -> 0.07092775 | BJ19: =Output!BF11 -> 11 | BM19: Utilities | BN19: =Output!BJ11 -> 1 | BO19: =Output!BK11 -> 5 | BP19: =Output!BL11 -> 4.5 | BQ19: =Output!BM11 -> Negative | BR19: =Output!BN11 -> 0 | BU19: =Output!BQ11 -> 0 | BV19: =Output!BR11 -> 4 | BW19: =Output!BS11 -> 3.8333333 | BX19: =Output!BT11 -> Negative | BY19: =Output!BU11 -> -0.059589914 | BZ19: =Output!BV11 -> -0.055163455
H20: Travel & leisure | I20: =Output!E12 -> 2 | J20: =Output!F12 -> 7.2540984 | L20: =Output!H12 -> 1.6952167 | M20: =Output!I12 -> 6.5983607 | O20: =Output!K12 -> 22.719799 | P20: =Output!L12 -> 6 | Q20: =Output!M12 -> 5.1297814 | S20: =Output!O12 -> 18.920226 | T20: =Output!P12 -> 6.2090164 | V20: =Output!R12 -> 13.612803 | W20: =Output!S12 -> 3.8046448 | Y20: =Output!U12 -> 24.042664 | Z20: =Output!V12 -> 1 | AA20: =Output!W12 -> 9.8360656 | AC20: =Output!Y12 -> 12.713618 | AD20: =Output!Z12 -> 10 | AF20: =Output!AB12 -> 11.235713 | AG20: =Output!AC12 -> 10 | AI20: =Output!AE12 -> 2.7514969 | AJ20: =Output!AF12 -> 12 | AK20: =Output!AG12 -> 4 | AL20: =Output!AH12 -> 0.050646403 | AM20: =Output!AI12 -> 3 | AN20: =Output!AJ12 -> 0.021117731 | AO20: =Output!AK12 -> 1 | AQ20: =Output!AM12 -> -0.21052632 | AR20: =Output!AN12 -> 11 | AS20: =Output!AO12 -> 4.5901639 | AU20: =Output!AQ12 -> 14.977821 | AV20: =Output!AR12 -> 0.32786885 | AX20: =Output!AT12 -> 6.7978974 | AY20: =Output!AU12 -> 0.98360656 | BA20: =Output!AW12 -> 10.162244 | BB20: =Output!AX12 -> 0.98360656 | BD20: =Output!AZ12 -> 12.014106 | BE20: =Output!BA12 -> 8 | BF20: =Output!BB12 -> 7.704918 | BG20: =Output!BC12 -> 0.17450673 | BH20: =Output!BD12 -> 0.32786885 | BI20: =Output!BE12 -> 0.1167738 | BJ20: =Output!BF12 -> 7 | BM20: Travel & leisure | BN20: =Output!BJ12 -> 0 | BO20: =Output!BK12 -> 0 | BP20: =Output!BL12 -> 6.1666667 | BQ20: =Output!BM12 -> Neutral | BR20: =Output!BN12 -> 0 | BU20: =Output!BQ12 -> 0 | BV20: =Output!BR12 -> 0 | BW20: =Output!BS12 -> 6.5 | BX20: =Output!BT12 -> Neutral | BY20: =Output!BU12 -> -0.095295803 | BZ20: =Output!BV12 -> -0.090869344
H21: Media | I21: =Output!E13 -> 3 | J21: =Output!F13 -> 6.7759563 | L21: =Output!H13 -> 1.0694065 | M21: =Output!I13 -> 7.0218579 | O21: =Output!K13 -> 26.131654 | P21: =Output!L13 -> 3 | Q21: =Output!M13 -> 7.3360656 | S21: =Output!O13 -> 17.178344 | T21: =Output!P13 -> 6.0177596 | V21: =Output!R13 -> 11.411406 | W21: =Output!S13 -> 7.431694 | Y21: =Output!U13 -> 29.294221 | Z21: =Output!V13 -> 4 | AA21: =Output!W13 -> 9.1803279 | AC21: =Output!Y13 -> 13.834502 | AD21: =Output!Z13 -> 9.0163934 | AF21: =Output!AB13 -> 11.969054 | AG21: =Output!AC13 -> 5.9016393 | AI21: =Output!AE13 -> 2.5892003 | AJ21: =Output!AF13 -> 10 | AK21: =Output!AG13 -> 2 | AL21: =Output!AH13 -> -0.03633281 | AM21: =Output!AI13 -> 1 | AN21: =Output!AJ13 -> -0.18719948 | AO21: =Output!AK13 -> 10 | AQ21: =Output!AM13 -> 0.36363636 | AR21: =Output!AN13 -> 12 | AS21: =Output!AO13 -> 3.6065574 | AU21: =Output!AQ13 -> 16.867662 | AV21: =Output!AR13 -> 0.16393443 | AX21: =Output!AT13 -> 6.6243557 | AY21: =Output!AU13 -> 0.16393443 | BA21: =Output!AW13 -> 12.536011 | BB21: =Output!AX13 -> 0.16393443 | BD21: =Output!AZ13 -> 6.6976182 | BE21: =Output!BA13 -> 4 | BF21: =Output!BB13 -> 6.8852459 | BG21: =Output!BC13 -> 0.24715147 | BH21: =Output!BD13 -> 7.0491803 | BI21: =Output!BE13 -> 0.11285839 | BJ21: =Output!BF13 -> 6 | BM21: Media | BN21: =Output!BJ13 -> 3 | BO21: =Output!BK13 -> 2 | BP21: =Output!BL13 -> 6.5 | BQ21: =Output!BM13 -> Neutral | BR21: =Output!BN13 -> 0 | BU21: =Output!BQ13 -> 3 | BV21: =Output!BR13 -> 2 | BW21: =Output!BS13 -> 6 | BX21: =Output!BT13 -> Neutral | BY21: =Output!BU13 -> -0.082060778 | BZ21: =Output!BV13 -> -0.07763432
H26: =TEXT(Output!B2,"[$-040C]mmm-yyyy")&" Commentaire : " -> sept.-2026 Commentaire :

Sheet Output
A1: Marché | B1: US | D1: Secteur | E1: Leverage | F1: Score net debt ebitda | H1: net debt ebitda | I1: Score fcf total debt | K1: fcf total debt | L1: Margin | M1: Score operating margin | O1: operating margin | P1: Score net margin | R1: net margin | S1: Score ebitda margin | U1: ebitda margin | V1: Value | W1: Score price fcf | Y1: price fcf | Z1: Score ev ebitda | AB1: ev ebitda | AC1: Score price sales | AE1: price sales | AF1: Momentum | AG1: Score momentum 6m 1m | AH1: momentum 6m 1m | AI1: Score momentum 12m 1m | AJ1: momentum 12m 1m | AK1: Score earnings revision ratio | AM1: earnings revision ratio | AN1: Growth | AO1: Score eps growth | AQ1: eps growth | AR1: Score sales growth | AT1: sales growth | AU1: Score ebitda growth | AW1: ebitda growth | AX1: Score cash flow growth | AZ1: cash flow growth | BA1: Volatility | BB1: Score volatility 6m | BC1: volatility 6m | BD1: Score downside volatility 18m | BE1: downside volatility 18m | BF1: Macro | BI1: Secteur | BJ1: Votes Top | BK1: Votes Worst | BL1: Score global | BM1: Reco | BN1: Variation reco | BQ1: Votes Top précédents | BR1: Votes Worst précédents | BS1: Score précédent | BT1: Reco précédente | BU1: Sept-2026 EQ Performance | BV1: Sept-2026 XSRet vs WIUSAU Index
A2: Date modèle | B2: 46295 | D2: Materials | E2: 7 | F2: 4.8019126 | H2: 1.22262 | I2: 4.2076503 | K2: 22.028238 | L2: 5 | M2: 6.4480874 | O2: 19.657374 | P2: 4.4672131 | R2: 12.336806 | S2: 5.5327869 | U2: 27.295065 | V2: 11 | W2: 0.6557377 | Y2: 12.53727 | Z2: 0.32786885 | AB2: 10.69341 | AC2: 0.49180328 | AE2: 3.0101644 | AF2: 3 | AG2: 8 | AH2: 0.099930284 | AI2: 10 | AJ2: 0.27859081 | AK2: 9 | AM2: 0.30769231 | AN2: 2 | AO2: 8.1967213 | AQ2: 19.596372 | AR2: 8.6885246 | AT2: 6.8923117 | AU2: 8.0327869 | AW2: 14.662707 | AX2: 9.0163934 | AZ2: 22.047794 | BA2: 1 | BB2: 9.3442623 | BC2: 0.17282112 | BD2: 9.1803279 | BE2: 0.086038617 | BF2: 3 | BI2: Materials | BJ2: 4 | BK2: 2 | BL2: 8.5 | BM2: Positive | BN2: 1 | BQ2: 2 | BR2: 1 | BS2: 6.5 | BT2: Neutral | BU2: -0.054387894 | BV2: -0.049961435
A3: Derniers piliers | B3: 46295 | D3: ConsStaples | E3: 8 | F3: 2.4795082 | H3: 1.9202542 | I3: 6.4412568 | K3: 25.178694 | L3: 12 | M3: 0.49863388 | O3: 6.9512161 | P3: 0.49863388 | R3: 4.979818 | S3: 0.49863388 | U3: 8.4210974 | V3: 6 | W3: 3.7704918 | Y3: 14.235069 | Z3: 3.2786885 | AB3: 12.611009 | AC3: 7.8688525 | AE3: 0.91152254 | AF3: 10 | AG3: 5 | AH3: 0.057409307 | AI3: 6 | AJ3: 0.10520092 | AK3: 2 | AM3: -0.038461538 | AN3: 8 | AO3: 7.8688525 | AQ3: 6.9321977 | AR3: 2.1311475 | AT3: 4.4229456 | AU3: 1.9672131 | AW3: 5.7536922 | AX3: 3.442623 | AZ3: 9.7312479 | BA3: 12 | BB3: 4.5901639 | BC3: 0.15794132 | BD3: 0.98360656 | BE3: 0.094598589 | BF3: 12 | BI3: ConsStaples | BJ3: 0 | BK3: 3 | BL3: 3.6666667 | BM3: Negative | BN3: 0 | BQ3: 0 | BR3: 2 | BS3: 4.1666667 | BT3: Negative | BU3: -0.036884392 | BV3: -0.032457934
A4: Allocation | B4: 46296 | D4: Retail | E4: 10 | F4: 4.3306011 | H4: 0.49591342 | I4: 2.397541 | K4: 17.857379 | L4: 11 | M4: 1.8989071 | O4: 8.9815098 | P4: 3.1284153 | R4: 7.0708821 | S4: 2.1448087 | U4: 13.587507 | V4: 2 | W4: 10 | Y4: 13.787961 | Z4: 10 | AB4: 11.773436 | AC4: 9.1803279 | AE4: 1.8559352 | AF4: 8 | AG4: 6 | AH4: 0.079188564 | AI4: 4 | AJ4: 0.081707795 | AK4: 8 | AM4: 0.2 | AN4: 3 | AO4: 2.4590164 | AQ4: 5.5615651 | AR4: 5.4098361 | AT4: 8.8864034 | AU4: 10 | AW4: 21.205741 | AX4: 3.6065574 | AZ4: 19.614034 | BA4: 8 | BB4: 0.6557377 | BC4: 0.26849553 | BD4: 7.3770492 | BE4: 0.084264252 | BF4: 5 | BI4: Retail | BJ4: 3 | BK4: 2 | BL4: 7 | BM4: Neutral | BN4: -1 | BQ4: 3 | BR4: 2 | BS4: 7.8333333 | BT4: Positive | BU4: -0.043559021 | BV4: -0.039132563
A5: Cycle | B5: E | D5: Fin | E5: 1 | F5: 9.0163934 | H5: -2.0866902 | I5: 6.6734973 | K5: 22.209445 | L5: 2 | M5: 7.9439891 | O5: 21.658118 | P5: 7.9439891 | R5: 16.054846 | S5: 5.1297814 | U5: 28.346714 | V5: 8 | W5: n.a. | Y5: n.a. | Z5: n.a. | AB5: n.a. | AC5: 5.7377049 | AE5: 2.8520047 | AF5: 6 | AG5: 11 | AH5: 0.14490912 | AI5: 5 | AJ5: 0.089314593 | AK5: 5 | AM5: 0.014925373 | AN5: 6 | AO5: 5.9016393 | AQ5: 9.7731301 | AR5: 2.4590164 | AT5: 6.0163324 | AU5: n.a. | AW5: n.a. | AX5: n.a. | AZ5: n.a. | BA5: 3 | BB5: 7.0491803 | BC5: 0.17070161 | BD5: 7.3770492 | BE5: 0.071893946 | BF5: 3 | BI5: Fin | BJ5: 5 | BK5: 0 | BL5: 8.5 | BM5: Positive | BN5: 0 | BQ5: 4 | BR5: 1 | BS5: 8.1666667 | BT5: Positive | BU5: -0.074213842 | BV5: -0.069787384
A6: Signal taux | B6: On | D6: HealthCare | E6: 9 | F6: 2.1653005 | H6: 1.7058441 | I6: 6.0519126 | K6: 27.543317 | L6: 8 | M6: 1.9057377 | O6: 12.913112 | P6: 1.7418033 | R6: 9.2893927 | S6: 8.5040984 | U6: 32.941353 | V6: 10 | W6: 0.16393443 | Y6: 16.987361 | Z6: 0.16393443 | AB6: 15.705992 | AC6: 6.0655738 | AE6: 2.4448214 | AF6: 4 | AG6: 10 | AH6: 0.14390425 | AI6: 9 | AJ6: 0.22268254 | AK6: 3 | AM6: 0 | AN6: 4 | AO6: 9.1803279 | AQ6: 17.856892 | AR6: 0.98360656 | AT6: 4.5266928 | AU6: 6.557377 | AW6: 14.497431 | AX6: 6.8852459 | AZ6: 15.896039 | BA6: 11 | BB6: 5.2459016 | BC6: 0.16169832 | BD6: 1.147541 | BE6: 0.086891746 | BF6: 9 | BI6: HealthCare | BJ6: 0 | BK6: 3 | BL6: 5.1666667 | BM6: Neutral | BN6: 0 | BQ6: 0 | BR6: 1 | BS6: 5 | BT6: Neutral | BU6: -0.0067022413 | BV6: -0.0022757826
A7: Derniers poids benchmark | B7: 46326 | D7: Indus | E7: 6 | F7: 2.6502732 | H7: 1.7344032 | I7: 8.6680328 | K7: 26.948095 | L7: 10 | M7: 2.1653005 | O7: 16.237674 | P7: 4.3101093 | R7: 12.887893 | S7: 1.3319672 | U7: 21.062697 | V7: 7 | W7: 1.6393443 | Y7: 17.405303 | Z7: 1.3114754 | AB7: 15.327033 | AC7: 7.5409836 | AE7: 2.9930543 | AF7: 6 | AG7: 7 | AH7: 0.093829499 | AI7: 7 | AJ7: 0.11693454 | AK7: 7 | AM7: 0.096774194 | AN7: 9 | AO7: 8.1967213 | AQ7: 13.931877 | AR7: 5.4098361 | AT7: 7.9835015 | AU7: 2.4590164 | AW7: 11.738682 | AX7: 2.1311475 | AZ7: 14.563399 | BA7: 9 | BB7: 5.7377049 | BC7: 0.18457319 | BD7: 1.4754098 | BE7: 0.099040037 | BF7: 8 | BI7: Indus | BJ7: 0 | BK7: 0 | BL7: 5.5 | BM7: Neutral | BN7: 0 | BQ7: 0 | BR7: 0 | BS7: 6 | BT7: Neutral | BU7: -0.048431204 | BV7: -0.044004745
A8: Derniers rendements | B8: 46295 | D8: Oil | E8: 5 | F8: 5.6352459 | H8: 1.0167123 | I8: 6.7964481 | K8: 36.24289 | L8: 9 | M8: 3.7978142 | O8: 13.425094 | P8: 3.6338798 | R8: 9.7795478 | S8: 3.6338798 | U8: 21.631408 | V8: 9 | W8: 1.4754098 | Y8: 7.3348122 | Z8: 0.98360656 | AB8: 6.8885213 | AC8: 4.4262295 | AE8: 1.5599016 | AF8: 3 | AG8: 3 | AH8: 0.021864807 | AI8: 12 | AJ8: 0.42613895 | AK8: 12 | AM8: 0.5 | AN8: 7 | AO8: 9.0163934 | AQ8: 14.60133 | AR8: 2.7868852 | AT8: 1.1215868 | AU8: 3.442623 | AW8: 8.1029064 | AX8: 4.9180328 | AZ8: 9.8949627 | BA8: 6 | BB8: 3.9344262 | BC8: 0.26727375 | BD8: 5.4098361 | BE8: 0.14596108 | BF8: 4 | BI8: Oil | BJ8: 1 | BK8: 0 | BL8: 7.3333333 | BM8: Neutral | BN8: 0 | BQ8: 2 | BR8: 0 | BS8: 8.5 | BT8: Neutral | BU8: -0.029401703 | BV8: -0.024975244
A9: Mois allocation | B9: Oct-2026 | D9: Tech | E9: 4 | F9: 5.6489071 | H9: 0.10783016 | I9: 6.8852459 | K9: 64.397494 | L9: 1 | M9: 10 | O9: 34.782338 | P9: 10 | R9: 30.22492 | S9: 10 | U9: 41.002375 | V9: 3 | W9: 8.3783784 | Y9: 18.31349 | Z9: 8.3783784 | AB9: 15.584779 | AC9: 3.6065574 | AE9: 7.5240099 | AF9: 1 | AG9: 12 | AH9: 0.40754468 | AI9: 11 | AJ9: 0.33255594 | AK9: 11 | AM9: 0.41558442 | AN9: 1 | AO9: 9.8360656 | AQ9: 36.001467 | AR9: 10 | AT9: 29.560464 | AU9: 10 | AW9: 38.714997 | AX9: 10 | AZ9: 40.42734 | BA9: 10 | BB9: 0.81967213 | BC9: 0.31534498 | BD9: 6.2295082 | BE9: 0.10283097 | BF9: 1 | BI9: Tech | BJ9: 6 | BK9: 1 | BL9: 9.6666667 | BM9: Positive | BN9: 0 | BQ9: 5 | BR9: 0 | BS9: 9.6666667 | BT9: Positive | BU9: 0.052258645 | BV9: 0.056685103
A10: Mois signal | B10: Sept-2026 | D10: Telco | E10: 11 | F10: 1.2431694 | H10: 2.5053768 | I10: 1.489071 | K10: 16.521243 | L10: 7 | M10: 4.3306011 | O10: 21.28983 | P10: 4.2486339 | R10: 14.124129 | S10: 4.2486339 | U10: 33.946443 | V10: 12 | W10: 0.16393443 | Y10: 8.3836912 | Z10: 0.16393443 | AB10: 9.0730263 | AC10: 0.16393443 | AE10: 2.4858615 | AF10: 7 | AG10: 9 | AH10: 0.10659809 | AI10: 8 | AJ10: 0.14705402 | AK10: 3 | AM10: 0 | AN10: 5 | AO10: 10 | AQ10: 11.360303 | AR10: 4.7540984 | AT10: 4.0875964 | AU10: 3.7704918 | AW10: 6.1977528 | AX10: 7.2131148 | AZ10: 9.3484409 | BA10: 5 | BB10: 3.1147541 | BC10: 0.1867086 | BD10: 6.8852459 | BE10: 0.062384629 | BF10: 11 | BI10: Telco | BJ10: 0 | BK10: 5 | BL10: 4.5 | BM10: Negative | BN10: 0 | BQ10: 0 | BR10: 3 | BS10: 4.5 | BT10: Negative | BU10: -0.043942083 | BV10: -0.039515624
A11: Classement courant | B11: Sectors Ranking Oct-2026 | D11: Utili | E11: 12 | F11: 0.74453552 | H11: 5.5479955 | I11: 0.49863388 | K11: -4.7788353 | L11: 4 | M11: 6.1270492 | O11: 21.232479 | P11: 4.6448087 | R11: 13.297373 | S11: 6.7964481 | U11: 37.04345 | V11: 5 | W11: 6.557377 | Y11: 7.9412878 | Z11: 6.3934426 | AB11: 10.88924 | AC11: 10 | AE11: 2.4471488 | AF11: 11 | AG11: 1 | AH11: -0.088632992 | AI11: 2 | AJ11: -0.0265588 | AK11: 6 | AM11: 0.032258065 | AN11: 10 | AO11: 6.8852459 | AQ11: 9.49338 | AR11: 3.1147541 | AT11: 5.8426547 | AU11: 2.1311475 | AW11: 10.967616 | AX11: 1.6393443 | AZ11: 8.1241154 | BA11: 2 | BB11: 8.6885246 | BC11: 0.12102276 | BD11: 6.0655738 | BE11: 0.07092775 | BF11: 11 | BI11: Utili | BJ11: 1 | BK11: 5 | BL11: 4.5 | BM11: Negative | BN11: 0 | BQ11: 0 | BR11: 4 | BS11: 3.8333333 | BT11: Negative | BU11: -0.059589914 | BV11: -0.055163455
A12: Classement précédent | B12: Sectors Ranking Sept-2026 | D12: Travel & leisure | E12: 2 | F12: 7.2540984 | H12: 1.6952167 | I12: 6.5983607 | K12: 22.719799 | L12: 6 | M12: 5.1297814 | O12: 18.920226 | P12: 6.2090164 | R12: 13.612803 | S12: 3.8046448 | U12: 24.042664 | V12: 1 | W12: 9.8360656 | Y12: 12.713618 | Z12: 10 | AB12: 11.235713 | AC12: 10 | AE12: 2.7514969 | AF12: 12 | AG12: 4 | AH12: 0.050646403 | AI12: 3 | AJ12: 0.021117731 | AK12: 1 | AM12: -0.21052632 | AN12: 11 | AO12: 4.5901639 | AQ12: 14.977821 | AR12: 0.32786885 | AT12: 6.7978974 | AU12: 0.98360656 | AW12: 10.162244 | AX12: 0.98360656 | AZ12: 12.014106 | BA12: 8 | BB12: 7.704918 | BC12: 0.17450673 | BD12: 0.32786885 | BE12: 0.1167738 | BF12: 7 | BI12: Travel & leisure | BJ12: 0 | BK12: 0 | BL12: 6.1666667 | BM12: Neutral | BN12: 0 | BQ12: 0 | BR12: 0 | BS12: 6.5 | BT12: Neutral | BU12: -0.095295803 | BV12: -0.090869344
A13: Classement macro | B13: Macro rank - Currently in Expansion | D13: Media | E13: 3 | F13: 6.7759563 | H13: 1.0694065 | I13: 7.0218579 | K13: 26.131654 | L13: 3 | M13: 7.3360656 | O13: 17.178344 | P13: 6.0177596 | R13: 11.411406 | S13: 7.431694 | U13: 29.294221 | V13: 4 | W13: 9.1803279 | Y13: 13.834502 | Z13: 9.0163934 | AB13: 11.969054 | AC13: 5.9016393 | AE13: 2.5892003 | AF13: 10 | AG13: 2 | AH13: -0.03633281 | AI13: 1 | AJ13: -0.18719948 | AK13: 10 | AM13: 0.36363636 | AN13: 12 | AO13: 3.6065574 | AQ13: 16.867662 | AR13: 0.16393443 | AT13: 6.6243557 | AU13: 0.16393443 | AW13: 12.536011 | AX13: 0.16393443 | AZ13: 6.6976182 | BA13: 4 | BB13: 6.8852459 | BC13: 0.24715147 | BD13: 7.0491803 | BE13: 0.11285839 | BF13: 6 | BI13: Media | BJ13: 3 | BK13: 2 | BL13: 6.5 | BM13: Neutral | BN13: 0 | BQ13: 3 | BR13: 2 | BS13: 6 | BT13: Neutral | BU13: -0.082060778 | BV13: -0.07763432
A14: Référence | B14: Bench
A15: Top | B15: -0.021838073
A16: Short | B16: 0.046805463
A17: Long / Short | B17: 0.02496739
A18: Portefeuille | B18: 0.00036872701
A19: Benchmark | B19: -0.0044264587
D22: US Reco | E22: 45870 | F22: 45901 | G22: 45931 | H22: 45962 | I22: 45992 | J22: 46023 | K22: 46054 | L22: 46082 | M22: 46113 | N22: 46143 | O22: 46174 | P22: 46204 | Q22: 46235 | R22: 46266 | S22: 46296 | W22: US equity sectors Performance
D23: Materials | E23: 0 | F23: -1 | G23: 0 | H23: 0 | I23: -1 | J23: -1 | K23: -1 | L23: -1 | M23: -1 | N23: -1 | O23: 0 | P23: 0 | Q23: 0 | R23: 0 | S23: 1 | W23: Materials | X23: ConsStaples | Y23: Retail | Z23: Fin | AA23: HealthCare | AB23: Indus | AC23: Oil | AD23: Tech | AE23: Telco | AF23: Utili | AG23: Travel & leisure | AH23: Media
D24: ConsStaples | E24: 0 | F24: -1 | G24: 1 | H24: 0 | I24: -1 | J24: 0 | K24: 0 | L24: -1 | M24: 0 | N24: -1 | O24: -1 | P24: -1 | Q24: 0 | R24: -1 | S24: -1 | V24: 1M | W24: -0.054387894 | X24: -0.036884392 | Y24: -0.043559021 | Z24: -0.074213842 | AA24: -0.0067022413 | AB24: -0.048431204 | AC24: -0.029401703 | AD24: 0.052258645 | AE24: -0.043942083 | AF24: -0.059589914 | AG24: -0.095295803 | AH24: -0.082060778
D25: Retail | E25: -1 | F25: 0 | G25: 0 | H25: 1 | I25: 1 | J25: 1 | K25: 0 | L25: 1 | M25: 1 | N25: 0 | O25: 0 | P25: 0 | Q25: 0 | R25: 1 | S25: 0 | V25: 3M | W25: 0.022004223 | X25: -0.01115737 | Y25: -0.011006285 | Z25: -0.010102395 | AA25: 0.063765978 | AB25: -0.06190348 | AC25: 0.16545088 | AD25: 0.069973117 | AE25: 0.0062520227 | AF25: -0.11929195 | AG25: -0.085463463 | AH25: 0.037707571
D26: Fin | E26: 1 | F26: 1 | G26: 1 | H26: 1 | I26: 1 | J26: 1 | K26: 1 | L26: 1 | M26: 1 | N26: 1 | O26: 1 | P26: 1 | Q26: 1 | R26: 1 | S26: 1 | V26: YTD | W26: 0.20541071 | X26: 0.087228865 | Y26: 0.014974824 | Z26: -0.010013544 | AA26: 0.094659587 | AB26: 0.043231188 | AC26: 0.3898813 | AD26: 0.25419521 | AE26: 0.16771374 | AF26: -0.056915906 | AG26: -0.092342557 | AH26: -0.16301121
D27: HealthCare | E27: 0 | F27: 0 | G27: -1 | H27: 0 | I27: 0 | J27: 0 | K27: 0 | L27: 0 | M27: 0 | N27: 0 | O27: 0 | P27: 0 | Q27: 0 | R27: 0 | S27: 0 | V27: 1Y | W27: 0.212058 | X27: 0.080928192 | Y27: 0.028165945 | Z27: 0.013429275 | AA27: 0.21959982 | AB27: 0.062532271 | AC27: 0.40668572 | AD27: 0.29408388 | AE27: 0.11531655 | AF27: -0.072420695 | AG27: -0.075556207 | AH27: -0.25897627
D28: Indus | E28: 0 | F28: 0 | G28: 0 | H28: -1 | I28: -1 | J28: -1 | K28: 0 | L28: 0 | M28: 0 | N28: -1 | O28: 0 | P28: -1 | Q28: 0 | R28: 0 | S28: 0 | V28: 3Y | W28: 0.49821157 | X28: 0.26368888 | Y28: 0.68488423 | Z28: 0.77351628 | AA28: 0.35713667 | AB28: 0.59130885 | AC28: 0.49387035 | AD28: 1.5938367 | AE28: 0.63564349 | AF28: 0.48205709 | AG28: 0.26472854 | AH28: 0.58533631
D29: Oil | E29: -1 | F29: -1 | G29: -1 | H29: -1 | I29: 0 | J29: -1 | K29: -1 | L29: 0 | M29: 0 | N29: 1 | O29: 0 | P29: 0 | Q29: -1 | R29: 0 | S29: 0 | V29: 5Y | W29: 0.60175942 | X29: 0.39610968 | Y29: 0.48958854 | Z29: 0.67544292 | AA29: 0.40138166 | AB29: 0.52281563 | AC29: 1.7207164 | AD29: 1.7811654 | AE29: 0.37843947 | AF29: 0.48404174 | AG29: 0.24155931 | AH29: -0.07980338
D30: Tech | E30: 1 | F30: 1 | G30: 1 | H30: 1 | I30: 1 | J30: 1 | K30: 1 | L30: 1 | M30: 1 | N30: 1 | O30: 1 | P30: 1 | Q30: 1 | R30: 1 | S30: 1
D31: Telco | E31: 1 | F31: 0 | G31: 0 | H31: -1 | I31: 0 | J31: 0 | K31: 0 | L31: 0 | M31: -1 | N31: 0 | O31: -1 | P31: -1 | Q31: -1 | R31: -1 | S31: -1
D32: Utili | E32: -1 | F32: 0 | G32: -1 | H32: 0 | I32: 0 | J32: 0 | K32: -1 | L32: -1 | M32: -1 | N32: 0 | O32: -1 | P32: 0 | Q32: -1 | R32: -1 | S32: -1
D33: Travel & leisure | E33: 0 | F33: 0 | G33: 0 | H33: 0 | I33: 0 | J33: 0 | K33: 0 | L33: 0 | M33: 0 | N33: 0 | O33: 0 | P33: 0 | Q33: 0 | R33: 0 | S33: 0
D34: Media | E34: 0 | F34: 1 | G34: 0 | H34: 0 | I34: 0 | J34: 0 | K34: 1 | L34: 0 | M34: 0 | N34: 0 | O34: 1 | P34: 1 | Q34: 1 | R34: 0 | S34: 0
D37: Variable | E37: Secteur | F37: 46295 | G37: 46265 | H37: 46234 | I37: 46203 | J37: 46173 | K37: 46142 | L37: 46112 | M37: 46081 | N37: 46053 | O37: 46022 | P37: 45991 | Q37: 45961 | R37: 45930 | S37: 45900 | T37: 45869 | U37: 45838 | V37: 45808 | W37: 45777 | X37: 45747 | Y37: 45716 | Z37: 45688 | AA37: 45657 | AB37: 45626 | AC37: 45596 | AD37: 45565 | AE37: 45535 | AF37: 45504 | AG37: 45473 | AH37: 45443 | AI37: 45412 | AJ37: 45382 | AK37: 45351 | AL37: 45322 | AM37: 45291 | AN37: 45260 | AO37: 45230 | AP37: 45199 | AQ37: 45169 | AR37: 45138 | AS37: 45107 | AT37: 45077 | AU37: 45046 | AV37: 45016 | AW37: 44985 | AX37: 44957 | AY37: 44926 | AZ37: 44895 | BA37: 44865 | BB37: 44834 | BC37: 44804 | BD37: 44773 | BE37: 44742 | BF37: 44712 | BG37: 44681 | BH37: 44651 | BI37: 44620 | BJ37: 44592 | BK37: 44561 | BL37: 44530 | BM37: 44500
D38: net_debt_ebitda | E38: Materials | F38: -0.1886202 | G38: -0.16656903 | H38: -0.14407259 | I38: -0.14333246 | J38: -0.14259649 | K38: -0.00050595779 | L38: 0.00079569051 | M38: -0.060725718 | N38: -0.095820443 | O38: -0.098133568 | P38: -0.095564738 | Q38: -0.035695971 | R38: -0.037418557 | S38: -0.11991504 | T38: -0.062352844 | U38: -0.066342639 | V38: -0.068328729 | W38: -0.24212693 | X38: -0.24439578 | Y38: -0.094247781 | Z38: -0.18267729 | AA38: -0.17201713 | AB38: -0.16674135 | AC38: -0.18160108 | AD38: -0.18892075 | AE38: -0.18684523 | AF38: -0.31122882 | AG38: -0.31499266 | AH38: -0.26697357 | AI38: -0.40446639 | AJ38: -0.40379739 | AK38: -0.40203954 | AL38: -0.50842786 | AM38: -0.51171699 | AN38: -0.509103 | AO38: -0.61073149 | AP38: -0.61039909 | AQ38: -0.68164145 | AR38: -0.83226261 | AS38: -0.84372812 | AT38: -0.83232673 | AU38: -0.96223965 | AV38: -0.96740042 | AW38: -0.97574544 | AX38: -1.1215382 | AY38: -1.129425 | AZ38: -1.1087628 | BA38: -1.1307898 | BB38: -1.1399409 | BC38: -1.1417231 | BD38: -1.1827264 | BE38: -1.1894902 | BF38: -1.1806219 | BG38: -1.0394366 | BH38: -1.0311144 | BI38: -1.009943 | BJ38: -1.0623405 | BK38: -1.0637501 | BL38: -1.0679769 | BM38: -1.193618
D39: net_debt_ebitda | E39: ConsStaples | F39: 0.50901394 | G39: 0.51303007 | H39: 0.50735014 | I39: 0.50572946 | J39: 0.51723143 | K39: 0.55873421 | L39: 0.54520613 | M39: 0.54788312 | N39: 0.69867216 | O39: 0.69628177 | P39: 0.71171689 | Q39: 0.74395303 | R39: 0.75446563 | S39: 0.64255636 | T39: 0.59656264 | U39: 0.58256649 | V39: 0.58838906 | W39: 0.49283813 | X39: 0.4821607 | Y39: 0.43707707 | Z39: 0.40294667 | AA39: 0.40154384 | AB39: 0.41666393 | AC39: 0.33165915 | AD39: 0.34379788 | AE39: 0.2989976 | AF39: 0.17948379 | AG39: 0.18228982 | AH39: 0.18208774 | AI39: 0.14481078 | AJ39: 0.13636133 | AK39: 0.12460735 | AL39: 0.17520076 | AM39: 0.16332954 | AN39: 0.16699828 | AO39: 0.16493624 | AP39: 0.20212414 | AQ39: 0.1273318 | AR39: 0.10568081 | AS39: 0.11490896 | AT39: 0.12023058 | AU39: 0.057115409 | AV39: 0.030369472 | AW39: 0.017374734 | AX39: -0.15059656 | AY39: -0.16332269 | AZ39: -0.14273463 | BA39: -0.1081705 | BB39: -0.11698021 | BC39: -0.13878219 | BD39: -0.17551542 | BE39: -0.17529628 | BF39: -0.16964135 | BG39: -0.15952683 | BH39: -0.1593386 | BI39: -0.1253832 | BJ39: -0.21675476 | BK39: -0.21703911 | BL39: -0.21581798 | BM39: -0.46343896
D40: net_debt_ebitda | E40: Retail | F40: -0.9153268 | G40: -0.88536835 | H40: -1.0024293 | I40: -1.0000459 | J40: -1.0040955 | K40: -1.0521065 | L40: -1.0515473 | M40: -1.0242029 | N40: -0.99330927 | O40: -0.98077691 | P40: -1.0445303 | Q40: -1.0674877 | R40: -1.0764109 | S40: -1.0913422 | T40: -1.0586786 | U40: -1.0584657 | V40: -1.0661104 | W40: -1.0717101 | X40: -1.0704964 | Y40: -1.0736624 | Z40: -1.0696266 | AA40: -1.0684357 | AB40: -1.0570889 | AC40: -1.046785 | AD40: -1.0603211 | AE40: -1.142092 | AF40: -1.1872412 | AG40: -1.1901721 | AH40: -1.1614228 | AI40: -1.1465167 | AJ40: -1.1867795 | AK40: -1.1450159 | AL40: -0.97232676 | AM40: -0.95928455 | AN40: -0.97277409 | AO40: -0.99225142 | AP40: -1.0114538 | AQ40: -1.0525555 | AR40: -1.046318 | AS40: -1.0629231 | AT40: -1.1097311 | AU40: -1.0768057 | AV40: -1.0782339 | AW40: -1.0255266 | AX40: -0.97877639 | AY40: -0.96704175 | AZ40: -1.0218702 | BA40: -1.0704458 | BB40: -1.1012367 | BC40: -1.130804 | BD40: -1.282958 | BE40: -1.2938003 | BF40: -1.4288119 | BG40: -1.5256111 | BH40: -1.5326979 | BI40: -1.5618381 | BJ40: -1.6227903 | BK40: -1.6160009 | BL40: -1.6634396 | BM40: -2.0477631
D41: net_debt_ebitda | E41: Fin | F41: -3.4979304 | G41: -3.6012179 | H41: -3.854494 | I41: -3.8559633 | J41: -3.83894 | K41: -3.7953749 | L41: -3.7997552 | M41: -3.7671223 | N41: -3.6272973 | O41: -3.6385274 | P41: -3.6233693 | Q41: -3.6366741 | R41: -3.6470905 | S41: -2.521433 | T41: -2.4869207 | U41: -2.4284502 | V41: -2.5021162 | W41: -2.3425056 | X41: -2.335032 | Y41: -2.3326482 | Z41: -2.4130504 | AA41: -2.3867641 | AB41: -2.5011118 | AC41: -2.2397563 | AD41: -2.2100308 | AE41: -2.1766398 | AF41: -1.2875748 | AG41: -1.289795 | AH41: -1.2703375 | AI41: -0.86636719 | AJ41: -0.86353895 | AK41: -0.87548747 | AL41: -0.73366844 | AM41: -0.73588137 | AN41: -0.7386563 | AO41: -0.62080882 | AP41: -0.61905526 | AQ41: 0.063151996 | AR41: 0.45268269 | AS41: 0.45694098 | AT41: 0.42009745 | AU41: 0.28362486 | AV41: 0.2809545 | AW41: 0.28207701 | AX41: 0.53474391 | AY41: 0.58164205 | AZ41: 0.44426515 | BA41: 0.57370196 | BB41: 0.56773761 | BC41: 0.58497625 | BD41: 0.7819976 | BE41: 0.83972166 | BF41: 0.77517265 | BG41: -0.2214089 | BH41: -0.20854306 | BI41: -0.11658157 | BJ41: -0.39182812 | BK41: -0.39170033 | BL41: -0.41551637 | BM41: -0.54955353
D42: net_debt_ebitda | E42: HealthCare | F42: 0.29460385 | G42: 0.28815496 | H42: 0.20519457 | I42: 0.20051305 | J42: 0.2005427 | K42: 0.095534184 | L42: 0.088137543 | M42: 0.08919031 | N42: 0.057560532 | O42: 0.054270754 | P42: 0.059274515 | Q42: 0.17771945 | R42: 0.17508546 | S42: 0.097437773 | T42: 0.077823697 | U42: 0.070571452 | V42: 0.081341938 | W42: 0.062566916 | X42: 0.057989536 | Y42: 0.034820714 | Z42: 0.1639829 | AA42: 0.15584557 | AB42: 0.17762351 | AC42: 0.23203157 | AD42: 0.22235357 | AE42: 0.18985745 | AF42: 0.1486736 | AG42: 0.14356589 | AH42: 0.15963199 | AI42: -0.032448091 | AJ42: -0.019887465 | AK42: -0.011074874 | AL42: -0.36807668 | AM42: -0.37343733 | AN42: -0.36030809 | AO42: -0.41284233 | AP42: -0.43383197 | AQ42: -0.47132293 | AR42: -0.6591661 | AS42: -0.671534 | AT42: -0.66140751 | AU42: -0.7329649 | AV42: -0.73947623 | AW42: -0.75562623 | AX42: -0.88511346 | AY42: -0.88485992 | AZ42: -0.86872951 | BA42: -0.83675384 | BB42: -0.84678009 | BC42: -0.86467454 | BD42: -0.80058889 | BE42: -0.8112418 | BF42: -0.79274891 | BG42: -0.72935271 | BH42: -0.72061611 | BI42: -0.71420194 | BJ42: -0.89572636 | BK42: -0.89871676 | BL42: -0.89583354 | BM42: -1.0702527
D43: net_debt_ebitda | E43: Indus | F43: 0.32316294 | G43: 0.33990022 | H43: 0.39323236 | I43: 0.38292046 | J43: 0.36734842 | K43: 0.28924947 | L43: 0.29963172 | M43: 0.35526308 | N43: 0.42897319 | O43: 0.42807276 | P43: 0.42544221 | Q43: 0.43031137 | R43: 0.44770761 | S43: 0.32536985 | T43: 0.28306304 | U43: 0.27286085 | V43: 0.28285635 | W43: 0.179721 | X43: 0.18464426 | Y43: 0.15113506 | Z43: 0.1511582 | AA43: 0.14176181 | AB43: 0.14301503 | AC43: 0.11494305 | AD43: 0.12481852 | AE43: 0.083474507 | AF43: -0.035448188 | AG43: -0.033687022 | AH43: -0.023274184 | AI43: -0.064122513 | AJ43: -0.072750828 | AK43: -0.070841753 | AL43: -0.064856192 | AM43: -0.079700467 | AN43: -0.1018135 | AO43: -0.16371283 | AP43: -0.16650101 | AQ43: -0.22104383 | AR43: -0.20602547 | AS43: -0.20755703 | AT43: -0.20848813 | AU43: -0.17848689 | AV43: -0.18075521 | AW43: -0.18954589 | AX43: -0.14474118 | AY43: -0.1671636 | AZ43: -0.13269222 | BA43: -0.16255759 | BB43: -0.16902794 | BC43: -0.19462957 | BD43: -0.28995851 | BE43: -0.28912332 | BF43: -0.28680106 | BG43: -0.29978862 | BH43: -0.2899714 | BI43: -0.283123 | BJ43: -0.37832615 | BK43: -0.38241539 | BL43: -0.37693085 | BM43: -0.65600567
D44: net_debt_ebitda | E44: Oil | F44: -0.39452795 | G44: -0.40439958 | H44: -0.11459055 | I44: -0.11887452 | J44: -0.12169714 | K44: -0.044724178 | L44: -0.047521704 | M44: -0.05460077 | N44: -0.032960452 | O44: -0.035989975 | P44: -0.038154621 | Q44: -0.11978825 | R44: -0.12434161 | S44: -0.23559575 | T44: -0.28580747 | U44: -0.29731913 | V44: -0.29301167 | W44: -0.35247035 | X44: -0.35352195 | Y44: -0.45300774 | Z44: -0.58600131 | AA44: -0.58464979 | AB44: -0.57217068 | AC44: -0.73498762 | AD44: -0.74512258 | AE44: -0.78639858 | AF44: -0.92791759 | AG44: -0.9312497 | AH44: -0.91485313 | AI44: -1.0144151 | AJ44: -1.0147372 | AK44: -1.0150973 | AL44: -1.0584529 | AM44: -1.0625992 | AN44: -1.070738 | AO44: -1.1932435 | AP44: -1.208659 | AQ44: -1.2750111 | AR44: -1.4549895 | AS44: -1.4699415 | AT44: -1.4723614 | AU44: -1.4383888 | AV44: -1.4458393 | AW44: -1.4765944 | AX44: -1.4315054 | AY44: -1.4390982 | AZ44: -1.4180016 | BA44: -1.3101305 | BB44: -1.3216611 | BC44: -1.3408481 | BD44: -1.0753002 | BE44: -1.0895868 | BF44: -1.0753618 | BG44: -0.7215256 | BH44: -0.7161404 | BI44: -0.69454673 | BJ44: -0.36194168 | BK44: -0.36134134 | BL44: -0.35149676 | BM44: -0.0039491088
D45: net_debt_ebitda | E45: Tech | F45: -1.3034101 | G45: -1.2945886 | H45: -1.2689331 | I45: -1.2569083 | J45: -1.2495807 | K45: -1.2516789 | L45: -1.2504551 | M45: -1.2701416 | N45: -1.2596035 | O45: -1.2639503 | P45: -1.2473385 | Q45: -1.2601937 | R45: -1.2613772 | S45: -1.3953755 | T45: -1.4138781 | U45: -1.4257271 | V45: -1.4088992 | W45: -1.4069962 | X45: -1.4114471 | Y45: -1.4381295 | Z45: -1.5155804 | AA45: -1.5256319 | AB45: -1.4942314 | AC45: -1.5239926 | AD45: -1.5307686 | AE45: -1.57444 | AF45: -1.6677339 | AG45: -1.6714767 | AH45: -1.6412107 | AI45: -1.6574706 | AJ45: -1.6554526 | AK45: -1.6837905 | AL45: -1.7448551 | AM45: -1.7515404 | AN45: -1.7269811 | AO45: -1.7697884 | AP45: -1.7827273 | AQ45: -1.8443182 | AR45: -1.8470577 | AS45: -1.8598801 | AT45: -1.8303833 | AU45: -1.7883418 | AV45: -1.7981521 | AW45: -1.795995 | AX45: -1.8005575 | AY45: -1.8162307 | AZ45: -1.8013622 | BA45: -1.880079 | BB45: -1.91782 | BC45: -1.9375383 | BD45: -2.0382662 | BE45: -2.0444631 | BF45: -2.0256263 | BG45: -2.0062191 | BH45: -1.999504 | BI45: -1.9999385 | BJ45: -2.1956928 | BK45: -2.2094882 | BL45: -2.1975582 | BM45: -2.5115309
D46: net_debt_ebitda | E46: Telco | F46: 1.0941366 | G46: 1.1337662 | H46: 1.155621 | I46: 1.1509981 | J46: 1.1624455 | K46: 1.0598675 | L46: 1.0566414 | M46: 1.0511736 | N46: 1.0448883 | O46: 1.0417993 | P46: 1.0470348 | Q46: 1.0284938 | R46: 1.0251585 | S46: 0.91741024 | T46: 0.92446369 | U46: 0.90835171 | V46: 0.92395606 | W46: 0.96115465 | X46: 0.9586251 | Y46: 0.92662427 | Z46: 0.95256464 | AA46: 0.94539555 | AB46: 0.93541321 | AC46: 0.94653984 | AD46: 0.93788808 | AE46: 0.92011835 | AF46: 0.8577165 | AG46: 0.85119132 | AH46: 0.71729806 | AI46: 0.72464086 | AJ46: 0.72340316 | AK46: 0.71186526 | AL46: 0.73497689 | AM46: 0.72746682 | AN46: 0.73897615 | AO46: 0.72096466 | AP46: 0.70119038 | AQ46: 0.66426501 | AR46: 0.66399433 | AS46: 0.64866889 | AT46: 0.67922599 | AU46: 0.69338131 | AV46: 0.67952152 | AW46: 0.68271857 | AX46: 0.62189195 | AY46: 0.6110406 | AZ46: 0.64097812 | BA46: 0.60197442 | BB46: 0.5898203 | BC46: 0.58810158 | BD46: 0.710618 | BE46: 0.70040212 | BF46: 0.71729874 | BG46: 0.64970886 | BH46: 0.6570302 | BI46: 0.68158254 | BJ46: 0.49926469 | BK46: 0.49719205 | BL46: 0.51361918 | BM46: 0.29596253
D47: net_debt_ebitda | E47: Utili | F47: 4.1367553 | G47: 4.1308377 | H47: 4.1575587 | I47: 4.154639 | J47: 4.1536378 | K47: 3.9385899 | L47: 3.9377689 | M47: 3.9321359 | N47: 3.709042 | O47: 3.6793906 | P47: 3.6796547 | Q47: 3.7477607 | R47: 3.7457564 | S47: 3.6297001 | T47: 3.5820313 | U47: 3.5764714 | V47: 3.5712857 | W47: 3.6713074 | X47: 3.6700276 | Y47: 3.6892964 | Z47: 3.8124095 | AA47: 3.8058394 | AB47: 3.8151474 | AC47: 3.814682 | AD47: 3.8073253 | AE47: 3.7521128 | AF47: 3.7226742 | AG47: 3.7200017 | AH47: 3.7163778 | AI47: 3.6259241 | AJ47: 3.6286152 | AK47: 3.6234583 | AL47: 3.7917843 | AM47: 3.7908889 | AN47: 3.7954187 | AO47: 3.8671184 | AP47: 3.8526209 | AQ47: 3.7752465 | AR47: 3.6158965 | AS47: 3.6045505 | AT47: 3.5965206 | AU47: 3.3249107 | AV47: 3.3184157 | AW47: 3.307477 | AX47: 3.1800679 | AY47: 3.1706917 | AZ47: 3.1828355 | BA47: 2.9181234 | BB47: 2.908138 | BC47: 2.8822601 | BD47: 2.7048943 | BE47: 2.6943253 | BF47: 2.7141483 | BG47: 3.0551803 | BH47: 3.0628618 | BI47: 3.0585978 | BJ47: 2.9092266 | BK47: 2.9084026 | BL47: 2.907606 | BM47: 2.7247566
D48: net_debt_ebitda | E48: Travel & leisure | F48: 0.28397651 | G48: 0.3152545 | H48: 0.32679434 | I48: 0.34823069 | J48: 0.34045395 | K48: 0.50970359 | L48: 0.53576618 | M48: 0.51444092 | N48: 0.43665359 | O48: 0.44469096 | P48: 0.44987309 | Q48: 0.39099244 | R48: 0.40012596 | S48: 0.28501794 | T48: 0.23777276 | U48: 0.26627595 | V48: 0.25334512 | W48: 0.31332701 | X48: 0.32798758 | Y48: 0.380969 | Z48: 0.40853451 | AA48: 0.41992876 | AB48: 0.41622748 | AC48: 0.32582759 | AD48: 0.34636443 | AE48: 0.60448618 | AF48: 0.51267462 | AG48: 0.53842418 | AH48: 0.53468322 | AI48: 0.61736672 | AJ48: 0.64284644 | AK48: 0.66634535 | AL48: 0.6269485 | AM48: 0.66300136 | AN48: 0.65423375 | AO48: 0.710486 | AP48: 0.78073651 | AQ48: 0.70278706 | AR48: 0.91752896 | AS48: 1.0161072 | AT48: 0.9740478 | AU48: 1.5192305 | AV48: 1.6065005 | AW48: 1.5983235 | AX48: 1.8330219 | AY48: 1.8667179 | AZ48: 1.8579784 | BA48: 2.0417548 | BB48: 2.1975085 | BC48: 2.3262789 | BD48: 3.082157 | BE48: 3.1042467 | BF48: 3.112782 | BG48: 3.6117767 | BH48: 3.5422533 | BI48: 3.3409995 | BJ48: 3.9577095 | BK48: 3.9747939 | BL48: 4.0093201 | BM48: 5.9232138
... D100: price_fcf | E100: Retail | F100: 0.74483673 | G100: 0.99976473 | H100: 1.8845952 | I100: 1.2332229 | J100: 2.2823273 | K100: 3.3023616 | L100: 1.659336 | M100: 1.5511066 | N100: 1.7490505 | O100: 1.3566783 | P100: 1.6143644 | Q100: 1.8950698 | R100: 1.5318349 | S100: 1.9345272 | T100: 2.1759341 | U100: 1.4014275 | V100: 1.841402 | W100: 1.0848263 | X100: 1.1715395 | Y100: 1.9942621 | Z100: 3.3269445 | AA100: 2.732949 | AB100: 2.161425 | AC100: 1.6836554 | AD100: 1.7928046 | AE100: 1.594128 | AF100: 1.8751653 | AG100: 2.233471 | AH100: 1.6023914 | AI100: 2.0823736 | AJ100: 2.2110893 | AK100: 2.4537974 | AL100: 1.820149 | AM100: 1.8591228 | AN100: 1.6454425 | AO100: 1.8434376 | AP100: 1.5915998 | AQ100: 2.0212785 | AR100: 2.3142538 | AS100: 2.2532006 | AT100: 2.0331892 | AU100: 1.4114265 | AV100: 1.0622699 | AW100: 0.97627107 | AX100: 1.4950501 | AY100: 0.93532946 | AZ100: 1.7256953 | BA100: 2.3244781 | BB100: 2.8939384 | BC100: 3.2189853 | BD100: 3.9038841 | BE100: 2.0265731 | BF100: 2.2949356 | BG100: 3.1006699 | BH100: 2.8033475 | BI100: 2.2831731 | BJ100: 3.4505985 | BK100: 3.7998767 | BL100: 3.04134 | BM100: 3.1315289
D101: price_fcf | E101: Fin
D102: price_fcf | E102: HealthCare | F102: 3.944237 | G102: 3.5250827 | H102: 3.1026524 | I102: 3.2696881 | J102: 1.9933714 | K102: 1.0837485 | L102: 1.8739082 | M102: 2.254636 | N102: 2.3809181 | O102: 2.7526252 | P102: 2.5175733 | Q102: 1.0742633 | R102: 0.32237746 | S102: 0.25385339 | T102: -0.30084991 | U102: -0.50754173 | V102: -0.34227797 | W102: 1.028332 | X102: 1.6624001 | Y102: 1.5357399 | Z102: 1.3696537 | AA102: 0.78100922 | AB102: 1.0868317 | AC102: 1.9993645 | AD102: 2.8637842 | AE102: 3.8734996 | AF102: 3.3997341 | AG102: 3.1428759 | AH102: 2.9478363 | AI102: 2.7482371 | AJ102: 3.1604431 | AK102: 3.3305454 | AL102: 3.3621186 | AM102: 2.8515291 | AN102: 2.7498397 | AO102: 2.9368044 | AP102: 2.7104858 | AQ102: 2.6172921 | AR102: 2.1676849 | AS102: 2.4548031 | AT102: 2.6210559 | AU102: 3.0888635 | AV102: 2.7629679 | AW102: 2.8138444 | AX102: 2.7943863 | AY102: 3.5837874 | AZ102: 2.8918034 | BA102: 2.7527601 | BB102: 2.5653949 | BC102: 1.6054496 | BD102: 2.2411466 | BE102: 2.7919404 | BF102: 1.9466387 | BG102: 1.8406223 | BH102: 0.51368264 | BI102: -0.25771804 | BJ102: -0.36717357 | BK102: -0.32396766 | BL102: -0.65484092 | BM102: -0.3372346
D103: price_fcf | E103: Indus | F103: 4.3621791 | G103: 4.5521177 | H103: 5.2594831 | I103: 5.6110291 | J103: 4.5557607 | K103: 4.7929881 | L103: 4.3103265 | M103: 5.0372516 | N103: 4.4739608 | O103: 4.2977911 | P103: 3.7993462 | Q103: 3.9721619 | R103: 3.6363088 | S103: 3.972612 | T103: 4.1838417 | U103: 3.9976542 | V103: 4.2813005 | W103: 3.7573989 | X103: 3.6815245 | Y103: 3.9441553 | Z103: 4.4308668 | AA103: 4.0284904 | AB103: 4.9021351 | AC103: 4.349969 | AD103: 4.1229704 | AE103: 4.1687288 | AF103: 4.1555259 | AG103: 3.0733476 | AH103: 3.6796235 | AI103: 3.7556804 | AJ103: 4.0587998 | AK103: 3.6350262 | AL103: 3.1791579 | AM103: 3.4004308 | AN103: 2.9183097 | AO103: 2.4607965 | AP103: 2.9221591 | AQ103: 3.1301781 | AR103: 3.0975819 | AS103: 2.9394127 | AT103: 2.243005 | AU103: 2.3388318 | AV103: 2.6165469 | AW103: 2.9974061 | AX103: 2.8995407 | AY103: 2.8883654 | AZ103: 2.9165802 | BA103: 2.6561823 | BB103: 1.9385776 | BC103: 2.4008665 | BD103: 2.9419088 | BE103: 2.4017037 | BF103: 2.685889 | BG103: 2.8891821 | BH103: 2.3927921 | BI103: 1.6584416 | BJ103: 2.0640374 | BK103: 1.8966518 | BL103: 1.635011 | BM103: 1.5212637
D104: price_fcf | E104: Oil | F104: -5.708312 | G104: -5.7694832 | H104: -5.9134836 | I104: -6.7616008 | J104: -6.6982659 | K104: -6.0695676 | L104: -4.1669834 | M104: -5.4551087 | N104: -5.7481792 | O104: -6.7350439 | P104: -7.1245256 | Q104: -7.1990538 | R104: -7.4721953 | S104: -7.3482752 | T104: -7.391073 | U104: -7.8634755 | V104: -7.6426109 | W104: -7.172928 | X104: -6.430822 | Y104: -7.4048206 | Z104: -7.5473708 | AA104: -7.0597225 | AB104: -7.175277 | AC104: -6.8854421 | AD104: -7.1499729 | AE104: -6.8544155 | AF104: -6.3709317 | AG104: -6.507524 | AH104: -6.2696973 | AI104: -5.9618092 | AJ104: -6.4716391 | AK104: -6.6431148 | AL104: -6.218254 | AM104: -6.2809651 | AN104: -5.993044 | AO104: -5.151567 | AP104: -4.827823 | AQ104: -5.5930685 | AR104: -6.0380684 | AS104: -6.5313097 | AT104: -6.2914022 | AU104: -6.0499483 | AV104: -6.1656375 | AW104: -5.9535199 | AX104: -5.946289 | AY104: -5.5383928 | AZ104: -6.1870207 | BA104: -5.5233393 | BB104: -5.4892891 | BC104: -6.1130796 | BD104: -6.3972412 | BE104: -5.7764901 | BF104: -5.7612234 | BG104: -6.5246396 | BH104: -7.6249512 | BI104: -7.5574545 | BJ104: -8.137516 | BK104: -10.020096 | BL104: -9.4450502 | BM104: -9.9596944
D105: price_fcf | E105: Tech | F105: 5.2703659 | G105: 4.3265545 | H105: 4.2877996 | I105: 5.4603088 | J105: 7.1015985 | K105: 5.3999929 | L105: 3.3792512 | M105: 4.5125153 | N105: 6.7587783 | O105: 7.3245271 | P105: 8.1752726 | Q105: 9.3937732 | R105: 8.5644282 | S105: 7.4291609 | T105: 8.2186591 | U105: 7.4400424 | V105: 6.2448505 | W105: 4.886836 | X105: 4.5711337 | Y105: 6.0089266 | Z105: 7.2278483 | AA105: 7.8420009 | AB105: 6.9579993 | AC105: 7.2171585 | AD105: 7.7034697 | AE105: 7.7891481 | AF105: 8.4639676 | AG105: 9.4237573 | AH105: 7.9938454 | AI105: 7.0509826 | AJ105: 7.7428237 | AK105: 7.9348012 | AL105: 7.4539352 | AM105: 7.4092492 | AN105: 7.2840236 | AO105: 6.1484186 | AP105: 6.4545044 | AQ105: 7.146866 | AR105: 7.6712669 | AS105: 7.5738827 | AT105: 7.3325948 | AU105: 5.4593807 | AV105: 5.333815 | AW105: 3.8113862 | AX105: 3.5057127 | AY105: 2.4464595 | AZ105: 3.0615278 | BA105: 2.7663947 | BB105: 2.8867598 | BC105: 3.6089539 | BD105: 4.3609429 | BE105: 3.0567956 | BF105: 3.2580016 | BG105: 3.7238213 | BH105: 4.6281735 | BI105: 4.3469477 | BJ105: 5.3226577 | BK105: 6.4698474 | BL105: 6.9037382 | BM105: 5.4421786
D106: price_fcf | E106: Telco | F106: -4.659433 | G106: -5.233486 | H106: -5.3415904 | I106: -5.2687104 | J106: -5.5570427 | K106: -6.1284717 | L106: -6.2673649 | M106: -7.2668608 | N106: -7.2198309 | O106: -7.2907305 | P106: -7.6464375 | Q106: -7.6602287 | R106: -7.7441268 | S106: -7.6053431 | T106: -7.829905 | U106: -7.7909982 | V106: -7.6469737 | W106: -7.1094806 | X106: -6.7859995 | Y106: -7.3895305 | Z106: -7.6533969 | AA106: -6.9684318 | AB106: -7.3108286 | AC106: -6.9282867 | AD106: -7.1469533 | AE106: -7.253277 | AF106: -7.0998522 | AG106: -7.1737078 | AH106: -7.2520789 | AI106: -7.2370516 | AJ106: -7.5428218 | AK106: -7.3625718 | AL106: -6.6744294 | AM106: -6.7845803 | AN106: -6.5346569 | AO106: -5.9491405 | AP106: -6.104562 | AQ106: -6.6338792 | AR106: -7.4493008 | AS106: -7.2548614 | AT106: -6.7540433 | AU106: -6.78722 | AV106: -6.5677612 | AW106: -6.4728476 | AX106: -6.7297819 | AY106: -6.4265735 | AZ106: -6.9027851 | BA106: -6.6833312 | BB106: -5.9642453 | BC106: -6.4352264 | BD106: -6.3413798 | BE106: -5.2972751 | BF106: -6.1309304 | BG106: -6.5037451 | BH106: -7.3320436 | BI106: -7.3714257 | BJ106: -7.6307346 | BK106: -8.3406523 | BL106: -8.2227061 | BM106: -8.9245909
D107: price_fcf | E107: Utili | F107: -5.1018364 | G107: -5.1471432 | H107: -4.6839365 | I107: -4.4568722 | J107: -4.9084346 | K107: -4.5903246 | L107: -4.2355786 | M107: -4.6031675 | N107: -5.0394356 | O107: -5.0181146 | P107: -4.8341254 | Q107: -5.0276258 | R107: -5.2977214 | S107: -5.5692184 | T107: -5.2937189 | U107: -5.9742 | V107: -5.4143039 | W107: -5.047754 | X107: -5.0112318 | Y107: -5.7640524 | Z107: -5.7927292 | AA107: -5.5015907 | AB107: -5.5634392 | AC107: -5.0621371 | AD107: -4.8992193 | AE107: -4.9781078 | AF107: -4.9961572 | AG107: -5.4178248 | AH107: -4.7567346 | AI107: -5.0388445 | AJ107: -5.8991717 | AK107: -5.991878 | AL107: -5.5583928 | AM107: -5.1328012 | AN107: -4.8593635 | AO107: -4.3181443 | AP107: -4.6398447 | AQ107: -4.9306163 | AR107: -4.9093562 | AS107: -4.8815468 | AT107: -4.2432584 | AU107: -4.0198122 | AV107: -4.144065 | AW107: -4.3377131 | AX107: -4.2356639 | AY107: -3.2688719 | AZ107: -3.8637349 | BA107: -3.6752439 | BB107: -2.5642619 | BC107: -2.5953898 | BD107: -2.8083507 | BE107: -2.2521757 | BF107: -3.0204405 | BG107: -3.2997587 | BH107: -4.7815336 | BI107: -5.6247417 | BJ107: -5.6200613 | BK107: -6.3382122 | BL107: -6.3588352 | BM107: -7.2028541
D108: price_fcf | E108: Travel & leisure | F108: -0.32950609 | G108: 0.46691086 | H108: 0.77295528 | I108: 0.65598049 | J108: 0.068481387 | K108: 0.33499455 | L108: 0.16741952 | M108: 0.21932951 | N108: 0.6096775 | O108: 1.0632402 | P108: 0.42274713 | Q108: -0.038120195 | R108: 0.4083866 | S108: 1.2143606 | T108: 1.0019162 | U108: 1.1736838 | V108: 1.1154955 | W108: 1.0489745 | X108: 0.51663332 | Y108: 1.1244212 | Z108: 0.95341741 | AA108: 1.4527064 | AB108: 1.5092525 | AC108: 1.191016 | AD108: 0.70381131 | AE108: -0.15930494 | AF108: -0.48480269 | AG108: -0.025492871 | AH108: -0.019638329 | AI108: 0.54316896 | AJ108: 0.3645697 | AK108: 0.5494693 | AL108: 0.88075467 | AM108: 1.2230945 | AN108: 0.94965207 | AO108: 0.56333018 | AP108: 0.77408711 | AQ108: 0.84582549 | AR108: 1.2488659 | AS108: 1.3050361 | AT108: 1.2117294 | AU108: 2.076305 | AV108: 1.9640825 | AW108: 1.9231032 | AX108: 2.3629306 | AY108: 1.7222618 | AZ108: 2.3622833 | BA108: 2.4252754 | BB108: 2.236867 | BC108: 2.479087 | BD108: 2.8966769 | BE108: 2.7942157 | BF108: 4.1270976 | BG108: 4.6896218 | BH108: 4.5816829 | BI108: 6.9552444 | BJ108: 6.1384111 | BK108: 6.0243853 | BL108: 5.7013857 | BM108: 7.0613948
D109: price_fcf | E109: Media | F109: 0.79137816 | G109: 1.3411221 | H109: 0.22241576 | I109: 0.017211156 | J109: 1.192313 | K109: 2.1276136 | L109: 2.8562724 | M109: 2.5332404 | N109: 2.1078681 | O109: 3.8534422 | P109: 4.9949718 | Q109: 6.5023126 | R109: 7.4418927 | S109: 7.2585723 | T109: 7.3840756 | U109: 9.8380032 | V109: 8.1345453 | W109: 7.3408168 | X109: 5.6458859 | Y109: 6.5560841 | Z109: 6.5419057 | AA109: 5.7652807 | AB109: 5.6109455 | AC109: 3.8149692 | AD109: 2.6731765 | AE109: 2.240277 | AF109: 1.8077185 | AG109: 2.6403704 | AH109: 2.8241134 | AI109: 2.466888 | AJ109: 3.5451184 | AK109: 3.6274257 | AL109: 3.1291112 | AM109: 2.166411 | AN109: 2.2229754 | AO109: 1.6949491 | AP109: 1.3899779 | AQ109: 1.925561 | AR109: 2.4583982 | AS109: 3.1706759 | AT109: 3.0461737 | AU109: 2.5322178 | AV109: 3.3999885 | AW109: 3.774895 | AX109: 4.1318627 | AY109: 2.4334081 | AZ109: 3.3763705 | BA109: 3.0887179 | BB109: 1.9577269 | BC109: 2.5368915 | BD109: -0.30408351 | BE109: -0.088400083 | BF109: 0.85975928 | BG109: -0.099946425 | BH109: 7.9780698 | BI109: 9.0930658 | BJ109: 8.8921174 | BK109: 12.173526 | BL109: 13.801278 | BM109: 17.021923
D110: ev_ebitda | E110: Materials | F110: -1.283973 | G110: -1.2797807 | H110: -1.8990914 | I110: -1.7868698 | J110: -1.7018224 | K110: -1.6883846 | L110: -1.4964603 | M110: -1.3128752 | N110: -1.8872383 | O110: -2.2545708 | P110: -2.4927665 | Q110: -2.7433016 | R110: -1.9581448 | S110: -2.1465003 | T110: -2.5339885 | U110: -2.3828951 | V110: -2.123174 | W110: -1.9087789 | X110: -1.4474987 | Y110: -1.7648877 | Z110: -1.9652594 | AA110: -2.5298117 | AB110: -2.1798402 | AC110: -1.7030484 | AD110: -1.422902 | AE110: -1.5473854 | AF110: -1.481776 | AG110: -1.6909529 | AH110: -1.4880031 | AI110: -1.4616911 | AJ110: -1.4429617 | AK110: -1.7160695 | AL110: -1.8282761 | AM110: -1.3644678 | AN110: -1.3304591 | AO110: -1.6865022 | AP110: -1.7351291 | AQ110: -1.8478149 | AR110: -2.0133637 | AS110: -2.4219641 | AT110: -2.6461453 | AU110: -2.3940357 | AV110: -2.3015876 | AW110: -1.7961474 | AX110: -2.1018568 | AY110: -2.2700299 | AZ110: -2.4790319 | BA110: -2.8593349 | BB110: -3.0865504 | BC110: -3.3542911 | BD110: -3.4640286 | BE110: -3.3299358 | BF110: -3.1943427 | BG110: -3.2274289 | BH110: -3.5894666 | BI110: -3.8462068 | BJ110: -4.0703504 | BK110: -4.1817302 | BL110: -4.3494379 | BM110: -4.6809335
D111: ev_ebitda | E111: ConsStaples | F111: 0.63362638 | G111: 0.59919865 | H111: 0.76866151 | I111: 0.56995877 | J111: 0.087777277 | K111: 0.27446872 | L111: 0.3076751 | M111: 0.69579503 | N111: 0.048547653 | O111: -0.43729203 | P111: -0.3502547 | Q111: -0.76479517 | R111: -0.69083837 | S111: -0.43897819 | T111: -0.68384441 | U111: -0.50917394 | V111: 0.067608093 | W111: 0.46882332 | X111: 0.56132824 | Y111: -0.2518461 | Z111: -1.0013658 | AA111: -0.67802506 | AB111: -0.55796951 | AC111: -0.42186531 | AD111: -0.17141629 | AE111: 0.1036443 | AF111: -0.092626602 | AG111: -0.43358871 | AH111: -0.19537092 | AI111: -0.0048318118 | AJ111: -0.41600546 | AK111: -0.44857173 | AL111: -0.096961791 | AM111: -0.015285245 | AN111: 0.24689941 | AO111: 0.6624012 | AP111: 0.49902972 | AQ111: 0.36236292 | AR111: 0.42566346 | AS111: 0.51499588 | AT111: 0.8186631 | AU111: 1.1830907 | AV111: 0.90695727 | AW111: 0.93765529 | AX111: 0.78153578 | AY111: 1.9016155 | AZ111: 1.6749632 | BA111: 1.7331395 | BB111: 1.6297274 | BC111: 1.6972968 | BD111: 1.6303127 | BE111: 2.2646265 | BF111: 1.8294668 | BG111: 1.9946818 | BH111: 0.51083713 | BI111: 0.65501258 | BJ111: 0.63842812 | BK111: -0.22181111 | BL111: -1.0878833 | BM111: -1.3145195
D112: ev_ebitda | E112: Retail | F112: -0.20394747 | G112: 0.24478358 | H112: 1.0173708 | I112: 0.52131576 | J112: 1.3347384 | K112: 1.7579293 | L112: 0.50631014 | M112: 0.34583404 | N112: 1.2572705 | O112: 0.98797432 | P112: 1.0100635 | Q112: 1.3197825 | R112: 0.88104712 | S112: 1.3252178 | T112: 1.6538231 | U112: 1.0985894 | V112: 1.2362081 | W112: 0.85663659 | X112: 0.77961168 | Y112: 1.5495466 | Z112: 2.5617617 | AA112: 2.1257066 | AB112: 1.6420981 | AC112: 1.2765967 | AD112: 1.3860774 | AE112: 1.0863805 | AF112: 1.4185027 | AG112: 1.6474788 | AH112: 1.1223315 | AI112: 1.3134626 | AJ112: 1.5838747 | AK112: 1.7749032 | AL112: 1.4664502 | AM112: 1.4392217 | AN112: 1.0887615 | AO112: 0.95649451 | AP112: 0.92311654 | AQ112: 1.2485288 | AR112: 1.6232047 | AS112: 1.4997133 | AT112: 1.2492461 | AU112: 0.75260822 | AV112: 0.78003086 | AW112: 0.78196219 | AX112: 1.2545606 | AY112: 0.71961823 | AZ112: 1.162908 | BA112: 1.4663903 | BB112: 1.9992853 | BC112: 2.216018 | BD112: 2.5201694 | BE112: 1.258128 | BF112: 1.3596013 | BG112: 1.8715501 | BH112: 2.2363107 | BI112: 2.1371085 | BJ112: 2.311103 | BK112: 3.1795655 | BL112: 3.7355401 | BM112: 2.9109646
D113: ev_ebitda | E113: Fin
D114: ev_ebitda | E114: HealthCare | F114: 3.7286091 | G114: 3.2928463 | H114: 2.7695963 | I114: 2.5491752 | J114: 1.6777663 | K114: 1.0586663 | L114: 1.9646754 | M114: 2.2371848 | N114: 2.1882054 | O114: 2.2181071 | P114: 2.1309689 | Q114: 0.96379662 | R114: 0.41598044 | S114: 0.33121644 | T114: 0.16137712 | U114: 0.15822167 | V114: 0.3955065 | W114: 1.4152737 | X114: 1.7344346 | Y114: 1.777015 | Z114: 1.4621576 | AA114: 1.1808961 | AB114: 1.30343 | AC114: 2.3217946 | AD114: 2.9062844 | AE114: 3.5933487 | AF114: 3.1249511 | AG114: 3.1586661 | AH114: 3.1211531 | AI114: 3.1989905 | AJ114: 3.057276 | AK114: 3.1267981 | AL114: 2.8977678 | AM114: 2.6057832 | AN114: 2.3536731 | AO114: 2.3834988 | AP114: 2.74584 | AQ114: 2.8876341 | AR114: 2.407653 | AS114: 2.349513 | AT114: 2.352098 | AU114: 2.7383373 | AV114: 2.4794366 | AW114: 2.384763 | AX114: 2.3180914 | AY114: 2.8682732 | AZ114: 2.3958587 | BA114: 2.1572496 | BB114: 1.7281058 | BC114: 1.0484185 | BD114: 1.5622308 | BE114: 1.9666492 | BF114: 1.4358953 | BG114: 1.0219136 | BH114: 0.36603881 | BI114: -0.097618591 | BJ114: -0.19812123 | BK114: -0.022332793 | BL114: -0.056604104 | BM114: 0.11605777
D115: ev_ebitda | E115: Indus | F115: 3.3496496 | G115: 3.4194918 | H115: 3.9592317 | I115: 4.1054539 | J115: 3.4336576 | K115: 3.5998741 | L115: 3.2013855 | M115: 3.751508 | N115: 3.4536537 | O115: 3.0962375 | P115: 2.7039145 | Q115: 2.8514833 | R115: 2.7219748 | S115: 2.9157769 | T115: 3.0406579 | U115: 2.7194042 | V115: 2.9552565 | W115: 2.4706265 | X115: 2.463855 | Y115: 2.6229585 | Z115: 2.9732798 | AA115: 2.5737441 | AB115: 3.0450761 | AC115: 2.6431128 | AD115: 2.5167097 | AE115: 2.5013421 | AF115: 2.4373471 | AG115: 1.6165238 | AH115: 2.162216 | AI115: 2.3819742 | AJ115: 2.4988229 | AK115: 2.3301653 | AL115: 2.1025218 | AM115: 2.3039152 | AN115: 1.8979006 | AO115: 1.5343629 | AP115: 1.7027129 | AQ115: 1.8838534 | AR115: 1.8297683 | AS115: 1.8164244 | AT115: 1.3696607 | AU115: 1.6929505 | AV115: 1.9195057 | AW115: 2.202093 | AX115: 2.2841628 | AY115: 2.1814014 | AZ115: 2.1943195 | BA115: 1.9412823 | BB115: 1.3182225 | BC115: 1.6803789 | BD115: 1.9355639 | BE115: 1.6026266 | BF115: 1.8709083 | BG115: 1.9517114 | BH115: 1.7912142 | BI115: 1.67625 | BJ115: 2.1637626 | BK115: 2.0262425 | BL115: 1.6312888 | BM115: 1.8980692
D116: ev_ebitda | E116: Oil | F116: -5.0888618 | G116: -5.1241283 | H116: -5.142868 | I116: -5.7268558 | J116: -5.6471214 | K116: -5.1543979 | L116: -3.442057 | M116: -4.3502706 | N116: -4.6023874 | O116: -5.5863363 | P116: -5.889038 | Q116: -6.066223 | R116: -6.2701184 | S116: -6.1638888 | T116: -6.2386598 | U116: -6.6423082 | V116: -6.4578792 | W116: -6.0234408 | X116: -5.6031464 | Y116: -6.4943041 | Z116: -6.6801553 | AA116: -6.3084126 | AB116: -6.4112757 | AC116: -6.2480516 | AD116: -6.5865747 | AE116: -6.4315426 | AF116: -6.1191495 | AG116: -6.2617204 | AH116: -6.032418 | AI116: -5.8472021 | AJ116: -6.1517766 | AK116: -6.2936394 | AL116: -6.0151367 | AM116: -6.0624979 | AN116: -5.8344659 | AO116: -5.0736189 | AP116: -4.8316421 | AQ116: -5.4518247 | AR116: -5.8230608 | AS116: -6.216964 | AT116: -5.992413 | AU116: -5.772632 | AV116: -5.9552509 | AW116: -5.7808039 | AX116: -5.7457645 | AY116: -5.4531289 | AZ116: -5.9739799 | BA116: -5.3944976 | BB116: -5.5145432 | BC116: -5.9174821 | BD116: -6.1579467 | BE116: -5.5102057 | BF116: -5.4095415 | BG116: -5.9938376 | BH116: -6.2747458 | BI116: -5.9794134 | BJ116: -6.3597395 | BK116: -7.6906972 | BL116: -7.3874292 | BM116: -7.3951793
D117: ev_ebitda | E117: Tech | F117: 3.6073962 | G117: 2.8030643 | H117: 2.9762926 | I117: 4.0597828 | J117: 5.4541376 | K117: 4.1626995 | L117: 2.2760894 | M117: 3.2824318 | N117: 4.9004859 | O117: 5.5293643 | P117: 6.2444457 | Q117: 7.4441884 | R117: 6.7295811 | S117: 5.6824039 | T117: 6.2375614 | U117: 5.6940613 | V117: 4.6799052 | W117: 3.5423753 | X117: 3.3307251 | Y117: 4.5823417 | Z117: 5.4563898 | AA117: 6.0068366 | AB117: 5.2766916 | AC117: 5.5235591 | AD117: 5.8538757 | AE117: 5.9109939 | AF117: 6.4809251 | AG117: 7.4218383 | AH117: 6.1808988 | AI117: 5.3230319 | AJ117: 5.9918048 | AK117: 6.0426106 | AL117: 5.7674838 | AM117: 5.5540323 | AN117: 5.4926096 | AO117: 4.5611655 | AP117: 4.7574431 | AQ117: 5.3756196 | AR117: 5.8864517 | AS117: 5.8588045 | AT117: 5.58129 | AU117: 4.0553251 | AV117: 4.1475924 | AW117: 2.8514374 | AX117: 2.5016358 | AY117: 1.6295732 | AZ117: 2.3350767 | BA117: 1.9626569 | BB117: 1.8347718 | BC117: 2.5799511 | BD117: 3.0483544 | BE117: 1.9395889 | BF117: 2.3066044 | BG117: 2.6736967 | BH117: 3.7782857 | BI117: 3.5952454 | BJ117: 4.3412417 | BK117: 5.4544249 | BL117: 5.7080394 | BM117: 4.9481223
D118: ev_ebitda | E118: Telco | F118: -2.9043568 | G118: -3.3332341 | H118: -3.3662514 | I118: -3.2739716 | J118: -3.5653865 | K118: -4.0342674 | L118: -4.1222058 | M118: -4.9220539 | N118: -5.0291017 | O118: -5.0768227 | P118: -5.4008909 | Q118: -5.3569387 | R118: -5.3103269 | S118: -5.1941761 | T118: -5.3519121 | U118: -5.4288903 | V118: -5.3083231 | W118: -4.8681621 | X118: -4.654193 | Y118: -5.1958826 | Z118: -5.3886286 | AA118: -4.9716199 | AB118: -5.2739154 | AC118: -4.9122216 | AD118: -5.1037577 | AE118: -5.1071957 | AF118: -4.9392009 | AG118: -5.0617372 | AH118: -5.2425772 | AI118: -5.1531723 | AJ118: -5.3752222 | AK118: -5.2328135 | AL118: -4.6511219 | AM118: -4.7655226 | AN118: -4.5831797 | AO118: -3.9806599 | AP118: -4.1458975 | AQ118: -4.4824249 | AR118: -5.1337275 | AS118: -4.8615091 | AT118: -4.4446545 | AU118: -4.5222241 | AV118: -4.3345853 | AW118: -4.2276305 | AX118: -4.3424071 | AY118: -4.0650397 | AZ118: -4.3349723 | BA118: -4.1008747 | BB118: -3.7036862 | BC118: -3.9376408 | BD118: -3.7949362 | BE118: -2.9625605 | BF118: -3.4879991 | BG118: -3.9586193 | BH118: -4.4720316 | BI118: -4.293455 | BJ118: -4.5989842 | BK118: -5.1992391 | BL118: -5.2676069 | BM118: -5.4973995
D119: ev_ebitda | E119: Utili | F119: -1.0881431 | G119: -1.1424929 | H119: -0.75556564 | I119: -0.54379111 | J119: -0.89759641 | K119: -0.6475575 | L119: -0.41835068 | M119: -0.86707614 | N119: -1.4336167 | O119: -1.3898957 | P119: -1.248116 | Q119: -1.3328611 | R119: -1.5126254 | S119: -1.6107349 | T119: -1.3890284 | U119: -1.8737547 | V119: -1.3107106 | W119: -1.0516586 | X119: -0.97886308 | Y119: -1.539354 | Z119: -1.8154896 | AA119: -1.5382666 | AB119: -1.4639168 | AC119: -0.96852054 | AD119: -0.98434678 | AE119: -1.0163881 | AF119: -1.0250012 | AG119: -1.3340176 | AH119: -0.75991435 | AI119: -1.0332049 | AJ119: -1.5706961 | AK119: -1.5790708 | AL119: -1.3517222 | AM119: -1.0831044 | AN119: -0.81223555 | AO119: -0.32977838 | AP119: -0.63035669 | AQ119: -0.82058863 | AR119: -0.85356278 | AS119: -0.776238 | AT119: -0.23608273 | AU119: -0.067337292 | AV119: -0.09558021 | AW119: -0.1094119 | AX119: -0.18488016 | AY119: 0.55155425 | AZ119: 0.26878727 | BA119: 0.32678587 | BB119: 1.1345207 | BC119: 1.1481455 | BD119: 0.78286492 | BE119: 1.3351089 | BF119: 0.86037139 | BG119: 0.60727046 | BH119: -0.2709234 | BI119: -0.68581712 | BJ119: -0.88518348 | BK119: -1.3665242 | BL119: -1.6290683 | BM119: -2.0077294
D120: ev_ebitda | E120: Travel & leisure | F120: -0.74166965 | G120: 0.064018877 | H120: 0.27975018 | I120: 0.23650078 | J120: -0.33860882 | K120: 0.021203414 | L120: 0.07465453 | M120: 0.19902671 | N120: 0.47942465 | O120: 0.65852025 | P120: 0.019679826 | Q120: -0.1451356 | R120: 0.4323286 | S120: 1.0518885 | T120: 0.74103159 | U120: 0.9897466 | V120: 0.97952138 | W120: 1.088221 | X120: 0.86361619 | Y120: 1.24305 | Z120: 0.62325541 | AA120: 0.82878518 | AB120: 1.434561 | AC120: 0.58210766 | AD120: 0.17960235 | AE120: -0.4074566 | AF120: -0.65213063 | AG120: -0.49169765 | AH120: -0.5183037 | AI120: -0.05651149 | AJ120: -0.1968849 | AK120: -0.010774599 | AL120: 0.15441552 | AM120: 0.43638479 | AN120: 0.23557801 | AO120: 0.14564256 | AP120: 0.28514973 | AQ120: 0.28771246 | AR120: 0.83391616 | AS120: 1.0607072 | AT120: 0.95788883 | AU120: 1.4691226 | AV120: 1.3342565 | AW120: 1.4270306 | AX120: 1.548442 | AY120: 1.4049963 | AZ120: 1.8933371 | BA120: 1.8602704 | BB120: 1.985226 | BC120: 2.0202177 | BD120: 2.4609989 | BE120: 2.468588 | BF120: 2.8167518 | BG120: 3.1760054 | BH120: 3.1331345 | BI120: 3.1525051 | BJ120: 2.8617284 | BK120: 2.7806154 | BL120: 2.9061132 | BM120: 4.5599178
D121: ev_ebitda | E121: Media | F121: -0.0083292823 | G121: 0.45623247 | H121: -0.6071267 | I121: -0.71069895 | J121: 0.16245833 | K121: 0.64976603 | L121: 1.1482836 | M121: 0.94049532 | N121: 0.62475624 | O121: 2.2547142 | P121: 3.2719936 | Q121: 3.8300043 | R121: 4.5611417 | S121: 4.2477746 | T121: 4.362982 | U121: 6.1769991 | V121: 4.8860811 | W121: 4.010084 | X121: 2.9501304 | Y121: 3.4713627 | Z121: 3.7740546 | AA121: 3.3101673 | AB121: 3.1850607 | AC121: 1.9065366 | AD121: 1.426448 | AE121: 1.314259 | AF121: 0.84815891 | AG121: 1.4292073 | AH121: 1.6499877 | AI121: 1.3391544 | AJ121: 2.0217685 | AK121: 2.0064622 | AL121: 1.5545795 | AM121: 0.95154077 | AN121: 1.244918 | AO121: 0.82699397 | AP121: 0.42973325 | AQ121: 0.5569419 | AR121: 0.81705738 | AS121: 1.1765168 | AT121: 0.99044875 | AU121: 0.86479468 | AV121: 1.1192245 | AW121: 1.3290522 | AX121: 1.6864802 | AY121: 0.53116645 | AZ121: 0.86273365 | BA121: 0.90693229 | BB121: 0.67492015 | BC121: 0.81898749 | BD121: -0.52358352 | BE121: -1.0326141 | BF121: -0.38771602 | BG121: -0.11694364 | BH121: 2.7913463 | BI121: 3.6863894 | BJ121: 3.7961149 | BK121: 5.2414863 | BL121: 5.7970483 | BM121: 6.4626296
D122: price_sales | E122: Materials | F122: 0.22473758 | G122: 0.23063311 | H122: 0.011489214 | I122: 0.025529062 | J122: 0.067742048 | K122: 0.052647043 | L122: 0.18025188 | M122: 0.26777542 | N122: 0.03404329 | O122: -0.18048482 | P122: -0.28797681 | Q122: -0.38701976 | R122: -0.2316266 | S122: -0.24821462 | T122: -0.35901523 | U122: -0.34886186 | V122: -0.28701794 | W122: -0.19564625 | X122: -0.13542269 | Y122: -0.28469506 | Z122: -0.29494382 | AA122: -0.39095101 | AB122: -0.23841122 | AC122: -0.11772103 | AD122: -0.031322681 | AE122: -0.1064541 | AF122: -0.12118605 | AG122: -0.1746851 | AH122: -0.26171872 | AI122: -0.22840102 | AJ122: -0.26626726 | AK122: -0.30764884 | AL122: -0.31629401 | AM122: -0.20601046 | AN122: -0.19501576 | AO122: -0.20155636 | AP122: -0.22478862 | AQ122: -0.23338616 | AR122: -0.24553656 | AS122: -0.31582299 | AT122: -0.37638652 | AU122: -0.28254751 | AV122: -0.27422567 | AW122: -0.15935509 | AX122: -0.18983619 | AY122: -0.23263077 | AZ122: -0.27294019 | BA122: -0.35504824 | BB122: -0.36694186 | BC122: -0.40133476 | BD122: -0.41629396 | BE122: -0.34864176 | BF122: -0.27103888 | BG122: -0.27749057 | BH122: -0.3746873 | BI122: -0.47182452 | BJ122: -0.51756435 | BK122: -0.49085655 | BL122: -0.52494049 | BM122: -0.56674009
D123: price_sales | E123: ConsStaples | F123: -1.8739043 | G123: -1.9383394 | H123: -1.902645 | I123: -1.9345196 | J123: -1.8886041 | K123: -1.8699133 | L123: -1.7533012 | M123: -1.8123267 | N123: -1.886575 | O123: -1.9302425 | P123: -1.950729 | Q123: -2.0069563 | R123: -2.0162414 | S123: -1.9290725 | T123: -1.9201166 | U123: -1.9140334 | V123: -1.7607842 | W123: -1.6277683 | X123: -1.6268364 | Y123: -1.8184249 | Z123: -1.9039516 | AA123: -1.8151746 | AB123: -1.8737673 | AC123: -1.7349443 | AD123: -1.71035 | AE123: -1.6364275 | AF123: -1.6189653 | AG123: -1.6418717 | AH123: -1.574584 | AI123: -1.4683015 | AJ123: -1.5810582 | AK123: -1.5089968 | AL123: -1.4082844 | AM123: -1.3737065 | AN123: -1.2928251 | AO123: -1.1447513 | AP123: -1.1809175 | AQ123: -1.2530267 | AR123: -1.2648169 | AS123: -1.2289928 | AT123: -1.1204998 | AU123: -1.0829793 | AV123: -1.1055366 | AW123: -1.0712334 | AX123: -1.1182457 | AY123: -0.93085805 | AZ123: -1.0242964 | BA123: -0.9611454 | BB123: -0.87852538 | BC123: -0.96903027 | BD123: -1.0201294 | BE123: -0.87368998 | BF123: -1.0421043 | BG123: -1.0143163 | BH123: -1.3071351 | BI123: -1.2696543 | BJ123: -1.3346018 | BK123: -1.5220954 | BL123: -1.5452645 | BM123: -1.6313799
D124: price_sales | E124: Retail | F124: -0.92949159 | G124: -0.93077706 | H124: -0.80243638 | I124: -0.94162197 | J124: -0.8374162 | K124: -0.756418 | L124: -0.87455407 | M124: -0.96074028 | N124: -0.84423 | O124: -0.919142 | P124: -0.9286906 | Q124: -0.90351779 | R124: -1.0033609 | S124: -0.92776825 | T124: -0.88288723 | U124: -0.97198994 | V124: -0.89883699 | W124: -0.86750056 | X124: -0.87936274 | Y124: -0.84169748 | Z124: -0.74632763 | AA124: -0.79189858 | AB124: -0.92020401 | AC124: -0.92849515 | AD124: -0.91673163 | AE124: -0.90091839 | AF124: -0.83009545 | AG124: -0.81123192 | AH124: -0.85132386 | AI124: -0.7976384 | AJ124: -0.82807289 | AK124: -0.7498372 | AL124: -0.80895657 | AM124: -0.80281601 | AN124: -0.80457605 | AO124: -0.73368297 | AP124: -0.79533748 | AQ124: -0.81013547 | AR124: -0.87115802 | AS124: -0.85751781 | AT124: -0.81837242 | AU124: -0.89954377 | AV124: -0.90341061 | AW124: -0.87319298 | AX124: -0.87614919 | AY124: -0.86526876 | AZ124: -0.86968199 | BA124: -0.78041421 | BB124: -0.63371296 | BC124: -0.72185983 | BD124: -0.73441058 | BE124: -0.78478909 | BF124: -0.87260449 | BG124: -0.78661632 | BH124: -0.84481196 | BI124: -0.84141349 | BJ124: -0.89281958 | BK124: -0.88185846 | BL124: -0.75368961 | BM124: -0.89423281
D125: price_sales | E125: Fin | F125: 0.066577869 | G125: 0.17405806 | H125: 0.21657087 | I125: 0.1132596 | J125: -0.02517294 | K125: 0.032736627 | L125: 0.04190468 | M125: -0.022812473 | N125: 0.13815324 | O125: 0.21215467 | P125: 0.095718295 | Q125: 0.018061847 | R125: 0.13485461 | S125: 0.16594877 | T125: 0.13583804 | U125: 0.12813608 | V125: 0.13359409 | W125: 0.14587913 | X125: 0.18324871 | Y125: 0.17153894 | Z125: 0.15676697 | AA125: 0.095154569 | AB125: 0.18780983 | AC125: 0.056789033 | AD125: 0.0016402445 | AE125: 0.11180057 | AF125: 0.070384944 | AG125: -0.060005458 | AH125: 0.025064738 | AI125: 0.025242873 | AJ125: 0.053404235 | AK125: 0.0065865085 | AL125: 0.030264665 | AM125: 0.023008323 | AN125: -0.014750465 | AO125: -0.055269922 | AP125: -0.025787764 | AQ125: -0.094084653 | AR125: -0.066906494 | AS125: -0.11711252 | AT125: -0.11059919 | AU125: -0.079512627 | AV125: -0.11114555 | AW125: 0.15745416 | AX125: 0.17091076 | AY125: 0.17369931 | AZ125: 0.19774155 | BA125: 0.17535398 | BB125: 0.13183633 | BC125: 0.12045927 | BD125: 0.11049932 | BE125: 0.128162 | BF125: 0.18279764 | BG125: 0.11319773 | BH125: 0.14137008 | BI125: 0.17488677 | BJ125: 0.16705735 | BK125: 0.02074 | BL125: 0.051846619 | BM125: 0.089764015
... D172: ebitda_growth | E172: Retail | F172: 7.1566697 | G172: 5.5636955 | H172: 5.4904316 | I172: 4.0318089 | J172: 3.93317 | K172: 3.7966773 | L172: 3.6610347 | M172: 5.1115151 | N172: 5.1209664 | O172: 3.7950693 | P172: 4.3196887 | Q172: 3.9072521 | R172: 3.063193 | S172: 2.8999981 | T172: 2.4338018 | U172: 2.1855984 | V172: 1.7718951 | W172: 1.8803167 | X172: 1.8307962 | Y172: 2.2522726 | Z172: 2.3827756 | AA172: 1.5386466 | AB172: 1.6481662 | AC172: 1.9200273 | AD172: 2.2004059 | AE172: 2.3466448 | AF172: 3.0962511 | AG172: 3.0506112 | AH172: 3.1624164 | AI172: 2.7804416 | AJ172: 2.6943267 | AK172: 2.8713137 | AL172: 1.76857 | AM172: 1.3121752 | AN172: 2.2706836 | AO172: 3.3997214 | AP172: 3.5851596 | AQ172: 4.1490001 | AR172: 3.386436 | AS172: 3.6650831 | AT172: 3.5728117 | AU172: 3.8862098 | AV172: 3.4249288 | AW172: 3.7988062 | AX172: 4.8808749 | AY172: 4.8042769 | AZ172: 3.5120872 | BA172: 1.734425 | BB172: 0.85028706 | BC172: -1.1625872 | BD172: -3.3260463 | BE172: -5.3144683 | BF172: -6.9337802 | BG172: -7.1996718 | BH172: -4.0845693 | BI172: -4.9103379 | BJ172: -4.4572317 | BK172: -5.0951497 | BL172: -6.5389111 | BM172: -7.8111815
D173: ebitda_growth | E173: Fin
D174: ebitda_growth | E174: HealthCare | F174: 0.44836018 | G174: -0.37068813 | H174: -1.5611412 | I174: -3.4820041 | J174: -4.2532876 | K174: -3.9077809 | L174: -3.4885088 | M174: -2.9627785 | N174: -3.2627268 | O174: -3.976626 | P174: -2.1622476 | Q174: -1.4787135 | R174: -1.320595 | S174: -0.74188376 | T174: -0.44306603 | U174: 1.5702186 | V174: 2.1475727 | W174: 3.194593 | X174: 3.9215282 | Y174: 4.508197 | Z174: 6.5982328 | AA174: 6.5734669 | AB174: 6.5315907 | AC174: 6.1228681 | AD174: 5.5364144 | AE174: 5.1666365 | AF174: 4.1817854 | AG174: 3.8271132 | AH174: 3.7208359 | AI174: 3.4564184 | AJ174: 5.9274351 | AK174: 6.6086541 | AL174: 6.9773828 | AM174: 7.3080208 | AN174: 5.8752064 | AO174: 2.1116772 | AP174: -1.5588099 | AQ174: -3.1604128 | AR174: -3.9696381 | AS174: -5.2859997 | AT174: -6.0853297 | AU174: -7.045319 | AV174: -7.7350971 | AW174: -9.2088212 | AX174: -7.5791492 | AY174: -7.1517326 | AZ174: -7.3784571 | BA174: -8.8487711 | BB174: -9.0049737 | BC174: -9.6046999 | BD174: -10.018833 | BE174: -10.436057 | BF174: -10.77399 | BG174: -10.271989 | BH174: -7.5091907 | BI174: -6.4744544 | BJ174: -7.4749646 | BK174: -7.891059 | BL174: -12.177903 | BM174: -14.208015
D175: ebitda_growth | E175: Indus | F175: -2.3103888 | G175: -2.8855784 | H175: -3.2393486 | I175: -3.6447428 | J175: -3.5089782 | K175: -3.6124078 | L175: -3.440269 | M175: -2.7929783 | N175: -2.64288 | O175: -0.95677116 | P175: -0.66224469 | Q175: -0.52600008 | R175: -0.61243478 | S175: -0.62490367 | T175: -0.46642618 | U175: -0.074774349 | V175: 0.21982296 | W175: 0.16751917 | X175: 0.69455807 | Y175: 1.2994639 | Z175: 1.2662304 | AA175: 1.3751675 | AB175: 0.4299437 | AC175: 0.14990541 | AD175: -0.25112655 | AE175: -0.32774666 | AF175: -0.36361104 | AG175: -0.35751259 | AH175: -0.58997409 | AI175: -0.47235117 | AJ175: 0.41665288 | AK175: 0.48715336 | AL175: 0.18232917 | AM175: -0.34250858 | AN175: 0.17023696 | AO175: 0.48490542 | AP175: 1.3821288 | AQ175: 2.0261514 | AR175: 2.6503979 | AS175: 2.820239 | AT175: 2.884358 | AU175: 2.6891952 | AV175: 2.6917294 | AW175: 2.8830599 | AX175: 2.931007 | AY175: 4.1960798 | AZ175: 3.0539523 | BA175: 1.783646 | BB175: 0.56661481 | BC175: -0.13892643 | BD175: -1.1573206 | BE175: -1.9249233 | BF175: -2.8118714 | BG175: -3.1452663 | BH175: -1.0700907 | BI175: -0.24638379 | BJ175: -0.98715216 | BK175: -2.8801427 | BL175: -4.547613 | BM175: -6.0151237
D176: ebitda_growth | E176: Oil | F176: -5.9461644 | G176: -3.4182486 | H176: -0.76320362 | I176: 1.7942182 | J176: 5.1302134 | K176: 4.9406832 | L176: -4.2724287 | M176: -8.4291309 | N176: -8.780165 | O176: -6.3284688 | P176: -4.9972933 | Q176: -5.3232077 | R176: -3.2724033 | S176: -3.3715189 | T176: -3.7440989 | U176: -4.8581447 | V176: -5.4041776 | W176: -5.5699813 | X176: -2.3567538 | Y176: -3.1296166 | Z176: -2.6441398 | AA176: -3.7008613 | AB176: -3.7963312 | AC176: -4.5539672 | AD176: -4.0904099 | AE176: -2.3527549 | AF176: -2.8054551 | AG176: -3.5641178 | AH176: -4.4216695 | AI176: -5.8556843 | AJ176: -7.7234894 | AK176: -9.5108549 | AL176: -9.53923 | AM176: -7.2714772 | AN176: -8.4591672 | AO176: -10.418708 | AP176: -12.619206 | AQ176: -14.578205 | AR176: -16.205801 | AS176: -16.780305 | AT176: -17.471581 | AU176: -18.382994 | AV176: -18.231789 | AW176: -18.225824 | AX176: -18.976663 | AY176: -17.718879 | AZ176: -9.6895047 | BA176: -3.5502989 | BB176: 1.649475 | BC176: 7.2662659 | BD176: 12.612911 | BE176: 13.09282 | BF176: 15.85224 | BG176: 18.708741 | BH176: 10.815635 | BI176: 4.0578552 | BJ176: 2.9676521 | BK176: -0.20660946 | BL176: 6.8209698 | BM176: 12.189783
D177: ebitda_growth | E177: Tech | F177: 24.665926 | G177: 24.339647 | H177: 22.009304 | I177: 21.880221 | J177: 19.397441 | K177: 17.624523 | L177: 17.696174 | M177: 15.53454 | N177: 13.996026 | O177: 13.220732 | P177: 11.685279 | Q177: 10.077861 | R177: 9.2664062 | S177: 8.5733916 | T177: 7.7564884 | U177: 6.8277583 | V177: 6.8215459 | W177: 6.9998417 | X177: 7.1975574 | Y177: 7.6692161 | Z177: 7.215275 | AA177: 8.2963149 | AB177: 8.6975014 | AC177: 8.9459774 | AD177: 9.0558849 | AE177: 9.3813783 | AF177: 8.703738 | AG177: 9.0319418 | AH177: 9.0866564 | AI177: 8.5794611 | AJ177: 8.712506 | AK177: 8.720007 | AL177: 7.3264333 | AM177: 7.167627 | AN177: 6.3986625 | AO177: 5.2168674 | AP177: 4.8611943 | AQ177: 4.7023614 | AR177: 3.4533385 | AS177: 2.0354146 | AT177: 1.3110631 | AU177: -0.1118928 | AV177: -0.90443069 | AW177: -1.6500808 | AX177: -1.8737938 | AY177: -1.264205 | AZ177: -2.3431046 | BA177: -3.1481169 | BB177: -2.3962357 | BC177: -3.1016377 | BD177: -3.620787 | BE177: -3.018238 | BF177: -3.3223656 | BG177: -4.2438344 | BH177: -2.7682423 | BI177: -2.2590248 | BJ177: -4.046795 | BK177: -6.1135869 | BL177: -7.0473804 | BM177: -8.0511769
D178: ebitda_growth | E178: Telco | F178: -7.8513181 | G178: -8.8371333 | H178: -9.8931166 | I178: -10.136571 | J178: -10.432128 | K178: -10.556679 | L178: -9.6285227 | M178: -8.6106658 | N178: -8.1951497 | O178: -8.3854075 | P178: -7.6213275 | Q178: -7.556112 | R178: -6.7444025 | S178: -6.4595255 | T178: -6.2649209 | U178: -5.8812288 | V178: -5.5302312 | W178: -5.6355793 | X178: -6.4371809 | Y178: -6.1983998 | Z178: -7.1019523 | AA178: -7.2316065 | AB178: -7.4303288 | AC178: -7.0835852 | AD178: -7.0943406 | AE178: -7.0998105 | AF178: -7.0869326 | AG178: -6.9369446 | AH178: -6.7763912 | AI178: -6.619112 | AJ178: -6.2353216 | AK178: -5.9991838 | AL178: -5.4219537 | AM178: -5.7696071 | AN178: -5.1274057 | AO178: -4.6540707 | AP178: -4.0865197 | AQ178: -3.8679777 | AR178: -3.2211014 | AS178: -3.0215605 | AT178: -2.6155952 | AU178: -2.2288166 | AV178: -2.0037073 | AW178: -2.8983609 | AX178: -3.104536 | AY178: -2.2679886 | AZ178: -4.2475612 | BA178: -6.4264991 | BB178: -8.6160059 | BC178: -10.41782 | BD178: -12.277477 | BE178: -13.509847 | BF178: -14.912579 | BG178: -15.82651 | BH178: -13.835052 | BI178: -13.103526 | BJ178: -13.131658 | BK178: -13.81296 | BL178: -16.124228 | BM178: -18.427779
D179: ebitda_growth | E179: Utili | F179: -3.0814548 | G179: -3.0214517 | H179: -3.0083298 | I179: -3.1981765 | J179: -3.1353673 | K179: -2.695334 | L179: -1.1718939 | M179: 1.3051181 | N179: 0.78402907 | O179: 0.78053169 | P179: 1.5072708 | Q179: 1.4017524 | R179: 1.6623107 | S179: 1.4631684 | T179: 1.7504562 | U179: 2.4528673 | V179: 2.5032829 | W179: 2.2351932 | X179: 1.5832597 | Y179: 2.6111229 | Z179: 2.0313416 | AA179: 0.32141824 | AB179: 0.33900654 | AC179: 0.44579557 | AD179: 0.17853544 | AE179: -0.1297841 | AF179: -0.22814598 | AG179: -0.29390185 | AH179: -0.54262633 | AI179: -0.23320607 | AJ179: -1.2420678 | AK179: -0.4828987 | AL179: -0.42554911 | AM179: -0.39177079 | AN179: 0.27441405 | AO179: 0.81821404 | AP179: 1.7801315 | AQ179: 2.2877836 | AR179: 3.1227704 | AS179: 3.95159 | AT179: 4.5301027 | AU179: 4.7655196 | AV179: 5.2927188 | AW179: 6.9072218 | AX179: 5.2959473 | AY179: 5.6033708 | AZ179: 3.8975196 | BA179: 2.8697982 | BB179: 0.87940205 | BC179: -0.19457597 | BD179: -1.4139375 | BE179: -3.1026941 | BF179: -3.3792054 | BG179: -3.4755701 | BH179: -3.8890527 | BI179: -3.9755996 | BJ179: -5.8092005 | BK179: -5.3226512 | BL179: -8.6411032 | BM179: -11.410672
D180: ebitda_growth | E180: Travel & leisure | F180: -3.886827 | G180: -4.137626 | H180: -4.2805239 | I180: -4.7497718 | J180: -5.1458609 | K180: -5.2152591 | L180: -3.5383484 | M180: -1.6377853 | N180: -0.83897816 | O180: -1.1510383 | P180: -0.39245628 | Q180: -0.32422727 | R180: -0.083394891 | S180: -0.075931133 | T180: -0.11448717 | U180: -0.2323354 | V180: -0.36705826 | W180: -0.63202649 | X180: -0.16868471 | Y180: -1.0747157 | Z180: -1.592412 | AA180: -1.6929133 | AB180: -1.4116602 | AC180: -1.6148493 | AD180: -0.96822809 | AE180: -1.604185 | AF180: -1.4076835 | AG180: -0.092555428 | AH180: 0.16148755 | AI180: 1.0385974 | AJ180: 1.3531314 | AK180: 1.3059862 | AL180: 1.6201547 | AM180: 1.9220864 | AN180: 4.5445931 | AO180: 7.0366826 | AP180: 11.290405 | AQ180: 13.956227 | AR180: 15.955954 | AS180: 18.180448 | AT180: 19.828485 | AU180: 22.288466 | AV180: 23.437581 | AW180: 25.425494 | AX180: 26.40567 | AY180: 25.277571 | AZ180: 26.192908 | BA180: 27.683096 | BB180: 27.962206 | BC180: 29.856868 | BD180: 32.370751 | BE180: 33.965143 | BF180: 35.779012 | BG180: 37.885709 | BH180: 41.48508 | BI180: 46.195846 | BJ180: 54.322414 | BK180: 62.505498 | BL180: 71.657657 | BM180: 78.315428
D181: ebitda_growth | E181: Media | F181: -1.5130601 | G181: -0.8524251 | H181: 0.35288816 | I181: 1.2740716 | J181: 1.3048843 | K181: 2.5935041 | L181: 4.2982815 | M181: 2.5751677 | N181: 3.2073011 | O181: 5.3731765 | P181: 2.4296275 | Q181: 3.1430181 | R181: 2.4019113 | S181: 2.7709675 | T181: 3.1091338 | U181: 2.9475168 | V181: 3.0811984 | W181: 3.0045992 | X181: 2.1429498 | Y181: 1.9078835 | Z181: 1.7818207 | AA181: 1.2396628 | AB181: 1.2913521 | AC181: 1.205135 | AD181: 1.416039 | AE181: 1.9808567 | AF181: 4.0441844 | AG181: 4.172807 | AH181: 4.9515602 | AI181: 5.7068589 | AJ181: 5.4235574 | AK181: 5.798527 | AL181: 6.0731563 | AM181: 5.8108284 | AN181: 5.1770761 | AO181: 6.7190068 | AP181: 6.4701244 | AQ181: 6.7350111 | AR181: 7.1772619 | AS181: 6.6923241 | AT181: 7.0377588 | AU181: 7.512019 | AV181: 7.8665893 | AW181: 8.1233276 | AX181: 7.524802 | AY181: 6.2164215 | AZ181: 6.0523309 | BA181: 9.2639778 | BB181: 9.103729 | BC181: 9.0986756 | BD181: 9.4148538 | BE181: 11.272012 | BF181: 11.365408 | BG181: 9.9402035 | BH181: 3.7329534 | BI181: 4.8870584 | BJ181: 4.5423136 | BK181: 7.648626 | BL181: 4.7554913 | BM181: 3.1467931
D182: cash_flow_growth | E182: Materials | F182: 6.7424214 | G182: 6.0711966 | H182: 6.7997172 | I182: 7.5295854 | J182: 9.0346875 | K182: 10.036801 | L182: 10.677871 | M182: 9.2793254 | N182: 6.4019676 | O182: 4.2300282 | P182: 1.3026579 | Q182: 1.5488534 | R182: -2.3482315 | S182: -0.68796463 | T182: -1.3504853 | U182: -2.8841041 | V182: -3.8958522 | W182: -4.4288953 | X182: -6.9252156 | Y182: -7.4086037 | Z182: -5.2670534 | AA182: -3.5235261 | AB182: -2.4047977 | AC182: -2.877596 | AD182: -2.4734292 | AE182: -2.5125729 | AF182: -3.1278896 | AG182: -4.063989 | AH182: -4.8353786 | AI182: -5.186593 | AJ182: -6.3455932 | AK182: -6.5606481 | AL182: -5.3648216 | AM182: -3.9414353 | AN182: -6.3536732 | AO182: -10.247421 | AP182: -10.82866 | AQ182: -12.330848 | AR182: -14.153438 | AS182: -14.215159 | AT182: -14.290118 | AU182: -15.128674 | AV182: -15.633626 | AW182: -17.871163 | AX182: -18.239627 | AY182: -18.488016 | AZ182: -17.057267 | BA182: -16.799707 | BB182: -13.841591 | BC182: -14.392166 | BD182: -14.985625 | BE182: -12.107476 | BF182: -10.917575 | BG182: -12.03644 | BH182: -10.114784 | BI182: -13.339936 | BJ182: -10.106246 | BK182: -11.896227 | BL182: -16.117039 | BM182: -18.917707
D183: cash_flow_growth | E183: ConsStaples | F183: -5.5741245 | G183: -5.9416565 | H183: -5.5591823 | I183: -5.5881179 | J183: -6.0865263 | K183: -5.3149641 | L183: -3.3498889 | M183: -1.644966 | N183: 1.6142931 | O183: 2.519022 | P183: 1.1087905 | Q183: 1.2100978 | R183: 1.3193128 | S183: -0.67551144 | T183: -1.1174354 | U183: -2.405593 | V183: -3.3750865 | W183: -4.8336324 | X183: -6.4034408 | Y183: -6.6929012 | Z183: -1.2205159 | AA183: -0.54236419 | AB183: -1.4438254 | AC183: -1.6483327 | AD183: -4.6687939 | AE183: -5.7165053 | AF183: -5.2494877 | AG183: -4.529596 | AH183: -4.8256725 | AI183: -3.9509396 | AJ183: -3.746729 | AK183: -2.23124 | AL183: -0.56671255 | AM183: 0.041475183 | AN183: 0.11988441 | AO183: 0.7135014 | AP183: 0.1915974 | AQ183: 0.035285112 | AR183: 0.20384066 | AS183: -0.19746256 | AT183: -0.03089854 | AU183: 0.16185664 | AV183: -0.62131239 | AW183: 1.2178895 | AX183: 3.9274273 | AY183: -1.6606932 | AZ183: -4.2018954 | BA183: -6.5290568 | BB183: -8.2138438 | BC183: -10.423327 | BD183: -14.154572 | BE183: -16.76767 | BF183: -18.631327 | BG183: -21.287176 | BH183: -18.222053 | BI183: -16.036945 | BJ183: -14.534257 | BK183: -16.929848 | BL183: -18.967311 | BM183: -23.221111
D184: cash_flow_growth | E184: Retail | F184: 4.3086612 | G184: 4.9819395 | H184: 5.3085881 | I184: 3.9460321 | J184: 3.4218138 | K184: 1.8673774 | L184: 1.968592 | M184: 2.6422473 | N184: 9.6576586 | O184: 9.8115016 | P184: 8.0817646 | Q184: 7.977054 | R184: 3.4684243 | S184: 3.8502328 | T184: 3.4802661 | U184: 4.2935155 | V184: 2.6522471 | W184: 4.7727511 | X184: 4.2866229 | Y184: 5.4939895 | Z184: 3.3134289 | AA184: 2.8624809 | AB184: 3.6771707 | AC184: 2.9939353 | AD184: 4.4875062 | AE184: 5.6624041 | AF184: 7.4131915 | AG184: 7.9013621 | AH184: 8.6346803 | AI184: 7.3959433 | AJ184: 8.573193 | AK184: 9.3242026 | AL184: 7.7602584 | AM184: 7.6129613 | AN184: 8.7855758 | AO184: 8.3363824 | AP184: 10.089814 | AQ184: 11.583842 | AR184: 12.252186 | AS184: 13.259061 | AT184: 14.587087 | AU184: 16.525282 | AV184: 19.998525 | AW184: 21.25705 | AX184: 17.897199 | AY184: 17.531115 | AZ184: 14.327942 | BA184: 10.541026 | BB184: 8.1714567 | BC184: 6.3877333 | BD184: 4.4814582 | BE184: 5.3389986 | BF184: 3.7085954 | BG184: 4.5520718 | BH184: 13.104657 | BI184: 14.599718 | BJ184: -10.488851 | BK184: -10.851305 | BL184: -9.7315062 | BM184: -19.243104
D185: cash_flow_growth | E185: Fin
D186: cash_flow_growth | E186: HealthCare | F186: 0.59066625 | G186: -0.62777921 | H186: -1.7433777 | I186: -3.630495 | J186: -3.8347392 | K186: -2.1453168 | L186: -2.2811247 | M186: -3.1754303 | N186: -4.2548696 | O186: -7.3792145 | P186: -5.7875432 | Q186: -4.2798294 | R186: -2.2904746 | S186: -2.200351 | T186: -2.595329 | U186: 0.0494988 | V186: 1.3131517 | W186: 2.7549917 | X186: 3.2199547 | Y186: 3.1125014 | Z186: 2.8814517 | AA186: 2.939187 | AB186: 4.1889322 | AC186: 6.2693389 | AD186: 5.8120847 | AE186: 4.5073772 | AF186: 3.0261229 | AG186: 2.9399853 | AH186: 3.482136 | AI186: 5.4379157 | AJ186: 5.7436303 | AK186: 6.3844669 | AL186: 6.5995638 | AM186: 3.6074878 | AN186: 0.84799587 | AO186: -2.3224431 | AP186: -7.2536398 | AQ186: -7.6453901 | AR186: -9.0338898 | AS186: -9.9697399 | AT186: -10.92636 | AU186: -12.751149 | AV186: -13.462174 | AW186: -13.374227 | AX186: -14.600669 | AY186: -17.064019 | AZ186: -15.216108 | BA186: -14.671043 | BB186: -14.863176 | BC186: -14.718252 | BD186: -15.383764 | BE186: -15.510786 | BF186: -15.858168 | BG186: -16.628587 | BH186: -11.324294 | BI186: -9.2661845 | BJ186: -6.9169703 | BK186: -10.395358 | BL186: -13.950889 | BM186: -17.422603
D187: cash_flow_growth | E187: Indus | F187: -0.74197332 | G187: -1.2362151 | H187: -1.1297423 | I187: -1.0976953 | J187: -0.073113253 | K187: -0.20256122 | L187: 0.69287483 | M187: 1.4650393 | N187: 0.6112341 | O187: 0.27129681 | P187: 0.44232605 | Q187: 1.4901677 | R187: 3.6400574 | S187: 3.796023 | T187: 4.5036011 | U187: 5.2490808 | V187: 5.939055 | W187: 5.9431446 | X187: 7.8081094 | Y187: 9.2957166 | Z187: 9.2808003 | AA187: 9.397384 | AB187: 6.261744 | AC187: 3.8873761 | AD187: 3.4992374 | AE187: 2.5317699 | AF187: 0.5832294 | AG187: -0.11325549 | AH187: -0.61319053 | AI187: -0.61337747 | AJ187: -0.62032624 | AK187: -0.24461942 | AL187: 0.38503096 | AM187: 1.6644451 | AN187: 1.1105183 | AO187: 2.4239149 | AP187: 2.7577681 | AQ187: 2.601363 | AR187: 1.918724 | AS187: 2.1878678 | AT187: 2.9854357 | AU187: 4.355374 | AV187: 4.4102868 | AW187: 6.0544006 | AX187: 3.9064374 | AY187: 3.1376815 | AZ187: 1.7292016 | BA187: 0.15216774 | BB187: 1.1145923 | BC187: 0.22828402 | BD187: -2.2652111 | BE187: -2.680896 | BF187: -4.0411106 | BG187: -5.0358241 | BH187: -0.88864166 | BI187: 1.9308272 | BJ187: -0.282914 | BK187: -3.1391506 | BL187: -6.788441 | BM187: -9.9768247
D188: cash_flow_growth | E188: Oil | F188: -5.4104097 | G188: -3.4246409 | H188: -1.4655207 | I188: 1.8990822 | J188: 5.7535177 | K188: 3.506103 | L188: -4.4984282 | M188: -7.7724515 | N188: -8.374737 | O188: -5.6041129 | P188: -4.8691033 | Q188: -5.4078416 | R188: -4.2765051 | S188: -3.7857554 | T188: -4.0288755 | U188: -5.3366134 | V188: -5.807655 | W188: -5.5511047 | X188: -3.4502952 | Y188: -3.5767065 | Z188: -2.9752062 | AA188: -7.1172583 | AB188: -6.693425 | AC188: -6.2911627 | AD188: -5.2524725 | AE188: -4.58295 | AF188: -4.839207 | AG188: -5.2579599 | AH188: -5.8178476 | AI188: -7.9772297 | AJ188: -8.9660928 | AK188: -10.422754 | AL188: -11.023468 | AM188: -7.8944012 | AN188: -9.1797621 | AO188: -10.375548 | AP188: -13.185607 | AQ188: -16.153754 | AR188: -17.810006 | AS188: -19.909563 | AT188: -20.392375 | AU188: -21.334835 | AV188: -21.869671 | AW188: -20.778677 | AX188: -21.821725 | AY188: -20.53033 | AZ188: -14.321328 | BA188: -9.0387792 | BB188: -4.7532357 | BC188: 0.085256887 | BD188: 4.0507477 | BE188: 5.4337985 | BF188: 7.338644 | BG188: 8.8441991 | BH188: 6.9595011 | BI188: 0.022000207 | BJ188: -1.6537181 | BK188: -6.0642884 | BL188: -1.0979596 | BM188: 2.7019605
D189: cash_flow_growth | E189: Tech | F189: 25.121968 | G189: 24.370831 | H189: 22.88434 | I189: 22.829014 | J189: 21.189423 | K189: 19.919696 | L189: 20.214579 | M189: 17.772391 | N189: 15.966183 | O189: 16.181384 | P189: 12.903225 | Q189: 10.611136 | R189: 9.4496773 | S189: 8.7939874 | T189: 7.8133208 | U189: 7.8415458 | V189: 8.465285 | W189: 8.4298498 | X189: 9.4770655 | Y189: 10.641005 | Z189: 8.0020064 | AA189: 8.8810743 | AB189: 9.4227971 | AC189: 11.017603 | AD189: 10.457854 | AE189: 10.779475 | AF189: 10.078942 | AG189: 10.887334 | AH189: 10.901568 | AI189: 11.169264 | AJ189: 10.918417 | AK189: 11.069925 | AL189: 11.037618 | AM189: 9.2727498 | AN189: 7.6074845 | AO189: 5.9775456 | AP189: 5.1010779 | AQ189: 4.8846148 | AR189: 2.8499827 | AS189: 0.88986945 | AT189: -0.05961275 | AU189: -1.6787984 | AV189: -2.3661669 | AW189: -1.9857907 | AX189: -3.8917689 | AY189: -3.6904707 | AZ189: -4.0353576 | BA189: -5.723446 | BB189: -4.2752281 | BC189: -4.7174533 | BD189: -6.0890139 | BE189: -5.1547439 | BF189: -5.6608331 | BG189: -6.924058 | BH189: -3.7214757 | BI189: -2.2579378 | BJ189: -4.3633524 | BK189: -8.9341957 | BL189: -12.58365 | BM189: -16.056222
D190: cash_flow_growth | E190: Telco | F190: -5.9569315 | G190: -7.2172591 | H190: -9.4314963 | I190: -9.4171777 | J190: -10.631218 | K190: -10.665707 | L190: -8.6341836 | M190: -7.49214 | N190: -8.5830926 | O190: -7.7453405 | P190: -8.0013321 | Q190: -7.4956662 | R190: -5.7411411 | S190: -4.8205987 | T190: -4.0021884 | U190: -4.1136255 | V190: -3.2954292 | W190: -3.3640426 | X190: -4.5599033 | Y190: -4.936869 | Z190: -5.7849162 | AA190: -6.1446394 | AB190: -6.3127172 | AC190: -6.7561575 | AD190: -6.3470182 | AE190: -6.8153922 | AF190: -6.9681752 | AG190: -7.5673611 | AH190: -7.5680984 | AI190: -8.0147719 | AJ190: -7.7268349 | AK190: -7.5759298 | AL190: -7.3121564 | AM190: -8.3670907 | AN190: -8.2201018 | AO190: -7.5363346 | AP190: -7.1361641 | AQ190: -6.4174164 | AR190: -5.4263503 | AS190: -5.518589 | AT190: -5.5470219 | AU190: -5.6700066 | AV190: -4.9163055 | AW190: -5.5341064 | AX190: -5.5755514 | AY190: -4.6035537 | AZ190: -6.8511302 | BA190: -8.4813342 | BB190: -9.9018816 | BC190: -11.925266 | BD190: -15.087479 | BE190: -16.651609 | BF190: -18.277933 | BG190: -20.425505 | BH190: -17.550011 | BI190: -15.51091 | BJ190: -16.613726 | BK190: -18.702685 | BL190: -23.455095 | BM190: -27.821065
D191: cash_flow_growth | E191: Utili | F191: -7.181257 | G191: -7.6512569 | H191: -7.3031544 | I191: -7.2667716 | J191: -7.2531478 | K191: -5.9279467 | L191: -5.4887056 | M191: -6.3948611 | N191: -6.3560071 | O191: -7.2926509 | P191: -5.5999546 | Q191: -5.418232 | R191: -5.3807921 | S191: -5.4338508 | T191: -4.3971564 | U191: -3.4352559 | V191: -2.4965207 | W191: -1.7583904 | X191: -2.5195005 | Y191: -2.8053817 | Z191: -4.5075094 | AA191: -4.2316619 | AB191: -3.1608784 | AC191: -2.4111596 | AD191: -3.0735074 | AE191: -2.8329987 | AF191: -2.274273 | AG191: -1.8404982 | AH191: -1.7899647 | AI191: -1.1062923 | AJ191: 0.66053784 | AK191: 0.49210362 | AL191: 0.33097191 | AM191: -0.085051547 | AN191: 1.3114726 | AO191: 0.61308519 | AP191: 0.91165273 | AQ191: 1.9228068 | AR191: 3.416624 | AS191: 4.5576507 | AT191: 5.8531323 | AU191: 9.3443892 | AV191: 10.942961 | AW191: 4.7597078 | AX191: -0.24315301 | AY191: -3.5900729 | AZ191: -2.1230592 | BA191: -1.4321694 | BB191: 0.2589557 | BC191: 0.90637123 | BD191: 0.7827495 | BE191: 1.1863749 | BF191: 2.7815056 | BG191: 4.7763246 | BH191: 0.21292496 | BI191: -8.8684912 | BJ191: -3.2477893 | BK191: -6.3195096 | BL191: -9.7010083 | BM191: -14.123589
D192: cash_flow_growth | E192: Travel & leisure | F192: -3.2912664 | G192: -3.3127922 | H192: -3.4782813 | I192: -3.5793484 | J192: -3.9347551 | K192: -4.4644841 | L192: -1.2383571 | M192: 0.49403872 | N192: 0.40428187 | O192: -0.91475618 | P192: -2.0616984 | Q192: -2.5088304 | R192: -0.32686959 | S192: -0.84648922 | T192: -1.0201828 | U192: -0.76139492 | V192: -0.88419206 | W192: -1.6021652 | X192: 0.1847335 | Y192: -1.5199823 | Z192: -1.2913765 | AA192: -0.86423379 | AB192: -1.4432371 | AC192: -1.1376629 | AD192: 0.24322825 | AE192: 0.19005239 | AF192: 0.73419459 | AG192: 1.8755261 | AH192: 2.1367061 | AI192: 3.162081 | AJ192: 4.279784 | AK192: 3.5986433 | AL192: 1.3558797 | AM192: 0.42889958 | AN192: 1.8030616 | AO192: 5.3194311 | AP192: 8.7071827 | AQ192: 9.873098 | AR192: 12.872252 | AS192: 15.241022 | AT192: 16.428481 | AU192: 15.302023 | AV192: 15.656375 | AW192: 16.419944 | AX192: 27.373349 | AY192: 31.850962 | AZ192: 31.497021 | BA192: 27.963491 | BB192: 27.623392 | BC192: 31.299341 | BD192: 28.819325 | BE192: 29.520709 | BF192: 29.424429 | BG192: 29.948652 | BH192: 33.818108 | BI192: 40.7909 | BJ192: 50.98883 | BK192: 77.064599 | BL192: 98.105476 | BM192: 128.84105
D193: cash_flow_growth | E193: Media | F193: -8.6077542 | G193: -6.0123671 | H193: -4.8818907 | I193: -5.6241077 | J193: -7.5859423 | K193: -6.6089967 | L193: -8.0632292 | M193: -5.1731924 | N193: -7.0869118 | O193: -4.0771579 | P193: 2.4808674 | Q193: 2.2730909 | R193: 2.4865422 | S193: 2.010278 | T193: 2.7144649 | U193: 1.502946 | V193: 1.3849969 | W193: -0.36250647 | X193: -1.1181307 | Y193: -1.6027678 | Z193: -2.4311097 | AA193: -1.6564425 | AB193: -2.0917632 | AC193: -3.0461821 | AD193: -2.6846896 | AE193: -1.2106595 | AF193: 0.62335215 | AG193: -0.23154763 | AH193: 0.29506213 | AI193: -0.31599963 | AJ193: -2.769986 | AK193: -3.8341501 | AL193: -3.2021635 | AM193: -2.34004 | AN193: 2.1675442 | AO193: 7.0978861 | AP193: 10.644978 | AQ193: 11.646398 | AR193: 12.910074 | AS193: 13.675043 | AT193: 11.39225 | AU193: 10.874536 | AV193: 7.8611069 | AW193: 9.8349718 | AX193: 11.268082 | AY193: 17.107398 | AZ193: 16.25198 | BA193: 24.018851 | BB193: 18.68056 | BC193: 17.269477 | BD193: 29.831384 | BE193: 27.3933 | BF193: 30.133773 | BG193: 34.216343 | BH193: 7.7260681 | BI193: 7.9369588 | BJ193: 17.218995 | BK193: 16.167969 | BL193: 14.287424 | BM193: 15.239217
D196: Date | E196: Secteur | F196: Pilier | G196: Variable | H196: Mesure | I196: Score
D197: 46295 | E197: Materials | F197: Leverage | G197: net_debt_ebitda | H197: 1.22262 | I197: 4.8019126
D198: 46295 | E198: ConsStaples | F198: Leverage | G198: net_debt_ebitda | H198: 1.9202542 | I198: 2.4795082
D199: 46295 | E199: Retail | F199: Leverage | G199: net_debt_ebitda | H199: 0.49591342 | I199: 4.3306011
D200: 46295 | E200: Fin | F200: Leverage | G200: net_debt_ebitda | H200: -2.0866902 | I200: 9.0163934
D201: 46295 | E201: HealthCare | F201: Leverage | G201: net_debt_ebitda | H201: 1.7058441 | I201: 2.1653005
D202: 46295 | E202: Indus | F202: Leverage | G202: net_debt_ebitda | H202: 1.7344032 | I202: 2.6502732
D203: 46295 | E203: Oil | F203: Leverage | G203: net_debt_ebitda | H203: 1.0167123 | I203: 5.6352459
...

Sheet Reco_histo
A1: Date | B1: Top | N1: Worst
A2: Date | B2: Materials | C2: ConsStaples | D2: Retail | E2: Fin | F2: HealthCare | G2: Indus | H2: Oil | I2: Tech | J2: Telco | K2: Utili | L2: Travel & leisure | M2: Media | N2: Materials | O2: ConsStaples | P2: Retail | Q2: Fin | R2: HealthCare | S2: Indus | T2: Oil | U2: Tech | V2: Telco | W2: Utili | X2: Travel & leisure | Y2: Media
A3: 40235 | B3: 0 | C3: 0 | D3: 0 | E3: 0 | F3: 1 | G3: 0 | H3: 0 | I3: 1 | J3: 0 | K3: 0 | L3: 0 | M3: 0 | N3: 0 | O3: 0 | P3: 1 | Q3: 0 | R3: 0 | S3: 0 | T3: 0 | U3: 0 | V3: 1 | W3: 1 | X3: 0 | Y3: 0
A4: 40268 | B4: 0 | C4: 0 | D4: 1 | E4: 0 | F4: 1 | G4: 0 | H4: 0 | I4: 1 | J4: 0 | K4: 0 | L4: 0 | M4: 0 | N4: 0 | O4: 0 | P4: 0 | Q4: 1 | R4: 0 | S4: 0 | T4: 0 | U4: 0 | V4: 1 | W4: 1 | X4: 0 | Y4: 0
A5: 40298 | B5: 0 | C5: 1 | D5: 0 | E5: 0 | F5: 1 | G5: 0 | H5: 0 | I5: 1 | J5: 0 | K5: 0 | L5: 0 | M5: 0 | N5: 0 | O5: 0 | P5: 0 | Q5: 1 | R5: 0 | S5: 1 | T5: 0 | U5: 0 | V5: 0 | W5: 1 | X5: 0 | Y5: 0
A6: 40326 | B6: 0 | C6: 0 | D6: 0 | E6: 0 | F6: 0 | G6: 0 | H6: 0 | I6: 1 | J6: 0 | K6: 0 | L6: 0 | M6: 1 | N6: 0 | O6: 0 | P6: 0 | Q6: 0 | R6: 0 | S6: 1 | T6: 0 | U6: 0 | V6: 1 | W6: 1 | X6: 0 | Y6: 0
A7: 40359 | B7: 0 | C7: 1 | D7: 0 | E7: 0 | F7: 0 | G7: 0 | H7: 0 | I7: 1 | J7: 0 | K7: 0 | L7: 0 | M7: 1 | N7: 0 | O7: 0 | P7: 0 | Q7: 0 | R7: 0 | S7: 1 | T7: 0 | U7: 0 | V7: 1 | W7: 1 | X7: 0 | Y7: 0
A8: 40389 | B8: 0 | C8: 1 | D8: 1 | E8: 0 | F8: 0 | G8: 0 | H8: 0 | I8: 1 | J8: 0 | K8: 0 | L8: 0 | M8: 0 | N8: 0 | O8: 0 | P8: 0 | Q8: 0 | R8: 0 | S8: 1 | T8: 1 | U8: 0 | V8: 0 | W8: 1 | X8: 0 | Y8: 0
A9: 40421 | B9: 0 | C9: 1 | D9: 0 | E9: 0 | F9: 0 | G9: 0 | H9: 0 | I9: 1 | J9: 0 | K9: 0 | L9: 0 | M9: 0 | N9: 0 | O9: 0 | P9: 0 | Q9: 1 | R9: 0 | S9: 0 | T9: 0 | U9: 0 | V9: 1 | W9: 1 | X9: 0 | Y9: 0
A10: 40451 | B10: 0 | C10: 1 | D10: 0 | E10: 0 | F10: 0 | G10: 0 | H10: 0 | I10: 0 | J10: 0 | K10: 0 | L10: 0 | M10: 1 | N10: 0 | O10: 0 | P10: 0 | Q10: 0 | R10: 0 | S10: 1 | T10: 1 | U10: 0 | V10: 0 | W10: 1 | X10: 0 | Y10: 0
A11: 40480 | B11: 0 | C11: 1 | D11: 0 | E11: 0 | F11: 0 | G11: 0 | H11: 0 | I11: 1 | J11: 0 | K11: 0 | L11: 0 | M11: 0 | N11: 0 | O11: 0 | P11: 0 | Q11: 1 | R11: 0 | S11: 0 | T11: 1 | U11: 0 | V11: 0 | W11: 1 | X11: 0 | Y11: 0
A12: 40512 | B12: 0 | C12: 1 | D12: 0 | E12: 0 | F12: 0 | G12: 0 | H12: 0 | I12: 1 | J12: 1 | K12: 0 | L12: 0 | M12: 0 | N12: 0 | O12: 0 | P12: 0 | Q12: 0 | R12: 0 | S12: 1 | T12: 1 | U12: 0 | V12: 0 | W12: 1 | X12: 0 | Y12: 0
A13: 40543 | B13: 0 | C13: 1 | D13: 0 | E13: 0 | F13: 0 | G13: 0 | H13: 0 | I13: 1 | J13: 0 | K13: 0 | L13: 0 | M13: 1 | N13: 1 | O13: 0 | P13: 0 | Q13: 0 | R13: 0 | S13: 0 | T13: 0 | U13: 0 | V13: 1 | W13: 1 | X13: 0 | Y13: 0
A14: 40574 | B14: 0 | C14: 1 | D14: 0 | E14: 0 | F14: 0 | G14: 0 | H14: 0 | I14: 1 | J14: 0 | K14: 0 | L14: 0 | M14: 0 | N14: 0 | O14: 0 | P14: 0 | Q14: 1 | R14: 0 | S14: 1 | T14: 0 | U14: 0 | V14: 0 | W14: 1 | X14: 0 | Y14: 0
... A203: 46295 | B203: 1 | C203: 0 | D203: 0 | E203: 1 | F203: 0 | G203: 0 | H203: 0 | I203: 1 | J203: 0 | K203: 0 | L203: 0 | M203: 0 | N203: 0 | O203: 0 | P203: 0 | Q203: 0 | R203: 1 | S203: 0 | T203: 0 | U203: 0 | V203: 1 | W203: 1 | X203: 0 | Y203: 0

Sheet Config
B4: FACTSET Ids | C4: INDEX NAME | D4: Named Range | E4: Secto Name
B7: SP50 | C7: {=_xll.FDS(B7,"FG_COMPANY_NAME")} -> S&P 500 | D7: IND_Bench | F7: Nb of Const
B8: I00072 | C8: {=_xll.FDS(B8,"FG_COMPANY_NAME")} -> FTSE US / Basic Materials - IND | D8: IND_Mat | E8: Materials | F8: {=_xll.FDS(B8,"FTAW_NUMBER_IDX(0,0,D,""CLOSE"")")} -> 14
B9: I00144 | C9: {=_xll.FDS(B9,"FG_COMPANY_NAME")} -> FTSE US / Consumer Staples - IND | D9: IND_ConsGd | E9: ConsStaples | F9: {=_xll.FDS(B9,"FTAW_NUMBER_IDX(0,0,D,""CLOSE"")")} -> 26
B10: I01044 | C10: {=_xll.FDS(B10,"FG_COMPANY_NAME")} -> FTSE US / Retailers - SEC | D10: IND_Retail | E10: Retail | F10: {=_xll.FDS(B10,"FTAW_NUMBER_IDX(0,0,D,""CLOSE"")")} -> 20
B11: I00288 | C11: {=_xll.FDS(B11,"FG_COMPANY_NAME")} -> FTSE US / Financials - IND | D11: IND_Fin | E11: Fin | F11: {=_xll.FDS(B11,"FTAW_NUMBER_IDX(0,0,D,""CLOSE"")")} -> 68
B12: I21862 | C12: {=_xll.FDS(B12,"FG_COMPANY_NAME")} -> FTSE US / Health Care - IND | D12: IND_Health | E12: HealthCare | F12: {=_xll.FDS(B12,"FTAW_NUMBER_IDX(0,0,D,""CLOSE"")")} -> 48
B13: I00108 | C13: {=_xll.FDS(B13,"FG_COMPANY_NAME")} -> FTSE US / Industrials - IND | D13: IND_Indus | E13: Indus | F13: {=_xll.FDS(B13,"FTAW_NUMBER_IDX(0,0,D,""CLOSE"")")} -> 93
B14: I21852 | C14: {=_xll.FDS(B14,"FG_COMPANY_NAME")} -> FTSE US / Energy - IND | D14: IND_Oil | E14: Oil | F14: {=_xll.FDS(B14,"FTAW_NUMBER_IDX(0,0,D,""CLOSE"")")} -> 22
B15: I21904 | C15: {=_xll.FDS(B15,"FG_COMPANY_NAME")} -> FTSE US / Technology - IND | D15: IND_Tech | E15: Tech | F15: {=_xll.FDS(B15,"FTAW_NUMBER_IDX(0,0,D,""CLOSE"")")} -> 77
B16: I21881 | C16: {=_xll.FDS(B16,"FG_COMPANY_NAME")} -> FTSE US / Telecommunications - IND | D16: IND_Telco | E16: Telco | F16: {=_xll.FDS(B16,"FTAW_NUMBER_IDX(0,0,D,""CLOSE"")")} -> 12
B17: I00612 | C17: {=_xll.FDS(B17,"FG_COMPANY_NAME")} -> FTSE US / Utilities - IND | D17: IND_Utili | E17: Utili | F17: {=_xll.FDS(B17,"FTAW_NUMBER_IDX(0,0,D,""CLOSE"")")} -> 31
B18: I00936 | C18: {=_xll.FDS(B18,"FG_COMPANY_NAME")} -> FTSE US / Travel and Leisure - SEC | D18: IND_Travel | E18: Travel & leisure | F18: {=_xll.FDS(B18,"FTAW_NUMBER_IDX(0,0,D,""CLOSE"")")} -> 19
B19: I00972 | C19: {=_xll.FDS(B19,"FG_COMPANY_NAME")} -> FTSE US / Media - SEC | D19: IND_Media | E19: Media | F19: {=_xll.FDS(B19,"FTAW_NUMBER_IDX(0,0,D,""CLOSE"")")} -> 10

Sheet Returns_EQ
A1: StartDate: | B1: 36494 | D1: CUMRET TIME SERIES
A2: EndDate: | B2: =TODAY() -> 46321 | D2: EQUITY
B4: =IND_Bench -> SP50 | C4: =IND_Mat -> I00072 | D4: =IND_ConsGd -> I00144 | E4: =Ind_Retail -> I01044 | F4: =IND_Fin -> I00288 | G4: =IND_Health -> I21862 | H4: =IND_Indus -> I00108 | I4: =IND_Oil -> I21852 | J4: =IND_Tech -> I21904 | K4: =IND_Telco -> I21881 | L4: =IND_Utili -> I00612 | M4: =Ind_Travel -> I00936 | N4: =Ind_Media -> I00972
B5: WIUSAU Index | C5: {=_xll.FDS(C4,"FG_COMPANY_NAME")} -> FTSE US / Basic Materials - IND | D5: {=_xll.FDS(D4,"FG_COMPANY_NAME")} -> FTSE US / Consumer Staples - IND | E5: {=_xll.FDS(E4,"FG_COMPANY_NAME")} -> FTSE US / Retailers - SEC | F5: {=_xll.FDS(F4,"FG_COMPANY_NAME")} -> FTSE US / Financials - IND | G5: {=_xll.FDS(G4,"FG_COMPANY_NAME")} -> FTSE US / Health Care - IND | H5: {=_xll.FDS(H4,"FG_COMPANY_NAME")} -> FTSE US / Industrials - IND | I5: {=_xll.FDS(I4,"FG_COMPANY_NAME")} -> FTSE US / Energy - IND | J5: {=_xll.FDS(J4,"FG_COMPANY_NAME")} -> FTSE US / Technology - IND | ... N5: {=_xll.FDS(N4,"FG_COMPANY_NAME")} -> FTSE US / Media - SEC
B6: PX_LAST
A7: {=_xll.FDS(B4,"JULIAN(FG_TOTAL_RET_IDX(0,-20AY,M,USD).dates)")} -> 46295 | B7: {=_xll.BDH(B$5,B$6,$A7)} -> 3225.27 | C7: {=_xll.FDS(C4,"FG_TOTAL_RET_IDX(0,-20AY,M,USD)")} -> 3558.324 | D7: {=_xll.FDS(D4,"FG_TOTAL_RET_IDX(0,-20AY,M,USD)")} -> 5474.6365 | E7: {=_xll.FDS(E4,"FG_TOTAL_RET_IDX(0,-20AY,M,USD)")} -> 14229.157 | F7: {=_xll.FDS(F4,"FG_TOTAL_RET_IDX(0,-20AY,M,USD)")} -> 4570.9913 | G7: {=_xll.FDS(G4,"FG_TOTAL_RET_IDX(0,-20AY,M,USD)")} -> 8436.0269 | H7: {=_xll.FDS(H4,"FG_TOTAL_RET_IDX(0,-20AY,M,USD)")} -> 6895.6731 | I7: {=_xll.FDS(I4,"FG_TOTAL_RET_IDX(0,-20AY,M,USD)")} -> 5015.2666 | J7: {=_xll.FDS(J4,"FG_TOTAL_RET_IDX(0,-20AY,M,USD)")} -> 14299.439 | ... N7: {=_xll.FDS(N4,"FG_TOTAL_RET_IDX(0,-20AY,M,USD)")} -> 2946.7882
A8: 46265 | B8: {=_xll.BDH(B$5,B$6,$A8)} -> 3239.61 | C8: 3762.9848 | D8: 5684.2984 | E8: 14877.193 | F8: 4937.4159 | G8: 8492.9486 | H8: 7246.6364 | I8: 5167.1909 | J8: 13589.282 | K8: 1970.7942 | L8: 4646.6035 | M8: 5400.4193 | N8: 3210.2215
A9: 46234 | B9: {=_xll.BDH(B$5,B$6,$A9)} -> 3152.52 | C9: 3471.3642 | D9: 5690.6344 | E9: 15453.72 | F9: 4883.2421 | G9: 8083.0739 | H9: 7355.5349 | I9: 4830.8882 | J9: 12967.483 | K9: 1877.7157 | L9: 4863.5017 | M9: 5452.2449 | N9: 2891.0719
A10: 46203 | B10: {=_xll.BDH(B$5,B$6,$A10)} -> 3156.52 | C10: 3481.7116 | D10: 5536.4082 | E10: 14387.51 | F10: 4617.6405 | G10: 7930.3409 | H10: 7350.7074 | I10: 4303.2845 | J10: 13364.297 | K10: 1872.4865 | L10: 4961.5906 | M10: 5342.3585 | N10: 2839.7096
A11: 46171 | B11: {=_xll.BDH(B$5,B$6,$A11)} -> 3187.85 | C11: 3522.3061 | D11: 5382.1341 | E11: 15354.887 | F11: 4421.5689 | G11: 7453.811 | H11: 6978.0371 | I11: 4531.4938 | J11: 13852.972 | K11: 1989.346 | L11: 4819.3727 | M11: 5153.8873 | N11: 3178.6035
A12: 46142 | B12: {=_xll.BDH(B$5,B$6,$A12)} -> 3027.81 | C12: 3457.2837 | D12: 5413.206 | E12: 15667.723 | F12: 4472.3023 | G12: 7253.1549 | H12: 7016.5757 | I12: 4785.7397 | J12: 12257.178 | K12: 1875.229 | L12: 5093.2443 | M12: 5224.7371 | N12: 3294.4772
A13: 46112 | B13: {=_xll.BDH(B$5,B$6,$A13)} -> 2742.79 | C13: 3374.8673 | D13: 5277.8575 | E13: 13642.816 | F13: 4249.3372 | G13: 7312.5039 | H13: 6538.6756 | I13: 4955.075 | J13: 10281.511 | K13: 1743.9377 | L13: 5000.9301 | M13: 5072.0153 | N13: 3296.7314
A14: 46080 | B14: {=_xll.BDH(B$5,B$6,$A14)} -> 2888.81 | C14: 3597.4535 | D14: 5841.2879 | E14: 14082.455 | F14: 4394.745 | G14: 7919.2561 | H14: 7102.7584 | I14: 4487.9213 | J14: 10804.749 | K14: 1791.7456 | L14: 5167.3238 | M14: 5441.16 | N14: 3406.7778
A15: 46052 | B15: {=_xll.BDH(B$5,B$6,$A15)} -> 2918.3 | C15: 3257.2615 | D15: 5370.1272 | E15: 14713.59 | F15: 4566.1287 | G15: 7685.0313 | H15: 6814.8819 | I15: 4109.6829 | J15: 11379.16 | K15: 1695.6762 | L15: 4694.3859 | M15: 5421.5162 | N15: 3247.1842
A16: 46022 | B16: {=_xll.BDH(B$5,B$6,$A16)} -> 2885.85 | C16: 2951.9598 | D16: 5035.4039 | E16: 14019.222 | F16: 4617.2261 | G16: 7706.5299 | H16: 6609.9184 | I16: 3608.4136 | J16: 11401.287 | K16: 1613.5747 | L16: 4633.4286 | M16: 5382.848 | N16: 3520.7021
A17: 45989 | B17: {=_xll.BDH(B$5,B$6,$A17)} -> 2889.9 | C17: 2850.7925 | D17: 5158.742 | E17: 14203.757 | F17: 4487.3493 | G17: 7808.6314 | H17: 6479.8317 | I17: 3609.423 | J17: 11461.272 | K17: 1609.0313 | L17: 4865.6454 | M17: 5189.6749 | N17: 3626.8337
A18: 45961 | B18: {=_xll.BDH(B$5,B$6,$A18)} -> 2891.33 | C18: 2753.8575 | D18: 4950.7425 | E18: 14362.542 | F18: 4368.8437 | G18: 7153.6004 | H18: 6511.6907 | I18: 3527.5518 | J18: 11728.024 | K18: 1627.2263 | L18: 4761.4598 | M18: 5050.5235 | N18: 3810.4342
A19: 45930 | B19: {=_xll.BDH(B$5,B$6,$A19)} -> 2827.68 | C19: 2935.7704 | D19: 5064.755 | E19: 13839.359 | F19: 4510.4196 | G19: 6917.045 | H19: 6489.8481 | I19: 3565.3071 | J19: 11049.855 | K19: 1689.3799 | L19: 4710.8779 | M19: 5285.1045 | N19: 3976.6448
... A246: 39021 | B246: {=_xll.BDH(B$5,B$6,$A246)} -> 571.29 | C246: 669.21 | D246: 893.92 | E246: 1138.21 | F246: 1342.54 | G246: 1127.66 | H246: 1005.84 | I246: 1353.33 | J246: 556.44 | K246: 649.09 | L246: 966.14 | M246: 766.03 | N246: 665.54

Sheet Leverage_FMA
A1: Time frame | AD1: Net Debt to EBITDA
A2: 60 | AD2: FMA_NDEBT_EBITDA
AD3: Historical Ratio
B6: Materials | C6: ConsStaples | D6: Retail | E6: Fin | F6: HealthCare | G6: Indus | H6: Oil | I6: Tech | J6: Telco | K6: Utili | L6: Travel & leisure | M6: Media | P6: Materials | Q6: ConsStaples | R6: Retail | S6: Fin | T6: HealthCare | U6: Indus | V6: Oil | W6: Tech | X6: Telco | Y6: Utili | Z6: Travel & leisure | AA6: Media | AD6: Materials | AE6: ConsStaples | AF6: Retail | AG6: Fin | AH6: HealthCare | AI6: Indus | AJ6: Oil | AK6: Tech | AL6: Telco | AM6: Utili | AN6: Travel & leisure | AO6: Media | AP6: Materials | AQ6: ConsStaples | AR6: Retail | AS6: Fin | AT6: HealthCare | AU6: Indus | AV6: Oil | AW6: Tech | AX6: Telco | AY6: Utili | AZ6: Travel & leisure | BA6: Media | BQ6: Materials | BR6: ConsStaples | BS6: Retail | BT6: Fin | BU6: HealthCare | BV6: Indus | BW6: Oil | BX6: Tech | BY6: Telco | BZ6: Utili | CA6: Travel & leisure | CB6: Media | CC6: Materials | CD6: ConsStaples | CE6: Retail | CF6: Fin | CG6: HealthCare | CH6: Indus | CI6: Oil | CJ6: Tech | CK6: Telco | CL6: Utili | CM6: Travel & leisure | CN6: Media | DD6: Materials | DE6: ConsStaples | DF6: Retail | DG6: Fin | DH6: HealthCare | DI6: Indus | DJ6: Oil | DK6: Tech | DL6: Telco | DM6: Utili | DN6: Travel & leisure | DO6: Media | DP6: Materials | DQ6: ConsStaples | DR6: Retail | DS6: Fin | DT6: HealthCare | DU6: Indus | DV6: Oil | DW6: Tech | DX6: Telco | DY6: Utili | DZ6: Travel & leisure | EA6: Media | EQ6: Materials | ER6: ConsStaples | ES6: Retail | ET6: Fin | EU6: HealthCare | EV6: Indus | EW6: Oil | EX6: Tech | EY6: Telco | EZ6: Utili | FA6: Travel & leisure | FB6: Media | FC6: Materials | FD6: ConsStaples | FE6: Retail | FF6: Fin | FG6: HealthCare | FH6: Indus | FI6: Oil | FJ6: Tech | FK6: Telco | FL6: Utili | FM6: Travel & leisure | FN6: Media | GD6: Materials | GE6: ConsStaples | GF6: Retail | GG6: Fin | GH6: HealthCare | GI6: Indus | GJ6: Oil | GK6: Tech | GL6: Telco | GM6: Utili | GN6: Travel & leisure | GO6: Media | GP6: Materials | GQ6: ConsStaples | GR6: Retail | GS6: Fin | GT6: HealthCare | GU6: Indus | GV6: Oil | GW6: Tech | GX6: Telco | GY6: Utili | GZ6: Travel & leisure | HA6: Media
AD7: I00072 | AE7: I00144 | AF7: I01044 | AG7: I00288 | AH7: I21862 | AI7: I00108 | AJ7: I21852 | AK7: I21904 | AL7: I21881 | AM7: I00612 | AN7: I00936 | AO7: I00972 | AP7: diff vs. moy | AQ7: diff vs. moy | AR7: diff vs. moy | AS7: diff vs. moy | AT7: diff vs. moy | AU7: diff vs. moy | AV7: diff vs. moy | AW7: diff vs. moy | AX7: diff vs. moy | AY7: diff vs. moy | AZ7: diff vs. moy | BA7: diff vs. moy | BQ7: I00072 | BR7: I00144 | BS7: I01044 | BT7: I00288 | BU7: I21862 | BV7: I00108 | BW7: I21852 | BX7: I21904 | BY7: I21881 | BZ7: I00612 | CA7: I00936 | CB7: I00972 | CC7: diff vs. moy | CD7: diff vs. moy | CE7: diff vs. moy | CF7: diff vs. moy | CG7: diff vs. moy | CH7: diff vs. moy | CI7: diff vs. moy | CJ7: diff vs. moy | CK7: diff vs. moy | CL7: diff vs. moy | CM7: diff vs. moy | CN7: diff vs. moy | DD7: I00072 | DE7: I00144 | DF7: I01044 | DG7: I00288 | DH7: I21862 | DI7: I00108 | DJ7: I21852 | DK7: I21904 | DL7: I21881 | DM7: I00612 | DN7: I00936 | DO7: I00972 | DP7: diff vs. moy | DQ7: diff vs. moy | DR7: diff vs. moy | DS7: diff vs. moy | DT7: diff vs. moy | DU7: diff vs. moy | DV7: diff vs. moy | DW7: diff vs. moy | DX7: diff vs. moy | DY7: diff vs. moy | DZ7: diff vs. moy | EA7: diff vs. moy | EQ7: I00072 | ER7: I00144 | ES7: I01044 | ET7: I00288 | EU7: I21862 | EV7: I00108 | EW7: I21852 | EX7: I21904 | EY7: I21881 | EZ7: I00612 | FA7: I00936 | FB7: I00972 | FC7: diff vs. moy | FD7: diff vs. moy | FE7: diff vs. moy | FF7: diff vs. moy | FG7: diff vs. moy | FH7: diff vs. moy | FI7: diff vs. moy | FJ7: diff vs. moy | FK7: diff vs. moy | FL7: diff vs. moy | FM7: diff vs. moy | FN7: diff vs. moy | GD7: I00072 | GE7: I00144 | GF7: I01044 | GG7: I00288 | GH7: I21862 | GI7: I00108 | GJ7: I21852 | GK7: I21904 | GL7: I21881 | GM7: I00612 | GN7: I00936 | GO7: I00972 | GP7: diff vs. moy | GQ7: diff vs. moy | GR7: diff vs. moy | GS7: diff vs. moy | GT7: diff vs. moy | GU7: diff vs. moy | GV7: diff vs. moy | GW7: diff vs. moy | GX7: diff vs. moy | GY7: diff vs. moy | GZ7: diff vs. moy | HA7: diff vs. moy
A8: =AC8 -> 46295 | AC8: {=_xll.FDS(AD7,"JULIAN(FMA_NDEBT_EBITDA(LTM,0,-20AY,M,EUR,""PORTAGG"",""MEANR"").dates)")} -> 46295 | AD8: {=_xll.FDS(AD7,"FMA_NDEBT_EBITDA(LTM,0,-20AY,M,EUR,""PORTAGG"",""MEANR"")")} -> 1.22262 | AE8: {=_xll.FDS(AE7,"FMA_NDEBT_EBITDA(LTM,0,-20AY,M,EUR,""PORTAGG"",""MEANR"")")} -> 1.9202542 | AF8: {=_xll.FDS(AF7,"FMA_NDEBT_EBITDA(LTM,0,-20AY,M,EUR,""PORTAGG"",""MEANR"")")} -> 0.49591342 | AG8: {=_xll.FDS(AG7,"FMA_NDEBT_EBITDA(LTM,0,-20AY,M,EUR,""PORTAGG"",""MEANR"")")} -> -2.0866902 | AH8: {=_xll.FDS(AH7,"FMA_NDEBT_EBITDA(LTM,0,-20AY,M,EUR,""PORTAGG"",""MEANR"")")} -> 1.7058441 | AI8: {=_xll.FDS(AI7,"FMA_NDEBT_EBITDA(LTM,0,-20AY,M,EUR,""PORTAGG"",""MEANR"")")} -> 1.7344032 | AJ8: {=_xll.FDS(AJ7,"FMA_NDEBT_EBITDA(LTM,0,-20AY,M,EUR,""PORTAGG"",""MEANR"")")} -> 1.0167123 | AK8: {=_xll.FDS(AK7,"FMA_NDEBT_EBITDA(LTM,0,-20AY,M,EUR,""PORTAGG"",""MEANR"")")} -> 0.10783016 | ... AO8: {=_xll.FDS(AO7,"FMA_NDEBT_EBITDA(LTM,0,-20AY,M,EUR,""PORTAGG"",""MEANR"")")} -> 1.0694065 | EQ8: {=_xll.FDS(EQ7,"FMA_FCF_DEBT(LTM,0,-20AY,M,""PORTAGG"")")} -> 22.028238 | ER8: {=_xll.FDS(ER7,"FMA_FCF_DEBT(LTM,0,-20AY,M,""PORTAGG"")")} -> 25.178694 | ES8: {=_xll.FDS(ES7,"FMA_FCF_DEBT(LTM,0,-20AY,M,""PORTAGG"")")} -> 17.857379 | ET8: {=_xll.FDS(ET7,"FMA_FCF_DEBT(LTM,0,-20AY,M,""PORTAGG"")")} -> 22.209445 | EU8: {=_xll.FDS(EU7,"FMA_FCF_DEBT(LTM,0,-20AY,M,""PORTAGG"")")} -> 27.543317 | EV8: {=_xll.FDS(EV7,"FMA_FCF_DEBT(LTM,0,-20AY,M,""PORTAGG"")")} -> 26.948095 | EW8: {=_xll.FDS(EW7,"FMA_FCF_DEBT(LTM,0,-20AY,M,""PORTAGG"")")} -> 36.24289 | EX8: {=_xll.FDS(EX7,"FMA_FCF_DEBT(LTM,0,-20AY,M,""PORTAGG"")")} -> 64.397494 | ... FB8: {=_xll.FDS(FB7,"FMA_FCF_DEBT(LTM,0,-20AY,M,""PORTAGG"")")} -> 26.131654
A9: =AC9 -> 46265 | AC9: 46265 | AD9: 1.2514925 | AE9: 1.9310916 | AF9: 0.53269315 | AG9: -2.1831564 | AH9: 1.7062165 | AI9: 1.7579617 | AJ9: 1.0136619 | AK9: 0.12347289 | AL9: 2.5518277 | AM9: 5.5488992 | AN9: 1.733316 | AO9: 1.0492613 | EQ9: 22.169631 | ER9: 25.169875 | ES9: 16.257858 | ET9: 22.408107 | EU9: 27.597077 | EV9: 26.878169 | EW9: 36.317843 | EX9: 64.480145 | EY9: 16.316475 | EZ9: -4.7724665 | FA9: 22.623869 | FB9: 26.712185
A10: =AC10 -> 46234 | AC10: 46234 | AD10: 1.297263 | AE10: 1.9486857 | AF10: 0.43890628 | AG10: -2.4131584 | AH10: 1.6465302 | AI10: 1.834568 | AJ10: 1.3267451 | AK10: 0.17240256 | AL10: 2.5969566 | AM10: 5.5988943 | AN10: 1.76813 | AO10: 1.080104 | EQ10: 20.120482 | ER10: 23.16477 | ES10: 19.516785 | ET10: 20.265794 | EU10: 25.857596 | EV10: 24.160666 | EW10: 21.710299 | EX10: 68.570966 | EY10: 15.834804 | EZ10: -4.6821696 | FA10: 22.429876 | FB10: 26.672695
A11: =AC11 -> 46203 | AC11: 46203 | AD11: 1.3023401 | AE11: 1.951402 | AF11: 0.44562671 | AG11: -2.4102907 | AH11: 1.6461856 | AI11: 1.828593 | AJ11: 1.326798 | AK11: 0.18876422 | AL11: 2.5966706 | AM11: 5.6003116 | AN11: 1.7939033 | AO11: 1.0777663 | EQ11: 20.025377 | ER11: 23.14006 | ES11: 19.583745 | ET11: 20.275639 | EU11: 25.854042 | EV11: 24.189973 | EW11: 21.674663 | EX11: 66.179178 | EY11: 15.838289 | EZ11: -4.6928777 | FA11: 22.145305 | FB11: 26.681741
A12: =AC12 -> 46171 | AC12: 46171 | AD12: 1.3042171 | AE12: 1.964045 | AF12: 0.44271813 | AG12: -2.3921264 | AH12: 1.6473563 | AI12: 1.814162 | AJ12: 1.3251165 | AK12: 0.19723292 | AL12: 2.6092591 | AM12: 5.6004514 | AN12: 1.7872676 | AO12: 1.0620636 | EQ12: 19.798438 | ER12: 22.688785 | ES12: 18.885429 | ET12: 20.354222 | EU12: 26.163476 | EV12: 24.181355 | EW12: 21.724259 | EX12: 65.044022 | EY12: 16.057348 | EZ12: -4.6447167 | FA12: 22.199349 | FB12: 27.7713
A13: =AC13 -> 46142 | AC13: 46142 | AD13: 1.3945794 | AE13: 1.9538196 | AF13: 0.34297887 | AG13: -2.4002896 | AH13: 1.4906195 | AI13: 1.6843348 | AJ13: 1.3503612 | AK13: 0.14340644 | AL13: 2.4549529 | AM13: 5.3336752 | AN13: 1.9047889 | AO13: 1.087797 | EQ13: 13.70179 | ER13: 23.583573 | ES13: 26.185659 | ET13: 23.094129 | EU13: 26.64263 | EV13: 23.94737 | EW13: 25.413688 | EX13: 67.67497 | EY13: 16.938053 | EZ13: -3.9518894 | FA13: 20.181667 | FB13: 26.269652
A14: =AC14 -> 46112 | AC14: 46112 | AD14: 1.3986079 | AE14: 1.9430183 | AF14: 0.34626493 | AG14: -2.401943 | AH14: 1.4859497 | AI14: 1.6974439 | AJ14: 1.3502905 | AK14: 0.14735708 | AL14: 2.4544535 | AM14: 5.3355811 | AN14: 1.9335784 | AO14: 1.0831439 | EQ14: 13.63443 | ER14: 23.644097 | ES14: 26.281066 | ET14: 23.088665 | EU14: 26.677757 | EV14: 23.819256 | EW14: 25.414138 | EX14: 68.721587 | EY14: 16.936163 | EZ14: -3.9572561 | FA14: 19.737091 | FB14: 26.322191
A15: =AC15 -> 46080 | AC15: 46080 | AD15: 1.3454808 | AE15: 1.9540896 | AF15: 0.38200364 | AG15: -2.3609158 | AH15: 1.4953968 | AI15: 1.7614696 | AJ15: 1.3516058 | AK15: 0.13606495 | AL15: 2.4573801 | AM15: 5.3383424 | AN15: 1.9206474 | AO15: 1.0929129 | EQ15: 14.812006 | ER15: 23.057229 | ES15: 26.06676 | ET15: 23.3038 | EU15: 26.541745 | EV15: 23.222357 | EW15: 25.377123 | EX15: 67.285858 | EY15: 17.015715 | EZ15: -3.9682024 | FA15: 19.859676 | FB15: 26.166689
A16: =AC16 -> 46052 | AC16: 46052 | AD16: 1.3322092 | AE16: 2.1267018 | AF16: 0.43472042 | AG16: -2.1992676 | AH16: 1.4855902 | AI16: 1.8570029 | AJ16: 1.3950692 | AK16: 0.16842615 | AL16: 2.472918 | AM16: 5.1370716 | AN16: 1.8646833 | AO16: 1.0612309 | EQ16: 13.799446 | ER16: 20.952896 | ES16: 28.652083 | ET16: 17.63594 | EU16: 28.324013 | EV16: 20.947133 | EW16: 23.67321 | EX16: 67.054677 | EY16: 17.493288 | EZ16: -3.6301511 | FA16: 20.992604 | FB16: 30.256621
A17: =AC17 -> 46022 | AC17: 46022 | AD17: 1.3329415 | AE17: 2.1273568 | AF17: 0.45029812 | AG17: -2.2074523 | AH17: 1.4853458 | AI17: 1.8591478 | AJ17: 1.3950851 | AK17: 0.16712475 | AL17: 2.4728743 | AM17: 5.1104657 | AN17: 1.875766 | AO17: 1.1039469 | EQ17: 13.779905 | ER17: 20.973518 | ES17: 27.892311 | ET17: 17.579251 | EU17: 28.327084 | EV17: 20.761299 | EW17: 23.672871 | EX17: 67.814725 | EY17: 17.494732 | EZ17: -3.6129912 | FA17: 21.165563 | FB17: 28.318405
A18: =AC18 -> 45989 | AC18: 45989 | AD18: 1.3334097 | AE18: 2.1406914 | AF18: 0.38444418 | AG18: -2.1943948 | AH18: 1.488249 | AI18: 1.8544167 | AJ18: 1.3908199 | AK18: 0.18163597 | AL18: 2.4760093 | AM18: 5.1086292 | AN18: 1.8788476 | AO18: 1.1049358 | EQ18: 13.775289 | ER18: 20.666862 | ES18: 28.719771 | ET18: 17.644912 | EU18: 28.341371 | EV18: 20.893344 | EW18: 23.745181 | EX18: 66.46091 | EY18: 17.55322 | EZ18: -3.6169868 | FA18: 21.113454 | FB18: 28.337697
A19: =AC19 -> 45961 | AC19: 45961 | AD19: 1.4321253 | AE19: 2.2117744 | AF19: 0.40033361 | AG19: -2.1688528 | AH19: 1.6455408 | AI19: 1.8981327 | AJ19: 1.3480331 | AK19: 0.20762765 | AL19: 2.4963151 | AM19: 5.2155821 | AN19: 1.8588138 | AO19: 1.0684302 | EQ19: 11.415908 | ER19: 18.005422 | ES19: 29.686478 | ET19: 13.197056 | EU19: 26.793546 | EV19: 20.049865 | EW19: 25.434467 | EX19: 64.320332 | EY19: 17.188696 | EZ19: -3.5905734 | FA19: 21.030155 | FB19: 30.116858
A20: =AC20 -> 45930 | AC20: 45930 | AD20: 1.4335161 | AE20: 2.2254003 | AF20: 0.39452372 | AG20: -2.1761558 | AH20: 1.6460201 | AI20: 1.9186422 | AJ20: 1.346593 | AK20: 0.20955749 | AL20: 2.4960932 | AM20: 5.216691 | AN20: 1.8710606 | AO20: 1.0692738 | EQ20: 11.393596 | ER20: 17.951059 | ES20: 29.764498 | ET20: 13.114791 | EU20: 26.78766 | EV20: 19.755669 | EW20: 25.467155 | EX20: 64.531459 | EY20: 17.189262 | EZ20: -3.5936362 | FA20: 20.839338 | FB20: 30.101461
... A247: =AC247 -> 39021 | AC247: 39021 | AD247: 1.1801396 | AE247: 1.943879 | AF247: 0.58216393 | AG247: 4.7691286 | AH247: 0.33960662 | AI247: 3.1670156 | AJ247: 0.28117766 | AK247: -0.94805623 | AL247: 1.7672021 | AM247: 3.3114988 | AN247: 2.2517301 | AO247: 2.7919478 | EQ247: 20.031557 | ER247: 6.3110464 | ES247: 32.538305 | ET247: 0.83807972 | EU247: 45.008615 | EV247: 12.233242 | EW247: 51.023088 | EX247: 89.809664 | EY247: 16.018093 | EZ247: 0.74148044 | FA247: 3.4770362 | FB247: 16.966261

Sheet Margin_FMA
A1: Time frame | BQ1: Operating Margin | DD1: Net Margin | GD1: EBITDA Margin
A2: 60 | BQ2: FMA_OPER_INC_SALES | DD2: FMA_NET_MGN | GD2: FMA_EBITDA_MARGIN
BQ3: Historical Ratio | DD3: Historical Ratio | GD3: Historical Ratio
B6: Materials | C6: ConsStaples | D6: Retail | E6: Fin | F6: HealthCare | G6: Indus | H6: Oil | I6: Tech | J6: Telco | K6: Utili | L6: Travel & leisure | M6: Media | P6: Materials | Q6: ConsStaples | R6: Retail | S6: Fin | T6: HealthCare | U6: Indus | V6: Oil | W6: Tech | X6: Telco | Y6: Utili | Z6: Travel & leisure | AA6: Media | AD6: Materials | AE6: ConsStaples | AF6: Retail | AG6: Fin | AH6: HealthCare | AI6: Indus | AJ6: Oil | AK6: Tech | AL6: Telco | AM6: Utili | AN6: Travel & leisure | AO6: Media | AP6: Materials | AQ6: ConsStaples | AR6: Retail | AS6: Fin | AT6: HealthCare | AU6: Indus | AV6: Oil | AW6: Tech | AX6: Telco | AY6: Utili | AZ6: Travel & leisure | BA6: Media | BQ6: Materials | BR6: ConsStaples | BS6: Retail | BT6: Fin | BU6: HealthCare | BV6: Indus | BW6: Oil | BX6: Tech | BY6: Telco | BZ6: Utili | CA6: Travel & leisure | CB6: Media | CC6: Materials | CD6: ConsStaples | CE6: Retail | CF6: Fin | CG6: HealthCare | CH6: Indus | CI6: Oil | CJ6: Tech | CK6: Telco | CL6: Utili | CM6: Travel & leisure | CN6: Media | DD6: Materials | DE6: ConsStaples | DF6: Retail | DG6: Fin | DH6: HealthCare | DI6: Indus | DJ6: Oil | DK6: Tech | DL6: Telco | DM6: Utili | DN6: Travel & leisure | DO6: Media | DP6: Materials | DQ6: ConsStaples | DR6: Retail | DS6: Fin | DT6: HealthCare | DU6: Indus | DV6: Oil | DW6: Tech | DX6: Telco | DY6: Utili | DZ6: Travel & leisure | EA6: Media | EQ6: Materials | ER6: ConsStaples | ES6: Retail | ET6: Fin | EU6: HealthCare | EV6: Indus | EW6: Oil | EX6: Tech | EY6: Telco | EZ6: Utili | FA6: Travel & leisure | FB6: Media | FC6: Materials | FD6: ConsStaples | FE6: Retail | FF6: Fin | FG6: HealthCare | FH6: Indus | FI6: Oil | FJ6: Tech | FK6: Telco | FL6: Utili | FM6: Travel & leisure | FN6: Media | GD6: Materials | GE6: ConsStaples | GF6: Retail | GG6: Fin | GH6: HealthCare | GI6: Indus | GJ6: Oil | GK6: Tech | GL6: Telco | GM6: Utili | GN6: Travel & leisure | GO6: Media | GP6: Materials | GQ6: ConsStaples | GR6: Retail | GS6: Fin | GT6: HealthCare | GU6: Indus | GV6: Oil | GW6: Tech | GX6: Telco | GY6: Utili | GZ6: Travel & leisure | HA6: Media
AD7: I00072 | AE7: I00144 | AF7: I01044 | AG7: I00288 | AH7: I21862 | AI7: I00108 | AJ7: I21852 | AK7: I21904 | AL7: I21881 | AM7: I00612 | AN7: I00936 | AO7: I00972 | AP7: diff vs. moy | AQ7: diff vs. moy | AR7: diff vs. moy | AS7: diff vs. moy | AT7: diff vs. moy | AU7: diff vs. moy | AV7: diff vs. moy | AW7: diff vs. moy | AX7: diff vs. moy | AY7: diff vs. moy | AZ7: diff vs. moy | BQ7: I00072 | BR7: I00144 | BS7: I01044 | BT7: I00288 | BU7: I21862 | BV7: I00108 | BW7: I21852 | BX7: I21904 | BY7: I21881 | BZ7: I00612 | CA7: I00936 | CB7: I00972 | CC7: diff vs. moy | CD7: diff vs. moy | CE7: diff vs. moy | CF7: diff vs. moy | CG7: diff vs. moy | CH7: diff vs. moy | CI7: diff vs. moy | CJ7: diff vs. moy | CK7: diff vs. moy | CL7: diff vs. moy | CM7: diff vs. moy | DD7: I00072 | DE7: I00144 | DF7: I01044 | DG7: I00288 | DH7: I21862 | DI7: I00108 | DJ7: I21852 | DK7: I21904 | DL7: I21881 | DM7: I00612 | DN7: I00936 | DO7: I00972 | DP7: diff vs. moy | DQ7: diff vs. moy | DR7: diff vs. moy | DS7: diff vs. moy | DT7: diff vs. moy | DU7: diff vs. moy | DV7: diff vs. moy | DW7: diff vs. moy | DX7: diff vs. moy | DY7: diff vs. moy | DZ7: diff vs. moy | EQ7: I00072 | ER7: I00144 | ES7: I01044 | ET7: I00288 | EU7: I21862 | EV7: I00108 | EW7: I21852 | EX7: I21904 | EY7: I21881 | EZ7: I00612 | FA7: I00936 | FB7: I00972 | FC7: diff vs. moy | FD7: diff vs. moy | FE7: diff vs. moy | FF7: diff vs. moy | FG7: diff vs. moy | FH7: diff vs. moy | FI7: diff vs. moy | FJ7: diff vs. moy | FK7: diff vs. moy | FL7: diff vs. moy | FM7: diff vs. moy | GD7: I00072 | GE7: I00144 | GF7: I01044 | GG7: I00288 | GH7: I21862 | GI7: I00108 | GJ7: I21852 | GK7: I21904 | GL7: I21881 | GM7: I00612 | GN7: I00936 | GO7: I00972 | GP7: diff vs. moy | GQ7: diff vs. moy | GR7: diff vs. moy | GS7: diff vs. moy | GT7: diff vs. moy | GU7: diff vs. moy | GV7: diff vs. moy | GW7: diff vs. moy | GX7: diff vs. moy | GY7: diff vs. moy | GZ7: diff vs. moy
A8: =AC8 -> 46295 | AC8: {=_xll.FDS(AD7,"JULIAN(FMA_GROSS_MARGIN(LTM,0,-20AY,M,EUR,""PORTAGG"",""MEANR"").dates)")} -> 46295 | BQ8: {=_xll.FDS(BQ7,"FMA_OPER_INC_SALES(LTM,0,-20AY,M,""PORTAGG"")")} -> 19.657374 | BR8: {=_xll.FDS(BR7,"FMA_OPER_INC_SALES(LTM,0,-20AY,M,""PORTAGG"")")} -> 6.9512161 | BS8: {=_xll.FDS(BS7,"FMA_OPER_INC_SALES(LTM,0,-20AY,M,""PORTAGG"")")} -> 8.9815098 | BT8: {=_xll.FDS(BT7,"FMA_OPER_INC_SALES(LTM,0,-20AY,M,""PORTAGG"")")} -> 21.658118 | BU8: {=_xll.FDS(BU7,"FMA_OPER_INC_SALES(LTM,0,-20AY,M,""PORTAGG"")")} -> 12.913112 | BV8: {=_xll.FDS(BV7,"FMA_OPER_INC_SALES(LTM,0,-20AY,M,""PORTAGG"")")} -> 16.237674 | BW8: {=_xll.FDS(BW7,"FMA_OPER_INC_SALES(LTM,0,-20AY,M,""PORTAGG"")")} -> 13.425094 | BX8: {=_xll.FDS(BX7,"FMA_OPER_INC_SALES(LTM,0,-20AY,M,""PORTAGG"")")} -> 34.782338 | ... CB8: {=_xll.FDS(CB7,"FMA_OPER_INC_SALES(LTM,0,-20AY,M,""PORTAGG"")")} -> 17.178344 | DD8: {=_xll.FDS(DD7,"FMA_NET_MGN(LTM,0,-20AY,M,""PORTAGG"")")} -> 12.336806 | DE8: {=_xll.FDS(DE7,"FMA_NET_MGN(LTM,0,-20AY,M,""PORTAGG"")")} -> 4.979818 | DF8: {=_xll.FDS(DF7,"FMA_NET_MGN(LTM,0,-20AY,M,""PORTAGG"")")} -> 7.0708821 | DG8: {=_xll.FDS(DG7,"FMA_NET_MGN(LTM,0,-20AY,M,""PORTAGG"")")} -> 16.054846 | DH8: {=_xll.FDS(DH7,"FMA_NET_MGN(LTM,0,-20AY,M,""PORTAGG"")")} -> 9.2893927 | DI8: {=_xll.FDS(DI7,"FMA_NET_MGN(LTM,0,-20AY,M,""PORTAGG"")")} -> 12.887893 | DJ8: {=_xll.FDS(DJ7,"FMA_NET_MGN(LTM,0,-20AY,M,""PORTAGG"")")} -> 9.7795478 | DK8: {=_xll.FDS(DK7,"FMA_NET_MGN(LTM,0,-20AY,M,""PORTAGG"")")} -> 30.22492 | ... DO8: {=_xll.FDS(DO7,"FMA_NET_MGN(LTM,0,-20AY,M,""PORTAGG"")")} -> 11.411406 | GD8: {=_xll.FDS(EQ7,"FMA_EBITDA_MARGIN(LTM,0,-20AY,M,""PORTAGG"")")} -> 27.295065 | GE8: {=_xll.FDS(ER7,"FMA_EBITDA_MARGIN(LTM,0,-20AY,M,""PORTAGG"")")} -> 8.4210974 | GF8: {=_xll.FDS(ES7,"FMA_EBITDA_MARGIN(LTM,0,-20AY,M,""PORTAGG"")")} -> 13.587507 | GG8: {=_xll.FDS(ET7,"FMA_EBITDA_MARGIN(LTM,0,-20AY,M,""PORTAGG"")")} -> 28.346714 | GH8: {=_xll.FDS(EU7,"FMA_EBITDA_MARGIN(LTM,0,-20AY,M,""PORTAGG"")")} -> 32.941353 | GI8: {=_xll.FDS(EV7,"FMA_EBITDA_MARGIN(LTM,0,-20AY,M,""PORTAGG"")")} -> 21.062697 | GJ8: {=_xll.FDS(EW7,"FMA_EBITDA_MARGIN(LTM,0,-20AY,M,""PORTAGG"")")} -> 21.631408 | GK8: {=_xll.FDS(EX7,"FMA_EBITDA_MARGIN(LTM,0,-20AY,M,""PORTAGG"")")} -> 41.002375 | ... GO8: {=_xll.FDS(FB7,"FMA_EBITDA_MARGIN(LTM,0,-20AY,M,""PORTAGG"")")} -> 29.294221
A9: =AC9 -> 46265 | AC9: 46265 | BQ9: 19.428011 | BR9: 6.9395252 | BS9: 8.7905959 | BT9: 21.452905 | BU9: 12.978206 | BV9: 16.288865 | BW9: 13.389626 | BX9: 34.012052 | BY9: 21.140949 | BZ9: 21.228441 | CA9: 18.89448 | CB9: 17.17454 | DD9: 12.166664 | DE9: 5.0066007 | DF9: 6.9149766 | DG9: 15.859122 | DH9: 9.3450871 | DI9: 12.934122 | DJ9: 9.7548725 | DK9: 29.466725 | DL9: 14.199496 | DM9: 13.298326 | DN9: 13.543636 | DO9: 11.400129 | GD9: 26.954103 | GE9: 8.3955847 | GF9: 13.409316 | GG9: 28.244803 | GH9: 32.990704 | GI9: 21.056293 | GJ9: 21.567659 | GK9: 40.326732 | GL9: 33.892034 | GM9: 37.036367 | GN9: 23.966633 | GO9: 29.103042
A10: =AC10 -> 46234 | AC10: 46234 | BQ10: 18.702434 | BR10: 6.7267302 | BS10: 8.5861385 | BT10: 20.522175 | BU10: 12.86124 | BV10: 15.608154 | BW10: 11.470503 | BX10: 33.776202 | BY10: 20.978993 | BZ10: 20.524217 | CA10: 19.074717 | CB10: 16.394378 | DD10: 11.747831 | DE10: 4.8543023 | DF10: 6.6913494 | DG10: 15.056158 | DH10: 9.436651 | DI10: 12.231815 | DJ10: 8.0300689 | DK10: 29.066188 | DL10: 15.609121 | DM10: 12.985389 | DN10: 13.406664 | DO10: 11.873436 | GD10: 26.449433 | GE10: 8.1808893 | GF10: 13.067873 | GG10: 28.216203 | GH10: 33.392351 | GI10: 20.857092 | GJ10: 20.068245 | GK10: 40.293428 | GL10: 33.787322 | GM10: 36.396182 | GN10: 24.193347 | GO10: 28.424332
A11: =AC11 -> 46203 | AC11: 46203 | BQ11: 18.66442 | BR11: 6.7464901 | BS11: 8.606122 | BT11: 20.529922 | BU11: 12.876116 | BV11: 15.651281 | BW11: 11.496732 | BX11: 33.025759 | BY11: 20.988243 | BZ11: 20.540686 | CA11: 19.046561 | CB11: 16.406569 | DD11: 11.720755 | DE11: 4.8907186 | DF11: 6.7045045 | DG11: 15.054376 | DH11: 9.4476892 | DI11: 12.264783 | DJ11: 8.0496398 | DK11: 28.457238 | DL11: 15.605931 | DM11: 12.995683 | DN11: 13.376221 | DO11: 11.890738 | GD11: 26.410123 | GE11: 8.2077172 | GF11: 13.106235 | GG11: 28.228387 | GH11: 33.415978 | GI11: 20.896034 | GJ11: 20.124272 | GK11: 39.592671 | GL11: 33.783962 | GM11: 36.42023 | GN11: 24.173182 | GO11: 28.485972
A12: =AC12 -> 46171 | AC12: 46171 | BQ12: 18.700558 | BR12: 7.4794415 | BS12: 8.6263793 | BT12: 20.540504 | BU12: 11.639522 | BV12: 15.661884 | BW12: 11.473781 | BX12: 32.30481 | BY12: 20.947704 | BZ12: 20.528302 | CA12: 19.05761 | CB12: 16.545684 | DD12: 11.694644 | DE12: 5.4374256 | DF12: 6.7276932 | DG12: 15.067353 | DH12: 8.547098 | DI12: 12.271842 | DJ12: 8.0359417 | DK12: 27.454294 | DL12: 15.527326 | DM12: 12.98345 | DN12: 13.357486 | DO12: 11.972123 | GD12: 26.409875 | GE12: 9.0881509 | GF12: 13.116552 | GG12: 28.294631 | GH12: 26.710214 | GI12: 20.952486 | GJ12: 20.073235 | GK12: 38.960453 | GL12: 33.770062 | GM12: 36.403699 | GN12: 24.196928 | GO12: 28.596245
A13: =AC13 -> 46142 | AC13: 46142 | BQ13: 17.901243 | BR13: 7.5747869 | BS13: 8.4897371 | BT13: 20.041389 | BU13: 11.807648 | BV13: 15.671415 | BW13: 11.05736 | BX13: 31.968141 | BY13: 21.233321 | BZ13: 21.204988 | CA13: 18.883856 | CB13: 16.038936 | DD13: 10.760574 | DE13: 5.3986255 | DF13: 6.6925896 | DG13: 14.473567 | DH13: 8.7810543 | DI13: 11.925122 | DJ13: 8.3433357 | DK13: 26.80062 | DL13: 15.954387 | DM13: 12.900644 | DN13: 12.720313 | DO13: 12.599764 | GD13: 25.495629 | GE13: 9.1977445 | GF13: 12.826054 | GG13: 28.180534 | GH13: 27.193478 | GI13: 20.943467 | GJ13: 19.700114 | GK13: 38.553179 | GL13: 34.090729 | GM13: 37.191996 | GN13: 24.103303 | GO13: 28.304079
A14: =AC14 -> 46112 | AC14: 46112 | BQ14: 17.871398 | BR14: 7.6288587 | BS14: 8.502504 | BT14: 20.052876 | BU14: 11.828944 | BV14: 15.684487 | BW14: 11.066419 | BX14: 31.61785 | BY14: 21.241713 | BZ14: 21.221527 | CA14: 18.836101 | CB14: 16.048771 | DD14: 10.737824 | DE14: 5.3933566 | DF14: 6.7025842 | DG14: 14.479488 | DH14: 8.7965151 | DI14: 11.933069 | DJ14: 8.3505326 | DK14: 26.50935 | DL14: 15.95556 | DM14: 12.911381 | DN14: 12.681097 | DO14: 12.588404 | GD14: 25.461047 | GE14: 9.2569474 | GF14: 12.850113 | GG14: 28.176118 | GH14: 27.231471 | GI14: 20.974981 | GJ14: 19.718442 | GK14: 38.221171 | GL14: 34.090856 | GM14: 37.222755 | GN14: 24.054512 | GO14: 28.364423
A15: =AC15 -> 46080 | AC15: 46080 | BQ15: 18.337163 | BR15: 7.597349 | BS15: 8.4943209 | BT15: 19.772401 | BU15: 11.707191 | BV15: 15.63549 | BW15: 11.061526 | BX15: 31.360968 | BY15: 21.286693 | BZ15: 21.285185 | CA15: 18.837074 | CB15: 16.015309 | DD15: 11.049838 | DE15: 5.3584997 | DF15: 6.5033764 | DG15: 14.496286 | DH15: 8.6927292 | DI15: 11.837815 | DJ15: 8.3421739 | DK15: 26.223161 | DL15: 15.959494 | DM15: 12.953484 | DN15: 12.684987 | DO15: 12.597782 | GD15: 26.076708 | GE15: 9.248201 | GF15: 12.817146 | GG15: 27.289918 | GH15: 27.293134 | GI15: 20.943831 | GJ15: 19.708908 | GK15: 37.990463 | GL15: 34.279013 | GM15: 37.341867 | GN15: 24.022558 | GO15: 28.320968
A16: =AC16 -> 46052 | AC16: 46052 | BQ16: 17.501477 | BR16: 7.2740755 | BS16: 8.3778737 | BT16: 19.36896 | BU16: 12.100738 | BV16: 15.510431 | BW16: 10.826755 | BX16: 31.202088 | BY16: 21.516526 | BZ16: 22.110402 | CA16: 18.893922 | CB16: 15.89826 | DD16: 9.9713511 | DE16: 5.0787913 | DF16: 6.3469897 | DG16: 14.685776 | DH16: 9.3394756 | DI16: 11.12825 | DJ16: 8.0452215 | DK16: 25.725524 | DL16: 16.801129 | DM16: 13.222635 | DN16: 13.581207 | DO16: 12.514204 | GD16: 25.509294 | GE16: 8.9193004 | GF16: 12.57828 | GG16: 27.774573 | GH16: 27.33446 | GI16: 20.868361 | GJ16: 19.214747 | GK16: 37.813641 | GL16: 34.515815 | GM16: 38.121352 | GN16: 24.069727 | GO16: 28.289774
A17: =AC17 -> 46022 | AC17: 46022 | BQ17: 17.493737 | BR17: 7.2922037 | BS17: 8.3950743 | BT17: 19.36543 | BU17: 12.114149 | BV17: 15.497767 | BW17: 10.826102 | BX17: 31.097108 | BY17: 21.531708 | BZ17: 21.964771 | CA17: 18.875756 | CB17: 15.652159 | DD17: 9.9659268 | DE17: 5.098847 | DF17: 6.3613721 | DG17: 14.683856 | DH17: 9.3507371 | DI17: 11.123073 | DJ17: 8.0449909 | DK17: 25.57216 | DL17: 16.79143 | DM17: 13.134643 | DN17: 13.531645 | DO17: 12.372543 | GD17: 25.499815 | GE17: 8.9383788 | GF17: 12.61051 | GG17: 27.749948 | GH17: 27.334595 | GI17: 20.861367 | GJ17: 19.213776 | GK17: 37.71204 | GL17: 34.51983 | GM17: 37.856193 | GN17: 24.062842 | GO17: 28.025639
A18: =AC18 -> 45989 | AC18: 45989 | BQ18: 17.474597 | BR18: 7.3366162 | BS18: 8.4265295 | BT18: 19.356377 | BU18: 12.100385 | BV18: 15.59169 | BW18: 10.801518 | BX18: 30.788937 | BY18: 21.405331 | BZ18: 21.949991 | CA18: 18.799045 | CB18: 15.688325 | DD18: 9.9584716 | DE18: 5.1401451 | DF18: 6.3902022 | DG18: 14.675249 | DH18: 9.3335677 | DI18: 11.190421 | DJ18: 8.0306374 | DK18: 25.205368 | DL18: 16.825142 | DM18: 13.122551 | DN18: 13.462268 | DO18: 12.4632 | GD18: 25.470028 | GE18: 8.9895247 | GF18: 12.643208 | GG18: 27.758087 | GH18: 27.315475 | GI18: 20.97147 | GJ18: 19.165477 | GK18: 37.494186 | GL18: 34.463986 | GM18: 37.826581 | GN18: 24.000748 | GO18: 28.366381
A19: =AC19 -> 45961 | AC19: 45961 | BQ19: 16.98131 | BR19: 7.3949608 | BS19: 8.3840895 | BT19: 18.457641 | BU19: 11.990343 | BV19: 15.389457 | BW19: 10.615565 | BX19: 30.366739 | BY19: 21.424108 | BZ19: 21.845443 | CA19: 18.630702 | CB19: 15.291692 | DD19: 11.632283 | DE19: 5.2689583 | DF19: 6.4382222 | DG19: 13.945824 | DH19: 9.5296505 | DI19: 11.244004 | DJ19: 8.0262925 | DK19: 24.868213 | DL19: 15.592288 | DM19: 13.077849 | DN19: 13.535273 | DO19: 12.384621 | GD19: 24.715557 | GE19: 9.0620401 | GF19: 12.489186 | GG19: 26.89987 | GH19: 26.769061 | GI19: 20.899114 | GJ19: 18.647663 | GK19: 36.908055 | GL19: 34.388878 | GM19: 37.7626 | GN19: 23.81069 | GO19: 27.774651
A20: =AC20 -> 45930 | AC20: 45930 | BQ20: 16.979089 | BR20: 7.4317115 | BS20: 8.4037815 | BT20: 18.461521 | BU20: 11.993061 | BV20: 15.333631 | BW20: 10.627703 | BX20: 30.310673 | BY20: 21.437068 | BZ20: 21.849112 | CA20: 18.641976 | CB20: 15.288654 | DD20: 11.628888 | DE20: 5.2503681 | DF20: 6.4522206 | DG20: 13.947291 | DH20: 9.5343698 | DI20: 11.203056 | DJ20: 8.0391186 | DK20: 24.800255 | DL20: 15.58923 | DM20: 13.077553 | DN20: 13.499837 | DO20: 12.383336 | GD20: 24.714638 | GE20: 9.0939613 | GF20: 12.521527 | GG20: 26.873809 | GH20: 26.766503 | GI20: 20.8208 | GJ20: 18.672537 | GK20: 36.866248 | GL20: 34.393979 | GM20: 37.774569 | GN20: 23.812982 | GO20: 27.779872
... A247: =AC247 -> 39021 | AC247: 39021 | BQ247: 11.433999 | BR247: 9.3817719 | BS247: 7.4018374 | BT247: 19.613034 | BU247: 15.615378 | BV247: 12.447918 | BW247: 15.484575 | BX247: 15.185418 | BY247: 15.776026 | BZ247: 15.43331 | CA247: 13.681114 | CB247: 12.044173 | DD247: 6.9404181 | DE247: 5.3969308 | DF247: 4.6012457 | DG247: 12.795088 | DH247: 11.619862 | DI247: 8.1299043 | DJ247: 10.39046 | DK247: 12.412926 | DL247: 8.4661294 | DM247: 7.9997374 | DN247: 8.5759358 | DO247: 4.6395819 | GD247: 16.241008 | GE247: 14.205817 | GF247: 9.6847199 | GG247: 30.596977 | GH247: 23.179216 | GI247: 16.321152 | GJ247: 19.547566 | GK247: 20.341564 | GL247: 33.749624 | GM247: 24.112712 | GN247: 19.561585 | GO247: 20.221968

Sheet Valuation_FMA_hist
A1: Time frame | AD1: Price Earnings | DD1: Price to Free Cash Flow | EQ1: EV to EBITDA | GD1: Price to Sales
A2: 60 | AD2: FMA_PE | DD2: FMA_PFCF | EQ2: FMA_EVAL_EBITDA | GD2: FMA_PSALES
AD3: 12M Forecast Ratio | DD3: 12M Forecast Ratio | EQ3: 12M Forecast Ratio | GD3: 12M Forecast Ratio
EQ4: EV to EBITDA
B6: Materials | C6: ConsStaples | D6: Retail | E6: Fin | F6: HealthCare | G6: Indus | H6: Oil | I6: Tech | J6: Telco | K6: Utili | L6: Travel & leisure | M6: Media | P6: Materials | Q6: ConsStaples | R6: Retail | S6: Fin | T6: HealthCare | U6: Indus | V6: Oil | W6: Tech | X6: Telco | Y6: Utili | Z6: Travel & leisure | AA6: Media | AD6: Materials | AE6: ConsStaples | AF6: Retail | AG6: Fin | AH6: HealthCare | AI6: Indus | AJ6: Oil | AK6: Tech | AL6: Telco | AM6: Utili | AN6: Travel & leisure | AO6: Media | AP6: Materials | AQ6: ConsStaples | AR6: Retail | AS6: Fin | AT6: HealthCare | AU6: Indus | AV6: Oil | AW6: Tech | AX6: Telco | AY6: Utili | AZ6: Travel & leisure | BA6: Media | BQ6: Materials | BR6: ConsStaples | BS6: Retail | BT6: Fin | BU6: HealthCare | BV6: Indus | BW6: Oil | BX6: Tech | BY6: Telco | BZ6: Utili | CA6: Travel & leisure | CB6: Media | CC6: Materials | CD6: ConsStaples | CE6: Retail | CF6: Fin | CG6: HealthCare | CH6: Indus | CI6: Oil | CJ6: Tech | CK6: Telco | CL6: Utili | CM6: Travel & leisure | CN6: Media | DD6: Materials | DE6: ConsStaples | DF6: Retail | DG6: Fin | DH6: HealthCare | DI6: Indus | DJ6: Oil | DK6: Tech | DL6: Telco | DM6: Utili | DN6: Travel & leisure | DO6: Media | DP6: Materials | DQ6: ConsStaples | DR6: Retail | DS6: Fin | DT6: HealthCare | DU6: Indus | DV6: Oil | DW6: Tech | DX6: Telco | DY6: Utili | DZ6: Travel & leisure | EA6: Media | EQ6: Materials | ER6: ConsStaples | ES6: Retail | ET6: Fin | EU6: HealthCare | EV6: Indus | EW6: Oil | EX6: Tech | EY6: Telco | EZ6: Utili | FA6: Travel & leisure | FB6: Media | FC6: Materials | FD6: ConsStaples | FE6: Retail | FF6: Fin | FG6: HealthCare | FH6: Indus | FI6: Oil | FJ6: Tech | FK6: Telco | FL6: Utili | FM6: Travel & leisure | FN6: Media | GD6: Materials | GE6: ConsStaples | GF6: Retail | GG6: Fin | GH6: HealthCare | GI6: Indus | GJ6: Oil | GK6: Tech | GL6: Telco | GM6: Utili | GN6: Travel & leisure | GO6: Media | GP6: Materials | GQ6: ConsStaples | GR6: Retail | GS6: Fin | GT6: HealthCare | GU6: Indus | GV6: Oil | GW6: Tech | GX6: Telco | GY6: Utili | GZ6: Travel & leisure | HA6: Media
AD7: I00072 | AE7: I00144 | AF7: I01044 | AG7: I00288 | AH7: I21862 | AI7: I00108 | AJ7: I21852 | AK7: I21904 | AL7: I21881 | AM7: I00612 | AN7: I00936 | AO7: I00972 | AP7: diff vs. moy | AQ7: diff vs. moy | AR7: diff vs. moy | AS7: diff vs. moy | AT7: diff vs. moy | AU7: diff vs. moy | AV7: diff vs. moy | AW7: diff vs. moy | AX7: diff vs. moy | AY7: diff vs. moy | AZ7: diff vs. moy | BA7: diff vs. moy | BQ7: I00072 | BR7: I00144 | BS7: I01044 | BT7: I00288 | BU7: I21862 | BV7: I00108 | BW7: I21852 | BX7: I21904 | BY7: I21881 | BZ7: I00612 | CA7: I00936 | CB7: I00972 | CC7: diff vs. moy | CD7: diff vs. moy | CE7: diff vs. moy | CF7: diff vs. moy | CG7: diff vs. moy | CH7: diff vs. moy | CI7: diff vs. moy | CJ7: diff vs. moy | CK7: diff vs. moy | CL7: diff vs. moy | CM7: diff vs. moy | CN7: diff vs. moy | DD7: I00072 | DE7: I00144 | DF7: I01044 | DG7: I00288 | DH7: I21862 | DI7: I00108 | DJ7: I21852 | DK7: I21904 | DL7: I21881 | DM7: I00612 | DN7: I00936 | DO7: I00972 | DP7: diff vs. moy | DQ7: diff vs. moy | DR7: diff vs. moy | DS7: diff vs. moy | DT7: diff vs. moy | DU7: diff vs. moy | DV7: diff vs. moy | DW7: diff vs. moy | DX7: diff vs. moy | DY7: diff vs. moy | DZ7: diff vs. moy | EA7: diff vs. moy | EQ7: I00072 | ER7: I00144 | ES7: I01044 | ET7: I00288 | EU7: I21862 | EV7: I00108 | EW7: I21852 | EX7: I21904 | EY7: I21881 | EZ7: I00612 | FA7: I00936 | FB7: I00972 | FC7: diff vs. moy | FD7: diff vs. moy | FE7: diff vs. moy | FF7: diff vs. moy | FG7: diff vs. moy | FH7: diff vs. moy | FI7: diff vs. moy | FJ7: diff vs. moy | FK7: diff vs. moy | FL7: diff vs. moy | FM7: diff vs. moy | FN7: diff vs. moy | GD7: I00072 | GE7: I00144 | GF7: I01044 | GG7: I00288 | GH7: I21862 | GI7: I00108 | GJ7: I21852 | GK7: I21904 | GL7: I21881 | GM7: I00612 | GN7: I00936 | GO7: I00972 | GP7: diff vs. moy | GQ7: diff vs. moy | GR7: diff vs. moy | GS7: diff vs. moy | GT7: diff vs. moy | GU7: diff vs. moy | GV7: diff vs. moy | GW7: diff vs. moy | GX7: diff vs. moy | GY7: diff vs. moy | GZ7: diff vs. moy | HA7: diff vs. moy
A8: =AC8 -> 46295 | AC8: {=_xll.FDS(AD7,"JULIAN(FMA_PE(NTMA,0,-20AY,M,""PORTAGG"",""MEANR"").dates)")} -> 46295 | AD8: {=_xll.FDS(AD7,"FMA_PE(NTMA,0,-20AY,M,""PORTAGG"",""MEANR"")")} -> 18.112035 | AE8: {=_xll.FDS(AE7,"FMA_PE(NTMA,0,-20AY,M,""PORTAGG"",""MEANR"")")} -> 17.180693 | AF8: {=_xll.FDS(AF7,"FMA_PE(NTMA,0,-20AY,M,""PORTAGG"",""MEANR"")")} -> 23.058586 | AG8: {=_xll.FDS(AG7,"FMA_PE(NTMA,0,-20AY,M,""PORTAGG"",""MEANR"")")} -> 13.582001 | AH8: {=_xll.FDS(AH7,"FMA_PE(NTMA,0,-20AY,M,""PORTAGG"",""MEANR"")")} -> 19.059543 | AI8: {=_xll.FDS(AI7,"FMA_PE(NTMA,0,-20AY,M,""PORTAGG"",""MEANR"")")} -> 21.15138 | AJ8: {=_xll.FDS(AJ7,"FMA_PE(NTMA,0,-20AY,M,""PORTAGG"",""MEANR"")")} -> 12.986916 | AK8: {=_xll.FDS(AK7,"FMA_PE(NTMA,0,-20AY,M,""PORTAGG"",""MEANR"")")} -> 21.654152 | ... AO8: {=_xll.FDS(AO7,"FMA_PE(NTMA,0,-20AY,M,""PORTAGG"",""MEANR"")")} -> 18.951054 | DD8: {=_xll.FDS(DD7,"FMA_PCF(NTMA,0,-20AY,M,""PORTAGG"",""MEANR"")")} -> 12.53727 | DE8: {=_xll.FDS(DE7,"FMA_PCF(NTMA,0,-20AY,M,""PORTAGG"",""MEANR"")")} -> 14.235069 | DF8: {=_xll.FDS(DF7,"FMA_PCF(NTMA,0,-20AY,M,""PORTAGG"",""MEANR"")")} -> 13.787961 | DG8: {=_xll.FDS(DG7,"FMA_PCF(NTMA,0,-20AY,M,""PORTAGG"",""MEANR"")")} -> #N/A | DH8: {=_xll.FDS(DH7,"FMA_PCF(NTMA,0,-20AY,M,""PORTAGG"",""MEANR"")")} -> 16.987361 | DI8: {=_xll.FDS(DI7,"FMA_PCF(NTMA,0,-20AY,M,""PORTAGG"",""MEANR"")")} -> 17.405303 | DJ8: {=_xll.FDS(DJ7,"FMA_PCF(NTMA,0,-20AY,M,""PORTAGG"",""MEANR"")")} -> 7.3348122 | DK8: {=_xll.FDS(DK7,"FMA_PCF(NTMA,0,-20AY,M,""PORTAGG"",""MEANR"")")} -> 18.31349 | ... DO8: {=_xll.FDS(DO7,"FMA_PCF(NTMA,0,-20AY,M,""PORTAGG"",""MEANR"")")} -> 13.834502 | EQ8: {=_xll.FDS(EQ7,"FMA_EVAL_EBITDA(NTMA,0,-20AY,M,""PORTAGG"",""MEANR"")")} -> 10.69341 | ER8: {=_xll.FDS(ER7,"FMA_EVAL_EBITDA(NTMA,0,-20AY,M,""PORTAGG"",""MEANR"")")} -> 12.611009 | ES8: {=_xll.FDS(ES7,"FMA_EVAL_EBITDA(NTMA,0,-20AY,M,""PORTAGG"",""MEANR"")")} -> 11.773436 | ET8: {=_xll.FDS(ET7,"FMA_EVAL_EBITDA(NTMA,0,-20AY,M,""PORTAGG"",""MEANR"")")} -> #N/A | EU8: {=_xll.FDS(EU7,"FMA_EVAL_EBITDA(NTMA,0,-20AY,M,""PORTAGG"",""MEANR"")")} -> 15.705992 | EV8: {=_xll.FDS(EV7,"FMA_EVAL_EBITDA(NTMA,0,-20AY,M,""PORTAGG"",""MEANR"")")} -> 15.327033 | EW8: {=_xll.FDS(EW7,"FMA_EVAL_EBITDA(NTMA,0,-20AY,M,""PORTAGG"",""MEANR"")")} -> 6.8885213 | EX8: {=_xll.FDS(EX7,"FMA_EVAL_EBITDA(NTMA,0,-20AY,M,""PORTAGG"",""MEANR"")")} -> 15.584779 | ... FB8: {=_xll.FDS(FB7,"FMA_EVAL_EBITDA(NTMA,0,-20AY,M,""PORTAGG"",""MEANR"")")} -> 11.969054 | GD8: {=_xll.FDS(GD7,"FMA_PSALES(NTMA,0,-20AY,M,""PORTAGG"",""MEANR"")")} -> 3.0101644 | GE8: {=_xll.FDS(GE7,"FMA_PSALES(NTMA,0,-20AY,M,""PORTAGG"",""MEANR"")")} -> 0.91152254 | GF8: {=_xll.FDS(GF7,"FMA_PSALES(NTMA,0,-20AY,M,""PORTAGG"",""MEANR"")")} -> 1.8559352 | GG8: {=_xll.FDS(GG7,"FMA_PSALES(NTMA,0,-20AY,M,""PORTAGG"",""MEANR"")")} -> 2.8520047 | GH8: {=_xll.FDS(GH7,"FMA_PSALES(NTMA,0,-20AY,M,""PORTAGG"",""MEANR"")")} -> 2.4448214 | GI8: {=_xll.FDS(GI7,"FMA_PSALES(NTMA,0,-20AY,M,""PORTAGG"",""MEANR"")")} -> 2.9930543 | GJ8: {=_xll.FDS(GJ7,"FMA_PSALES(NTMA,0,-20AY,M,""PORTAGG"",""MEANR"")")} -> 1.5599016 | GK8: {=_xll.FDS(GK7,"FMA_PSALES(NTMA,0,-20AY,M,""PORTAGG"",""MEANR"")")} -> 7.5240099 | ... GO8: {=_xll.FDS(GO7,"FMA_PSALES(NTMA,0,-20AY,M,""PORTAGG"",""MEANR"")")} -> 2.5892003
A9: =AC9 -> 46265 | AC9: 46265 | AD9: 19.140859 | AE9: 17.920349 | AF9: 24.181024 | AG9: 14.683664 | AH9: 19.309608 | AI9: 22.11485 | AJ9: 14.135723 | AK9: 21.147851 | AL9: 15.63192 | AM9: 17.330329 | AN9: 20.213612 | AO9: 20.917852 | DD9: 13.344337 | DE9: 14.921011 | DF9: 14.663159 | DG9: #N/A | DH9: 17.188477 | DI9: 18.215512 | DJ9: 7.8939108 | DK9: 17.989949 | DL9: 8.4299081 | DM9: 8.5162509 | DN9: 14.130305 | DO9: 15.004516 | EQ9: 11.218002 | ER9: 13.096981 | ES9: 12.742566 | ET9: #N/A | EU9: 15.790629 | EV9: 15.917274 | EW9: 7.3736541 | EX9: 15.300847 | EY9: 9.1645482 | EZ9: 11.355289 | FA9: 12.561801 | FB9: 12.954015 | GD9: 3.1161202 | GE9: 0.94714772 | GF9: 1.9547101 | GG9: 3.0595452 | GH9: 2.4607759 | GI9: 3.1276783 | GJ9: 1.6370578 | GK9: 7.3542655 | GL9: 2.4812919 | GM9: 2.6210558 | GN9: 3.0377733 | GO9: 2.828424
A10: =AC10 -> 46234 | AC10: 46234 | AD10: 17.889471 | AE10: 18.160613 | AF10: 25.161171 | AG10: 14.730236 | AH10: 18.868282 | AI10: 22.851668 | AJ10: 13.820266 | AK10: 21.324245 | AL10: 15.528597 | AM10: 18.286458 | AN10: 20.663806 | AO10: 19.211681 | DD10: 12.45944 | DE10: 15.243526 | DF10: 15.531523 | DG10: #N/A | DH10: 16.749581 | DI10: 18.906411 | DJ10: 7.7334446 | DK10: 17.934728 | DL10: 8.3053378 | DM10: 8.9629917 | DN10: 14.419883 | DO10: 13.869344 | EQ10: 10.520272 | ER10: 13.188025 | ES10: 13.436734 | ET10: #N/A | EU10: 15.18896 | EV10: 16.378595 | EW10: 7.2764956 | EX10: 15.395656 | EY10: 9.0531122 | EZ10: 11.663798 | FA10: 12.699114 | FB10: 11.812237 | GD10: 2.8655605 | GE10: 0.95142636 | GF10: 2.051635 | GG10: 3.0706422 | GH10: 2.3576356 | GI10: 3.2102778 | GJ10: 1.5714004 | GK10: 7.3695673 | GL10: 2.3923684 | GM10: 2.7716425 | GN10: 3.0834301 | GO10: 2.5532698
A11: =AC11 -> 46203 | AC11: 46203 | AD11: 18.070196 | AE11: 17.827666 | AF11: 26.152576 | AG11: 14.531662 | AH11: 18.815661 | AI11: 23.335537 | AJ11: 12.747469 | AK11: 23.239128 | AL11: 15.814341 | AM11: 18.760164 | AN11: 20.692439 | AO11: 19.073388 | DD11: 12.68463 | DE11: 14.915859 | DF11: 14.913596 | DG11: #N/A | DH11: 16.950061 | DI11: 19.291402 | DJ11: 6.9187722 | DK11: 19.140682 | DL11: 8.4116626 | DM11: 9.2235007 | DN11: 14.336353 | DO11: 13.697584 | EQ11: 10.628818 | ER11: 12.985647 | ES11: 12.937004 | ET11: #N/A | EU11: 14.964863 | EV11: 16.521142 | EW11: 6.6888325 | EX11: 16.475471 | EY11: 9.1417167 | EZ11: 11.871897 | FA11: 12.652189 | FB11: 11.704989 | GD11: 2.8943264 | GE11: 0.93427771 | GF11: 1.9271754 | GG11: 2.982057 | GH11: 2.3473724 | GI11: 3.2430651 | GJ11: 1.406727 | GK11: 7.8515023 | GL11: 2.403406 | GM11: 2.8434929 | GN11: 3.0583669 | GO11: 2.5337993
A12: =AC12 -> 46171 | AC12: 46171 | AD12: 18.66267 | AE12: 17.484527 | AF12: 28.248865 | AG12: 14.096422 | AH12: 17.96394 | AI12: 22.246108 | AJ12: 13.411432 | AK12: 25.59297 | AL12: 15.651038 | AM12: 18.448296 | AN12: 20.257731 | AO12: 21.097491 | DD12: 13.09477 | DE12: 14.736779 | DF12: 16.213157 | DG12: #N/A | DH12: 15.924201 | DI12: 18.48659 | DJ12: 7.2325635 | DK12: 21.032428 | DL12: 8.3737867 | DM12: 9.0223948 | DN12: 13.999311 | DO12: 15.123142 | EQ12: 10.968692 | ER12: 12.758291 | ES12: 14.005252 | ET12: #N/A | EU12: 14.34828 | EV12: 16.104172 | EW12: 7.0233926 | EX12: 18.124652 | EY12: 9.1051275 | EZ12: 11.772918 | FA12: 12.331905 | FB12: 12.832972 | GD12: 2.9755629 | GE12: 1.0192167 | GF12: 2.0704046 | GG12: 2.8826479 | GH12: 1.9940462 | GI12: 3.1414944 | GJ12: 1.4793992 | GK12: 8.4136549 | GL12: 2.378921 | GM12: 2.7743955 | GN12: 2.9696502 | GO12: 2.7944564
A13: =AC13 -> 46142 | AC13: 46142 | AD13: 18.85561 | AE13: 17.821067 | AF13: 29.488895 | AG13: 14.399866 | AH13: 17.285648 | AI13: 22.848272 | AJ13: 15.139179 | AK13: 23.803719 | AL13: 15.036423 | AM13: 19.734435 | AN13: 20.791119 | AO13: 21.317138 | DD13: 13.12998 | DE13: 14.822539 | DF13: 17.405289 | DG13: #N/A | DH13: 15.186676 | DI13: 18.895915 | DJ13: 8.0333594 | DK13: 19.50292 | DL13: 7.9744553 | DM13: 9.5126024 | DN13: 14.437922 | DO13: 16.230541 | EQ13: 11.004977 | ER13: 12.96783 | ES13: 14.451291 | ET13: #N/A | EU13: 13.752028 | EV13: 16.293236 | EW13: 7.5389637 | EX13: 16.856061 | EY13: 8.6590942 | EZ13: 12.045804 | FA13: 12.714565 | FB13: 13.343128 | GD13: 2.9501996 | GE13: 1.0276392 | GF13: 2.1411345 | GG13: 2.9302892 | GH13: 1.9524773 | GI13: 3.1978345 | GJ13: 1.6060884 | GK13: 7.7917281 | GL13: 2.260512 | GM13: 2.9736797 | GN13: 3.019525 | GO13: 2.9195228
A14: =AC14 -> 46112 | AC14: 46112 | AD14: 19.139126 | AE14: 17.453194 | AF14: 27.31951 | AG14: 13.948181 | AH14: 17.729838 | AI14: 22.048302 | AJ14: 19.200307 | AK14: 21.054504 | AL14: 14.221249 | AM14: 19.537256 | AN14: 20.111234 | AO14: 22.435791 | DD14: 13.317637 | DE14: 14.560581 | DF14: 15.386739 | DG14: #N/A | DH14: 15.601311 | DI14: 18.037729 | DJ14: 9.5604192 | DK14: 17.106654 | DL14: 7.4600377 | DM14: 9.491824 | DN14: 13.894822 | DO14: 16.583675 | EQ14: 10.935069 | ER14: 12.739205 | ES14: 12.93784 | ET14: #N/A | EU14: 14.396205 | EV14: 15.632915 | EW14: 8.9894725 | EX14: 14.707619 | EY14: 8.3093237 | EZ14: 12.013179 | FA14: 12.506184 | FB14: 13.579813 | GD14: 2.9456597 | GE14: 1.0121067 | GF14: 1.8908538 | GG14: 2.8073125 | GH14: 1.9917906 | GI14: 3.038844 | GJ14: 1.7843776 | GK14: 6.7230938 | GL14: 2.1288052 | GM14: 2.9396692 | GN14: 2.9544067 | GO14: 2.9679744
A15: =AC15 -> 46080 | AC15: 46080 | AD15: 21.223825 | AE15: 19.450613 | AF15: 28.656472 | AG15: 14.450922 | AH15: 19.171508 | AI15: 24.000699 | AJ15: 20.252298 | AK15: 23.756352 | AL15: 14.153313 | AM15: 20.405675 | AN15: 21.560547 | AO15: 23.420239 | DD15: 14.352075 | DE15: 16.167384 | DF15: 16.202307 | DG15: #N/A | DH15: 16.905837 | DI15: 19.688452 | DJ15: 9.1960917 | DK15: 19.163716 | DL15: 7.3843397 | DM15: 10.048033 | DN15: 14.87053 | DO15: 17.184441 | EQ15: 11.886079 | ER15: 13.894749 | ES15: 13.544788 | ET15: #N/A | EU15: 15.436139 | EV15: 16.950462 | EW15: 8.8486838 | EX15: 16.481386 | EY15: 8.2769005 | EZ15: 12.331878 | FA15: 13.397981 | FB15: 14.13945 | GD15: 3.1959973 | GE15: 1.1158952 | GF15: 1.9674816 | GG15: 2.9054094 | GH15: 2.1144986 | GI15: 3.2774992 | GJ15: 1.7039649 | GK15: 7.338803 | GL15: 2.125324 | GM15: 3.100927 | GN15: 3.2097305 | GO15: 3.0831321
A16: =AC16 -> 46052 | AC16: 46052 | AD16: 19.775156 | AE16: 17.999632 | AF16: 29.689059 | AG16: 15.137795 | AH16: 18.862793 | AI16: 23.311572 | AJ16: 18.717135 | AK16: 25.652229 | AL16: 13.509949 | AM16: 18.791788 | AN16: 21.642228 | AO16: 23.075587 | DD16: 13.530024 | DE16: 14.966903 | DF16: 16.033918 | DG16: #N/A | DH16: 16.665786 | DI16: 18.758828 | DJ16: 8.5366883 | DK16: 21.043646 | DL16: 7.0650365 | DM16: 9.2454319 | DN16: 14.894545 | DO16: 16.392736 | EQ16: 11.183523 | ER16: 13.119309 | ES16: 14.328032 | ET16: #N/A | EU16: 15.258967 | EV16: 16.524415 | EW16: 8.4683738 | EX16: 17.971247 | EY16: 8.0416595 | EZ16: 11.637144 | FA16: 13.550186 | FB16: 13.695517 | GD16: 2.9529853 | GE16: 1.0323671 | GF16: 2.0747121 | GG16: 3.0570953 | GH16: 2.0782709 | GI16: 3.1844978 | GJ16: 1.5977194 | GK16: 7.9826097 | GL16: 2.0266809 | GM16: 2.8519203 | GN16: 3.2487407 | GO16: 2.9397053
A17: =AC17 -> 46022 | AC17: 46022 | AD17: 18.749383 | AE17: 16.993821 | AF17: 28.675157 | AG17: 15.57068 | AH17: 18.584797 | AI17: 22.796597 | AJ17: 15.681258 | AK17: 26.485256 | AL17: 13.03326 | AM17: 18.682122 | AN17: 21.845739 | AO17: 25.481504 | DD17: 12.471202 | DE17: 14.13538 | DF17: 15.462177 | DG17: #N/A | DH17: 16.858124 | DI17: 18.40329 | DJ17: 7.3704548 | DK17: 21.430026 | DL17: 6.8147683 | DM17: 9.0873841 | DN17: 15.168739 | DO17: 17.958941 | EQ17: 10.697279 | ER17: 12.514558 | ES17: 13.939824 | ET17: #N/A | EU17: 15.169957 | EV17: 16.048087 | EW17: 7.3655135 | EX17: 18.481214 | EY17: 7.8750271 | EZ17: 11.561954 | FA17: 13.61037 | FB17: 15.206564 | GD17: 2.7252731 | GE17: 0.97551543 | GF17: 1.9866159 | GG17: 3.1179126 | GH17: 2.0814452 | GI17: 3.1212967 | GJ17: 1.3771094 | GK17: 8.2103391 | GL17: 1.9624381 | GM17: 2.7883093 | GN17: 3.238301 | GO17: 3.2845389
A18: =AC18 -> 45989 | AC18: 45989 | AD18: 18.934751 | AE18: 17.608807 | AF18: 29.379309 | AG18: 15.243224 | AH18: 18.933908 | AI18: 22.629534 | AJ18: 15.435941 | AK18: 28.4922 | AL18: 12.965772 | AM18: 19.841415 | AN18: 21.419509 | AO18: 27.293417 | DD18: 12.393517 | DE18: 14.543543 | DF18: 16.042488 | DG18: #N/A | DH18: 16.945696 | DI18: 18.227469 | DJ18: 7.3035976 | DK18: 22.603396 | DL18: 6.7816856 | DM18: 9.5939977 | DN18: 14.85087 | DO18: 19.423095 | EQ18: 10.763646 | ER18: 12.906157 | ES18: 14.266476 | ET18: #N/A | EU18: 15.387381 | EV18: 15.960327 | EW18: 7.3673742 | EX18: 19.500858 | EY18: 7.8555213 | EZ18: 12.008296 | FA18: 13.276092 | FB18: 16.528406 | GD18: 2.6703931 | GE18: 1.007641 | GF18: 2.0296793 | GG18: 3.0540882 | GH18: 2.1185601 | GI18: 3.0866998 | GJ18: 1.3735523 | GK18: 8.4997395 | GL18: 1.9546323 | GM18: 2.9476238 | GN18: 3.1450914 | GO18: 3.6127386
A19: =AC19 -> 45961 | AC19: 45961 | AD19: 18.698788 | AE19: 16.99203 | AF19: 29.841264 | AG19: 15.061797 | AH19: 17.554568 | AI19: 22.945982 | AJ19: 15.376325 | AK19: 30.309848 | AL19: 13.19024 | AM19: 19.649052 | AN19: 20.99157 | AO19: 29.516774 | DD19: 12.055712 | DE19: 14.073466 | DF19: 16.415935 | DG19: #N/A | DH19: 15.595129 | DI19: 18.493027 | DJ19: 7.3218117 | DK19: 23.914639 | DL19: 6.8606369 | DM19: 9.4932397 | DN19: 14.482745 | DO19: 21.023178 | EQ19: 10.579987 | ER19: 12.558493 | ES19: 14.643071 | ET19: #N/A | EU19: 14.287085 | EV19: 16.174772 | EW19: 7.2570653 | EX19: 20.767477 | EY19: 7.9663496 | EZ19: 11.990427 | FA19: 13.178153 | FB19: 17.153293 | GD19: 2.591145 | GE19: 0.97120841 | GF19: 2.0746469 | GG19: 2.9962266 | GH19: 1.9578102 | GI19: 3.1214556 | GJ19: 1.3533222 | GK19: 8.9624082 | GL19: 1.9853188 | GM19: 2.9178755 | GN19: 3.0810253 | GO19: 3.725534
A20: =AC20 -> 45930 | AC20: 45930 | AD20: 21.035705 | AE20: 17.511929 | AF20: 29.439251 | AG20: 16.038113 | AH20: 17.073335 | AI20: 22.958973 | AJ20: 15.307321 | AK20: 29.519019 | AL20: 13.638807 | AM20: 19.578173 | AN20: 22.171931 | AO20: 31.171319 | DD20: 13.759407 | DE20: 14.637468 | DF20: 16.425865 | DG20: #N/A | DH20: 15.216408 | DI20: 18.530339 | DJ20: 7.4218348 | DK20: 23.458458 | DL20: 7.1499034 | DM20: 9.5963087 | DN20: 15.302417 | DO20: 22.335923 | EQ20: 11.566957 | ER20: 12.834264 | ES20: 14.406149 | ET20: #N/A | EU20: 13.941082 | EV20: 16.247077 | EW20: 7.2549835 | EX20: 20.254683 | EY20: 8.214775 | EZ20: 12.012477 | FA20: 13.957431 | FB20: 18.086244 | GD20: 2.7913213 | GE20: 1.0067065 | GF20: 2.019587 | GG20: 3.1578025 | GH20: 1.9187254 | GI20: 3.1346213 | GJ20: 1.3756519 | GK20: 8.6944601 | GL20: 2.0891951 | GM20: 2.9222222 | GN20: 3.2530327 | GO20: 3.9120488
... A67: =AC67 -> 44498 | AC67: 44498 | AD67: 15.503395 | AE67: 17.710343 | AF67: 34.181827 | AG67: 15.176769 | AH67: 18.26744 | AI67: 21.990506 | AJ67: 13.291668 | AK67: 28.277998 | AL67: 13.218792 | AM67: 19.783283 | AN67: 839.33235 | AO67: 34.375946 | DD67: 10.806991 | DE67: 14.265477 | DF67: 19.54472 | DG67: #N/A | DH67: 16.075957 | DI67: 17.934455 | DJ67: 6.4534968 | DK67: 21.85537 | DL67: 7.4886004 | DM67: 9.2103372 | DN67: 23.474586 | DO67: 33.435114 | EQ67: 9.452521 | ER67: 12.818935 | ES67: 17.044419 | ET67: #N/A | EU67: 14.249512 | EV67: 16.031524 | EW67: 6.7382753 | EX67: 19.081577 | EY67: 8.636055 | EZ67: 12.125725 | FA67: 18.693372 | FB67: 20.596084 | GD67: 2.2113721 | GE67: 1.1467323 | GF67: 1.8838794 | GG67: 2.8678762 | GH67: 2.6033205 | GI67: 3.0252749 | GJ67: 1.1741755 | GK67: 6.6236635 | GL67: 2.006811 | GM67: 2.74659 | GN67: 3.3927579 | GO67: 3.6548932
A68: =AC68 -> 44469 | AC68: 44469 | AD68: 14.691359 | AE68: 17.05637 | AF68: 30.7661 | AG68: 14.224761 | AH68: 17.592017 | AI68: 21.498732 | AJ68: 14.103417 | AK68: 26.170909 | AL68: 13.630231 | AM68: 18.910413 | AN68: 217.4334 | AO68: 34.001855 | DD68: 10.108005 | DE68: 13.929279 | DF68: 18.368181 | DG68: #N/A | DH68: 15.637818 | DI68: 17.388368 | DJ68: 6.3278415 | DK68: 20.132827 | DL68: 7.5287729 | DM68: 8.8955262 | DN68: 24.886813 | DO68: 33.880835 | EQ68: 9.0342156 | ER68: 12.572629 | ES68: 15.868193 | ET68: 15.454378 | EU68: 14.018965 | EV68: 15.591687 | EW68: 6.659432 | EX68: 17.675508 | EY68: 8.8259859 | EZ68: 11.866326 | FA68: 19.190748 | FB68: 20.178912 | GD68: 2.1019222 | GE68: 1.1237202 | GF68: 1.7820023 | GG68: 2.6931636 | GH68: 2.517143 | GI68: 2.9396735 | GJ68: 1.0825733 | GK68: 6.1505951 | GL68: 2.0773774 | GM68: 2.6249819 | GN68: 3.4679353 | GO68: 3.5135871
A69: =AC69 -> 44439 | AC69: 44439 | AD69: 16.040865 | AE69: 17.892081 | AF69: 32.635809 | AG69: 14.309758 | AH69: 18.755686 | AI69: 23.000234 | AJ69: 13.746287 | AK69: 27.82322 | AL69: 14.893612 | AM69: 20.306304 | AN69: 160.30618 | AO69: 33.35857 | DD69: 11.183768 | DE69: 14.712314 | DF69: 19.52068 | DG69: #N/A | DH69: 16.699625 | DI69: 18.532587 | DJ69: 6.1029113 | DK69: 21.528514 | DL69: 8.0415155 | DM69: 9.5261105 | DN69: 25.55498 | DO69: 31.480693 | EQ69: 9.6620874 | ER69: 13.080604 | ES69: 16.715008 | ET69: 16.183367 | EU69: 14.817739 | EV69: 16.664158 | EW69: 6.4891392 | EX69: 18.882524 | EY69: 9.229607 | EZ69: 12.405667 | FA69: 20.078333 | FB69: 20.316768 | GD69: 2.2837554 | GE69: 1.1778418 | GF69: 1.8760934 | GG69: 2.7230066 | GH69: 2.6697729 | GI69: 3.1461146 | GJ69: 0.99493686 | GK69: 6.5747505 | GL69: 2.2052861 | GM69: 2.7912038 | GN69: 3.570203 | GO69: 3.5740641
A70: =AC70 -> 44407 | AC70: 44407 | AD70: 16.238512 | AE70: 17.857346 | AF70: 32.765586 | AG70: 13.685915 | AH70: 18.621255 | AI70: 23.530891 | AJ70: 14.736246 | AK70: 27.005414 | AL70: 14.939154 | AM70: 19.724439 | AN70: 136.0943 | AO70: 33.077998 | DD70: 11.307264 | DE70: 14.671514 | DF70: 19.627362 | DG70: #N/A | DH70: 16.49668 | DI70: 18.947782 | DJ70: 6.4544361 | DK70: 21.081847 | DL70: 8.0119985 | DM70: 9.2946251 | DN70: 25.804622 | DO70: 31.444672 | EQ70: 9.7651854 | ER70: 13.087412 | ES70: 16.740441 | ET70: 16.590292 | EU70: 14.623572 | EV70: 16.94117 | EW70: 6.9575059 | EX70: 18.282015 | EY70: 9.2026438 | EZ70: 12.215583 | FA70: 20.899806 | FB70: 20.025922 | GD70: 2.3065434 | GE70: 1.1810559 | GF70: 1.8697587 | GG70: 2.6410184 | GH70: 2.6496535 | GI70: 3.181859 | GJ70: 1.0431834 | GK70: 6.3505822 | GL70: 2.1277828 | GM70: 2.7151264 | GN70: 3.6896401 | GO70: 3.467084
A71: =AC71 -> 44377 | AC71: 44377 | AD71: 16.665792 | AE71: 17.771539 | AF71: 32.818622 | AG71: 14.1869 | AH71: 17.950001 | AI71: 24.023622 | AJ71: 18.182452 | AK71: 27.453806 | AL71: 15.318091 | AM71: 18.965724 | AN71: 203.62466 | AO71: 34.774246 | DD71: 11.447059 | DE71: 14.202718 | DF71: 18.827781 | DG71: #N/A | DH71: 15.915522 | DI71: 19.047515 | DJ71: 7.4629942 | DK71: 21.220171 | DL71: 7.9494041 | DM71: 9.1123125 | DN71: 28.434071 | DO71: 32.717418 | EQ71: 9.8531594 | ER71: 13.026789 | ES71: 16.811568 | ET71: 15.806591 | EU71: 14.069343 | EV71: 17.076069 | EW71: 7.9268989 | EX71: 18.414661 | EY71: 9.1942821 | EZ71: 11.945938 | FA71: 22.163418 | FB71: 20.944733 | GD71: 2.3112247 | GE71: 1.1799915 | GF71: 1.8727676 | GG71: 2.7084481 | GH71: 2.5832579 | GI71: 3.1796453 | GJ71: 1.2020947 | GK71: 6.2997216 | GL71: 2.1167864 | GM71: 2.6240206 | GN71: 3.7575413 | GO71: 3.5788817
A72: =AC72 -> 44344 | AC72: 44344 | AD72: 18.709808 | AE72: 18.192836 | AF72: 31.751396 | AG72: 14.688925 | AH72: 17.504416 | AI72: 24.886235 | AJ72: 18.838383 | AK72: 25.456445 | AL72: 15.210934 | AM72: 19.456736 | AN72: 150.12801 | AO72: 34.861378 | DD72: 12.824775 | DE72: 14.464131 | DF72: 18.066564 | DG72: #N/A | DH72: 15.410544 | DI72: 19.822348 | DJ72: 7.287759 | DK72: 19.786609 | DL72: 7.8535442 | DM72: 9.2176508 | DN72: 30.928921 | DO72: 31.583758 | EQ72: 10.817685 | ER72: 13.280044 | ES72: 16.247704 | ET72: 15.997832 | EU72: 13.630972 | EV72: 17.439356 | EW72: 7.8649665 | EX72: 17.194908 | EY72: 9.0774118 | EZ72: 12.085704 | FA72: 23.235915 | FB72: 20.813982 | GD72: 2.5218121 | GE72: 1.2113689 | GF72: 1.8062472 | GG72: 2.8042181 | GH72: 2.5083362 | GI72: 3.2307188 | GJ72: 1.1542916 | GK72: 5.8774191 | GL72: 2.1014157 | GM72: 2.6988867 | GN72: 3.9708603 | GO72: 3.5302508
A73: =AC73 -> 44316 | AC73: 44316 | AD73: 18.298876 | AE73: 17.998937 | AF73: 35.885659 | AG73: 14.225801 | AH73: 17.570677 | AI73: 25.315021 | AJ73: 19.373228 | AK73: 26.164877 | AL73: 15.146607 | AM73: 20.256057 | AN73: 160.51555 | AO73: 37.959942 | DD73: 12.28712 | DE73: 14.323971 | DF73: 20.502349 | DG73: #N/A | DH73: 15.409812 | DI73: 20.140319 | DJ73: 7.2118783 | DK73: 20.434806 | DL73: 7.8433814 | DM73: 9.4903717 | DN73: 33.771638 | DO73: 32.738865 | EQ73: 10.530554 | ER73: 13.125304 | ES73: 17.835888 | ET73: 15.332733 | EU73: 13.796424 | EV73: 17.656729 | EW73: 7.8353849 | EX73: 17.560077 | EY73: 8.764077 | EZ73: 12.052127 | FA73: 24.396979 | FB73: 22.417445 | GD73: 2.3899618 | GE73: 1.1996819 | GF73: 1.9444561 | GG73: 2.7139674 | GH73: 2.4990706 | GI73: 3.2525813 | GJ73: 1.1378487 | GK73: 6.0137965 | GL73: 2.0968511 | GM73: 2.7983657 | GN73: 4.077353 | GO73: 3.6780373
A74: =AC74 -> 44286 | AC74: 44286 | AD74: 19.370388 | AE74: 17.895712 | AF74: 34.892088 | AG74: 14.817981 | AH74: 17.060163 | AI74: 25.351446 | AJ74: 22.279346 | AK74: 26.683022 | AL74: 15.018823 | AM74: 19.343784 | AN74: 114.34037 | AO74: 39.908018 | DD74: 12.416044 | DE74: 14.191801 | DF74: 19.970164 | DG74: #N/A | DH74: 15.124677 | DI74: 19.825424 | DJ74: 7.5409073 | DK74: 20.292066 | DL74: 7.6846847 | DM74: 9.1115361 | DN74: 29.149832 | DO74: 33.565236 | EQ74: 10.829619 | ER74: 13.003582 | ES74: 17.06349 | ET74: 14.352354 | EU74: 13.461377 | EV74: 17.376151 | EW74: 8.1857116 | EX74: 17.465653 | EY74: 8.6181884 | EZ74: 11.81907 | FA74: 23.934544 | FB74: 22.842553 | GD74: 2.378049 | GE74: 1.1891887 | GF74: 1.8278254 | GG74: 2.6152462 | GH74: 2.4311159 | GI74: 3.1427295 | GJ74: 1.183108 | GK74: 5.8541467 | GL74: 2.0585368 | GM74: 2.6967204 | GN74: 4.0103567 | GO74: 3.7217788
A75: =AC75 -> 44253 | AC75: 44253 | AD75: 19.339883 | AE75: 21.514593 | AF75: 35.249537 | AG75: 16.743814 | AH75: 16.321755 | AI75: 24.196993 | AJ75: 27.132733 | AK75: 25.853909 | AL75: 10.814295 | AM75: 17.39787 | AN75: 82.696561 | AO75: 36.034129 | DD75: 12.087259 | DE75: 17.911995 | DF75: 20.06586 | DG75: 15.505407 | DH75: 14.312825 | DI75: 17.778496 | DJ75: 7.5869397 | DK75: 19.918336 | DL75: 5.2419577 | DM75: 8.122258 | DN75: 27.755401 | DO75: 18.365324 | EQ75: 10.688547 | ER75: 15.092255 | ES75: 17.110161 | ET75: 20.082945 | EU75: 13.039511 | EV75: 15.612055 | EW75: 8.6343476 | EX75: 17.048278 | EY75: 6.7725297 | EZ75: 11.225614 | FA75: 23.248929 | FB75: 15.764543 | GD75: 2.2442045 | GE75: 2.2942463 | GF75: 1.86401 | GG75: 3.2007695 | GH75: 2.3082357 | GI75: 2.588124 | GJ75: 1.1565955 | GK75: 5.8531818 | GL75: 1.403624 | GM75: 2.4748606 | GN75: 3.9291541 | GO75: 3.1339077
A76: =AC76 -> 44225 | AC76: 44225 | AD76: 18.858926 | AE76: 22.294802 | AF76: 37.338005 | AG76: 15.562947 | AH76: 16.978271 | AI76: 23.463987 | AJ76: 24.525251 | AK76: 26.423964 | AL76: 11.009803 | AM76: 18.353083 | AN76: 63.632001 | AO76: 34.80406 | DD76: 11.531747 | DE76: 18.093688 | DF76: 21.117266 | DG76: 14.93432 | DH76: 14.698585 | DI76: 16.928578 | DJ76: 6.5608599 | DK76: 20.50764 | DL76: 5.3235458 | DM76: 8.5849969 | DN76: 25.192631 | DO76: 17.116692 | EQ76: 10.177721 | ER76: 15.620974 | ES76: 18.094808 | ET76: 19.254123 | EU76: 13.443873 | EV76: 15.164981 | EW76: 7.8813727 | EX76: 17.333221 | EY76: 6.8380326 | EZ76: 11.51191 | FA76: 20.47263 | FB76: 14.959728 | GD76: 2.1029234 | GE76: 2.3825359 | GF76: 1.9560988 | GG76: 2.9510529 | GH76: 2.4066356 | GI76: 2.4859413 | GJ76: 0.98419374 | GK76: 5.916541 | GL76: 1.421713 | GM76: 2.6398425 | GN76: 3.4693653 | GO76: 2.9308815
A77: =AC77 -> 44196 | AC77: 44196 | AD77: 21.037436 | AE77: 23.004449 | AF77: 38.480535 | AG77: 17.216112 | AH77: 17.12465 | AI77: 24.859614 | AJ77: 29.809957 | AK77: 27.757506 | AL77: 11.470628 | AM77: 18.671816 | AN77: 62.406799 | AO77: 35.289716 | DD77: 12.520943 | DE77: 18.467316 | DF77: 21.666084 | DG77: 16.013775 | DH77: 14.617243 | DI77: 18.053822 | DJ77: 6.8332028 | DK77: 21.254777 | DL77: 5.4886166 | DM77: 8.6666603 | DN77: 25.601093 | DO77: 17.890112 | EQ77: 11.215704 | ER77: 16.108494 | ES77: 18.552849 | ET77: 20.293987 | EU77: 13.432423 | EV77: 15.856012 | EW77: 8.1761217 | EX77: 18.04117 | EY77: 6.9365886 | EZ77: 11.644107 | FA77: 21.077595 | FB77: 15.709755 | GD77: 2.3167403 | GE77: 2.4553608 | GF77: 1.9923655 | GG77: 3.0748026 | GH77: 2.4170428 | GI77: 2.6033402 | GJ77: 0.97417833 | GK77: 6.0574333 | GL77: 1.4794273 | GM77: 2.6547985 | GN77: 3.7471404 | GO77: 3.101652
A78: =AC78 -> 44165 | AC78: 44165 | AD78: 21.58061 | AE78: 22.058539 | AF78: 39.176854 | AG78: 16.793987 | AH78: 16.814867 | AI78: 24.867737 | AJ78: 6.3701046 | AK78: 26.924095 | AL78: 11.603827 | AM78: 18.659193 | AN78: 46.56656 | AO78: 32.459811 | DD78: 12.675917 | DE78: 17.818924 | DF78: 21.782623 | DG78: 15.615493 | DH78: 14.279963 | DI78: 18.061893 | DJ78: 6.9467882 | DK78: 20.592536 | DL78: 5.5777451 | DM78: 8.6656964 | DN78: 3.5817891 | DO78: 16.178194 | EQ78: 11.472882 | ER78: 15.542593 | ES78: 18.742948 | ET78: 20.086019 | EU78: 13.296316 | EV78: 15.811366 | EW78: 8.3463631 | EX78: 17.564134 | EY78: 6.9905039 | EZ78: 11.650396 | FA78: 24.136467 | FB78: 14.59039 | GD78: 2.327155 | GE78: 2.3225087 | GF78: 1.9886492 | GG78: 2.935207 | GH78: 2.3443973 | GI78: 2.5605657 | GJ78: 0.9530775 | GK78: 5.8704502 | GL78: 1.5018859 | GM78: 2.6415074 | GN78: 3.6552219 | GO78: 2.8571825
A79: =AC79 -> 44134 | AC79: 44134 | AD79: 19.572637 | AE79: 20.281241 | AF79: 38.165118 | AG79: 15.00329 | AH79: 16.021632 | AI79: 21.892085 | AJ79: -8.4245861 | AK79: 25.088233 | AL79: 10.852022 | AM79: 18.651073 | AN79: 26.20696 | AO79: 25.640222 | DD79: 11.257744 | DE79: 16.486369 | DF79: 20.700591 | DG79: 14.146521 | DH79: 13.729989 | DI79: 15.884805 | DJ79: 5.6823345 | DK79: 19.069128 | DL79: 5.1917534 | DM79: 8.6810781 | DN79: -23.51981 | DO79: 13.861726 | EQ79: 10.668149 | ER79: 14.528242 | ES79: 17.938694 | ET79: 18.404379 | EU79: 13.075512 | EV79: 14.347969 | EW79: 7.4190342 | EX79: 16.285714 | EY79: 6.7310355 | EZ79: 11.660611 | FA79: 25.102765 | FB79: 13.109565 | GD79: 2.0613553 | GE79: 2.0880857 | GF79: 1.8833368 | GG79: 2.5780206 | GH79: 2.2073014 | GI79: 2.2452778 | GJ79: 0.75399382 | GK79: 5.440521 | GL79: 1.3919571 | GM79: 2.6347965 | GN79: 3.1437652 | GO79: 2.4853953
A80: =AC80 -> 44104 | AC80: 44104 | AD80: 22.188586 | AE80: 22.421085 | AF80: 41.868843 | AG80: 16.210691 | AH80: 17.013273 | AI80: 23.110592 | AJ80: -77.292896 | AK80: 26.591897 | AL80: 11.508049 | AM80: 17.954427 | AN80: 12.802232 | AO80: 27.607585 | DD80: 12.375085 | DE80: 17.985416 | DF80: 22.124478 | DG80: 15.085145 | DH80: 14.795344 | DI80: 16.896886 | DJ80: 5.9528199 | DK80: 19.987 | DL80: 5.4871883 | DM80: 8.4020906 | DN80: -538.5765 | DO80: 14.843141 | EQ80: 11.449761 | ER80: 15.617525 | ES80: 18.920928 | ET80: 19.65117 | EU80: 13.961474 | EV80: 14.968062 | EW80: 7.7414899 | EX80: 17.169678 | EY80: 6.9577272 | EZ80: 11.384913 | FA80: 28.496141 | FB80: 13.736328 | GD80: 2.1667977 | GE80: 2.2054142 | GF80: 1.9760828 | GG80: 2.6873686 | GH80: 2.3277803 | GI80: 2.314418 | GJ80: 0.75486192 | GK80: 5.7000491 | GL80: 1.4739595 | GM80: 2.5165034 | GN80: 3.2157569 | GO80: 2.6090063
A81: =AC81 -> 44074 | AC81: 44074 | AD81: 23.679859 | AE81: 23.610888 | AF81: 45.77346 | AG81: 17.072057 | AH81: 17.168543 | AI81: 23.639205 | AJ81: -49.311056 | AK81: 28.455704 | AL81: 11.733447 | AM81: 17.651757 | AN81: 8.4996387 | AO81: 28.751813 | DD81: 12.674559 | DE81: 18.861717 | DF81: 23.098369 | DG81: 15.631005 | DH81: 15.09755 | DI81: 16.978218 | DJ81: 6.6855647 | DK81: 21.338615 | DL81: 5.5617291 | DM81: 8.6076817 | DN81: -56.264746 | DO81: 15.120317 | EQ81: 11.834288 | ER81: 16.236489 | ES81: 20.120258 | ET81: 20.488235 | EU81: 14.069402 | EV81: 15.099382 | EW81: 8.371574 | EX81: 18.349542 | EY81: 7.0498859 | EZ81: 11.214722 | FA81: 34.767745 | FB81: 14.031367 | GD81: 2.1369392 | GE81: 2.2447676 | GF81: 2.0152545 | GG81: 2.7589105 | GH81: 2.3377874 | GI81: 2.2515181 | GJ81: 0.8923077 | GK81: 6.060428 | GL81: 1.5064149 | GM81: 2.4454017 | GN81: 3.3295356 | GO81: 2.6367091
A82: =AC82 -> 44043 | AC82: 44043 | AD82: 23.886825 | AE82: 21.764077 | AF82: 46.161917 | AG82: 16.707186 | AH82: 17.088814 | AI82: 22.822432 | AJ82: -110.66851 | AK82: 25.791679 | AL82: 11.414854 | AM82: 18.304411 | AN82: -7.2589846 | AO82: 27.930907 | DD82: 12.659897 | DE82: 17.343541 | DF82: 23.697781 | DG82: 15.33334 | DH82: 14.999994 | DI82: 16.376694 | DJ82: 6.9938566 | DK82: 19.188111 | DL82: 5.4212118 | DM82: 8.9485928 | DN82: -419.22521 | DO82: 14.345786 | EQ82: 11.830332 | ER82: 15.157345 | ES82: 19.800672 | ET82: 19.476789 | EU82: 13.877352 | EV82: 14.653065 | EW82: 8.5505047 | EX82: 16.540394 | EY82: 6.9158214 | EZ82: 11.34838 | FA82: 32.114831 | FB82: 13.68015 | GD82: 2.0676728 | GE82: 2.0339785 | GF82: 1.9017101 | GG82: 2.6486281 | GH82: 2.3030656 | GI82: 2.1205372 | GJ82: 0.89435501 | GK82: 5.4404536 | GL82: 1.4673678 | GM82: 2.5411982 | GN82: 2.9152344 | GO82: 2.4437149
A83: =AC83 -> 44012 | AC83: 44012 | AD83: 23.140133 | AE83: 21.928766 | AF83: 46.740265 | AG83: 16.691312 | AH83: 16.960861 | AI83: 22.40313 | AJ83: -70.131403 | AK83: 25.102612 | AL83: 11.187739 | AM83: 16.921204 | AN83: -24.405514 | AO83: 26.703455 | DD83: 12.007322 | DE83: 16.850247 | DF83: 22.606552 | DG83: 14.713425 | DH83: 14.623269 | DI83: 15.842325 | DJ83: 7.7906756 | DK83: 18.649868 | DL83: 5.3804378 | DM83: 8.1028382 | DN83: 138.03354 | DO83: 13.513898 | EQ83: 11.406725 | ER83: 14.944067 | ES83: 19.096597 | ET83: 19.017056 | EU83: 13.853905 | EV83: 14.376755 | EW83: 9.4562362 | EX83: 15.88482 | EY83: 6.8228102 | EZ83: 10.741738 | FA83: 28.76907 | FB83: 13.146953 | GD83: 1.8960122 | GE83: 1.9233987 | GF83: 1.7585744 | GG83: 2.6063871 | GH83: 2.2224502 | GI83: 2.0480488 | GJ83: 0.9691055 | GK83: 5.2321434 | GL83: 1.447542 | GM83: 2.3307313 | GN83: 2.8124748 | GO83: 2.2957811
A84: =AC84 -> 43980 | AC84: 43980 | AD84: 21.833294 | AE84: 22.024919 | AF84: 42.867925 | AG84: 17.107002 | AH84: 17.562042 | AI84: 22.56641 | AJ84: -57.001337 | AK84: 23.84217 | AL84: 11.142789 | AM84: 17.381841 | AN84: -71.976524 | AO84: 26.752792 | DD84: 11.402436 | DE84: 16.610809 | DF84: 21.22325 | DG84: 14.982886 | DH84: 15.137586 | DI84: 15.867403 | DJ84: 8.0889175 | DK84: 17.66652 | DL84: 5.5068783 | DM84: 8.3529583 | DN84: 72.521018 | DO84: 13.304732 | EQ84: 11.161768 | ER84: 14.935703 | ES84: 18.272365 | ET84: 19.071972 | EU84: 14.267287 | EV84: 14.456432 | EW84: 9.7192216 | EX84: 15.026603 | EY84: 6.9441287 | EZ84: 10.873477 | FA84: 28.248917 | FB84: 13.120288 | GD84: 1.8174739 | GE84: 1.8988367 | GF84: 1.6717847 | GG84: 2.6156264 | GH84: 2.2842815 | GI84: 2.0422688 | GJ84: 1.0036126 | GK84: 4.9525519 | GL84: 1.4740752 | GM84: 2.400995 | GN84: 2.879884 | GO84: 2.2911867
A85: =AC85 -> 43951 | AC85: 43951 | AD85: 19.522722 | AE85: 20.545783 | AF85: 37.144501 | AG85: 16.071416 | AH85: 17.119016 | AI85: 20.632405 | AJ85: -51.419978 | AK85: 22.443753 | AL85: 10.711024 | AM85: 16.676013 | AN85: 72.099709 | AO85: 23.55905 | DD85: 10.077331 | DE85: 16.041647 | DF85: 18.90943 | DG85: 14.004782 | DH85: 14.230399 | DI85: 14.786327 | DJ85: 8.1413558 | DK85: 16.629113 | DL85: 5.4645271 | DM85: 8.0141065 | DN85: 29.875409 | DO85: 11.865456 | EQ85: 10.467108 | ER85: 14.268774 | ES85: 16.823819 | ET85: 17.974748 | EU85: 13.85243 | EV85: 13.349551 | EW85: 9.8465698 | EX85: 14.110276 | EY85: 6.9918028 | EZ85: 10.663768 | FA85: 19.792492 | FB85: 12.26195 | GD85: 1.6588582 | GE85: 1.8032327 | GF85: 1.6194088 | GG85: 2.4694761 | GH85: 2.2393396 | GI85: 1.8947952 | GJ85: 0.98092534 | GK85: 4.6493337 | GL85: 1.4875834 | GM85: 2.2785503 | GN85: 2.6218061 | GO85: 2.1424117
A86: =AC86 -> 43921 | AC86: 43921 | AD86: 14.748242 | AE86: 16.321624 | AF86: 28.966182 | AG86: 11.208339 | AH86: 14.384648 | AI86: 15.698986 | AJ86: 53.55019 | AK86: 18.62358 | AL86: 9.5265423 | AM86: 16.071757 | AN86: 18.855093 | AO86: 17.025662 | DD86: 8.2435812 | DE86: 12.66398 | DF86: 15.029862 | DG86: 11.608537 | DH86: 12.31433 | DI86: 11.904708 | DJ86: 5.0486026 | DK86: 14.281182 | DL86: 4.8887146 | DM86: 7.7564874 | DN86: 11.87452 | DO86: 9.9235134 | EQ86: 8.7337786 | ER86: 12.151367 | ES86: 13.682349 | ET86: 16.02443 | EU86: 11.678951 | EV86: 10.973506 | EW86: 7.0320309 | EX86: 11.984942 | EY86: 6.4919585 | EZ86: 10.445958 | FA86: 11.195637 | FB86: 10.076659 | GD86: 1.3762222 | GE86: 1.5655654 | GF86: 1.3367997 | GG86: 2.1614939 | GH86: 1.9594671 | GI86: 1.6187842 | GJ86: 0.66140741 | GK86: 3.9495334 | GL86: 1.3163455 | GM86: 2.1852443 | GN86: 1.9034059 | GO86: 1.8028523
A87: =AC87 -> 43889 | AC87: 43889 | AD87: 16.028019 | AE87: 17.09013 | AF87: 29.000652 | AG87: 13.330936 | AH87: 14.822193 | AI87: 18.226273 | AJ87: 14.776903 | AK87: 19.905588 | AL87: 10.501019 | AM87: 18.014163 | AN87: 18.05562 | AO87: 18.950475 | DD87: 9.3995885 | DE87: 13.713498 | DF87: 15.389504 | DG87: 13.3524 | DH87: 12.745652 | DI87: 13.754635 | DJ87: 5.4859931 | DK87: 15.191526 | DL87: 5.4399119 | DM87: 8.6004282 | DN87: 11.676885 | DO87: 10.80668 | EQ87: 9.3997413 | ER87: 12.808823 | ES87: 14.135249 | ET87: 17.606593 | EU87: 11.939668 | EV87: 12.456648 | EW87: 6.2377919 | EX87: 12.82154 | EY87: 6.8742187 | EZ87: 11.142903 | FA87: 11.417551 | FB87: 11.025041 | GD87: 1.5961075 | GE87: 1.714896 | GF87: 1.4059419 | GG87: 2.6318875 | GH87: 2.012491 | GI87: 1.9098352 | GJ87: 0.84469102 | GK87: 4.2772502 | GL87: 1.4493494 | GM87: 2.4130118 | GN87: 2.2378615 | GO87: 2.027828
A88: =AC88 -> 43861 | AC88: 43861 | AD88: 17.271169 | AE88: 18.353803 | AF88: 31.194968 | AG88: 14.863862 | AH88: 15.790343 | AI88: 19.997736 | AJ88: 16.259172 | AK88: 21.637217 | AL88: 11.22815 | AM88: 20.076987 | AN88: 19.389903 | AO88: 20.238001 | DD88: 10.275346 | DE88: 14.939141 | DF88: 16.460947 | DG88: #N/A | DH88: 13.292891 | DI88: 15.031358 | DJ88: 6.3049148 | DK88: 16.312186 | DL88: 5.7890932 | DM88: 9.6079801 | DN88: 12.754157 | DO88: 12.094439 | EQ88: 9.9792496 | ER88: 13.68222 | ES88: 15.087014 | ET88: 18.744705 | EU88: 12.625184 | EV88: 13.454288 | EW88: 6.9912622 | EX88: 13.938486 | EY88: 7.1888329 | EZ88: 11.67657 | FA88: 12.226644 | FB88: 11.550551 | GD88: 1.7410209 | GE88: 1.8636249 | GF88: 1.497926 | GG88: 2.9498069 | GH88: 2.2116862 | GI88: 2.1045741 | GJ88: 0.99255484 | GK88: 4.6447931 | GL88: 1.5579485 | GM88: 2.66846 | GN88: 2.4945642 | GO88: 2.1921344
A89: =AC89 -> 43830 | AC89: 43830 | AD89: 17.800671 | AE89: 18.351126 | AF89: 30.751755 | AG89: 15.113722 | AH89: 16.402148 | AI89: 19.158509 | AJ89: 17.833636 | AK89: 21.482816 | AL89: 11.636928 | AM89: 18.862053 | AN89: 19.95006 | AO89: 20.89858 | DD89: 10.879467 | DE89: 14.805371 | DF89: 16.632188 | DG89: #N/A | DH89: 13.833467 | DI89: 14.165118 | DJ89: 6.9807081 | DK89: 15.812931 | DL89: 5.8348736 | DM89: 8.8732767 | DN89: 13.092289 | DO89: 12.354783 | EQ89: 10.393368 | ER89: 13.682197 | ES89: 14.819258 | ET89: 18.337906 | EU89: 12.899438 | EV89: 13.03323 | EW89: 7.4570613 | EX89: 13.779096 | EY89: 7.2644937 | EZ89: 11.145483 | FA89: 12.471702 | FB89: 11.646962 | GD89: 1.8652586 | GE89: 1.8610559 | GF89: 1.4602174 | GG89: 3.012159 | GH89: 2.2524803 | GI89: 2.0727514 | GJ89: 1.1104575 | GK89: 4.5590831 | GL89: 1.6157068 | GM89: 2.4774142 | GN89: 2.5759637 | GO89: 2.2311437
A90: =AC90 -> 43798 | AC90: 43798 | AD90: 17.272378 | AE90: 17.874247 | AF90: 29.983992 | AG90: 14.869462 | AH90: 15.937993 | AI90: 19.112634 | AJ90: 17.163249 | AK90: 20.739197 | AL90: 11.35496 | AM90: 18.352932 | AN90: 19.343641 | AO90: 18.447782 | DD90: 10.530837 | DE90: 14.600527 | DF90: 17.659063 | DG90: #N/A | DH90: 13.275076 | DI90: 14.120636 | DJ90: 6.6822119 | DK90: 15.131349 | DL90: 5.6896614 | DM90: 8.6095763 | DN90: 12.756921 | DO90: 9.9991012 | EQ90: 10.118486 | ER90: 13.435863 | ES90: 14.888975 | ET90: 18.255337 | EU90: 12.638967 | EV90: 13.018965 | EW90: 7.2153639 | EX90: 13.291964 | EY90: 7.177273 | EZ90: 10.99702 | FA90: 12.181483 | FB90: 10.661683 | GD90: 1.8106182 | GE90: 1.8000766 | GF90: 1.5170803 | GG90: 2.9502252 | GH90: 2.1828632 | GI90: 2.0669427 | GJ90: 1.0497317 | GK90: 4.3963527 | GL90: 1.5780828 | GM90: 2.3956936 | GN90: 2.4929857 | GO90: 2.0140582
A91: =AC91 -> 43769 | AC91: 43769 | AD91: 16.772151 | AE91: 17.745795 | AF91: 29.68065 | AG91: 14.431636 | AH91: 15.283462 | AI91: 18.389983 | AJ91: 16.901113 | AK91: 19.824355 | AL91: 11.546333 | AM91: 18.855324 | AN91: 19.165741 | AO91: 17.405506 | DD91: 10.120452 | DE91: 14.507237 | DF91: 17.7326 | DG91: #N/A | DH91: 12.90106 | DI91: 13.515356 | DJ91: 6.5842057 | DK91: 14.657055 | DL91: 6.0257425 | DM91: 9.0113666 | DN91: 12.968227 | DO91: 9.2317696 | EQ91: 9.9118486 | ER91: 13.405764 | ES91: 14.788505 | ET91: 18.042831 | EU91: 11.990193 | EV91: 12.59601 | EW91: 6.9328193 | EX91: 12.622872 | EY91: 7.2926523 | EZ91: 11.157952 | FA91: 12.198173 | FB91: 10.492631 | GD91: 1.7410688 | GE91: 1.7792663 | GF91: 1.5005217 | GG91: 2.8556675 | GH91: 2.0975803 | GI91: 1.9761941 | GJ91: 1.05408 | GK91: 4.2065982 | GL91: 1.6027154 | GM91: 2.4564747 | GN91: 2.4901354 | GO91: 1.9177035
A92: =AC92 -> 43738 | AC92: 43738 | AD92: 16.548939 | AE92: 17.627453 | AF92: 28.589263 | AG92: 14.117988 | AH92: 14.655635 | AI92: 18.12925 | AJ92: 16.328819 | AK92: 19.291825 | AL92: 11.459012 | AM92: 19.137679 | AN92: 19.507618 | AO92: 17.134868 | DD92: 10.113909 | DE92: 14.648121 | DF92: 16.601795 | DG92: #N/A | DH92: 12.141306 | DI92: 13.240703 | DJ92: 6.477212 | DK92: 14.360181 | DL92: 5.793785 | DM92: 9.1856629 | DN92: 13.269743 | DO92: 9.0660662 | EQ92: 9.8308879 | ER92: 13.335308 | ES92: 14.445346 | ET92: 17.862285 | EU92: 11.666146 | EV92: 12.538612 | EW92: 6.8833588 | EX92: 12.259011 | EY92: 7.2095697 | EZ92: 11.276667 | FA92: 12.468748 | FB92: 10.361866 | GD92: 1.7088218 | GE92: 1.7742214 | GF92: 1.4803173 | GG92: 2.8130988 | GH92: 2.0141248 | GI92: 1.9356215 | GJ92: 1.068513 | GK92: 4.1015156 | GL92: 1.5840368 | GM92: 2.4852265 | GN92: 2.5574493 | GO92: 1.8894976
A93: =AC93 -> 43707 | AC93: 43707 | AD93: 15.99791 | AE93: 17.258826 | AF93: 28.936503 | AG93: 13.697048 | AH93: 14.877443 | AI93: 17.853393 | AJ93: 15.571033 | AK93: 18.931822 | AL93: 10.916072 | AM93: 18.49218 | AN93: 19.908208 | AO93: 17.496324 | DD93: 9.6428232 | DE93: 14.243139 | DF93: 16.840589 | DG93: #N/A | DH93: 12.860004 | DI93: 13.062591 | DJ93: 6.1553359 | DK93: 14.0773 | DL93: 5.5835052 | DM93: 8.8189255 | DN93: 13.521186 | DO93: 9.3423092 | EQ93: 9.3865669 | ER93: 13.04706 | ES93: 14.625369 | ET93: 18.047 | EU93: 12.058343 | EV93: 12.370224 | EW93: 6.6792661 | EX93: 12.052129 | EY93: 6.9877714 | EZ93: 11.037958 | FA93: 12.759137 | FB93: 10.501398 | GD93: 1.5910034 | GE93: 1.7128216 | GF93: 1.4975574 | GG93: 2.7535076 | GH93: 2.041824 | GI93: 1.9025117 | GJ93: 1.0153372 | GK93: 4.0136831 | GL93: 1.5007473 | GM93: 2.3880851 | GN93: 2.6231955 | GO93: 1.937325
A94: =AC94 -> 43677 | AC94: 43677 | AD94: 17.085664 | AE94: 17.464088 | AF94: 29.53047 | AG94: 14.070942 | AH94: 15.150598 | AI94: 18.325327 | AJ94: 16.951595 | AK94: 19.501286 | AL94: 10.590852 | AM94: 17.841426 | AN94: 20.162903 | AO94: 17.552538 | DD94: 10.151795 | DE94: 14.365842 | DF94: 17.069057 | DG94: #N/A | DH94: 12.887676 | DI94: 13.433735 | DJ94: 6.7353276 | DK94: 14.419203 | DL94: 5.4040185 | DM94: 8.4889211 | DN94: 13.626677 | DO94: 9.5265655 | EQ94: 9.9968235 | ER94: 13.295715 | ES94: 14.910613 | ET94: 17.840017 | EU94: 12.13647 | EV94: 12.773944 | EW94: 6.9733433 | EX94: 12.511367 | EY94: 6.8845484 | EZ94: 10.750222 | FA94: 12.85015 | FB94: 10.651955 | GD94: 1.6713318 | GE94: 1.7180174 | GF94: 1.520334 | GG94: 2.8362065 | GH94: 2.0830563 | GI94: 1.9538475 | GJ94: 1.1446491 | GK94: 4.150185 | GL94: 1.444859 | GM94: 2.2927877 | GN94: 2.6417007 | GO94: 1.9782729
A95: =AC95 -> 43644 | AC95: 43644 | AD95: 16.769285 | AE95: 17.188085 | AF95: 29.241903 | AG95: 13.770722 | AH95: 15.582565 | AI95: 18.075088 | AJ95: 16.287734 | AK95: 19.05722 | AL95: 10.650257 | AM95: 18.018541 | AN95: 19.854621 | AO95: 17.461977 | DD95: 10.102254 | DE95: 14.058296 | DF95: 17.869908 | DG95: #N/A | DH95: 13.537301 | DI95: 13.639017 | DJ95: 6.8218129 | DK95: 13.945384 | DL95: 5.4343221 | DM95: 8.4455816 | DN95: 13.257445 | DO95: 9.396185 | EQ95: 10.011759 | ER95: 13.058253 | ES95: 15.007302 | ET95: 17.657019 | EU95: 12.398584 | EV95: 12.593987 | EW95: 7.0766917 | EX95: 12.291716 | EY95: 6.9050809 | EZ95: 10.829373 | FA95: 12.742536 | FB95: 10.599386 | GD95: 1.6938281 | GE95: 1.691045 | GF95: 1.5411416 | GG95: 2.8089388 | GH95: 2.1481911 | GI95: 1.9223542 | GJ95: 1.1718063 | GK95: 4.0661318 | GL95: 1.4490441 | GM95: 2.3007745 | GN95: 2.6025615 | GO95: 1.9565209
A96: =AC96 -> 43616 | AC96: 43616 | AD96: 14.662658 | AE96: 16.257584 | AF96: 27.249733 | AG96: 13.036042 | AH96: 14.657019 | AI96: 16.88267 | AJ96: 14.758335 | AK96: 17.616497 | AL96: 9.9825675 | AM96: 17.538611 | AN96: 18.430391 | AO96: 16.32126 | DD96: 9.055999 | DE96: 13.394777 | DF96: 16.706322 | DG96: #N/A | DH96: 12.882341 | DI96: 12.622777 | DJ96: 6.2284942 | DK96: 12.996114 | DL96: 5.0832085 | DM96: 8.1806561 | DN96: 12.350147 | DO96: 8.6294371 | EQ96: 9.0394236 | ER96: 12.527653 | ES96: 14.148488 | ET96: 17.065957 | EU96: 11.630281 | EV96: 11.866084 | EW96: 6.5670264 | EX96: 11.378435 | EY96: 6.6467813 | EZ96: 10.66868 | FA96: 12.007817 | FB96: 10.142499 | GD96: 1.5000878 | GE96: 1.5966638 | GF96: 1.441076 | GG96: 2.6592792 | GH96: 2.0344577 | GI96: 1.7817972 | GJ96: 1.0679505 | GK96: 3.7655935 | GL96: 1.357256 | GM96: 2.232701 | GN96: 2.4223792 | GO96: 1.8543365
A97: =AC97 -> 43585 | AC97: 43585 | AD97: 15.750722 | AE97: 17.435822 | AF97: 29.096645 | AG97: 13.853085 | AH97: 15.192954 | AI97: 18.281358 | AJ97: 17.137344 | AK97: 19.659181 | AL97: 10.281817 | AM97: 17.917372 | AN97: 19.615917 | AO97: 17.029051 | DD97: 9.7999426 | DE97: 14.293501 | DF97: 17.849122 | DG97: #N/A | DH97: 13.341168 | DI97: 13.690409 | DJ97: 7.0845313 | DK97: 14.359896 | DL97: 5.2329787 | DM97: 8.3371051 | DN97: 13.236686 | DO97: 8.9791631 | EQ97: 9.6111485 | ER97: 13.128788 | ES97: 15.057374 | ET97: 17.540154 | EU97: 11.940544 | EV97: 12.543033 | EW97: 7.226418 | EX97: 12.72006 | EY97: 6.7781308 | EZ97: 10.845603 | FA97: 12.549019 | FB97: 10.079268 | GD97: 1.6189642 | GE97: 1.7037824 | GF97: 1.5470581 | GG97: 2.8218175 | GH97: 2.104863 | GI97: 1.9150069 | GJ97: 1.2154571 | GK97: 4.2099955 | GL97: 1.3963483 | GM97: 2.2783502 | GN97: 2.5636913 | GO97: 1.9713555
A98: =AC98 -> 43553 | AC98: 43553 | AD98: 15.221297 | AE98: 16.941927 | AF98: 27.906927 | AG98: 13.099618 | AH98: 15.874392 | AI98: 17.566218 | AJ98: 18.217633 | AK98: 18.594019 | AL98: 10.581926 | AM98: 17.798773 | AN98: 18.711137 | AO98: 15.153252 | DD98: 9.5868596 | DE98: 13.872827 | DF98: 16.629314 | DG98: #N/A | DH98: 13.751812 | DI98: 13.109873 | DJ98: 7.2685817 | DK98: 13.670571 | DL98: 5.312352 | DM98: 8.2350602 | DN98: 12.585005 | DO98: 8.0037932 | EQ98: 9.0609134 | ER98: 12.821717 | ES98: 14.582869 | ET98: 17.06564 | EU98: 12.614386 | EV98: 12.117235 | EW98: 7.3884575 | EX98: 12.030593 | EY98: 6.8229989 | EZ98: 10.811126 | FA98: 12.172287 | FB98: 9.3932674 | GD98: 1.5801176 | GE98: 1.653174 | GF98: 1.4811061 | GG98: 2.6605281 | GH98: 2.1914075 | GI98: 1.8484675 | GJ98: 1.2416252 | GK98: 3.9828584 | GL98: 1.4200489 | GM98: 2.2670847 | GN98: 2.4698234 | GO98: 1.8066643
A99: =AC99 -> 43524 | AC99: 43524 | AD99: 15.111879 | AE99: 16.46765 | AF99: 26.640991 | AG99: 13.18412 | AH99: 15.901482 | AI99: 17.595671 | AJ99: 18.280977 | AK99: 17.744216 | AL99: 10.43692 | AM99: 17.323339 | AN99: 18.00678 | AO99: 16.408383 | DD99: 9.492213 | DE99: 13.353868 | DF99: 15.927116 | DG99: #N/A | DH99: 13.538211 | DI99: 13.002463 | DJ99: 7.1684225 | DK99: 13.258991 | DL99: 5.2275356 | DM99: 7.9993173 | DN99: 12.237197 | DO99: 8.4407263 | EQ99: 9.0396232 | ER99: 12.465478 | ES99: 13.986178 | ET99: 16.669649 | EU99: 12.586768 | EV99: 12.114894 | EW99: 7.2790891 | EX99: 11.44207 | EY99: 6.7645077 | EZ99: 10.668611 | FA99: 11.960172 | FB99: 9.3383153 | GD99: 1.5715843 | GE99: 1.5778634 | GF99: 1.4031188 | GG99: 2.6719963 | GH99: 2.1896336 | GI99: 1.8533345 | GJ99: 1.2142201 | GK99: 3.809297 | GL99: 1.396083 | GM99: 2.2212284 | GN99: 2.4604459 | GO99: 1.8116008
... A247: =AC247 -> 39021 | AC247: 39021 | AD247: 13.074811 | AE247: 17.007415 | AF247: 15.591935 | AG247: 12.352161 | AH247: 16.851094 | AI247: 15.290303 | AJ247: 9.4894303 | AK247: 18.961473 | AL247: 15.846094 | AM247: 14.641796 | AN247: 17.062283 | AO247: 21.617524 | DD247: 7.8878088 | DE247: 11.84195 | DF247: 10.900517 | DG247: #N/A | DH247: 12.676001 | DI247: 10.605657 | DJ247: 6.2359061 | DK247: 14.170512 | DL247: 6.490274 | DM247: 7.3428324 | DN247: 10.892184 | DO247: 13.168885 | EQ247: 6.934855 | ER247: 10.209222 | ES247: 8.2654562 | ET247: 17.201184 | EU247: 11.233971 | EV247: 10.994581 | EW247: 4.6211309 | EX247: 10.751802 | EY247: 6.2254684 | EZ247: 7.8741222 | FA247: 10.621321 | FB247: 9.9131248 | GD247: 1.1224993 | GE247: 1.1068875 | GF247: 0.7576717 | GG247: 2.546541 | GH247: 2.0896135 | GI247: 1.2967802 | GJ247: 1.1018265 | GK247: 2.5296565 | GL247: 1.5020328 | GM247: 1.3296739 | GN247: 1.6951588 | GO247: 2.0082679

Sheet MOM_FMA
AQ1: 6M Returns - 1M | DD1: Number of Companies with Upward Revisions | DQ1: Number of Companies with Downward Revisions | ED1: Number of Companies with Unchanged Estimates
AQ2: P_PRICE_RETURNS_PR('52W' | DD2: FMA_COS_UP | DQ2: FMA_COS_DOWN | ED2: FMA_COS_UNCH
AQ3: 12M Forecast Ratio | DD3: 1M | DQ3: 1M | ED3: 1M
B6: Materials | C6: ConsStaples | D6: Retail | E6: Fin | F6: HealthCare | G6: Indus | H6: Oil | I6: Tech | J6: Telco | K6: Utili | L6: Travel & leisure | M6: Media | P6: Materials | Q6: ConsStaples | R6: Retail | S6: Fin | T6: HealthCare | U6: Indus | V6: Oil | W6: Tech | X6: Telco | Y6: Utili | Z6: Travel & leisure | AA6: Media | AD6: Materials | AE6: ConsStaples | AF6: Retail | AG6: Fin | AH6: HealthCare | AI6: Indus | AJ6: Oil | AK6: Tech | AL6: Telco | AM6: Utili | AN6: Travel & leisure | AO6: Media | AQ6: Materials | AR6: ConsStaples | AS6: Retail | AT6: Fin | AU6: HealthCare | AV6: Indus | AW6: Oil | AX6: Tech | AY6: Telco | AZ6: Utili | BA6: Travel & leisure | BB6: Media | BD6: Materials | BE6: ConsStaples | BF6: Retail | BG6: Fin | BH6: HealthCare | BI6: Indus | BJ6: Oil | BK6: Tech | BL6: Telco | BM6: Utili | BN6: Travel & leisure | BO6: Media | BQ6: Materials | BR6: ConsStaples | BS6: Retail | BT6: Fin | BU6: HealthCare | BV6: Indus | BW6: Oil | BX6: Tech | BY6: Telco | BZ6: Utili | CA6: Travel & leisure | CB6: Media | CD6: Materials | CE6: ConsStaples | CF6: Retail | CG6: Fin | CH6: HealthCare | CI6: Indus | CJ6: Oil | CK6: Tech | CL6: Telco | CM6: Utili | CN6: Travel & leisure | CO6: Media | CQ6: Materials | CR6: ConsStaples | CS6: Retail | CT6: Fin | CU6: HealthCare | CV6: Indus | CW6: Oil | CX6: Tech | CY6: Telco | CZ6: Utili | DA6: Travel & leisure | DB6: Media | DD6: Materials | DE6: ConsStaples | DF6: Retail | DG6: Fin | DH6: HealthCare | DI6: Indus | DJ6: Oil | DK6: Tech | DL6: Telco | DM6: Utili | DN6: Travel & leisure | DO6: Media | DQ6: Materials | DR6: ConsStaples | DS6: Retail | DT6: Fin | DU6: HealthCare | DV6: Indus | DW6: Oil | DX6: Tech | DY6: Telco | DZ6: Utili | EA6: Travel & leisure | EB6: Media | ED6: Materials | EE6: ConsStaples | EF6: Retail | EG6: Fin | EH6: HealthCare | EI6: Indus | EJ6: Oil | EK6: Tech | EL6: Telco | EM6: Utili | EN6: Travel & leisure | EO6: Media | EQ6: Materials | ER6: ConsStaples | ES6: Retail | ET6: Fin | EU6: HealthCare | EV6: Indus | EW6: Oil | EX6: Tech | EY6: Telco | EZ6: Utili | FA6: Travel & leisure | FB6: Media | FD6: Materials | FE6: ConsStaples | FF6: Retail | FG6: Fin | FH6: HealthCare | FI6: Indus | FJ6: Oil | FK6: Tech | FL6: Telco | FM6: Utili | FN6: Travel & leisure | FO6: Media
AD7: I00072 | AE7: I00144 | AF7: I01044 | AG7: I00288 | AH7: I21862 | AI7: I00108 | AJ7: I21852 | AK7: I21904 | AL7: I21881 | AM7: I00612 | AN7: I00936 | AO7: I00972 | AQ7: I00072 | AR7: I00144 | AS7: I01044 | AT7: I00288 | AU7: I21862 | AV7: I00108 | AW7: I21852 | AX7: I21904 | AY7: I21881 | AZ7: I00612 | BA7: I00936 | BB7: I00972 | DD7: I00072 | DE7: I00144 | DF7: I01044 | DG7: I00288 | DH7: I21862 | DI7: I00108 | DJ7: I21852 | DK7: I21904 | DL7: I21881 | DM7: I00612 | DN7: I00936 | DO7: I00972 | DQ7: I00072 | DR7: I00144 | DS7: I01044 | DT7: I00288 | DU7: I21862 | DV7: I00108 | DW7: I21852 | DX7: I21904 | DY7: I21881 | DZ7: I00612 | EA7: I00936 | EB7: I00972 | ED7: I00072 | EE7: I00144 | EF7: I01044 | EG7: I00288 | EH7: I21862 | EI7: I00108 | EJ7: I21852 | EK7: I21904 | EL7: I21881 | EM7: I00612 | EN7: I00936 | EO7: I00972
A8: =AP8 -> 46295 | AP8: {=_xll.FDS(AQ7,"JULIAN(FG_PRICE(0,-20AY,M,EUR).dates)")} -> 46295 | AQ8: {=_xll.FDS(AQ7,"FG_PRICE(0,-20AY,M,EUR)")} -> 1387.111 | AR8: {=_xll.FDS(AR7,"FG_PRICE(0,-20AY,M,EUR)")} -> 2036.9601 | AS8: {=_xll.FDS(AS7,"FG_PRICE(0,-20AY,M,EUR)")} -> 9153.0008 | AT8: {=_xll.FDS(AT7,"FG_PRICE(0,-20AY,M,EUR)")} -> 1811.066 | AU8: {=_xll.FDS(AU7,"FG_PRICE(0,-20AY,M,EUR)")} -> 4054.481 | AV8: {=_xll.FDS(AV7,"FG_PRICE(0,-20AY,M,EUR)")} -> 3312.4189 | AW8: {=_xll.FDS(AW7,"FG_PRICE(0,-20AY,M,EUR)")} -> 1528.3443 | AX8: {=_xll.FDS(AX7,"FG_PRICE(0,-20AY,M,EUR)")} -> 9460.7815 | ... BB8: {=_xll.FDS(BB7,"FG_PRICE(0,-20AY,M,EUR)")} -> 1895.2722 | DD8: {=_xll.FDS(DD7,"FMA_COS_UP(""EPS"",""1M"",+1,0,-20AY,M,""PORTAGG"",""MEANR"")")} -> 6 | DE8: {=_xll.FDS(DE7,"FMA_COS_UP(""EPS"",""1M"",+1,0,-20AY,M,""PORTAGG"",""MEANR"")")} -> 8 | DF8: {=_xll.FDS(DF7,"FMA_COS_UP(""EPS"",""1M"",+1,0,-20AY,M,""PORTAGG"",""MEANR"")")} -> 10 | DG8: {=_xll.FDS(DG7,"FMA_COS_UP(""EPS"",""1M"",+1,0,-20AY,M,""PORTAGG"",""MEANR"")")} -> 25 | DH8: {=_xll.FDS(DH7,"FMA_COS_UP(""EPS"",""1M"",+1,0,-20AY,M,""PORTAGG"",""MEANR"")")} -> 16 | DI8: {=_xll.FDS(DI7,"FMA_COS_UP(""EPS"",""1M"",+1,0,-20AY,M,""PORTAGG"",""MEANR"")")} -> 38 | DJ8: {=_xll.FDS(DJ7,"FMA_COS_UP(""EPS"",""1M"",+1,0,-20AY,M,""PORTAGG"",""MEANR"")")} -> 15 | DK8: {=_xll.FDS(DK7,"FMA_COS_UP(""EPS"",""1M"",+1,0,-20AY,M,""PORTAGG"",""MEANR"")")} -> 43 | ... DO8: {=_xll.FDS(DO7,"FMA_COS_UP(""EPS"",""1M"",+1,0,-20AY,M,""PORTAGG"",""MEANR"")")} -> 5 | DQ8: {=_xll.FDS(DQ7,"FMA_COS_DOWN(""EPS"",""1M"",+1,0,-20AY,M,""PORTAGG"",""MEANR"")")} -> 2 | DR8: {=_xll.FDS(DR7,"FMA_COS_DOWN(""EPS"",""1M"",+1,0,-20AY,M,""PORTAGG"",""MEANR"")")} -> 9 | DS8: {=_xll.FDS(DS7,"FMA_COS_DOWN(""EPS"",""1M"",+1,0,-20AY,M,""PORTAGG"",""MEANR"")")} -> 6 | DT8: {=_xll.FDS(DT7,"FMA_COS_DOWN(""EPS"",""1M"",+1,0,-20AY,M,""PORTAGG"",""MEANR"")")} -> 24 | DU8: {=_xll.FDS(DU7,"FMA_COS_DOWN(""EPS"",""1M"",+1,0,-20AY,M,""PORTAGG"",""MEANR"")")} -> 16 | DV8: {=_xll.FDS(DV7,"FMA_COS_DOWN(""EPS"",""1M"",+1,0,-20AY,M,""PORTAGG"",""MEANR"")")} -> 29 | DW8: {=_xll.FDS(DW7,"FMA_COS_DOWN(""EPS"",""1M"",+1,0,-20AY,M,""PORTAGG"",""MEANR"")")} -> 4 | DX8: {=_xll.FDS(DX7,"FMA_COS_DOWN(""EPS"",""1M"",+1,0,-20AY,M,""PORTAGG"",""MEANR"")")} -> 11 | ... EB8: {=_xll.FDS(EB7,"FMA_COS_DOWN(""EPS"",""1M"",+1,0,-20AY,M,""PORTAGG"",""MEANR"")")} -> 1 | ED8: {=_xll.FDS(ED7,"FMA_COS_UNCH(""EPS"",""1M"",+1,0,-20AY,M,""PORTAGG"",""MEANR"")")} -> 5 | EE8: {=_xll.FDS(EE7,"FMA_COS_UNCH(""EPS"",""1M"",+1,0,-20AY,M,""PORTAGG"",""MEANR"")")} -> 9 | EF8: {=_xll.FDS(EF7,"FMA_COS_UNCH(""EPS"",""1M"",+1,0,-20AY,M,""PORTAGG"",""MEANR"")")} -> 4 | EG8: {=_xll.FDS(EG7,"FMA_COS_UNCH(""EPS"",""1M"",+1,0,-20AY,M,""PORTAGG"",""MEANR"")")} -> 18 | EH8: {=_xll.FDS(EH7,"FMA_COS_UNCH(""EPS"",""1M"",+1,0,-20AY,M,""PORTAGG"",""MEANR"")")} -> 16 | EI8: {=_xll.FDS(EI7,"FMA_COS_UNCH(""EPS"",""1M"",+1,0,-20AY,M,""PORTAGG"",""MEANR"")")} -> 26 | EJ8: {=_xll.FDS(EJ7,"FMA_COS_UNCH(""EPS"",""1M"",+1,0,-20AY,M,""PORTAGG"",""MEANR"")")} -> 3 | EK8: {=_xll.FDS(EK7,"FMA_COS_UNCH(""EPS"",""1M"",+1,0,-20AY,M,""PORTAGG"",""MEANR"")")} -> 23 | ... EO8: {=_xll.FDS(EO7,"FMA_COS_UNCH(""EPS"",""1M"",+1,0,-20AY,M,""PORTAGG"",""MEANR"")")} -> 5
